Workbook

Sheet Dashboard
A1: EXOS Aerospace Fundraise CRM Dashboard
A3: Round Target | B3: $10.0M Series A | D3: Daily Call Goal | E3: 2 | F3: Stretch Goal | G3: 3
A6: As of | B6: =TODAY() | D6: Pipeline by Stage | G6: Tier Mix
A7: Total Contacts | B7: =COUNTA(CRM_Master!E:E)-1 | D7: Research | E7: =COUNTIF(CRM_Master!L:L,"Research") | G7: Tier 1 | H7: =COUNTIF(CRM_Master!N:N,"Tier 1")
A8: Unique Firms | B8: =COUNTA(Firm_Summary!A:A)-1 | D8: Contacted | E8: =COUNTIF(CRM_Master!L:L,"Contacted") | G8: Tier 2 | H8: =COUNTIF(CRM_Master!N:N,"Tier 2")
A9: Active (not passed) | B9: =COUNTIF(CRM_Master!AC:AC,"Active") | D9: Follow Up | E9: =COUNTIF(CRM_Master!L:L,"Follow Up") | G9: Tier 3 | H9: =COUNTIF(CRM_Master!N:N,"Tier 3")
A10: Due Now | B10: =COUNTIF(CRM_Master!S:S,"DUE") | D10: Meeting Requested | E10: =COUNTIF(CRM_Master!L:L,"Meeting Requested")
A11: Tier 1 Due Now | B11: =COUNTIFS(CRM_Master!S:S,"DUE",CRM_Master!N:N,"Tier 1") | D11: Meeting Held | E11: =COUNTIF(CRM_Master!L:L,"Meeting Held")
A12: Meetings / Engaged | B12: =COUNTIFS(CRM_Master!L:L,"Meeting Requested")+COUNTIFS(CRM_Master!L:L,"Meeting Held")+COUNTIFS(CRM_Master!L:L,"Engaged")+COUNTIFS(CRM_Master!L:L,"Term Sheet / Proposal") | D12: How to use | E12: =COUNTIF(CRM_Master!L:L,"Engaged")
A13: Suggested Calls Today | B13: =MIN($G$3,COUNTIFS(CRM_Master!S:S,"DUE",CRM_Master!AC:AC,"Active",CRM_Master!N:N,"<>Tier 3")) | D13: 1) Work Today_Queue first. 2) Log every touch in CRM_Master. 3) Update Stage, Last Touch, and Notes after each interaction. 4) Keep 2–3 calls/day booked.

Sheet CRM_Master
A1: Record ID | B1: Source Sheets | C1: Category | D1: Company | E1: Contact Name | F1: Title / Role | G1: Primary Email | H1: Additional Emails | I1: Phone | J1: LinkedIn / Bio | K1: Owner | L1: Stage | M1: Fit Thesis | N1: Priority Tier | O1: First Outreach | P1: Last Touch | Q1: Days Since Last Touch | R1: Next Touch | S1: Due? | T1: Meeting Status | U1: Warm Intro / Referral | V1: Offer / Structure | W1: Notes | X1: Source Row(s) | Y1: Next Action | Z1: Cadence (Days) | AA1: Priority Score | AB1: Book Call? | AC1: Status
A2: EXOS-0001 | B2: Derek Contacts | JQ Follow Up | Term Sheets | C2: Financial Investor | D2: AxisCades | E2: Suresh Babu Suryadevara | F2: VP Aerospace & Defense | G2: suresh.s@axiscades.in | H2: arun.arumugam@axiscades.in; rithvick.naidu@axiscades.in | K2: John Quinn | L2: Term Sheet / Proposal | M2: Space / Defense / Aerospace / Advanced Manufacturing | N2: Tier 1 | P2: 46055 | Q2: =IF(P2="","",TODAY()-P2) | R2: =IF(OR(L2="Passed",Z2=""),"",P2+Z2) | S2: =IF(OR(R2="",L2="Passed"),"",IF(R2<=TODAY(),"DUE",IF(R2<=TODAY()+3,"Next 3 Days","Later"))) | T2: Meeting scheduled / held | V2: Strategic Partnership- Equity deal | W2: Missed call toady at 08:30 - Follow-up framework shared outlining a phased, ITAR/EAR-compliant strategic partnership. Proposal includes AxisCades acquiring 51% of SSLC for $10M (phased capital), international sales support with commission structure, and long-term India-based manufacturing under TAA/MLA approvals. Discussions ongoing to confirm alignment on structure, valuation, and next steps. | toured SSLC on 2/16 | met in person at EXOS on 12/19, follow up set for onsite visit 1/19 | request for SSLC visit on hold pending establishment of basic term sheet. | X2: Term Sheets!2 | JQ Follow Up!4 | Derek Contacts!8 | Y2: Review terms and push decision process | Z2: 2 | AA2: =IF(AC2="Archived",0,ROUND((IF(N2="Tier 1",35,IF(N2="Tier 2",20,8))+IF(C2="Financial Investor",15,IF(C2="Intermediary / Banker",12,8))+IF(L2="Term Sheet / Proposal",25,IF(L2="Engaged",20,IF(L2="Meeting Requested",18,IF(L2="Meeting Held",14,IF(L2="Follow Up",10,5)))))+MIN(Q2,30)+IF(S2="DUE",15,IF(S2="Next 3 Days",8,0))),0)) | AB2: =IF(AND(AC2="Active",OR(N2="Tier 1",N2="Tier 2"),OR(S2="DUE",S2="Next 3 Days")),"YES","") | AC2: =IF(L2="Passed","Archived","Active")
A3: EXOS-0002 | B3: Term Sheets | C3: Intermediary / Banker | D3: Bancroft Capital (Bancroft4Vets) | E3: Jason Diamond | G3: jdiamond@bancroft4vets.com | H3: kcariaga@bancroft4vets.com; rmalin@bancroft4vets.com; jgoodman@bancroft4vets.com | K3: John Quinn | L3: Term Sheet / Proposal | M3: Capital raise support / placement | N3: Tier 1 | Q3: =IF(P3="","",TODAY()-P3) | R3: =IF(OR(L3="Passed",Z3=""),"",P3+Z3) | S3: =IF(OR(R3="",L3="Passed"),"",IF(R3<=TODAY(),"DUE",IF(R3<=TODAY()+3,"Next 3 Days","Later"))) | T3: Meeting scheduled / held | V3: Investment Banking / Capital Raise | W3: Introduced via Kipton Cariaga. Terms/presentation shared. Defense- and veteran-focused investment bank. Logged for tracking and follow-up; no term sheet yet. Engaging BTIG 2-26-26 | 01/16/2026 | At their request, sent forward-ready cover email with high-level company overview and $10M raise summary, along with attached presentations. Materials prepared for direct circulation to IB partners and investor network (Jason forwarding internally). Awaiting feedback and/or investor introductions. | X3: Term Sheets!6 | Y3: Review terms and push decision process | Z3: 2 | AA3: =IF(AC3="Archived",0,ROUND((IF(N3="Tier 1",35,IF(N3="Tier 2",20,8))+IF(C3="Financial Investor",15,IF(C3="Intermediary / Banker",12,8))+IF(L3="Term Sheet / Proposal",25,IF(L3="Engaged",20,IF(L3="Meeting Requested",18,IF(L3="Meeting Held",14,IF(L3="Follow Up",10,5)))))+MIN(Q3,30)+IF(S3="DUE",15,IF(S3="Next 3 Days",8,0))),0)) | AB3: =IF(AND(AC3="Active",OR(N3="Tier 1",N3="Tier 2"),OR(S3="DUE",S3="Next 3 Days")),"YES","") | AC3: =IF(L3="Passed","Archived","Active")
A4: EXOS-0003 | B4: John - Investor Contacts | C4: Financial Investor | D4: Cerberus Capital Management | E4: Dan Quayle | G4: dquayle@cerberus.com | K4: John Quinn | L4: Term Sheet / Proposal | M4: Space / Defense / Aerospace / Advanced Manufacturing | N4: Tier 1 | O4: 45968 | P4: 46023 | Q4: =IF(P4="","",TODAY()-P4) | R4: =IF(OR(L4="Passed",Z4=""),"",P4+Z4) | S4: =IF(OR(R4="",L4="Passed"),"",IF(R4<=TODAY(),"DUE",IF(R4<=TODAY()+3,"Next 3 Days","Later"))) | T4: Meeting scheduled / held | V4: Strategic Partner / Growth Capital | W4: 01/14/2026 | Introductory conversation held; John sent story deck, finance-focused deck, and one-pager today. Framed as strategic partner aligned with Scorpius acquisition, revenue expansion, and hypersonics / Golden Dome support. Added as potential strategic partner for board consideration. Awaiting response. | X4: John - Investor Contacts!862 | Y4: Review terms and push decision process | Z4: 2 | AA4: =IF(AC4="Archived",0,ROUND((IF(N4="Tier 1",35,IF(N4="Tier 2",20,8))+IF(C4="Financial Investor",15,IF(C4="Intermediary / Banker",12,8))+IF(L4="Term Sheet / Proposal",25,IF(L4="Engaged",20,IF(L4="Meeting Requested",18,IF(L4="Meeting Held",14,IF(L4="Follow Up",10,5)))))+MIN(Q4,30)+IF(S4="DUE",15,IF(S4="Next 3 Days",8,0))),0)) | AB4: =IF(AND(AC4="Active",OR(N4="Tier 1",N4="Tier 2"),OR(S4="DUE",S4="Next 3 Days")),"YES","") | AC4: =IF(L4="Passed","Archived","Active")
A5: EXOS-0004 | B5: John - Investor Contacts | C5: Financial Investor | D5: Cerberus Capital Management | E5: Frank Bruno | G5: fbruno@cerberus.com | K5: John Quinn | L5: Term Sheet / Proposal | M5: Space / Defense / Aerospace / Advanced Manufacturing | N5: Tier 1 | O5: 45968 | P5: 46023 | Q5: =IF(P5="","",TODAY()-P5) | R5: =IF(OR(L5="Passed",Z5=""),"",P5+Z5) | S5: =IF(OR(R5="",L5="Passed"),"",IF(R5<=TODAY(),"DUE",IF(R5<=TODAY()+3,"Next 3 Days","Later"))) | T5: Meeting scheduled / held | V5: Strategic Partner / Growth Capital | W5: 01/14/2026 | Introductory conversation held; John sent story deck, finance-focused deck, and one-pager today. Framed as strategic partner aligned with Scorpius acquisition, revenue expansion, and hypersonics / Golden Dome support. Added as potential strategic partner for board consideration. Awaiting response. | X5: John - Investor Contacts!861 | Y5: Review terms and push decision process | Z5: 2 | AA5: =IF(AC5="Archived",0,ROUND((IF(N5="Tier 1",35,IF(N5="Tier 2",20,8))+IF(C5="Financial Investor",15,IF(C5="Intermediary / Banker",12,8))+IF(L5="Term Sheet / Proposal",25,IF(L5="Engaged",20,IF(L5="Meeting Requested",18,IF(L5="Meeting Held",14,IF(L5="Follow Up",10,5)))))+MIN(Q5,30)+IF(S5="DUE",15,IF(S5="Next 3 Days",8,0))),0)) | AB5: =IF(AND(AC5="Active",OR(N5="Tier 1",N5="Tier 2"),OR(S5="DUE",S5="Next 3 Days")),"YES","") | AC5: =IF(L5="Passed","Archived","Active")
A6: EXOS-0005 | B6: JQ Follow Up | Term Sheets | C6: Financial Investor | D6: Cerberus Capital Management | E6: Kent (Cerberus Ops) | G6: consult-klietzau@cerberusoperations.com | K6: John Quinn | L6: Term Sheet / Proposal | M6: Space / Defense / Aerospace / Advanced Manufacturing | N6: Tier 1 | P6: 46023 | Q6: =IF(P6="","",TODAY()-P6) | R6: =IF(OR(L6="Passed",Z6=""),"",P6+Z6) | S6: =IF(OR(R6="",L6="Passed"),"",IF(R6<=TODAY(),"DUE",IF(R6<=TODAY()+3,"Next 3 Days","Later"))) | T6: Meeting scheduled / held | V6: Strategic Partner / Growth Capital | W6: Introductory conversation held; John sent story deck, finance-focused deck, and one-pager today. Framed as strategic partner aligned with Scorpius acquisition, revenue expansion, and hypersonics / Golden Dome support. Added as potential strategic partner for board consideration. Awaiting response. | X6: Term Sheets!11 | JQ Follow Up!25 | Y6: Review terms and push decision process | Z6: 2 | AA6: =IF(AC6="Archived",0,ROUND((IF(N6="Tier 1",35,IF(N6="Tier 2",20,8))+IF(C6="Financial Investor",15,IF(C6="Intermediary / Banker",12,8))+IF(L6="Term Sheet / Proposal",25,IF(L6="Engaged",20,IF(L6="Meeting Requested",18,IF(L6="Meeting Held",14,IF(L6="Follow Up",10,5)))))+MIN(Q6,30)+IF(S6="DUE",15,IF(S6="Next 3 Days",8,0))),0)) | AB6: =IF(AND(AC6="Active",OR(N6="Tier 1",N6="Tier 2"),OR(S6="DUE",S6="Next 3 Days")),"YES","") | AC6: =IF(L6="Passed","Archived","Active")
A7: EXOS-0006 | B7: Derek Contacts | JQ Follow Up | Term Sheets | C7: Financial Investor | D7: Cloris Capital Group LLC | E7: Tahmina Khan | F7: CEO | G7: tahmina.investing@gmail.com | H7: hawken@edgewatersg.com; daniel.murillo@edgewatersg.com | K7: John Quinn | L7: Term Sheet / Proposal | M7: Space / Defense / Aerospace / Advanced Manufacturing | N7: Tier 1 | Q7: =IF(P7="","",TODAY()-P7) | R7: =IF(OR(L7="Passed",Z7=""),"",P7+Z7) | S7: =IF(OR(R7="",L7="Passed"),"",IF(R7<=TODAY(),"DUE",IF(R7<=TODAY()+3,"Next 3 Days","Later"))) | T7: Meeting scheduled / held | U7: referred by Dereck | V7: Capital Partner (Equity / Strategic) 2% of transaction | W7: Completed discussions with both ETL and IronGate. No follow-up correspondence received to date. Awaiting next steps or investor feedback. | Investor requested documentation showing revenue for the past three years and indicated interest if trailing 12-month revenue reflects ~$1M. Financial documents sent by John. Awaiting response/feedback. | 11/24 call and materials sent | email outreach has been sent to all | X7: Term Sheets!4 | JQ Follow Up!16 | Derek Contacts!12 | Y7: Review terms and push decision process | Z7: 2 | AA7: =IF(AC7="Archived",0,ROUND((IF(N7="Tier 1",35,IF(N7="Tier 2",20,8))+IF(C7="Financial Investor",15,IF(C7="Intermediary / Banker",12,8))+IF(L7="Term Sheet / Proposal",25,IF(L7="Engaged",20,IF(L7="Meeting Requested",18,IF(L7="Meeting Held",14,IF(L7="Follow Up",10,5)))))+MIN(Q7,30)+IF(S7="DUE",15,IF(S7="Next 3 Days",8,0))),0)) | AB7: =IF(AND(AC7="Active",OR(N7="Tier 1",N7="Tier 2"),OR(S7="DUE",S7="Next 3 Days")),"YES","") | AC7: =IF(L7="Passed","Archived","Active")
A8: EXOS-0007 | B8: Derek Contacts | JQ Follow Up | Term Sheets | C8: Financial Investor | D8: Craft Capital | E8: Brandon Golenda | G8: bgolenda@craftcm.com | H8: alexhamilton@optonline.net; ryanhamilton02@gmail.com | K8: John Quinn | L8: Term Sheet / Proposal | M8: Space / Defense / Aerospace / Advanced Manufacturing | N8: Tier 1 | P8: 46020 | Q8: =IF(P8="","",TODAY()-P8) | R8: =IF(OR(L8="Passed",Z8=""),"",P8+Z8) | S8: =IF(OR(R8="",L8="Passed"),"",IF(R8<=TODAY(),"DUE",IF(R8<=TODAY()+3,"Next 3 Days","Later"))) | T8: Meeting scheduled / held | U8: referred by Dereck | V8: Advisory (Paid) Cost of finance: $30k fixed + 4–8% cash + 8% equity/warrants (if they introduce the capital) How to exclude other funding: The agreement already limits fees to Craft-introduced investors only, but You should formalize exclusions in writing immediately to avoid disputes. | W8: Advisory offer contingent on $30K fee. We chose not to proceed; parked. | $30K Investment bank enagement $10k/mo for 3 months advisor only. no funds. | X8: Term Sheets!21 | JQ Follow Up!9 | Derek Contacts!13 | Y8: Review terms and push decision process | Z8: 2 | AA8: =IF(AC8="Archived",0,ROUND((IF(N8="Tier 1",35,IF(N8="Tier 2",20,8))+IF(C8="Financial Investor",15,IF(C8="Intermediary / Banker",12,8))+IF(L8="Term Sheet / Proposal",25,IF(L8="Engaged",20,IF(L8="Meeting Requested",18,IF(L8="Meeting Held",14,IF(L8="Follow Up",10,5)))))+MIN(Q8,30)+IF(S8="DUE",15,IF(S8="Next 3 Days",8,0))),0)) | AB8: =IF(AND(AC8="Active",OR(N8="Tier 1",N8="Tier 2"),OR(S8="DUE",S8="Next 3 Days")),"YES","") | AC8: =IF(L8="Passed","Archived","Active")
A9: EXOS-0008 | B9: Term Sheets | C9: Financial Investor | D9: DelMorgan & Co | E9: RJ Mollen | G9: rjm@delmorganco.com | K9: John Quinn | L9: Term Sheet / Proposal | M9: Space / Defense / Aerospace / Advanced Manufacturing | N9: Tier 1 | P9: 46037 | Q9: =IF(P9="","",TODAY()-P9) | R9: =IF(OR(L9="Passed",Z9=""),"",P9+Z9) | S9: =IF(OR(R9="",L9="Passed"),"",IF(R9<=TODAY(),"DUE",IF(R9<=TODAY()+3,"Next 3 Days","Later"))) | T9: Meeting scheduled / held | V9: Strategic Advisory / Infrastructure & Capital Access | W9: Talked and rejected offer- RJ proposed two alternative advisory paths outside the DelMorgan framework: (1) Fast Space infrastructure and asset monetization strategy, and (2) Gleam Consulting advisory + investor introductions tied to a $10M raise. Fee-based advisory with equity success bonuses. Not aligned with current priorities; documented for reference. | X9: Term Sheets!24 | Y9: Review terms and push decision process | Z9: 2 | AA9: =IF(AC9="Archived",0,ROUND((IF(N9="Tier 1",35,IF(N9="Tier 2",20,8))+IF(C9="Financial Investor",15,IF(C9="Intermediary / Banker",12,8))+IF(L9="Term Sheet / Proposal",25,IF(L9="Engaged",20,IF(L9="Meeting Requested",18,IF(L9="Meeting Held",14,IF(L9="Follow Up",10,5)))))+MIN(Q9,30)+IF(S9="DUE",15,IF(S9="Next 3 Days",8,0))),0)) | AB9: =IF(AND(AC9="Active",OR(N9="Tier 1",N9="Tier 2"),OR(S9="DUE",S9="Next 3 Days")),"YES","") | AC9: =IF(L9="Passed","Archived","Active")
A10: EXOS-0009 | B10: Term Sheets | C10: Financial Investor | D10: InvestFortuna | E10: Sean Bromley | G10: sbromley@investfortuna.com | H10: veghtesad@investfortuna.com | K10: John Quinn | L10: Term Sheet / Proposal | M10: Space / Defense / Aerospace / Advanced Manufacturing | N10: Tier 1 | P10: 46023 | Q10: =IF(P10="","",TODAY()-P10) | R10: =IF(OR(L10="Passed",Z10=""),"",P10+Z10) | S10: =IF(OR(R10="",L10="Passed"),"",IF(R10<=TODAY(),"DUE",IF(R10<=TODAY()+3,"Next 3 Days","Later"))) | T10: Meeting scheduled / held | V10: Advisory + Bridge / IPO Path | W10: The .4 term sheet, as drafted, is not registrable, not exchange-compliant, and not defensible for directors. It can be salvaged only through structural changes that align it with industry norms that they rejected. | 01/15/2026 | Fortuna proposed an IPO-led advisory structure including a warrant offering, $5M minimum bridge financing (convertible at significant discount), and a $15M IPO financing, with substantial embedded dilution and control provisions. EXOS submitted a formal counter-term sheet replacing discounted instruments and automatic vesting with performance-based earn-out equity tied to post-IPO share price and market cap milestones, preserving a clean cap table and fiduciary compliance. Negotiations ongoing; awaiting Fortuna response. | X10: Term Sheets!16 | Y10: Review terms and push decision process | Z10: 2 | AA10: =IF(AC10="Archived",0,ROUND((IF(N10="Tier 1",35,IF(N10="Tier 2",20,8))+IF(C10="Financial Investor",15,IF(C10="Intermediary / Banker",12,8))+IF(L10="Term Sheet / Proposal",25,IF(L10="Engaged",20,IF(L10="Meeting Requested",18,IF(L10="Meeting Held",14,IF(L10="Follow Up",10,5)))))+MIN(Q10,30)+IF(S10="DUE",15,IF(S10="Next 3 Days",8,0))),0)) | AB10: =IF(AND(AC10="Active",OR(N10="Tier 1",N10="Tier 2"),OR(S10="DUE",S10="Next 3 Days")),"YES","") | AC10: =IF(L10="Passed","Archived","Active")
A11: EXOS-0010 | B11: Term Sheets | C11: Financial Investor | D11: Pickwick Capital | E11: Crescent Varrone | G11: varronec@pickwickcapital.com | H11: alvarezd@pickwickcapital.com; sauterm@pickwickcapital.com | K11: John Quinn | L11: Term Sheet / Proposal | M11: Space / Defense / Aerospace / Advanced Manufacturing | N11: Tier 1 | P11: 46031 | Q11: =IF(P11="","",TODAY()-P11) | R11: =IF(OR(L11="Passed",Z11=""),"",P11+Z11) | S11: =IF(OR(R11="",L11="Passed"),"",IF(R11<=TODAY(),"DUE",IF(R11<=TODAY()+3,"Next 3 Days","Later"))) | T11: Meeting scheduled / held | V11: Capital Partner (Equity / Strategic) $15k/ mon 6 Months | W11: Active discussions underway. Pickwick has expressed interest; no term sheet yet. John had producitive meeting on 1/9. | 01/15/2026 | X11: Term Sheets!15 | Y11: Review terms and push decision process | Z11: 2 | AA11: =IF(AC11="Archived",0,ROUND((IF(N11="Tier 1",35,IF(N11="Tier 2",20,8))+IF(C11="Financial Investor",15,IF(C11="Intermediary / Banker",12,8))+IF(L11="Term Sheet / Proposal",25,IF(L11="Engaged",20,IF(L11="Meeting Requested",18,IF(L11="Meeting Held",14,IF(L11="Follow Up",10,5)))))+MIN(Q11,30)+IF(S11="DUE",15,IF(S11="Next 3 Days",8,0))),0)) | AB11: =IF(AND(AC11="Active",OR(N11="Tier 1",N11="Tier 2"),OR(S11="DUE",S11="Next 3 Days")),"YES","") | AC11: =IF(L11="Passed","Archived","Active")
A12: EXOS-0011 | B12: JQ Follow Up | C12: Financial Investor | D12: Pickwick Capital | E12: Crescent Varrone | G12: alvarezd@pickwickcapital.com | H12: sauterm@pickwickcapital.com | I12: Capital Partner (Equity / Strategic) | K12: John Quinn | L12: Term Sheet / Proposal | M12: Space / Defense / Aerospace / Advanced Manufacturing | N12: Tier 1 | P12: 46031 | Q12: =IF(P12="","",TODAY()-P12) | R12: =IF(OR(L12="Passed",Z12=""),"",P12+Z12) | S12: =IF(OR(R12="",L12="Passed"),"",IF(R12<=TODAY(),"DUE",IF(R12<=TODAY()+3,"Next 3 Days","Later"))) | T12: Meeting scheduled / held | U12: varronec@pickwickcapital.com | V12: Capital Partner (Equity / Strategic) $15k/ mon 6 Months | W12: Active discussions underway. Pickwick has expressed interest; no term sheet yet. John had producitive meeting on 1/9. | 01/15/2026 | X12: JQ Follow Up!29 | Y12: Review terms and push decision process | Z12: 2 | AA12: =IF(AC12="Archived",0,ROUND((IF(N12="Tier 1",35,IF(N12="Tier 2",20,8))+IF(C12="Financial Investor",15,IF(C12="Intermediary / Banker",12,8))+IF(L12="Term Sheet / Proposal",25,IF(L12="Engaged",20,IF(L12="Meeting Requested",18,IF(L12="Meeting Held",14,IF(L12="Follow Up",10,5)))))+MIN(Q12,30)+IF(S12="DUE",15,IF(S12="Next 3 Days",8,0))),0)) | AB12: =IF(AND(AC12="Active",OR(N12="Tier 1",N12="Tier 2"),OR(S12="DUE",S12="Next 3 Days")),"YES","") | AC12: =IF(L12="Passed","Archived","Active")
A13: EXOS-0012 | B13: Term Sheets | C13: Intermediary / Banker | D13: Sunbelt Dallas Metro | E13: Bill Nicholson | G13: bnicholson@sunbeltnetwork.com | K13: John Quinn | L13: Term Sheet / Proposal | M13: Capital raise support / placement | N13: Tier 1 | P13: 46083 | Q13: =IF(P13="","",TODAY()-P13) | R13: =IF(OR(L13="Passed",Z13=""),"",P13+Z13) | S13: =IF(OR(R13="",L13="Passed"),"",IF(R13<=TODAY(),"DUE",IF(R13<=TODAY()+3,"Next 3 Days","Later"))) | T13: Meeting scheduled / held | V13: Proposed intermediary engagement (retainer + success fee model under discussion; Board requesting performance-based structure) | W13: Sunbelt inquired about including a retainer amount in the Engagement Letter. John responded that the EXOS Board is unlikely to approve another open-ended retainer structure due to prior experiences with retainers that did not yield measurable outcomes. The Board is prioritizing: Clearly defined deliverables Performance-aligned compensation Objective execution milestones Defined transaction targets SEC-compliant structure (broker-dealer participation as required) John encouraged Sunbelt to propose a performance-based framework (reduced/deferred retainer, milestone-triggered payments, or primarily success-fee based on capital secured). Bill acknowledged and is coordinating internally to revise the proposal. He requested timing of the next Board meeting. Status: Awaiting revised engagement structure from Sunbelt for Board review. | sent email letting him know board doesn't want to pat retainer fees | X13: Term Sheets!9 | Y13: Review terms and push decision process | Z13: 2 | AA13: =IF(AC13="Archived",0,ROUND((IF(N13="Tier 1",35,IF(N13="Tier 2",20,8))+IF(C13="Financial Investor",15,IF(C13="Intermediary / Banker",12,8))+IF(L13="Term Sheet / Proposal",25,IF(L13="Engaged",20,IF(L13="Meeting Requested",18,IF(L13="Meeting Held",14,IF(L13="Follow Up",10,5)))))+MIN(Q13,30)+IF(S13="DUE",15,IF(S13="Next 3 Days",8,0))),0)) | AB13: =IF(AND(AC13="Active",OR(N13="Tier 1",N13="Tier 2"),OR(S13="DUE",S13="Next 3 Days")),"YES","") | AC13: =IF(L13="Passed","Archived","Active")
A14: EXOS-0013 | B14: JQ Follow Up | Term Sheets | C14: Financial Investor | D14: US Capital | E14: Ashley Curless | G14: acurless@uscapital.com | H14: csims@uscapital.com; bchristopher@uscapital.com; mjlevas@uscapital.com; jhgonzalez@uscapital.com; mcohen@uscapital.com | K14: John Quinn | L14: Term Sheet / Proposal | M14: Space / Defense / Aerospace / Advanced Manufacturing | N14: Tier 1 | P14: 45986 | Q14: =IF(P14="","",TODAY()-P14) | R14: =IF(OR(L14="Passed",Z14=""),"",P14+Z14) | S14: =IF(OR(R14="",L14="Passed"),"",IF(R14<=TODAY(),"DUE",IF(R14<=TODAY()+3,"Next 3 Days","Later"))) | T14: Meeting scheduled / held | U14: referred by Dereck | V14: Capital Raise (Equity / Convertible) | W14: Terms shared; fee-heavy engagement model. $120K + 8% $920K | 01/15/2026 | Submitted formal equity financing proposal for up to $10M. Structure includes 8% cash banking fee, 8% warrant coverage, and $120K upfront compliance/diligence/distribution fees. Process is heavily intermediary-led with broad investor marketing and placement focus. High fees and limited strategic value relative to capital efficiency; not a preferred path at this stage. | in data room ; sent terms but are they a strategic enough partner? | X14: Term Sheets!19 | JQ Follow Up!20 | Y14: Review terms and push decision process | Z14: 2 | AA14: =IF(AC14="Archived",0,ROUND((IF(N14="Tier 1",35,IF(N14="Tier 2",20,8))+IF(C14="Financial Investor",15,IF(C14="Intermediary / Banker",12,8))+IF(L14="Term Sheet / Proposal",25,IF(L14="Engaged",20,IF(L14="Meeting Requested",18,IF(L14="Meeting Held",14,IF(L14="Follow Up",10,5)))))+MIN(Q14,30)+IF(S14="DUE",15,IF(S14="Next 3 Days",8,0))),0)) | AB14: =IF(AND(AC14="Active",OR(N14="Tier 1",N14="Tier 2"),OR(S14="DUE",S14="Next 3 Days")),"YES","") | AC14: =IF(L14="Passed","Archived","Active")
A15: EXOS-0014 | B15: Derek Contacts | C15: Intermediary / Banker | D15: US Capital | E15: Mitch; Steve Wilburn; Charles Sims | F15: CEO | G15: mambe@uscapital.com | H15: csims@craftcm.com | K15: John Quinn | L15: Term Sheet / Proposal | M15: Capital raise support / placement | N15: Tier 1 | P15: 45986 | Q15: =IF(P15="","",TODAY()-P15) | R15: =IF(OR(L15="Passed",Z15=""),"",P15+Z15) | S15: =IF(OR(R15="",L15="Passed"),"",IF(R15<=TODAY(),"DUE",IF(R15<=TODAY()+3,"Next 3 Days","Later"))) | T15: Meeting scheduled / held | V15: Capital Raise (Equity / Convertible) | W15: Terms shared; fee-heavy engagement model. $120K + 8% $920K | 01/15/2026 | Submitted formal equity financing proposal for up to $10M. Structure includes 8% cash banking fee, 8% warrant coverage, and $120K upfront compliance/diligence/distribution fees. Process is heavily intermediary-led with broad investor marketing and placement focus. High fees and limited strategic value relative to capital efficiency; not a preferred path at this stage. | X15: Derek Contacts!57 | Y15: Review terms and push decision process | Z15: 2 | AA15: =IF(AC15="Archived",0,ROUND((IF(N15="Tier 1",35,IF(N15="Tier 2",20,8))+IF(C15="Financial Investor",15,IF(C15="Intermediary / Banker",12,8))+IF(L15="Term Sheet / Proposal",25,IF(L15="Engaged",20,IF(L15="Meeting Requested",18,IF(L15="Meeting Held",14,IF(L15="Follow Up",10,5)))))+MIN(Q15,30)+IF(S15="DUE",15,IF(S15="Next 3 Days",8,0))),0)) | AB15: =IF(AND(AC15="Active",OR(N15="Tier 1",N15="Tier 2"),OR(S15="DUE",S15="Next 3 Days")),"YES","") | AC15: =IF(L15="Passed","Archived","Active")
A16: EXOS-0015 | B16: Term Sheets | C16: Other / Review | D16: Black in Play | K16: John Quinn | L16: Engaged | M16: Needs qualification | N16: Tier 1 | Q16: =IF(P16="","",TODAY()-P16) | R16: =IF(OR(L16="Passed",Z16=""),"",P16+Z16) | S16: =IF(OR(R16="",L16="Passed"),"",IF(R16<=TODAY(),"DUE",IF(R16<=TODAY()+3,"Next 3 Days","Later"))) | T16: Meeting scheduled / held | X16: Term Sheets!28 | Y16: Advance diligence / proposal discussion | Z16: 5 | AA16: =IF(AC16="Archived",0,ROUND((IF(N16="Tier 1",35,IF(N16="Tier 2",20,8))+IF(C16="Financial Investor",15,IF(C16="Intermediary / Banker",12,8))+IF(L16="Term Sheet / Proposal",25,IF(L16="Engaged",20,IF(L16="Meeting Requested",18,IF(L16="Meeting Held",14,IF(L16="Follow Up",10,5)))))+MIN(Q16,30)+IF(S16="DUE",15,IF(S16="Next 3 Days",8,0))),0)) | AB16: =IF(AND(AC16="Active",OR(N16="Tier 1",N16="Tier 2"),OR(S16="DUE",S16="Next 3 Days")),"YES","") | AC16: =IF(L16="Passed","Archived","Active")
A17: EXOS-0016 | B17: Term Sheets | C17: Other / Review | D17: Blue under contract engagement | K17: John Quinn | L17: Engaged | M17: Needs qualification | N17: Tier 1 | Q17: =IF(P17="","",TODAY()-P17) | R17: =IF(OR(L17="Passed",Z17=""),"",P17+Z17) | S17: =IF(OR(R17="",L17="Passed"),"",IF(R17<=TODAY(),"DUE",IF(R17<=TODAY()+3,"Next 3 Days","Later"))) | T17: Meeting scheduled / held | X17: Term Sheets!29 | Y17: Advance diligence / proposal discussion | Z17: 5 | AA17: =IF(AC17="Archived",0,ROUND((IF(N17="Tier 1",35,IF(N17="Tier 2",20,8))+IF(C17="Financial Investor",15,IF(C17="Intermediary / Banker",12,8))+IF(L17="Term Sheet / Proposal",25,IF(L17="Engaged",20,IF(L17="Meeting Requested",18,IF(L17="Meeting Held",14,IF(L17="Follow Up",10,5)))))+MIN(Q17,30)+IF(S17="DUE",15,IF(S17="Next 3 Days",8,0))),0)) | AB17: =IF(AND(AC17="Active",OR(N17="Tier 1",N17="Tier 2"),OR(S17="DUE",S17="Next 3 Days")),"YES","") | AC17: =IF(L17="Passed","Archived","Active")
A18: EXOS-0017 | B18: JQ Follow Up | John - Investor Contacts | Term Sheets | C18: Financial Investor | D18: Concord Ventures | E18: Salim Dada | G18: salim.d@concordventuresinc.com | H18: ted.b@concordventuresinc.com; safia.d@concordventuresinc.com | K18: John Quinn | L18: Engaged | M18: Space / Defense / Aerospace / Advanced Manufacturing | N18: Tier 1 | O18: 45950 | P18: 45958 | Q18: =IF(P18="","",TODAY()-P18) | R18: =IF(OR(L18="Passed",Z18=""),"",P18+Z18) | S18: =IF(OR(R18="",L18="Passed"),"",IF(R18<=TODAY(),"DUE",IF(R18<=TODAY()+3,"Next 3 Days","Later"))) | T18: Meeting scheduled / held | V18: Sell-Side / Marketing Advisory (Exclusive) | W18: Revised agreement sent; no follow-up since; inactive. | offer for $2500/month for 3 months plan | Offer for $2500/month to run program | X18: Term Sheets!23 | JQ Follow Up!11 | John - Investor Contacts!899 | Y18: Advance diligence / proposal discussion | Z18: 5 | AA18: =IF(AC18="Archived",0,ROUND((IF(N18="Tier 1",35,IF(N18="Tier 2",20,8))+IF(C18="Financial Investor",15,IF(C18="Intermediary / Banker",12,8))+IF(L18="Term Sheet / Proposal",25,IF(L18="Engaged",20,IF(L18="Meeting Requested",18,IF(L18="Meeting Held",14,IF(L18="Follow Up",10,5)))))+MIN(Q18,30)+IF(S18="DUE",15,IF(S18="Next 3 Days",8,0))),0)) | AB18: =IF(AND(AC18="Active",OR(N18="Tier 1",N18="Tier 2"),OR(S18="DUE",S18="Next 3 Days")),"YES","") | AC18: =IF(L18="Passed","Archived","Active")
A19: EXOS-0018 | B19: John - Investor Contacts | C19: Financial Investor | D19: Concord Ventures | E19: Salim Dada | K19: John Quinn | L19: Engaged | M19: Space / Defense / Aerospace / Advanced Manufacturing | N19: Tier 1 | O19: 45917 | P19: 45958 | Q19: =IF(P19="","",TODAY()-P19) | R19: =IF(OR(L19="Passed",Z19=""),"",P19+Z19) | S19: =IF(OR(R19="",L19="Passed"),"",IF(R19<=TODAY(),"DUE",IF(R19<=TODAY()+3,"Next 3 Days","Later"))) | T19: Meeting scheduled / held | U19: Salim Dada, Safia Dada | V19: Sell-Side / Marketing Advisory (Exclusive) | W19: Revised agreement sent; no follow-up since; inactive. | X19: John - Investor Contacts!3 | Y19: Advance diligence / proposal discussion | Z19: 5 | AA19: =IF(AC19="Archived",0,ROUND((IF(N19="Tier 1",35,IF(N19="Tier 2",20,8))+IF(C19="Financial Investor",15,IF(C19="Intermediary / Banker",12,8))+IF(L19="Term Sheet / Proposal",25,IF(L19="Engaged",20,IF(L19="Meeting Requested",18,IF(L19="Meeting Held",14,IF(L19="Follow Up",10,5)))))+MIN(Q19,30)+IF(S19="DUE",15,IF(S19="Next 3 Days",8,0))),0)) | AB19: =IF(AND(AC19="Active",OR(N19="Tier 1",N19="Tier 2"),OR(S19="DUE",S19="Next 3 Days")),"YES","") | AC19: =IF(L19="Passed","Archived","Active")
A20: EXOS-0019 | B20: JQ Follow Up | Term Sheets | C20: Other / Review | D20: CounterFlow Solutions | E20: Dan Garretson | G20: dgarretson@counterflowsolutions.com | K20: John Quinn | L20: Engaged | M20: Needs qualification | N20: Tier 1 | P20: 46024 | Q20: =IF(P20="","",TODAY()-P20) | R20: =IF(OR(L20="Passed",Z20=""),"",P20+Z20) | S20: =IF(OR(R20="",L20="Passed"),"",IF(R20<=TODAY(),"DUE",IF(R20<=TODAY()+3,"Next 3 Days","Later"))) | T20: Meeting scheduled / held | V20: Strategic Advisory (Narrative / Framing) | W20: Proposed short sprint to reframe EXOS + Scorpius narrative. Decision pending. | 12/23 john sent follow up reply | Costs for wrong scope | X20: Term Sheets!20 | JQ Follow Up!19 | Y20: Advance diligence / proposal discussion | Z20: 5 | AA20: =IF(AC20="Archived",0,ROUND((IF(N20="Tier 1",35,IF(N20="Tier 2",20,8))+IF(C20="Financial Investor",15,IF(C20="Intermediary / Banker",12,8))+IF(L20="Term Sheet / Proposal",25,IF(L20="Engaged",20,IF(L20="Meeting Requested",18,IF(L20="Meeting Held",14,IF(L20="Follow Up",10,5)))))+MIN(Q20,30)+IF(S20="DUE",15,IF(S20="Next 3 Days",8,0))),0)) | AB20: =IF(AND(AC20="Active",OR(N20="Tier 1",N20="Tier 2"),OR(S20="DUE",S20="Next 3 Days")),"YES","") | AC20: =IF(L20="Passed","Archived","Active")
A21: EXOS-0020 | B21: Term Sheets | C21: Financial Investor | D21: CrossRoads Capital | E21: Rchard Phillips | K21: John Quinn | L21: Engaged | M21: Space / Defense / Aerospace / Advanced Manufacturing | N21: Tier 1 | P21: 46038 | Q21: =IF(P21="","",TODAY()-P21) | R21: =IF(OR(L21="Passed",Z21=""),"",P21+Z21) | S21: =IF(OR(R21="",L21="Passed"),"",IF(R21<=TODAY(),"DUE",IF(R21<=TODAY()+3,"Next 3 Days","Later"))) | T21: Meeting scheduled / held | V21: CTD acquisition or JV opportunity | W21: have new 18,000 sf facility just North of Denver Co. $3-4M to scale | X21: Term Sheets!17 | Y21: Advance diligence / proposal discussion | Z21: 5 | AA21: =IF(AC21="Archived",0,ROUND((IF(N21="Tier 1",35,IF(N21="Tier 2",20,8))+IF(C21="Financial Investor",15,IF(C21="Intermediary / Banker",12,8))+IF(L21="Term Sheet / Proposal",25,IF(L21="Engaged",20,IF(L21="Meeting Requested",18,IF(L21="Meeting Held",14,IF(L21="Follow Up",10,5)))))+MIN(Q21,30)+IF(S21="DUE",15,IF(S21="Next 3 Days",8,0))),0)) | AB21: =IF(AND(AC21="Active",OR(N21="Tier 1",N21="Tier 2"),OR(S21="DUE",S21="Next 3 Days")),"YES","") | AC21: =IF(L21="Passed","Archived","Active")
A22: EXOS-0021 | B22: John - Investor Contacts | C22: Financial Investor | D22: Crossroads Capital | E22: Andrew J. Buchholtz and David Ford | G22: andy@abuchholtz.com | H22: rphillips@crossroadscapitaldc.com; df@silverpeakib.com | K22: John Quinn | L22: Engaged | M22: Space / Defense / Aerospace / Advanced Manufacturing | N22: Tier 1 | O22: 45846 | P22: 46038 | Q22: =IF(P22="","",TODAY()-P22) | R22: =IF(OR(L22="Passed",Z22=""),"",P22+Z22) | S22: =IF(OR(R22="",L22="Passed"),"",IF(R22<=TODAY(),"DUE",IF(R22<=TODAY()+3,"Next 3 Days","Later"))) | T22: Meeting scheduled / held | U22: Richard Phillips | V22: CTD acquisition or JV opportunity | W22: Sent you the ELA draft this morning — let me if you didn’t receive or if you have any questions. We can schedule another call if you’d like to review together. | have new 18,000 sf facility just North of Denver Co. $3-4M to scale | had a call, sent deck | X22: John - Investor Contacts!4 | John - Investor Contacts!358 | Y22: Advance diligence / proposal discussion | Z22: 5 | AA22: =IF(AC22="Archived",0,ROUND((IF(N22="Tier 1",35,IF(N22="Tier 2",20,8))+IF(C22="Financial Investor",15,IF(C22="Intermediary / Banker",12,8))+IF(L22="Term Sheet / Proposal",25,IF(L22="Engaged",20,IF(L22="Meeting Requested",18,IF(L22="Meeting Held",14,IF(L22="Follow Up",10,5)))))+MIN(Q22,30)+IF(S22="DUE",15,IF(S22="Next 3 Days",8,0))),0)) | AB22: =IF(AND(AC22="Active",OR(N22="Tier 1",N22="Tier 2"),OR(S22="DUE",S22="Next 3 Days")),"YES","") | AC22: =IF(L22="Passed","Archived","Active")
A23: EXOS-0022 | B23: Term Sheets | C23: Financial Investor | D23: DC Finance | E23: Morris | K23: John Quinn | L23: Engaged | M23: Space / Defense / Aerospace / Advanced Manufacturing | N23: Tier 1 | Q23: =IF(P23="","",TODAY()-P23) | R23: =IF(OR(L23="Passed",Z23=""),"",P23+Z23) | S23: =IF(OR(R23="",L23="Passed"),"",IF(R23<=TODAY(),"DUE",IF(R23<=TODAY()+3,"Next 3 Days","Later"))) | T23: Meeting scheduled / held | V23: 10K or 30k to put you in a room with 12 Family offices | X23: Term Sheets!18 | Y23: Advance diligence / proposal discussion | Z23: 5 | AA23: =IF(AC23="Archived",0,ROUND((IF(N23="Tier 1",35,IF(N23="Tier 2",20,8))+IF(C23="Financial Investor",15,IF(C23="Intermediary / Banker",12,8))+IF(L23="Term Sheet / Proposal",25,IF(L23="Engaged",20,IF(L23="Meeting Requested",18,IF(L23="Meeting Held",14,IF(L23="Follow Up",10,5)))))+MIN(Q23,30)+IF(S23="DUE",15,IF(S23="Next 3 Days",8,0))),0)) | AB23: =IF(AND(AC23="Active",OR(N23="Tier 1",N23="Tier 2"),OR(S23="DUE",S23="Next 3 Days")),"YES","") | AC23: =IF(L23="Passed","Archived","Active")
A24: EXOS-0023 | B24: Term Sheets | C24: Financial Investor | D24: Digital Asset Management | E24: Juan Lorenzana | K24: John Quinn | L24: Engaged | M24: Space / Defense / Aerospace / Advanced Manufacturing | N24: Tier 1 | P24: 46059 | Q24: =IF(P24="","",TODAY()-P24) | R24: =IF(OR(L24="Passed",Z24=""),"",P24+Z24) | S24: =IF(OR(R24="",L24="Passed"),"",IF(R24<=TODAY(),"DUE",IF(R24<=TODAY()+3,"Next 3 Days","Later"))) | T24: Meeting scheduled / held | V24: no feedback on SEC filing AUM record | W24: $30K refundable. Fund with hedge of Gold metals real estate etc. | X24: Term Sheets!5 | Y24: Advance diligence / proposal discussion | Z24: 5 | AA24: =IF(AC24="Archived",0,ROUND((IF(N24="Tier 1",35,IF(N24="Tier 2",20,8))+IF(C24="Financial Investor",15,IF(C24="Intermediary / Banker",12,8))+IF(L24="Term Sheet / Proposal",25,IF(L24="Engaged",20,IF(L24="Meeting Requested",18,IF(L24="Meeting Held",14,IF(L24="Follow Up",10,5)))))+MIN(Q24,30)+IF(S24="DUE",15,IF(S24="Next 3 Days",8,0))),0)) | AB24: =IF(AND(AC24="Active",OR(N24="Tier 1",N24="Tier 2"),OR(S24="DUE",S24="Next 3 Days")),"YES","") | AC24: =IF(L24="Passed","Archived","Active")
A25: EXOS-0024 | B25: Term Sheets | C25: Other / Review | D25: Green- costs | K25: John Quinn | L25: Engaged | M25: Needs qualification | N25: Tier 1 | Q25: =IF(P25="","",TODAY()-P25) | R25: =IF(OR(L25="Passed",Z25=""),"",P25+Z25) | S25: =IF(OR(R25="",L25="Passed"),"",IF(R25<=TODAY(),"DUE",IF(R25<=TODAY()+3,"Next 3 Days","Later"))) | T25: Meeting scheduled / held | X25: Term Sheets!27 | Y25: Advance diligence / proposal discussion | Z25: 5 | AA25: =IF(AC25="Archived",0,ROUND((IF(N25="Tier 1",35,IF(N25="Tier 2",20,8))+IF(C25="Financial Investor",15,IF(C25="Intermediary / Banker",12,8))+IF(L25="Term Sheet / Proposal",25,IF(L25="Engaged",20,IF(L25="Meeting Requested",18,IF(L25="Meeting Held",14,IF(L25="Follow Up",10,5)))))+MIN(Q25,30)+IF(S25="DUE",15,IF(S25="Next 3 Days",8,0))),0)) | AB25: =IF(AND(AC25="Active",OR(N25="Tier 1",N25="Tier 2"),OR(S25="DUE",S25="Next 3 Days")),"YES","") | AC25: =IF(L25="Passed","Archived","Active")
A26: EXOS-0025 | B26: Term Sheets | C26: Other / Review | D26: Ivy Asset Management | E26: Chris Roberts "Christopher Virginia Roberts" | G26: chrisr@ivyassetmngmt.com | K26: John Quinn | L26: Engaged | M26: Needs qualification | N26: Tier 1 | Q26: =IF(P26="","",TODAY()-P26) | R26: =IF(OR(L26="Passed",Z26=""),"",P26+Z26) | S26: =IF(OR(R26="",L26="Passed"),"",IF(R26<=TODAY(),"DUE",IF(R26<=TODAY()+3,"Next 3 Days","Later"))) | T26: Meeting scheduled / held | X26: Term Sheets!13 | Y26: Advance diligence / proposal discussion | Z26: 5 | AA26: =IF(AC26="Archived",0,ROUND((IF(N26="Tier 1",35,IF(N26="Tier 2",20,8))+IF(C26="Financial Investor",15,IF(C26="Intermediary / Banker",12,8))+IF(L26="Term Sheet / Proposal",25,IF(L26="Engaged",20,IF(L26="Meeting Requested",18,IF(L26="Meeting Held",14,IF(L26="Follow Up",10,5)))))+MIN(Q26,30)+IF(S26="DUE",15,IF(S26="Next 3 Days",8,0))),0)) | AB26: =IF(AND(AC26="Active",OR(N26="Tier 1",N26="Tier 2"),OR(S26="DUE",S26="Next 3 Days")),"YES","") | AC26: =IF(L26="Passed","Archived","Active")
A27: EXOS-0026 | B27: JQ Follow Up | Term Sheets | C27: Financial Investor | D27: Odeon Capital | E27: Eric Gomberg | G27: egomberg@odeoncap.com | K27: John Quinn | L27: Engaged | M27: Space / Defense / Aerospace / Advanced Manufacturing | N27: Tier 1 | P27: 46028 | Q27: =IF(P27="","",TODAY()-P27) | R27: =IF(OR(L27="Passed",Z27=""),"",P27+Z27) | S27: =IF(OR(R27="",L27="Passed"),"",IF(R27<=TODAY(),"DUE",IF(R27<=TODAY()+3,"Next 3 Days","Later"))) | T27: Meeting scheduled / held | V27: Capital Discussion | W27: MNDA + data room sent Dec 17. No response prior to year-end. Follow-up email sent today. | 01/15/2026 | 1. Reduced Retainer of $30,000 Upfront. 2. Success Fee of $400,000 at the back end. We will credit the $30K Retainer back at the end upon a successful completion. 3. Any reasonable travel authorized by the client in advance of any travel. Please let us know if this is okay, then we can proceed with the detailed proposal/engagement letter. Regards, Bill Bill Nicholson, MBA, M&AMI®, CM&AA® | X27: Term Sheets!7 | JQ Follow Up!8 | Y27: Advance diligence / proposal discussion | Z27: 5 | AA27: =IF(AC27="Archived",0,ROUND((IF(N27="Tier 1",35,IF(N27="Tier 2",20,8))+IF(C27="Financial Investor",15,IF(C27="Intermediary / Banker",12,8))+IF(L27="Term Sheet / Proposal",25,IF(L27="Engaged",20,IF(L27="Meeting Requested",18,IF(L27="Meeting Held",14,IF(L27="Follow Up",10,5)))))+MIN(Q27,30)+IF(S27="DUE",15,IF(S27="Next 3 Days",8,0))),0)) | AB27: =IF(AND(AC27="Active",OR(N27="Tier 1",N27="Tier 2"),OR(S27="DUE",S27="Next 3 Days")),"YES","") | AC27: =IF(L27="Passed","Archived","Active")
A28: EXOS-0027 | B28: Term Sheets | C28: Other / Review | D28: Red dropped | K28: John Quinn | L28: Engaged | M28: Needs qualification | N28: Tier 1 | Q28: =IF(P28="","",TODAY()-P28) | R28: =IF(OR(L28="Passed",Z28=""),"",P28+Z28) | S28: =IF(OR(R28="",L28="Passed"),"",IF(R28<=TODAY(),"DUE",IF(R28<=TODAY()+3,"Next 3 Days","Later"))) | T28: Meeting scheduled / held | X28: Term Sheets!26 | Y28: Advance diligence / proposal discussion | Z28: 5 | AA28: =IF(AC28="Archived",0,ROUND((IF(N28="Tier 1",35,IF(N28="Tier 2",20,8))+IF(C28="Financial Investor",15,IF(C28="Intermediary / Banker",12,8))+IF(L28="Term Sheet / Proposal",25,IF(L28="Engaged",20,IF(L28="Meeting Requested",18,IF(L28="Meeting Held",14,IF(L28="Follow Up",10,5)))))+MIN(Q28,30)+IF(S28="DUE",15,IF(S28="Next 3 Days",8,0))),0)) | AB28: =IF(AND(AC28="Active",OR(N28="Tier 1",N28="Tier 2"),OR(S28="DUE",S28="Next 3 Days")),"YES","") | AC28: =IF(L28="Passed","Archived","Active")
A29: EXOS-0028 | B29: Term Sheets | C29: Financial Investor | D29: Ricci Global Partners | E29: Riccardo Ricci | G29: riccardo@riccicapitalpartners.com | K29: John Quinn | L29: Engaged | M29: Space / Defense / Aerospace / Advanced Manufacturing | N29: Tier 1 | P29: 46028 | Q29: =IF(P29="","",TODAY()-P29) | R29: =IF(OR(L29="Passed",Z29=""),"",P29+Z29) | S29: =IF(OR(R29="",L29="Passed"),"",IF(R29<=TODAY(),"DUE",IF(R29<=TODAY()+3,"Next 3 Days","Later"))) | T29: Meeting scheduled / held | V29: Capital Partner (Equity / Strategic) | W29: MNDA executed and data room shared. Ricci requested finance working session and followed up again today to move forward | 01/15/2026 | 03/13/2026 | X29: Term Sheets!10 | Y29: Advance diligence / proposal discussion | Z29: 5 | AA29: =IF(AC29="Archived",0,ROUND((IF(N29="Tier 1",35,IF(N29="Tier 2",20,8))+IF(C29="Financial Investor",15,IF(C29="Intermediary / Banker",12,8))+IF(L29="Term Sheet / Proposal",25,IF(L29="Engaged",20,IF(L29="Meeting Requested",18,IF(L29="Meeting Held",14,IF(L29="Follow Up",10,5)))))+MIN(Q29,30)+IF(S29="DUE",15,IF(S29="Next 3 Days",8,0))),0)) | AB29: =IF(AND(AC29="Active",OR(N29="Tier 1",N29="Tier 2"),OR(S29="DUE",S29="Next 3 Days")),"YES","") | AC29: =IF(L29="Passed","Archived","Active")
A30: EXOS-0029 | B30: JQ Follow Up | C30: Financial Investor | D30: Ricci Global Partners | E30: Riccardo Ricci | G30: riccardo-ricci@ricciglobalpartners.com | K30: John Quinn | L30: Engaged | M30: Space / Defense / Aerospace / Advanced Manufacturing | N30: Tier 1 | P30: 46028 | Q30: =IF(P30="","",TODAY()-P30) | R30: =IF(OR(L30="Passed",Z30=""),"",P30+Z30) | S30: =IF(OR(R30="",L30="Passed"),"",IF(R30<=TODAY(),"DUE",IF(R30<=TODAY()+3,"Next 3 Days","Later"))) | T30: Meeting scheduled / held | U30: referred by Tom Wright | V30: Capital Partner (Equity / Strategic) | W30: MNDA executed and data room shared. Ricci requested finance working session and followed up again today to move forward | 01/15/2026 | 03/13/2026 | X30: JQ Follow Up!10 | Y30: Advance diligence / proposal discussion | Z30: 5 | AA30: =IF(AC30="Archived",0,ROUND((IF(N30="Tier 1",35,IF(N30="Tier 2",20,8))+IF(C30="Financial Investor",15,IF(C30="Intermediary / Banker",12,8))+IF(L30="Term Sheet / Proposal",25,IF(L30="Engaged",20,IF(L30="Meeting Requested",18,IF(L30="Meeting Held",14,IF(L30="Follow Up",10,5)))))+MIN(Q30,30)+IF(S30="DUE",15,IF(S30="Next 3 Days",8,0))),0)) | AB30: =IF(AND(AC30="Active",OR(N30="Tier 1",N30="Tier 2"),OR(S30="DUE",S30="Next 3 Days")),"YES","") | AC30: =IF(L30="Passed","Archived","Active")
A31: EXOS-0030 | B31: Term Sheets | C31: Other / Review | D31: Screen with Visual Conmpliance | K31: John Quinn | L31: Engaged | M31: Needs qualification | N31: Tier 1 | Q31: =IF(P31="","",TODAY()-P31) | R31: =IF(OR(L31="Passed",Z31=""),"",P31+Z31) | S31: =IF(OR(R31="",L31="Passed"),"",IF(R31<=TODAY(),"DUE",IF(R31<=TODAY()+3,"Next 3 Days","Later"))) | T31: Meeting scheduled / held | X31: Term Sheets!30 | Y31: Advance diligence / proposal discussion | Z31: 5 | AA31: =IF(AC31="Archived",0,ROUND((IF(N31="Tier 1",35,IF(N31="Tier 2",20,8))+IF(C31="Financial Investor",15,IF(C31="Intermediary / Banker",12,8))+IF(L31="Term Sheet / Proposal",25,IF(L31="Engaged",20,IF(L31="Meeting Requested",18,IF(L31="Meeting Held",14,IF(L31="Follow Up",10,5)))))+MIN(Q31,30)+IF(S31="DUE",15,IF(S31="Next 3 Days",8,0))),0)) | AB31: =IF(AND(AC31="Active",OR(N31="Tier 1",N31="Tier 2"),OR(S31="DUE",S31="Next 3 Days")),"YES","") | AC31: =IF(L31="Passed","Archived","Active")
A32: EXOS-0031 | B32: Term Sheets | C32: Other / Review | D32: The Unity Group | E32: Alex Durie via Tahmina K | G32: alex@unity-group.com | H32: shorgan05@gmail.com; harry.young@theacquisitionrudis.com; jeremy@unity-group.com; victor.tan@unity-group.com | K32: John Quinn | L32: Engaged | M32: Needs qualification | N32: Tier 1 | Q32: =IF(P32="","",TODAY()-P32) | R32: =IF(OR(L32="Passed",Z32=""),"",P32+Z32) | S32: =IF(OR(R32="",L32="Passed"),"",IF(R32<=TODAY(),"DUE",IF(R32<=TODAY()+3,"Next 3 Days","Later"))) | T32: Meeting scheduled / held | X32: Term Sheets!8 | Y32: Advance diligence / proposal discussion | Z32: 5 | AA32: =IF(AC32="Archived",0,ROUND((IF(N32="Tier 1",35,IF(N32="Tier 2",20,8))+IF(C32="Financial Investor",15,IF(C32="Intermediary / Banker",12,8))+IF(L32="Term Sheet / Proposal",25,IF(L32="Engaged",20,IF(L32="Meeting Requested",18,IF(L32="Meeting Held",14,IF(L32="Follow Up",10,5)))))+MIN(Q32,30)+IF(S32="DUE",15,IF(S32="Next 3 Days",8,0))),0)) | AB32: =IF(AND(AC32="Active",OR(N32="Tier 1",N32="Tier 2"),OR(S32="DUE",S32="Next 3 Days")),"YES","") | AC32: =IF(L32="Passed","Archived","Active")
A33: EXOS-0032 | B33: Derek Contacts | JQ Follow Up | Term Sheets | C33: Intermediary / Banker | D33: Tristate Capital | E33: Sulaiman Sulaimani | G33: sulaiman@tristatecap.com | I33: 11/17 meeting held and follow up sent | K33: John Quinn | L33: Engaged | M33: Capital raise support / placement | N33: Tier 1 | P33: 46054 | Q33: =IF(P33="","",TODAY()-P33) | R33: =IF(OR(L33="Passed",Z33=""),"",P33+Z33) | S33: =IF(OR(R33="",L33="Passed"),"",IF(R33<=TODAY(),"DUE",IF(R33<=TODAY()+3,"Next 3 Days","Later"))) | T33: Meeting scheduled / held | U33: referred by Dereck | V33: Capital Introduction (Success Fee + Equity) Cost of finance under Tristate: 2.0% cash + 1.0% non-voting equity Only on Tristate-sourced, closed capital | W33: https://www.irongatevc.com/ Contracted with Sulaiman Sulaimani ​John Quinn​ ​Neil Milburn​ John, I'm scheduled to speak with our strategic partner Ty McCoy tomorrow. He just emailed me a company now that appears to be a close contact of his as there is someone on their team that is former CIA. I think we found the right partner for you and your team. Please give me sometime as I work on this for you and your team. I'll be back in touch. Thanks for the call yesterday. I enjoyed speaking with you. I was able to connect with our strategic partner Ty McCoy with IronGate. He is available to speak with us next week at 12 pm CST on 2/10. I was also able to circle up with our clients from ETL. Hanshin Lee emailed me that he is interested in Exos Aerospace and speaking with us next week at 8 am CST on 2/10. If you can please send me calendar invites for both calls on 2/10 8 am CST with ETL, and 12 pm CST with IronGate. Once I receive both invites, I'll be sure to pass them along. | 01/15/2026 | 2/10 – Calls Held: | etl dean rx? match with portfolio co | X33: Term Sheets!3 | JQ Follow Up!7 | Derek Contacts!55 | Y33: Advance diligence / proposal discussion | Z33: 5 | AA33: =IF(AC33="Archived",0,ROUND((IF(N33="Tier 1",35,IF(N33="Tier 2",20,8))+IF(C33="Financial Investor",15,IF(C33="Intermediary / Banker",12,8))+IF(L33="Term Sheet / Proposal",25,IF(L33="Engaged",20,IF(L33="Meeting Requested",18,IF(L33="Meeting Held",14,IF(L33="Follow Up",10,5)))))+MIN(Q33,30)+IF(S33="DUE",15,IF(S33="Next 3 Days",8,0))),0)) | AB33: =IF(AND(AC33="Active",OR(N33="Tier 1",N33="Tier 2"),OR(S33="DUE",S33="Next 3 Days")),"YES","") | AC33: =IF(L33="Passed","Archived","Active")
A34: EXOS-0033 | B34: Term Sheets | C34: Other / Review | D34: Viking Mergers & Acquisitions | E34: A. Rehwinkel | G34: arehwinkel@vikingmergers.com | K34: John Quinn | L34: Engaged | M34: Needs qualification | N34: Tier 1 | Q34: =IF(P34="","",TODAY()-P34) | R34: =IF(OR(L34="Passed",Z34=""),"",P34+Z34) | S34: =IF(OR(R34="",L34="Passed"),"",IF(R34<=TODAY(),"DUE",IF(R34<=TODAY()+3,"Next 3 Days","Later"))) | T34: Meeting scheduled / held | W34: Initial engagement underway; reviewing materials in data room. | X34: Term Sheets!12 | Y34: Advance diligence / proposal discussion | Z34: 5 | AA34: =IF(AC34="Archived",0,ROUND((IF(N34="Tier 1",35,IF(N34="Tier 2",20,8))+IF(C34="Financial Investor",15,IF(C34="Intermediary / Banker",12,8))+IF(L34="Term Sheet / Proposal",25,IF(L34="Engaged",20,IF(L34="Meeting Requested",18,IF(L34="Meeting Held",14,IF(L34="Follow Up",10,5)))))+MIN(Q34,30)+IF(S34="DUE",15,IF(S34="Next 3 Days",8,0))),0)) | AB34: =IF(AND(AC34="Active",OR(N34="Tier 1",N34="Tier 2"),OR(S34="DUE",S34="Next 3 Days")),"YES","") | AC34: =IF(L34="Passed","Archived","Active")
A35: EXOS-0034 | B35: John - Investor Contacts | C35: Financial Investor | D35: Collective Equity | E35: Mike Royston | G35: mike@collectiveequity.com | K35: John Quinn | L35: Meeting Requested | M35: Space / Defense / Aerospace / Advanced Manufacturing | N35: Tier 1 | Q35: =IF(P35="","",TODAY()-P35) | R35: =IF(OR(L35="Passed",Z35=""),"",P35+Z35) | S35: =IF(OR(R35="",L35="Passed"),"",IF(R35<=TODAY(),"DUE",IF(R35<=TODAY()+3,"Next 3 Days","Later"))) | T35: Meeting scheduled / held | W35: | | meeting on 6/25 / follow up meeting in the works / ziyi@collectiveequity.com | X35: John - Investor Contacts!249 | Y35: Book call and send agenda/deck | Z35: 2 | AA35: =IF(AC35="Archived",0,ROUND((IF(N35="Tier 1",35,IF(N35="Tier 2",20,8))+IF(C35="Financial Investor",15,IF(C35="Intermediary / Banker",12,8))+IF(L35="Term Sheet / Proposal",25,IF(L35="Engaged",20,IF(L35="Meeting Requested",18,IF(L35="Meeting Held",14,IF(L35="Follow Up",10,5)))))+MIN(Q35,30)+IF(S35="DUE",15,IF(S35="Next 3 Days",8,0))),0)) | AB35: =IF(AND(AC35="Active",OR(N35="Tier 1",N35="Tier 2"),OR(S35="DUE",S35="Next 3 Days")),"YES","") | AC35: =IF(L35="Passed","Archived","Active")
A36: EXOS-0035 | B36: Tank Contacts | C36: Strategic / Corporate | D36: Gravitics | E36: Scott Macklin | G36: smacklin@gravitics.com | H36: scottjmacklin@gmail.com | J36: https://www.linkedin.com/in/scmacklin/ | K36: John Quinn | L36: Meeting Requested | M36: Strategic space / aerospace alignment | N36: Tier 1 | O36: 45744 | P36: 45744 | Q36: =IF(P36="","",TODAY()-P36) | R36: =IF(OR(L36="Passed",Z36=""),"",P36+Z36) | S36: =IF(OR(R36="",L36="Passed"),"",IF(R36<=TODAY(),"DUE",IF(R36<=TODAY()+3,"Next 3 Days","Later"))) | T36: Meeting scheduled / held | W36: meeting set for 4/3 | X36: Tank Contacts!12 | Y36: Book call and send agenda/deck | Z36: 2 | AA36: =IF(AC36="Archived",0,ROUND((IF(N36="Tier 1",35,IF(N36="Tier 2",20,8))+IF(C36="Financial Investor",15,IF(C36="Intermediary / Banker",12,8))+IF(L36="Term Sheet / Proposal",25,IF(L36="Engaged",20,IF(L36="Meeting Requested",18,IF(L36="Meeting Held",14,IF(L36="Follow Up",10,5)))))+MIN(Q36,30)+IF(S36="DUE",15,IF(S36="Next 3 Days",8,0))),0)) | AB36: =IF(AND(AC36="Active",OR(N36="Tier 1",N36="Tier 2"),OR(S36="DUE",S36="Next 3 Days")),"YES","") | AC36: =IF(L36="Passed","Archived","Active")
A37: EXOS-0036 | B37: JQ Follow Up | John - Investor Contacts | C37: Financial Investor | D37: Investor Ready Capital | E37: Samuel Levitz | G37: samuel@investorreadycapital.com | I37: last email exchange I see is 11/23 and it looked promising - notes on what happened here? Looks like we need to follow up? | K37: John Quinn | L37: Meeting Requested | M37: Space / Defense / Aerospace / Advanced Manufacturing | N37: Tier 1 | Q37: =IF(P37="","",TODAY()-P37) | R37: =IF(OR(L37="Passed",Z37=""),"",P37+Z37) | S37: =IF(OR(R37="",L37="Passed"),"",IF(R37<=TODAY(),"DUE",IF(R37<=TODAY()+3,"Next 3 Days","Later"))) | T37: Meeting scheduled / held | W37: meeting held on 6/24 / follow up meeting on 6/27- Question replied to and followed up on 7-11 | X37: JQ Follow Up!23 | John - Investor Contacts!250 | Y37: Book call and send agenda/deck | Z37: 2 | AA37: =IF(AC37="Archived",0,ROUND((IF(N37="Tier 1",35,IF(N37="Tier 2",20,8))+IF(C37="Financial Investor",15,IF(C37="Intermediary / Banker",12,8))+IF(L37="Term Sheet / Proposal",25,IF(L37="Engaged",20,IF(L37="Meeting Requested",18,IF(L37="Meeting Held",14,IF(L37="Follow Up",10,5)))))+MIN(Q37,30)+IF(S37="DUE",15,IF(S37="Next 3 Days",8,0))),0)) | AB37: =IF(AND(AC37="Active",OR(N37="Tier 1",N37="Tier 2"),OR(S37="DUE",S37="Next 3 Days")),"YES","") | AC37: =IF(L37="Passed","Archived","Active")
A38: EXOS-0037 | B38: JQ Follow Up | John - Investor Contacts | OSC | C38: Financial Investor | D38: One Bow River | E38: Stowe Faircloth | G38: shane.sherman@onebowriver.com | H38: stowe.faircloth@onebowriver.com | I38: 720.910.9483 | J38: https://www.linkedin.com/in/shane-sherman/ | K38: John Quinn | L38: Meeting Requested | M38: Space / Defense / Aerospace / Advanced Manufacturing | N38: Tier 1 | O38: 45814 | P38: 45922 | Q38: =IF(P38="","",TODAY()-P38) | R38: =IF(OR(L38="Passed",Z38=""),"",P38+Z38) | S38: =IF(OR(R38="",L38="Passed"),"",IF(R38<=TODAY(),"DUE",IF(R38<=TODAY()+3,"Next 3 Days","Later"))) | T38: Meeting scheduled / held | U38: https://www.linkedin.com/in/shane-sherman/ | W38: 08/12/2025 | Stowe Faircloth <Stowe.faircloth@onebowriver.com>replied requesting a meeting on 9/22 | X38: JQ Follow Up!14 | John - Investor Contacts!144 | OSC!11 | Y38: Book call and send agenda/deck | Z38: 2 | AA38: =IF(AC38="Archived",0,ROUND((IF(N38="Tier 1",35,IF(N38="Tier 2",20,8))+IF(C38="Financial Investor",15,IF(C38="Intermediary / Banker",12,8))+IF(L38="Term Sheet / Proposal",25,IF(L38="Engaged",20,IF(L38="Meeting Requested",18,IF(L38="Meeting Held",14,IF(L38="Follow Up",10,5)))))+MIN(Q38,30)+IF(S38="DUE",15,IF(S38="Next 3 Days",8,0))),0)) | AB38: =IF(AND(AC38="Active",OR(N38="Tier 1",N38="Tier 2"),OR(S38="DUE",S38="Next 3 Days")),"YES","") | AC38: =IF(L38="Passed","Archived","Active")
A39: EXOS-0038 | B39: JQ Follow Up | John - Investor Contacts | C39: Financial Investor | D39: TEL Venture Capital | E39: Sergey Fedotov | G39: sergey.fedotov@tel.com | I39: 650.360.8669 | J39: https://www.linkedin.com/in/sergey-a-fedotov/ | K39: John Quinn | L39: Meeting Requested | M39: Space / Defense / Aerospace / Advanced Manufacturing | N39: Tier 1 | O39: 45912 | P39: 45912 | Q39: =IF(P39="","",TODAY()-P39) | R39: =IF(OR(L39="Passed",Z39=""),"",P39+Z39) | S39: =IF(OR(R39="",L39="Passed"),"",IF(R39<=TODAY(),"DUE",IF(R39<=TODAY()+3,"Next 3 Days","Later"))) | T39: Meeting scheduled / held | U39: https://www.linkedin.com/in/sergey-a-fedotov/ | W39: 9/24 - meeting set for 10/2 | X39: JQ Follow Up!13 | John - Investor Contacts!681 | Y39: Book call and send agenda/deck | Z39: 2 | AA39: =IF(AC39="Archived",0,ROUND((IF(N39="Tier 1",35,IF(N39="Tier 2",20,8))+IF(C39="Financial Investor",15,IF(C39="Intermediary / Banker",12,8))+IF(L39="Term Sheet / Proposal",25,IF(L39="Engaged",20,IF(L39="Meeting Requested",18,IF(L39="Meeting Held",14,IF(L39="Follow Up",10,5)))))+MIN(Q39,30)+IF(S39="DUE",15,IF(S39="Next 3 Days",8,0))),0)) | AB39: =IF(AND(AC39="Active",OR(N39="Tier 1",N39="Tier 2"),OR(S39="DUE",S39="Next 3 Days")),"YES","") | AC39: =IF(L39="Passed","Archived","Active")
A40: EXOS-0039 | B40: John - Investor Contacts | C40: Financial Investor | D40: referred by andy@abucholtz.com | E40: Richard Phillips | K40: John Quinn | L40: Meeting Requested | M40: Space / Defense / Aerospace / Advanced Manufacturing | N40: Tier 1 | O40: 45903 | P40: 45903 | Q40: =IF(P40="","",TODAY()-P40) | R40: =IF(OR(L40="Passed",Z40=""),"",P40+Z40) | S40: =IF(OR(R40="",L40="Passed"),"",IF(R40<=TODAY(),"DUE",IF(R40<=TODAY()+3,"Next 3 Days","Later"))) | T40: Meeting scheduled / held | U40: phillips@crossroadscapitaldc.com | W40: | meeting set 9/8/ NDA 9/12 | | X40: John - Investor Contacts!610 | Y40: Book call and send agenda/deck | Z40: 2 | AA40: =IF(AC40="Archived",0,ROUND((IF(N40="Tier 1",35,IF(N40="Tier 2",20,8))+IF(C40="Financial Investor",15,IF(C40="Intermediary / Banker",12,8))+IF(L40="Term Sheet / Proposal",25,IF(L40="Engaged",20,IF(L40="Meeting Requested",18,IF(L40="Meeting Held",14,IF(L40="Follow Up",10,5)))))+MIN(Q40,30)+IF(S40="DUE",15,IF(S40="Next 3 Days",8,0))),0)) | AB40: =IF(AND(AC40="Active",OR(N40="Tier 1",N40="Tier 2"),OR(S40="DUE",S40="Next 3 Days")),"YES","") | AC40: =IF(L40="Passed","Archived","Active")
A41: EXOS-0040 | B41: JQ Follow Up | Term Sheets | C41: Financial Investor | D41: Cerebro Capital | E41: Steven Agathoklis | G41: sagathoklis@cerebrocapital.com | K41: John Quinn | L41: Meeting Held | M41: Space / Defense / Aerospace / Advanced Manufacturing | N41: Tier 1 | P41: 45951 | Q41: =IF(P41="","",TODAY()-P41) | R41: =IF(OR(L41="Passed",Z41=""),"",P41+Z41) | S41: =IF(OR(R41="",L41="Passed"),"",IF(R41<=TODAY(),"DUE",IF(R41<=TODAY()+3,"Next 3 Days","Later"))) | T41: Meeting scheduled / held | V41: Bridge Loan | W41: NDA signed; full financials provided. No response since; inactive. | meeting held on 10/16 | X41: Term Sheets!22 | JQ Follow Up!15 | Y41: Send recap, materials, and next-step ask | Z41: 5 | AA41: =IF(AC41="Archived",0,ROUND((IF(N41="Tier 1",35,IF(N41="Tier 2",20,8))+IF(C41="Financial Investor",15,IF(C41="Intermediary / Banker",12,8))+IF(L41="Term Sheet / Proposal",25,IF(L41="Engaged",20,IF(L41="Meeting Requested",18,IF(L41="Meeting Held",14,IF(L41="Follow Up",10,5)))))+MIN(Q41,30)+IF(S41="DUE",15,IF(S41="Next 3 Days",8,0))),0)) | AB41: =IF(AND(AC41="Active",OR(N41="Tier 1",N41="Tier 2"),OR(S41="DUE",S41="Next 3 Days")),"YES","") | AC41: =IF(L41="Passed","Archived","Active")
A42: EXOS-0041 | B42: John - Investor Contacts | C42: Financial Investor | D42: IPO Club | E42: Edoardo Zarghetta | G42: edozar@gmail.com | K42: John Quinn | L42: Meeting Held | M42: Space / Defense / Aerospace / Advanced Manufacturing | N42: Tier 1 | O42: 46030 | P42: 46030 | Q42: =IF(P42="","",TODAY()-P42) | R42: =IF(OR(L42="Passed",Z42=""),"",P42+Z42) | S42: =IF(OR(R42="",L42="Passed"),"",IF(R42<=TODAY(),"DUE",IF(R42<=TODAY()+3,"Next 3 Days","Later"))) | T42: Meeting scheduled / held | U42: linkedin.com/in/edozar | W42: | meeting held on 1/13 - pitch deck sent for brother | | X42: John - Investor Contacts!908 | Y42: Send recap, materials, and next-step ask | Z42: 5 | AA42: =IF(AC42="Archived",0,ROUND((IF(N42="Tier 1",35,IF(N42="Tier 2",20,8))+IF(C42="Financial Investor",15,IF(C42="Intermediary / Banker",12,8))+IF(L42="Term Sheet / Proposal",25,IF(L42="Engaged",20,IF(L42="Meeting Requested",18,IF(L42="Meeting Held",14,IF(L42="Follow Up",10,5)))))+MIN(Q42,30)+IF(S42="DUE",15,IF(S42="Next 3 Days",8,0))),0)) | AB42: =IF(AND(AC42="Active",OR(N42="Tier 1",N42="Tier 2"),OR(S42="DUE",S42="Next 3 Days")),"YES","") | AC42: =IF(L42="Passed","Archived","Active")
A43: EXOS-0042 | B43: JQ Follow Up | John - Investor Contacts | C43: Financial Investor | D43: Noblis Ventures | E43: Bill Collier | G43: bill.collier@noblis.org | I43: 09/03/2025 | J43: https://www.linkedin.com/in/williammarcuscollier/ | K43: John Quinn | L43: Meeting Held | M43: Space / Defense / Aerospace / Advanced Manufacturing | N43: Tier 1 | O43: 45903 | P43: 45972 | Q43: =IF(P43="","",TODAY()-P43) | R43: =IF(OR(L43="Passed",Z43=""),"",P43+Z43) | S43: =IF(OR(R43="",L43="Passed"),"",IF(R43<=TODAY(),"DUE",IF(R43<=TODAY()+3,"Next 3 Days","Later"))) | T43: Meeting scheduled / held | U43: https://www.linkedin.com/in/williammarcuscollier/ | W43: 12/5 follow up sent | meeting held and follow up emails sent. most recent follow up 12/5 | X43: JQ Follow Up!17 | John - Investor Contacts!615 | Y43: Send recap, materials, and next-step ask | Z43: 5 | AA43: =IF(AC43="Archived",0,ROUND((IF(N43="Tier 1",35,IF(N43="Tier 2",20,8))+IF(C43="Financial Investor",15,IF(C43="Intermediary / Banker",12,8))+IF(L43="Term Sheet / Proposal",25,IF(L43="Engaged",20,IF(L43="Meeting Requested",18,IF(L43="Meeting Held",14,IF(L43="Follow Up",10,5)))))+MIN(Q43,30)+IF(S43="DUE",15,IF(S43="Next 3 Days",8,0))),0)) | AB43: =IF(AND(AC43="Active",OR(N43="Tier 1",N43="Tier 2"),OR(S43="DUE",S43="Next 3 Days")),"YES","") | AC43: =IF(L43="Passed","Archived","Active")
A44: EXOS-0043 | B44: John - Investor Contacts | C44: Financial Investor | D44: Palm Drive Capital | E44: Carter Dessommes | G44: carter@palmdrive.vc | K44: John Quinn | L44: Meeting Held | M44: Space / Defense / Aerospace / Advanced Manufacturing | N44: Tier 1 | O44: 45859 | P44: 45859 | Q44: =IF(P44="","",TODAY()-P44) | R44: =IF(OR(L44="Passed",Z44=""),"",P44+Z44) | S44: =IF(OR(R44="",L44="Passed"),"",IF(R44<=TODAY(),"DUE",IF(R44<=TODAY()+3,"Next 3 Days","Later"))) | T44: Meeting scheduled / held | W44: | meeting held | | X44: John - Investor Contacts!413 | Y44: Send recap, materials, and next-step ask | Z44: 5 | AA44: =IF(AC44="Archived",0,ROUND((IF(N44="Tier 1",35,IF(N44="Tier 2",20,8))+IF(C44="Financial Investor",15,IF(C44="Intermediary / Banker",12,8))+IF(L44="Term Sheet / Proposal",25,IF(L44="Engaged",20,IF(L44="Meeting Requested",18,IF(L44="Meeting Held",14,IF(L44="Follow Up",10,5)))))+MIN(Q44,30)+IF(S44="DUE",15,IF(S44="Next 3 Days",8,0))),0)) | AB44: =IF(AND(AC44="Active",OR(N44="Tier 1",N44="Tier 2"),OR(S44="DUE",S44="Next 3 Days")),"YES","") | AC44: =IF(L44="Passed","Archived","Active")
A45: EXOS-0044 | B45: JQ Follow Up | C45: Financial Investor | D45: Prospect Capital | E45: Sulaiman Sulaimani | I45: Capital Partner (Debt / Structured Capital) | K45: John Quinn | L45: Meeting Held | M45: Space / Defense / Aerospace / Advanced Manufacturing | N45: Tier 1 | P45: 46030 | Q45: =IF(P45="","",TODAY()-P45) | R45: =IF(OR(L45="Passed",Z45=""),"",P45+Z45) | S45: =IF(OR(R45="",L45="Passed"),"",IF(R45<=TODAY(),"DUE",IF(R45<=TODAY()+3,"Next 3 Days","Later"))) | T45: Meeting scheduled / held | U45: sulaiman@prospectcapital.com | W45: Introductory meeting held Jan 8. Prospect Capital operates through two distinct divisions; conversations are exploratory at this stage. Two divisions: core BDC credit and structured/special situations. EXOS aligns better with structured, event-driven capital vs traditional cash-flow lending. | | X45: JQ Follow Up!28 | Y45: Send recap, materials, and next-step ask | Z45: 5 | AA45: =IF(AC45="Archived",0,ROUND((IF(N45="Tier 1",35,IF(N45="Tier 2",20,8))+IF(C45="Financial Investor",15,IF(C45="Intermediary / Banker",12,8))+IF(L45="Term Sheet / Proposal",25,IF(L45="Engaged",20,IF(L45="Meeting Requested",18,IF(L45="Meeting Held",14,IF(L45="Follow Up",10,5)))))+MIN(Q45,30)+IF(S45="DUE",15,IF(S45="Next 3 Days",8,0))),0)) | AB45: =IF(AND(AC45="Active",OR(N45="Tier 1",N45="Tier 2"),OR(S45="DUE",S45="Next 3 Days")),"YES","") | AC45: =IF(L45="Passed","Archived","Active")
A46: EXOS-0045 | B46: John - Investor Contacts | C46: Financial Investor | D46: REI | K46: John Quinn | L46: Meeting Held | M46: Space / Defense / Aerospace / Advanced Manufacturing | N46: Tier 1 | O46: 45917 | P46: 45917 | Q46: =IF(P46="","",TODAY()-P46) | R46: =IF(OR(L46="Passed",Z46=""),"",P46+Z46) | S46: =IF(OR(R46="",L46="Passed"),"",IF(R46<=TODAY(),"DUE",IF(R46<=TODAY()+3,"Next 3 Days","Later"))) | T46: Meeting scheduled / held | U46: Nick Book | W46: Choctaw nation investor group interested in Space investments. Requesting site tour on 9-26 If you could send me a new link for a warehouse visit over the next week or so I’d really like to continue to dig into this and see where or who we can fit in. Also, please send me the deck and anything else you would like me to consider. | | | X46: John - Investor Contacts!2 | Y46: Send recap, materials, and next-step ask | Z46: 5 | AA46: =IF(AC46="Archived",0,ROUND((IF(N46="Tier 1",35,IF(N46="Tier 2",20,8))+IF(C46="Financial Investor",15,IF(C46="Intermediary / Banker",12,8))+IF(L46="Term Sheet / Proposal",25,IF(L46="Engaged",20,IF(L46="Meeting Requested",18,IF(L46="Meeting Held",14,IF(L46="Follow Up",10,5)))))+MIN(Q46,30)+IF(S46="DUE",15,IF(S46="Next 3 Days",8,0))),0)) | AB46: =IF(AND(AC46="Active",OR(N46="Tier 1",N46="Tier 2"),OR(S46="DUE",S46="Next 3 Days")),"YES","") | AC46: =IF(L46="Passed","Archived","Active")
A47: EXOS-0046 | B47: John - Investor Contacts | C47: Financial Investor | D47: Rockfleet Financial | E47: John Swift | G47: john.swift@rockfleetfinancial.com | K47: John Quinn | L47: Meeting Held | M47: Space / Defense / Aerospace / Advanced Manufacturing | N47: Tier 1 | O47: 45831 | P47: 45831 | Q47: =IF(P47="","",TODAY()-P47) | R47: =IF(OR(L47="Passed",Z47=""),"",P47+Z47) | S47: =IF(OR(R47="",L47="Passed"),"",IF(R47<=TODAY(),"DUE",IF(R47<=TODAY()+3,"Next 3 Days","Later"))) | T47: Meeting scheduled / held | U47: linkedin.com/in/jr-swift | W47: | meeting held on 7/2 & NDA in process- Followed up 7-11 | | X47: John - Investor Contacts!238 | Y47: Send recap, materials, and next-step ask | Z47: 5 | AA47: =IF(AC47="Archived",0,ROUND((IF(N47="Tier 1",35,IF(N47="Tier 2",20,8))+IF(C47="Financial Investor",15,IF(C47="Intermediary / Banker",12,8))+IF(L47="Term Sheet / Proposal",25,IF(L47="Engaged",20,IF(L47="Meeting Requested",18,IF(L47="Meeting Held",14,IF(L47="Follow Up",10,5)))))+MIN(Q47,30)+IF(S47="DUE",15,IF(S47="Next 3 Days",8,0))),0)) | AB47: =IF(AND(AC47="Active",OR(N47="Tier 1",N47="Tier 2"),OR(S47="DUE",S47="Next 3 Days")),"YES","") | AC47: =IF(L47="Passed","Archived","Active")
A48: EXOS-0047 | B48: John - Investor Contacts | C48: Financial Investor | E48: Clay | G48: claysba1@gmail.com | K48: John Quinn | L48: Follow Up | M48: Space / Defense / Aerospace / Advanced Manufacturing | N48: Tier 2 | O48: 45810 | P48: 45841 | Q48: =IF(P48="","",TODAY()-P48) | R48: =IF(OR(L48="Passed",Z48=""),"",P48+Z48) | S48: =IF(OR(R48="",L48="Passed"),"",IF(R48<=TODAY(),"DUE",IF(R48<=TODAY()+3,"Next 3 Days","Later"))) | U48: Tom referral | W48: | | | X48: John - Investor Contacts!110 | Y48: Send next follow-up with traction + CTA | Z48: 7 | AA48: =IF(AC48="Archived",0,ROUND((IF(N48="Tier 1",35,IF(N48="Tier 2",20,8))+IF(C48="Financial Investor",15,IF(C48="Intermediary / Banker",12,8))+IF(L48="Term Sheet / Proposal",25,IF(L48="Engaged",20,IF(L48="Meeting Requested",18,IF(L48="Meeting Held",14,IF(L48="Follow Up",10,5)))))+MIN(Q48,30)+IF(S48="DUE",15,IF(S48="Next 3 Days",8,0))),0)) | AB48: =IF(AND(AC48="Active",OR(N48="Tier 1",N48="Tier 2"),OR(S48="DUE",S48="Next 3 Days")),"YES","") | AC48: =IF(L48="Passed","Archived","Active")
A49: EXOS-0048 | B49: John - Investor Contacts | C49: Financial Investor | E49: Drew Tulchin | G49: drew@nmangels.com | K49: John Quinn | L49: Follow Up | M49: Space / Defense / Aerospace / Advanced Manufacturing | N49: Tier 2 | O49: 45957 | P49: 45985 | Q49: =IF(P49="","",TODAY()-P49) | R49: =IF(OR(L49="Passed",Z49=""),"",P49+Z49) | S49: =IF(OR(R49="",L49="Passed"),"",IF(R49<=TODAY(),"DUE",IF(R49<=TODAY()+3,"Next 3 Days","Later"))) | W49: | not sure what to do with this one?? | | X49: John - Investor Contacts!810 | Y49: Send next follow-up with traction + CTA | Z49: 7 | AA49: =IF(AC49="Archived",0,ROUND((IF(N49="Tier 1",35,IF(N49="Tier 2",20,8))+IF(C49="Financial Investor",15,IF(C49="Intermediary / Banker",12,8))+IF(L49="Term Sheet / Proposal",25,IF(L49="Engaged",20,IF(L49="Meeting Requested",18,IF(L49="Meeting Held",14,IF(L49="Follow Up",10,5)))))+MIN(Q49,30)+IF(S49="DUE",15,IF(S49="Next 3 Days",8,0))),0)) | AB49: =IF(AND(AC49="Active",OR(N49="Tier 1",N49="Tier 2"),OR(S49="DUE",S49="Next 3 Days")),"YES","") | AC49: =IF(L49="Passed","Archived","Active")
A50: EXOS-0049 | B50: John - Investor Contacts | C50: Financial Investor | E50: EXOS + Plug & Play: Introductions | G50: jacob.reedy@trinet.com | H50: matt.darton@trinet.com; a.irizarry@pnptc.com | K50: John Quinn | L50: Follow Up | M50: Space / Defense / Aerospace / Advanced Manufacturing | N50: Tier 2 | O50: 45891 | P50: 45994 | Q50: =IF(P50="","",TODAY()-P50) | R50: =IF(OR(L50="Passed",Z50=""),"",P50+Z50) | S50: =IF(OR(R50="",L50="Passed"),"",IF(R50<=TODAY(),"DUE",IF(R50<=TODAY()+3,"Next 3 Days","Later"))) | W50: | | | X50: John - Investor Contacts!503 | Y50: Send next follow-up with traction + CTA | Z50: 7 | AA50: =IF(AC50="Archived",0,ROUND((IF(N50="Tier 1",35,IF(N50="Tier 2",20,8))+IF(C50="Financial Investor",15,IF(C50="Intermediary / Banker",12,8))+IF(L50="Term Sheet / Proposal",25,IF(L50="Engaged",20,IF(L50="Meeting Requested",18,IF(L50="Meeting Held",14,IF(L50="Follow Up",10,5)))))+MIN(Q50,30)+IF(S50="DUE",15,IF(S50="Next 3 Days",8,0))),0)) | AB50: =IF(AND(AC50="Active",OR(N50="Tier 1",N50="Tier 2"),OR(S50="DUE",S50="Next 3 Days")),"YES","") | AC50: =IF(L50="Passed","Archived","Active")
A51: EXOS-0050 | B51: John - Investor Contacts | C51: Financial Investor | E51: James Cameron | G51: james@visionaryleadership.co.nz | K51: John Quinn | L51: Follow Up | M51: Space / Defense / Aerospace / Advanced Manufacturing | N51: Tier 2 | P51: 45821 | Q51: =IF(P51="","",TODAY()-P51) | R51: =IF(OR(L51="Passed",Z51=""),"",P51+Z51) | S51: =IF(OR(R51="",L51="Passed"),"",IF(R51<=TODAY(),"DUE",IF(R51<=TODAY()+3,"Next 3 Days","Later"))) | W51: | dns fail | | X51: John - Investor Contacts!77 | Y51: Send next follow-up with traction + CTA | Z51: 7 | AA51: =IF(AC51="Archived",0,ROUND((IF(N51="Tier 1",35,IF(N51="Tier 2",20,8))+IF(C51="Financial Investor",15,IF(C51="Intermediary / Banker",12,8))+IF(L51="Term Sheet / Proposal",25,IF(L51="Engaged",20,IF(L51="Meeting Requested",18,IF(L51="Meeting Held",14,IF(L51="Follow Up",10,5)))))+MIN(Q51,30)+IF(S51="DUE",15,IF(S51="Next 3 Days",8,0))),0)) | AB51: =IF(AND(AC51="Active",OR(N51="Tier 1",N51="Tier 2"),OR(S51="DUE",S51="Next 3 Days")),"YES","") | AC51: =IF(L51="Passed","Archived","Active")
A52: EXOS-0051 | B52: John - Investor Contacts | C52: Financial Investor | E52: Jason Schwartz / Paul Gloyer GTL | G52: jason@leagueadvisors.com | H52: paul.gloyer@gtlcompany.com | K52: John Quinn | L52: Follow Up | M52: Space / Defense / Aerospace / Advanced Manufacturing | N52: Tier 2 | O52: 45799 | P52: 45821 | Q52: =IF(P52="","",TODAY()-P52) | R52: =IF(OR(L52="Passed",Z52=""),"",P52+Z52) | S52: =IF(OR(R52="",L52="Passed"),"",IF(R52<=TODAY(),"DUE",IF(R52<=TODAY()+3,"Next 3 Days","Later"))) | W52: | | | X52: John - Investor Contacts!78 | Y52: Send next follow-up with traction + CTA | Z52: 7 | AA52: =IF(AC52="Archived",0,ROUND((IF(N52="Tier 1",35,IF(N52="Tier 2",20,8))+IF(C52="Financial Investor",15,IF(C52="Intermediary / Banker",12,8))+IF(L52="Term Sheet / Proposal",25,IF(L52="Engaged",20,IF(L52="Meeting Requested",18,IF(L52="Meeting Held",14,IF(L52="Follow Up",10,5)))))+MIN(Q52,30)+IF(S52="DUE",15,IF(S52="Next 3 Days",8,0))),0)) | AB52: =IF(AND(AC52="Active",OR(N52="Tier 1",N52="Tier 2"),OR(S52="DUE",S52="Next 3 Days")),"YES","") | AC52: =IF(L52="Passed","Archived","Active")
A53: EXOS-0052 | B53: John - Investor Contacts | C53: Financial Investor | E53: SAFRAN | G53: explore.newspace@alcimed.com | K53: John Quinn | L53: Follow Up | M53: Space / Defense / Aerospace / Advanced Manufacturing | N53: Tier 2 | O53: 45902 | P53: 45972 | Q53: =IF(P53="","",TODAY()-P53) | R53: =IF(OR(L53="Passed",Z53=""),"",P53+Z53) | S53: =IF(OR(R53="",L53="Passed"),"",IF(R53<=TODAY(),"DUE",IF(R53<=TODAY()+3,"Next 3 Days","Later"))) | W53: | 12/05/2025 | | X53: John - Investor Contacts!609 | Y53: Send next follow-up with traction + CTA | Z53: 7 | AA53: =IF(AC53="Archived",0,ROUND((IF(N53="Tier 1",35,IF(N53="Tier 2",20,8))+IF(C53="Financial Investor",15,IF(C53="Intermediary / Banker",12,8))+IF(L53="Term Sheet / Proposal",25,IF(L53="Engaged",20,IF(L53="Meeting Requested",18,IF(L53="Meeting Held",14,IF(L53="Follow Up",10,5)))))+MIN(Q53,30)+IF(S53="DUE",15,IF(S53="Next 3 Days",8,0))),0)) | AB53: =IF(AND(AC53="Active",OR(N53="Tier 1",N53="Tier 2"),OR(S53="DUE",S53="Next 3 Days")),"YES","") | AC53: =IF(L53="Passed","Archived","Active")
A54: EXOS-0053 | B54: John - Investor Contacts | C54: Financial Investor | D54: .406 Ventures | E54: Graham Brooks | G54: gbrooks@406ventures.com | J54: https://www.linkedin.com/in/grahambrooks/ | K54: John Quinn | L54: Follow Up | M54: Space / Defense / Aerospace / Advanced Manufacturing | N54: Tier 2 | O54: 45792 | P54: 45841 | Q54: =IF(P54="","",TODAY()-P54) | R54: =IF(OR(L54="Passed",Z54=""),"",P54+Z54) | S54: =IF(OR(R54="",L54="Passed"),"",IF(R54<=TODAY(),"DUE",IF(R54<=TODAY()+3,"Next 3 Days","Later"))) | U54: https://www.linkedin.com/in/grahambrooks/ | W54: | | | X54: John - Investor Contacts!44 | Y54: Send next follow-up with traction + CTA | Z54: 7 | AA54: =IF(AC54="Archived",0,ROUND((IF(N54="Tier 1",35,IF(N54="Tier 2",20,8))+IF(C54="Financial Investor",15,IF(C54="Intermediary / Banker",12,8))+IF(L54="Term Sheet / Proposal",25,IF(L54="Engaged",20,IF(L54="Meeting Requested",18,IF(L54="Meeting Held",14,IF(L54="Follow Up",10,5)))))+MIN(Q54,30)+IF(S54="DUE",15,IF(S54="Next 3 Days",8,0))),0)) | AB54: =IF(AND(AC54="Active",OR(N54="Tier 1",N54="Tier 2"),OR(S54="DUE",S54="Next 3 Days")),"YES","") | AC54: =IF(L54="Passed","Archived","Active")
A55: EXOS-0054 | B55: John - Investor Contacts | C55: Financial Investor | D55: .406 Ventures | E55: Greg Dracon | G55: gdracon@406ventures.com | J55: https://www.linkedin.com/in/gdracon/ | K55: John Quinn | L55: Follow Up | M55: Space / Defense / Aerospace / Advanced Manufacturing | N55: Tier 2 | O55: 45792 | P55: 45841 | Q55: =IF(P55="","",TODAY()-P55) | R55: =IF(OR(L55="Passed",Z55=""),"",P55+Z55) | S55: =IF(OR(R55="",L55="Passed"),"",IF(R55<=TODAY(),"DUE",IF(R55<=TODAY()+3,"Next 3 Days","Later"))) | U55: https://www.linkedin.com/in/gdracon/ | W55: | | | X55: John - Investor Contacts!43 | Y55: Send next follow-up with traction + CTA | Z55: 7 | AA55: =IF(AC55="Archived",0,ROUND((IF(N55="Tier 1",35,IF(N55="Tier 2",20,8))+IF(C55="Financial Investor",15,IF(C55="Intermediary / Banker",12,8))+IF(L55="Term Sheet / Proposal",25,IF(L55="Engaged",20,IF(L55="Meeting Requested",18,IF(L55="Meeting Held",14,IF(L55="Follow Up",10,5)))))+MIN(Q55,30)+IF(S55="DUE",15,IF(S55="Next 3 Days",8,0))),0)) | AB55: =IF(AND(AC55="Active",OR(N55="Tier 1",N55="Tier 2"),OR(S55="DUE",S55="Next 3 Days")),"YES","") | AC55: =IF(L55="Passed","Archived","Active")
A56: EXOS-0055 | B56: John - Investor Contacts | C56: Financial Investor | D56: .406 Ventures | E56: Liam Donohue | G56: ldonohue@406ventures.com | J56: https://www.linkedin.com/in/ldonohue/ | K56: John Quinn | L56: Follow Up | M56: Space / Defense / Aerospace / Advanced Manufacturing | N56: Tier 2 | O56: 45792 | P56: 45841 | Q56: =IF(P56="","",TODAY()-P56) | R56: =IF(OR(L56="Passed",Z56=""),"",P56+Z56) | S56: =IF(OR(R56="",L56="Passed"),"",IF(R56<=TODAY(),"DUE",IF(R56<=TODAY()+3,"Next 3 Days","Later"))) | U56: https://www.linkedin.com/in/ldonohue/ | W56: | | | X56: John - Investor Contacts!45 | Y56: Send next follow-up with traction + CTA | Z56: 7 | AA56: =IF(AC56="Archived",0,ROUND((IF(N56="Tier 1",35,IF(N56="Tier 2",20,8))+IF(C56="Financial Investor",15,IF(C56="Intermediary / Banker",12,8))+IF(L56="Term Sheet / Proposal",25,IF(L56="Engaged",20,IF(L56="Meeting Requested",18,IF(L56="Meeting Held",14,IF(L56="Follow Up",10,5)))))+MIN(Q56,30)+IF(S56="DUE",15,IF(S56="Next 3 Days",8,0))),0)) | AB56: =IF(AND(AC56="Active",OR(N56="Tier 1",N56="Tier 2"),OR(S56="DUE",S56="Next 3 Days")),"YES","") | AC56: =IF(L56="Passed","Archived","Active")
A57: EXOS-0056 | B57: John - Investor Contacts | C57: Financial Investor | D57: .406 Ventures | E57: Payal Agrawal Divakaran | G57: payal@406ventures.com | J57: https://www.linkedin.com/in/payaldivakaran/ | K57: John Quinn | L57: Follow Up | M57: Space / Defense / Aerospace / Advanced Manufacturing | N57: Tier 2 | O57: 45792 | P57: 45841 | Q57: =IF(P57="","",TODAY()-P57) | R57: =IF(OR(L57="Passed",Z57=""),"",P57+Z57) | S57: =IF(OR(R57="",L57="Passed"),"",IF(R57<=TODAY(),"DUE",IF(R57<=TODAY()+3,"Next 3 Days","Later"))) | U57: https://www.linkedin.com/in/payaldivakaran/ | W57: | | | X57: John - Investor Contacts!42 | Y57: Send next follow-up with traction + CTA | Z57: 7 | AA57: =IF(AC57="Archived",0,ROUND((IF(N57="Tier 1",35,IF(N57="Tier 2",20,8))+IF(C57="Financial Investor",15,IF(C57="Intermediary / Banker",12,8))+IF(L57="Term Sheet / Proposal",25,IF(L57="Engaged",20,IF(L57="Meeting Requested",18,IF(L57="Meeting Held",14,IF(L57="Follow Up",10,5)))))+MIN(Q57,30)+IF(S57="DUE",15,IF(S57="Next 3 Days",8,0))),0)) | AB57: =IF(AND(AC57="Active",OR(N57="Tier 1",N57="Tier 2"),OR(S57="DUE",S57="Next 3 Days")),"YES","") | AC57: =IF(L57="Passed","Archived","Active")
A58: EXOS-0057 | B58: John - Investor Contacts | C58: Financial Investor | D58: 137 Ventures | E58: Alexander Jacobson | G58: alex@137ventures.com | J58: https://www.linkedin.com/in/jacobsonalex/ | K58: John Quinn | L58: Follow Up | M58: Space / Defense / Aerospace / Advanced Manufacturing | N58: Tier 2 | O58: 45946 | P58: 45973 | Q58: =IF(P58="","",TODAY()-P58) | R58: =IF(OR(L58="Passed",Z58=""),"",P58+Z58) | S58: =IF(OR(R58="",L58="Passed"),"",IF(R58<=TODAY(),"DUE",IF(R58<=TODAY()+3,"Next 3 Days","Later"))) | U58: https://www.linkedin.com/in/jacobsonalex/ | W58: | 12/30/2025 | | X58: John - Investor Contacts!764 | Y58: Send next follow-up with traction + CTA | Z58: 7 | AA58: =IF(AC58="Archived",0,ROUND((IF(N58="Tier 1",35,IF(N58="Tier 2",20,8))+IF(C58="Financial Investor",15,IF(C58="Intermediary / Banker",12,8))+IF(L58="Term Sheet / Proposal",25,IF(L58="Engaged",20,IF(L58="Meeting Requested",18,IF(L58="Meeting Held",14,IF(L58="Follow Up",10,5)))))+MIN(Q58,30)+IF(S58="DUE",15,IF(S58="Next 3 Days",8,0))),0)) | AB58: =IF(AND(AC58="Active",OR(N58="Tier 1",N58="Tier 2"),OR(S58="DUE",S58="Next 3 Days")),"YES","") | AC58: =IF(L58="Passed","Archived","Active")
A59: EXOS-0058 | B59: John - Investor Contacts | C59: Financial Investor | D59: 137 Ventures | E59: Andrew Hansen | G59: andrew@137ventures.com | J59: https://www.linkedin.com/in/andrewhansen1/ | K59: John Quinn | L59: Follow Up | M59: Space / Defense / Aerospace / Advanced Manufacturing | N59: Tier 2 | O59: 45946 | P59: 45973 | Q59: =IF(P59="","",TODAY()-P59) | R59: =IF(OR(L59="Passed",Z59=""),"",P59+Z59) | S59: =IF(OR(R59="",L59="Passed"),"",IF(R59<=TODAY(),"DUE",IF(R59<=TODAY()+3,"Next 3 Days","Later"))) | U59: https://www.linkedin.com/in/andrewhansen1/ | W59: | 12/30/2025 | | X59: John - Investor Contacts!766 | Y59: Send next follow-up with traction + CTA | Z59: 7 | AA59: =IF(AC59="Archived",0,ROUND((IF(N59="Tier 1",35,IF(N59="Tier 2",20,8))+IF(C59="Financial Investor",15,IF(C59="Intermediary / Banker",12,8))+IF(L59="Term Sheet / Proposal",25,IF(L59="Engaged",20,IF(L59="Meeting Requested",18,IF(L59="Meeting Held",14,IF(L59="Follow Up",10,5)))))+MIN(Q59,30)+IF(S59="DUE",15,IF(S59="Next 3 Days",8,0))),0)) | AB59: =IF(AND(AC59="Active",OR(N59="Tier 1",N59="Tier 2"),OR(S59="DUE",S59="Next 3 Days")),"YES","") | AC59: =IF(L59="Passed","Archived","Active")
A60: EXOS-0059 | B60: John - Investor Contacts | C60: Financial Investor | D60: 137 Ventures | E60: Christian Garrett | G60: christian@137ventures.com | J60: https://www.linkedin.com/in/christiangarrett15/ | K60: John Quinn | L60: Follow Up | M60: Space / Defense / Aerospace / Advanced Manufacturing | N60: Tier 2 | O60: 45946 | P60: 45973 | Q60: =IF(P60="","",TODAY()-P60) | R60: =IF(OR(L60="Passed",Z60=""),"",P60+Z60) | S60: =IF(OR(R60="",L60="Passed"),"",IF(R60<=TODAY(),"DUE",IF(R60<=TODAY()+3,"Next 3 Days","Later"))) | U60: https://www.linkedin.com/in/christiangarrett15/ | W60: | 12/30/2025 | | X60: John - Investor Contacts!765 | Y60: Send next follow-up with traction + CTA | Z60: 7 | AA60: =IF(AC60="Archived",0,ROUND((IF(N60="Tier 1",35,IF(N60="Tier 2",20,8))+IF(C60="Financial Investor",15,IF(C60="Intermediary / Banker",12,8))+IF(L60="Term Sheet / Proposal",25,IF(L60="Engaged",20,IF(L60="Meeting Requested",18,IF(L60="Meeting Held",14,IF(L60="Follow Up",10,5)))))+MIN(Q60,30)+IF(S60="DUE",15,IF(S60="Next 3 Days",8,0))),0)) | AB60: =IF(AND(AC60="Active",OR(N60="Tier 1",N60="Tier 2"),OR(S60="DUE",S60="Next 3 Days")),"YES","") | AC60: =IF(L60="Passed","Archived","Active")
A61: EXOS-0060 | B61: John - Investor Contacts | C61: Financial Investor | D61: 137 Ventures | E61: James Pardee | G61: james@137ventures.com | J61: https://www.linkedin.com/in/jameslpardee/ | K61: John Quinn | L61: Follow Up | M61: Space / Defense / Aerospace / Advanced Manufacturing | N61: Tier 2 | O61: 45946 | P61: 45973 | Q61: =IF(P61="","",TODAY()-P61) | R61: =IF(OR(L61="Passed",Z61=""),"",P61+Z61) | S61: =IF(OR(R61="",L61="Passed"),"",IF(R61<=TODAY(),"DUE",IF(R61<=TODAY()+3,"Next 3 Days","Later"))) | U61: https://www.linkedin.com/in/jameslpardee/ | W61: | 12/30/2025 | | X61: John - Investor Contacts!767 | Y61: Send next follow-up with traction + CTA | Z61: 7 | AA61: =IF(AC61="Archived",0,ROUND((IF(N61="Tier 1",35,IF(N61="Tier 2",20,8))+IF(C61="Financial Investor",15,IF(C61="Intermediary / Banker",12,8))+IF(L61="Term Sheet / Proposal",25,IF(L61="Engaged",20,IF(L61="Meeting Requested",18,IF(L61="Meeting Held",14,IF(L61="Follow Up",10,5)))))+MIN(Q61,30)+IF(S61="DUE",15,IF(S61="Next 3 Days",8,0))),0)) | AB61: =IF(AND(AC61="Active",OR(N61="Tier 1",N61="Tier 2"),OR(S61="DUE",S61="Next 3 Days")),"YES","") | AC61: =IF(L61="Passed","Archived","Active")
A62: EXOS-0061 | B62: John - Investor Contacts | C62: Financial Investor | D62: 137 Ventures | E62: Justin Fishner-Wolfson | G62: justin@137ventures.com | K62: John Quinn | L62: Follow Up | M62: Space / Defense / Aerospace / Advanced Manufacturing | N62: Tier 2 | O62: 45946 | P62: 45973 | Q62: =IF(P62="","",TODAY()-P62) | R62: =IF(OR(L62="Passed",Z62=""),"",P62+Z62) | S62: =IF(OR(R62="",L62="Passed"),"",IF(R62<=TODAY(),"DUE",IF(R62<=TODAY()+3,"Next 3 Days","Later"))) | U62: linkedin.com/in/justinfw | W62: | 12/30/2025 | | X62: John - Investor Contacts!768 | Y62: Send next follow-up with traction + CTA | Z62: 7 | AA62: =IF(AC62="Archived",0,ROUND((IF(N62="Tier 1",35,IF(N62="Tier 2",20,8))+IF(C62="Financial Investor",15,IF(C62="Intermediary / Banker",12,8))+IF(L62="Term Sheet / Proposal",25,IF(L62="Engaged",20,IF(L62="Meeting Requested",18,IF(L62="Meeting Held",14,IF(L62="Follow Up",10,5)))))+MIN(Q62,30)+IF(S62="DUE",15,IF(S62="Next 3 Days",8,0))),0)) | AB62: =IF(AND(AC62="Active",OR(N62="Tier 1",N62="Tier 2"),OR(S62="DUE",S62="Next 3 Days")),"YES","") | AC62: =IF(L62="Passed","Archived","Active")
A63: EXOS-0062 | B63: John - Investor Contacts | C63: Financial Investor | D63: 1Up Ventures | E63: Ed Fries | G63: ed@1upfund.com | J63: https://www.linkedin.com/in/edfries/ | K63: John Quinn | L63: Follow Up | M63: Space / Defense / Aerospace / Advanced Manufacturing | N63: Tier 2 | O63: 45912 | P63: 45973 | Q63: =IF(P63="","",TODAY()-P63) | R63: =IF(OR(L63="Passed",Z63=""),"",P63+Z63) | S63: =IF(OR(R63="",L63="Passed"),"",IF(R63<=TODAY(),"DUE",IF(R63<=TODAY()+3,"Next 3 Days","Later"))) | U63: https://www.linkedin.com/in/edfries/ | W63: | 12/19/2025 | | X63: John - Investor Contacts!682 | Y63: Send next follow-up with traction + CTA | Z63: 7 | AA63: =IF(AC63="Archived",0,ROUND((IF(N63="Tier 1",35,IF(N63="Tier 2",20,8))+IF(C63="Financial Investor",15,IF(C63="Intermediary / Banker",12,8))+IF(L63="Term Sheet / Proposal",25,IF(L63="Engaged",20,IF(L63="Meeting Requested",18,IF(L63="Meeting Held",14,IF(L63="Follow Up",10,5)))))+MIN(Q63,30)+IF(S63="DUE",15,IF(S63="Next 3 Days",8,0))),0)) | AB63: =IF(AND(AC63="Active",OR(N63="Tier 1",N63="Tier 2"),OR(S63="DUE",S63="Next 3 Days")),"YES","") | AC63: =IF(L63="Passed","Archived","Active")
A64: EXOS-0063 | B64: John - Investor Contacts | C64: Financial Investor | D64: 3 Lines VC | E64: Hemant Elhence | G64: hemant@3lines.vc | J64: https://www.linkedin.com/in/hemantelhence/ | K64: John Quinn | L64: Follow Up | M64: Space / Defense / Aerospace / Advanced Manufacturing | N64: Tier 2 | O64: 45840 | P64: 45861 | Q64: =IF(P64="","",TODAY()-P64) | R64: =IF(OR(L64="Passed",Z64=""),"",P64+Z64) | S64: =IF(OR(R64="",L64="Passed"),"",IF(R64<=TODAY(),"DUE",IF(R64<=TODAY()+3,"Next 3 Days","Later"))) | U64: https://www.linkedin.com/in/hemantelhence/ | W64: | 12/26/2025 | online application: https://3lines.vc/appl | X64: John - Investor Contacts!316 | Y64: Send next follow-up with traction + CTA | Z64: 7 | AA64: =IF(AC64="Archived",0,ROUND((IF(N64="Tier 1",35,IF(N64="Tier 2",20,8))+IF(C64="Financial Investor",15,IF(C64="Intermediary / Banker",12,8))+IF(L64="Term Sheet / Proposal",25,IF(L64="Engaged",20,IF(L64="Meeting Requested",18,IF(L64="Meeting Held",14,IF(L64="Follow Up",10,5)))))+MIN(Q64,30)+IF(S64="DUE",15,IF(S64="Next 3 Days",8,0))),0)) | AB64: =IF(AND(AC64="Active",OR(N64="Tier 1",N64="Tier 2"),OR(S64="DUE",S64="Next 3 Days")),"YES","") | AC64: =IF(L64="Passed","Archived","Active")
A65: EXOS-0064 | B65: John - Investor Contacts | C65: Financial Investor | D65: 3 Lines VC | E65: Kamalesh Dwivedi | G65: kamalesh.dwivedi@3lines.vc | K65: John Quinn | L65: Follow Up | M65: Space / Defense / Aerospace / Advanced Manufacturing | N65: Tier 2 | O65: 45840 | P65: 45861 | Q65: =IF(P65="","",TODAY()-P65) | R65: =IF(OR(L65="Passed",Z65=""),"",P65+Z65) | S65: =IF(OR(R65="",L65="Passed"),"",IF(R65<=TODAY(),"DUE",IF(R65<=TODAY()+3,"Next 3 Days","Later"))) | W65: | 12/26/2025 | | X65: John - Investor Contacts!319 | Y65: Send next follow-up with traction + CTA | Z65: 7 | AA65: =IF(AC65="Archived",0,ROUND((IF(N65="Tier 1",35,IF(N65="Tier 2",20,8))+IF(C65="Financial Investor",15,IF(C65="Intermediary / Banker",12,8))+IF(L65="Term Sheet / Proposal",25,IF(L65="Engaged",20,IF(L65="Meeting Requested",18,IF(L65="Meeting Held",14,IF(L65="Follow Up",10,5)))))+MIN(Q65,30)+IF(S65="DUE",15,IF(S65="Next 3 Days",8,0))),0)) | AB65: =IF(AND(AC65="Active",OR(N65="Tier 1",N65="Tier 2"),OR(S65="DUE",S65="Next 3 Days")),"YES","") | AC65: =IF(L65="Passed","Archived","Active")
A66: EXOS-0065 | B66: John - Investor Contacts | C66: Financial Investor | D66: 3 Lines VC | E66: Krishna Kunapuli | G66: krishna.kunapuli@3lines.vc | J66: https://www.linkedin.com/in/krishna-kunapuli-3lines/ | K66: John Quinn | L66: Follow Up | M66: Space / Defense / Aerospace / Advanced Manufacturing | N66: Tier 2 | O66: 45840 | P66: 45861 | Q66: =IF(P66="","",TODAY()-P66) | R66: =IF(OR(L66="Passed",Z66=""),"",P66+Z66) | S66: =IF(OR(R66="",L66="Passed"),"",IF(R66<=TODAY(),"DUE",IF(R66<=TODAY()+3,"Next 3 Days","Later"))) | U66: https://www.linkedin.com/in/krishna-kunapuli-3lines/ | W66: | 12/26/2025 | | X66: John - Investor Contacts!320 | Y66: Send next follow-up with traction + CTA | Z66: 7 | AA66: =IF(AC66="Archived",0,ROUND((IF(N66="Tier 1",35,IF(N66="Tier 2",20,8))+IF(C66="Financial Investor",15,IF(C66="Intermediary / Banker",12,8))+IF(L66="Term Sheet / Proposal",25,IF(L66="Engaged",20,IF(L66="Meeting Requested",18,IF(L66="Meeting Held",14,IF(L66="Follow Up",10,5)))))+MIN(Q66,30)+IF(S66="DUE",15,IF(S66="Next 3 Days",8,0))),0)) | AB66: =IF(AND(AC66="Active",OR(N66="Tier 1",N66="Tier 2"),OR(S66="DUE",S66="Next 3 Days")),"YES","") | AC66: =IF(L66="Passed","Archived","Active")
A67: EXOS-0066 | B67: John - Investor Contacts | C67: Financial Investor | D67: 3 Lines VC | E67: Pallab K. Chatterjee | G67: pallab.chatterjee@3lines.vc | J67: https://www.linkedin.com/in/dr-pallab-chatterjee-854921/ | K67: John Quinn | L67: Follow Up | M67: Space / Defense / Aerospace / Advanced Manufacturing | N67: Tier 2 | O67: 45840 | P67: 45861 | Q67: =IF(P67="","",TODAY()-P67) | R67: =IF(OR(L67="Passed",Z67=""),"",P67+Z67) | S67: =IF(OR(R67="",L67="Passed"),"",IF(R67<=TODAY(),"DUE",IF(R67<=TODAY()+3,"Next 3 Days","Later"))) | U67: https://www.linkedin.com/in/dr-pallab-chatterjee-854921/ | W67: | 12/26/2025 | | X67: John - Investor Contacts!321 | Y67: Send next follow-up with traction + CTA | Z67: 7 | AA67: =IF(AC67="Archived",0,ROUND((IF(N67="Tier 1",35,IF(N67="Tier 2",20,8))+IF(C67="Financial Investor",15,IF(C67="Intermediary / Banker",12,8))+IF(L67="Term Sheet / Proposal",25,IF(L67="Engaged",20,IF(L67="Meeting Requested",18,IF(L67="Meeting Held",14,IF(L67="Follow Up",10,5)))))+MIN(Q67,30)+IF(S67="DUE",15,IF(S67="Next 3 Days",8,0))),0)) | AB67: =IF(AND(AC67="Active",OR(N67="Tier 1",N67="Tier 2"),OR(S67="DUE",S67="Next 3 Days")),"YES","") | AC67: =IF(L67="Passed","Archived","Active")
A68: EXOS-0067 | B68: John - Investor Contacts | C68: Financial Investor | D68: 3 Lines VC | E68: Rajiv Roy | G68: rajiv.roy@3lines.vc | J68: https://www.linkedin.com/in/rajivroy/ | K68: John Quinn | L68: Follow Up | M68: Space / Defense / Aerospace / Advanced Manufacturing | N68: Tier 2 | O68: 45840 | P68: 45861 | Q68: =IF(P68="","",TODAY()-P68) | R68: =IF(OR(L68="Passed",Z68=""),"",P68+Z68) | S68: =IF(OR(R68="",L68="Passed"),"",IF(R68<=TODAY(),"DUE",IF(R68<=TODAY()+3,"Next 3 Days","Later"))) | U68: https://www.linkedin.com/in/rajivroy/ | W68: | 12/26/2025 | | X68: John - Investor Contacts!318 | Y68: Send next follow-up with traction + CTA | Z68: 7 | AA68: =IF(AC68="Archived",0,ROUND((IF(N68="Tier 1",35,IF(N68="Tier 2",20,8))+IF(C68="Financial Investor",15,IF(C68="Intermediary / Banker",12,8))+IF(L68="Term Sheet / Proposal",25,IF(L68="Engaged",20,IF(L68="Meeting Requested",18,IF(L68="Meeting Held",14,IF(L68="Follow Up",10,5)))))+MIN(Q68,30)+IF(S68="DUE",15,IF(S68="Next 3 Days",8,0))),0)) | AB68: =IF(AND(AC68="Active",OR(N68="Tier 1",N68="Tier 2"),OR(S68="DUE",S68="Next 3 Days")),"YES","") | AC68: =IF(L68="Passed","Archived","Active")
A69: EXOS-0068 | B69: John - Investor Contacts | C69: Financial Investor | D69: 3 Lines VC | E69: Sumanth Channabasappa | G69: sumanth@3lines.vc | K69: John Quinn | L69: Follow Up | M69: Space / Defense / Aerospace / Advanced Manufacturing | N69: Tier 2 | O69: 45840 | P69: 45861 | Q69: =IF(P69="","",TODAY()-P69) | R69: =IF(OR(L69="Passed",Z69=""),"",P69+Z69) | S69: =IF(OR(R69="",L69="Passed"),"",IF(R69<=TODAY(),"DUE",IF(R69<=TODAY()+3,"Next 3 Days","Later"))) | U69: linkedin.com/in/sumanthc | W69: | 12/26/2025 | | X69: John - Investor Contacts!317 | Y69: Send next follow-up with traction + CTA | Z69: 7 | AA69: =IF(AC69="Archived",0,ROUND((IF(N69="Tier 1",35,IF(N69="Tier 2",20,8))+IF(C69="Financial Investor",15,IF(C69="Intermediary / Banker",12,8))+IF(L69="Term Sheet / Proposal",25,IF(L69="Engaged",20,IF(L69="Meeting Requested",18,IF(L69="Meeting Held",14,IF(L69="Follow Up",10,5)))))+MIN(Q69,30)+IF(S69="DUE",15,IF(S69="Next 3 Days",8,0))),0)) | AB69: =IF(AND(AC69="Active",OR(N69="Tier 1",N69="Tier 2"),OR(S69="DUE",S69="Next 3 Days")),"YES","") | AC69: =IF(L69="Passed","Archived","Active")
A70: EXOS-0069 | B70: John - Investor Contacts | C70: Financial Investor | D70: 3LB Seed Capital | E70: Alberto Emprin | G70: a.emprin@3lbseed.com | J70: https://www.linkedin.com/in/albertoemprin/ | K70: John Quinn | L70: Follow Up | M70: Space / Defense / Aerospace / Advanced Manufacturing | N70: Tier 2 | O70: 45989 | P70: 46036 | Q70: =IF(P70="","",TODAY()-P70) | R70: =IF(OR(L70="Passed",Z70=""),"",P70+Z70) | S70: =IF(OR(R70="",L70="Passed"),"",IF(R70<=TODAY(),"DUE",IF(R70<=TODAY()+3,"Next 3 Days","Later"))) | U70: https://www.linkedin.com/in/albertoemprin/ | W70: | 02/26/2026 | | X70: John - Investor Contacts!897 | Y70: Send next follow-up with traction + CTA | Z70: 7 | AA70: =IF(AC70="Archived",0,ROUND((IF(N70="Tier 1",35,IF(N70="Tier 2",20,8))+IF(C70="Financial Investor",15,IF(C70="Intermediary / Banker",12,8))+IF(L70="Term Sheet / Proposal",25,IF(L70="Engaged",20,IF(L70="Meeting Requested",18,IF(L70="Meeting Held",14,IF(L70="Follow Up",10,5)))))+MIN(Q70,30)+IF(S70="DUE",15,IF(S70="Next 3 Days",8,0))),0)) | AB70: =IF(AND(AC70="Active",OR(N70="Tier 1",N70="Tier 2"),OR(S70="DUE",S70="Next 3 Days")),"YES","") | AC70: =IF(L70="Passed","Archived","Active")
A71: EXOS-0070 | B71: John - Investor Contacts | C71: Financial Investor | D71: 4490 Ventures | E71: Dan Malven | G71: dm@4490ventures.com | J71: https://www.linkedin.com/in/danmalven | K71: John Quinn | L71: Follow Up | M71: Space / Defense / Aerospace / Advanced Manufacturing | N71: Tier 2 | O71: 45897 | P71: 45929 | Q71: =IF(P71="","",TODAY()-P71) | R71: =IF(OR(L71="Passed",Z71=""),"",P71+Z71) | S71: =IF(OR(R71="",L71="Passed"),"",IF(R71<=TODAY(),"DUE",IF(R71<=TODAY()+3,"Next 3 Days","Later"))) | U71: https://www.linkedin.com/in/danmalven | W71: | 12/05/2025 | | X71: John - Investor Contacts!568 | Y71: Send next follow-up with traction + CTA | Z71: 7 | AA71: =IF(AC71="Archived",0,ROUND((IF(N71="Tier 1",35,IF(N71="Tier 2",20,8))+IF(C71="Financial Investor",15,IF(C71="Intermediary / Banker",12,8))+IF(L71="Term Sheet / Proposal",25,IF(L71="Engaged",20,IF(L71="Meeting Requested",18,IF(L71="Meeting Held",14,IF(L71="Follow Up",10,5)))))+MIN(Q71,30)+IF(S71="DUE",15,IF(S71="Next 3 Days",8,0))),0)) | AB71: =IF(AND(AC71="Active",OR(N71="Tier 1",N71="Tier 2"),OR(S71="DUE",S71="Next 3 Days")),"YES","") | AC71: =IF(L71="Passed","Archived","Active")
A72: EXOS-0071 | B72: John - Investor Contacts | C72: Financial Investor | D72: 776 Fund | E72: Alexis Ohanian | G72: alexis.ohanian@sevensevensix.com | J72: https://www.linkedin.com/in/alexisohanian/ | K72: John Quinn | L72: Follow Up | M72: Space / Defense / Aerospace / Advanced Manufacturing | N72: Tier 2 | O72: 45897 | P72: 45929 | Q72: =IF(P72="","",TODAY()-P72) | R72: =IF(OR(L72="Passed",Z72=""),"",P72+Z72) | S72: =IF(OR(R72="",L72="Passed"),"",IF(R72<=TODAY(),"DUE",IF(R72<=TODAY()+3,"Next 3 Days","Later"))) | U72: https://www.linkedin.com/in/alexisohanian/ | W72: | 12/05/2025 | | X72: John - Investor Contacts!569 | Y72: Send next follow-up with traction + CTA | Z72: 7 | AA72: =IF(AC72="Archived",0,ROUND((IF(N72="Tier 1",35,IF(N72="Tier 2",20,8))+IF(C72="Financial Investor",15,IF(C72="Intermediary / Banker",12,8))+IF(L72="Term Sheet / Proposal",25,IF(L72="Engaged",20,IF(L72="Meeting Requested",18,IF(L72="Meeting Held",14,IF(L72="Follow Up",10,5)))))+MIN(Q72,30)+IF(S72="DUE",15,IF(S72="Next 3 Days",8,0))),0)) | AB72: =IF(AND(AC72="Active",OR(N72="Tier 1",N72="Tier 2"),OR(S72="DUE",S72="Next 3 Days")),"YES","") | AC72: =IF(L72="Passed","Archived","Active")
A73: EXOS-0072 | B73: John - Investor Contacts | C73: Financial Investor | D73: 8VC | E73: Alex Kolicich | G73: alex@8vc.com | K73: John Quinn | L73: Follow Up | M73: Space / Defense / Aerospace / Advanced Manufacturing | N73: Tier 2 | O73: 45966 | P73: 45985 | Q73: =IF(P73="","",TODAY()-P73) | R73: =IF(OR(L73="Passed",Z73=""),"",P73+Z73) | S73: =IF(OR(R73="",L73="Passed"),"",IF(R73<=TODAY(),"DUE",IF(R73<=TODAY()+3,"Next 3 Days","Later"))) | U73: linkedin.com/in/alex-kolicich-b71732a | W73: | 01/14/2026 | | X73: John - Investor Contacts!827 | Y73: Send next follow-up with traction + CTA | Z73: 7 | AA73: =IF(AC73="Archived",0,ROUND((IF(N73="Tier 1",35,IF(N73="Tier 2",20,8))+IF(C73="Financial Investor",15,IF(C73="Intermediary / Banker",12,8))+IF(L73="Term Sheet / Proposal",25,IF(L73="Engaged",20,IF(L73="Meeting Requested",18,IF(L73="Meeting Held",14,IF(L73="Follow Up",10,5)))))+MIN(Q73,30)+IF(S73="DUE",15,IF(S73="Next 3 Days",8,0))),0)) | AB73: =IF(AND(AC73="Active",OR(N73="Tier 1",N73="Tier 2"),OR(S73="DUE",S73="Next 3 Days")),"YES","") | AC73: =IF(L73="Passed","Archived","Active")
A74: EXOS-0073 | B74: John - Investor Contacts | C74: Financial Investor | D74: 8VC | E74: Drew Oetting | G74: drew@8vc.com | K74: John Quinn | L74: Follow Up | M74: Space / Defense / Aerospace / Advanced Manufacturing | N74: Tier 2 | O74: 45966 | P74: 45985 | Q74: =IF(P74="","",TODAY()-P74) | R74: =IF(OR(L74="Passed",Z74=""),"",P74+Z74) | S74: =IF(OR(R74="",L74="Passed"),"",IF(R74<=TODAY(),"DUE",IF(R74<=TODAY()+3,"Next 3 Days","Later"))) | U74: linkedin.com/in/drew-oetting-52463337 | W74: | 01/14/2026 | | X74: John - Investor Contacts!824 | Y74: Send next follow-up with traction + CTA | Z74: 7 | AA74: =IF(AC74="Archived",0,ROUND((IF(N74="Tier 1",35,IF(N74="Tier 2",20,8))+IF(C74="Financial Investor",15,IF(C74="Intermediary / Banker",12,8))+IF(L74="Term Sheet / Proposal",25,IF(L74="Engaged",20,IF(L74="Meeting Requested",18,IF(L74="Meeting Held",14,IF(L74="Follow Up",10,5)))))+MIN(Q74,30)+IF(S74="DUE",15,IF(S74="Next 3 Days",8,0))),0)) | AB74: =IF(AND(AC74="Active",OR(N74="Tier 1",N74="Tier 2"),OR(S74="DUE",S74="Next 3 Days")),"YES","") | AC74: =IF(L74="Passed","Archived","Active")
A75: EXOS-0074 | B75: John - Investor Contacts | C75: Financial Investor | D75: 8VC | E75: Joe Lonsdale | G75: joe@8vc.com | J75: https://www.linkedin.com/in/jtlonsdale | K75: John Quinn | L75: Follow Up | M75: Space / Defense / Aerospace / Advanced Manufacturing | N75: Tier 2 | O75: 45966 | P75: 45985 | Q75: =IF(P75="","",TODAY()-P75) | R75: =IF(OR(L75="Passed",Z75=""),"",P75+Z75) | S75: =IF(OR(R75="",L75="Passed"),"",IF(R75<=TODAY(),"DUE",IF(R75<=TODAY()+3,"Next 3 Days","Later"))) | U75: https://www.linkedin.com/in/jtlonsdale | W75: | 01/14/2026 | | X75: John - Investor Contacts!825 | Y75: Send next follow-up with traction + CTA | Z75: 7 | AA75: =IF(AC75="Archived",0,ROUND((IF(N75="Tier 1",35,IF(N75="Tier 2",20,8))+IF(C75="Financial Investor",15,IF(C75="Intermediary / Banker",12,8))+IF(L75="Term Sheet / Proposal",25,IF(L75="Engaged",20,IF(L75="Meeting Requested",18,IF(L75="Meeting Held",14,IF(L75="Follow Up",10,5)))))+MIN(Q75,30)+IF(S75="DUE",15,IF(S75="Next 3 Days",8,0))),0)) | AB75: =IF(AND(AC75="Active",OR(N75="Tier 1",N75="Tier 2"),OR(S75="DUE",S75="Next 3 Days")),"YES","") | AC75: =IF(L75="Passed","Archived","Active")
A76: EXOS-0075 | B76: John - Investor Contacts | C76: Financial Investor | D76: 8VC | E76: Kimmy Scotti | G76: kimmy@8vc.com | K76: John Quinn | L76: Follow Up | M76: Space / Defense / Aerospace / Advanced Manufacturing | N76: Tier 2 | O76: 45966 | P76: 45985 | Q76: =IF(P76="","",TODAY()-P76) | R76: =IF(OR(L76="Passed",Z76=""),"",P76+Z76) | S76: =IF(OR(R76="",L76="Passed"),"",IF(R76<=TODAY(),"DUE",IF(R76<=TODAY()+3,"Next 3 Days","Later"))) | U76: linkedin.com/in/kimmyscotti | W76: | 01/14/2026 | | X76: John - Investor Contacts!826 | Y76: Send next follow-up with traction + CTA | Z76: 7 | AA76: =IF(AC76="Archived",0,ROUND((IF(N76="Tier 1",35,IF(N76="Tier 2",20,8))+IF(C76="Financial Investor",15,IF(C76="Intermediary / Banker",12,8))+IF(L76="Term Sheet / Proposal",25,IF(L76="Engaged",20,IF(L76="Meeting Requested",18,IF(L76="Meeting Held",14,IF(L76="Follow Up",10,5)))))+MIN(Q76,30)+IF(S76="DUE",15,IF(S76="Next 3 Days",8,0))),0)) | AB76: =IF(AND(AC76="Active",OR(N76="Tier 1",N76="Tier 2"),OR(S76="DUE",S76="Next 3 Days")),"YES","") | AC76: =IF(L76="Passed","Archived","Active")
A77: EXOS-0076 | B77: John - Investor Contacts | C77: Financial Investor | D77: 97212 VC | E77: Eyal Bino | G77: eyalbino@gmail.com | J77: https://www.linkedin.com/in/eyal-bino/ | K77: John Quinn | L77: Follow Up | M77: Space / Defense / Aerospace / Advanced Manufacturing | N77: Tier 2 | O77: 45872 | P77: 45890 | Q77: =IF(P77="","",TODAY()-P77) | R77: =IF(OR(L77="Passed",Z77=""),"",P77+Z77) | S77: =IF(OR(R77="",L77="Passed"),"",IF(R77<=TODAY(),"DUE",IF(R77<=TODAY()+3,"Next 3 Days","Later"))) | U77: https://www.linkedin.com/in/eyal-bino/ | W77: | 12/29/2025 | | X77: John - Investor Contacts!434 | Y77: Send next follow-up with traction + CTA | Z77: 7 | AA77: =IF(AC77="Archived",0,ROUND((IF(N77="Tier 1",35,IF(N77="Tier 2",20,8))+IF(C77="Financial Investor",15,IF(C77="Intermediary / Banker",12,8))+IF(L77="Term Sheet / Proposal",25,IF(L77="Engaged",20,IF(L77="Meeting Requested",18,IF(L77="Meeting Held",14,IF(L77="Follow Up",10,5)))))+MIN(Q77,30)+IF(S77="DUE",15,IF(S77="Next 3 Days",8,0))),0)) | AB77: =IF(AND(AC77="Active",OR(N77="Tier 1",N77="Tier 2"),OR(S77="DUE",S77="Next 3 Days")),"YES","") | AC77: =IF(L77="Passed","Archived","Active")
A78: EXOS-0077 | B78: John - Investor Contacts | C78: Financial Investor | D78: 97212 VC | E78: Ronie Lavi | G78: ronnie@97212.vc | J78: https://www.linkedin.com/in/ronnielavi/ | K78: John Quinn | L78: Follow Up | M78: Space / Defense / Aerospace / Advanced Manufacturing | N78: Tier 2 | O78: 45872 | P78: 45890 | Q78: =IF(P78="","",TODAY()-P78) | R78: =IF(OR(L78="Passed",Z78=""),"",P78+Z78) | S78: =IF(OR(R78="",L78="Passed"),"",IF(R78<=TODAY(),"DUE",IF(R78<=TODAY()+3,"Next 3 Days","Later"))) | U78: https://www.linkedin.com/in/ronnielavi/ | W78: | 12/29/2025 | | X78: John - Investor Contacts!433 | Y78: Send next follow-up with traction + CTA | Z78: 7 | AA78: =IF(AC78="Archived",0,ROUND((IF(N78="Tier 1",35,IF(N78="Tier 2",20,8))+IF(C78="Financial Investor",15,IF(C78="Intermediary / Banker",12,8))+IF(L78="Term Sheet / Proposal",25,IF(L78="Engaged",20,IF(L78="Meeting Requested",18,IF(L78="Meeting Held",14,IF(L78="Follow Up",10,5)))))+MIN(Q78,30)+IF(S78="DUE",15,IF(S78="Next 3 Days",8,0))),0)) | AB78: =IF(AND(AC78="Active",OR(N78="Tier 1",N78="Tier 2"),OR(S78="DUE",S78="Next 3 Days")),"YES","") | AC78: =IF(L78="Passed","Archived","Active")
A79: EXOS-0078 | B79: John - Investor Contacts | C79: Financial Investor | D79: ACMI Group | E79: Kishen Raghunath | G79: kraghunath@acmigroup.com | K79: John Quinn | L79: Follow Up | M79: Space / Defense / Aerospace / Advanced Manufacturing | N79: Tier 2 | Q79: =IF(P79="","",TODAY()-P79) | R79: =IF(OR(L79="Passed",Z79=""),"",P79+Z79) | S79: =IF(OR(R79="",L79="Passed"),"",IF(R79<=TODAY(),"DUE",IF(R79<=TODAY()+3,"Next 3 Days","Later"))) | W79: follow up email sent 5/27 // put you in contact with vboelscher@acmigroup.com // also talking to jbowling@acmigroup.com | | | X79: John - Investor Contacts!79 | Y79: Send next follow-up with traction + CTA | Z79: 7 | AA79: =IF(AC79="Archived",0,ROUND((IF(N79="Tier 1",35,IF(N79="Tier 2",20,8))+IF(C79="Financial Investor",15,IF(C79="Intermediary / Banker",12,8))+IF(L79="Term Sheet / Proposal",25,IF(L79="Engaged",20,IF(L79="Meeting Requested",18,IF(L79="Meeting Held",14,IF(L79="Follow Up",10,5)))))+MIN(Q79,30)+IF(S79="DUE",15,IF(S79="Next 3 Days",8,0))),0)) | AB79: =IF(AND(AC79="Active",OR(N79="Tier 1",N79="Tier 2"),OR(S79="DUE",S79="Next 3 Days")),"YES","") | AC79: =IF(L79="Passed","Archived","Active")
A80: EXOS-0079 | B80: John - Investor Contacts | C80: Financial Investor | D80: AIN Ventures | E80: Emily McMahan | G80: emily@academyinvestor.com | K80: John Quinn | L80: Follow Up | M80: Space / Defense / Aerospace / Advanced Manufacturing | N80: Tier 2 | O80: 45912 | P80: 45973 | Q80: =IF(P80="","",TODAY()-P80) | R80: =IF(OR(L80="Passed",Z80=""),"",P80+Z80) | S80: =IF(OR(R80="",L80="Passed"),"",IF(R80<=TODAY(),"DUE",IF(R80<=TODAY()+3,"Next 3 Days","Later"))) | U80: linkedin.com/in/emilymcmahan | W80: | 12/19/2025 | | X80: John - Investor Contacts!669 | Y80: Send next follow-up with traction + CTA | Z80: 7 | AA80: =IF(AC80="Archived",0,ROUND((IF(N80="Tier 1",35,IF(N80="Tier 2",20,8))+IF(C80="Financial Investor",15,IF(C80="Intermediary / Banker",12,8))+IF(L80="Term Sheet / Proposal",25,IF(L80="Engaged",20,IF(L80="Meeting Requested",18,IF(L80="Meeting Held",14,IF(L80="Follow Up",10,5)))))+MIN(Q80,30)+IF(S80="DUE",15,IF(S80="Next 3 Days",8,0))),0)) | AB80: =IF(AND(AC80="Active",OR(N80="Tier 1",N80="Tier 2"),OR(S80="DUE",S80="Next 3 Days")),"YES","") | AC80: =IF(L80="Passed","Archived","Active")
A81: EXOS-0080 | B81: John - Investor Contacts | C81: Financial Investor | D81: AIN Ventures | E81: Forrest Underwood | G81: forrest@academyinvestor.com | J81: https://www.linkedin.com/in/forrestunderwood | K81: John Quinn | L81: Follow Up | M81: Space / Defense / Aerospace / Advanced Manufacturing | N81: Tier 2 | O81: 45912 | P81: 45973 | Q81: =IF(P81="","",TODAY()-P81) | R81: =IF(OR(L81="Passed",Z81=""),"",P81+Z81) | S81: =IF(OR(R81="",L81="Passed"),"",IF(R81<=TODAY(),"DUE",IF(R81<=TODAY()+3,"Next 3 Days","Later"))) | U81: https://www.linkedin.com/in/forrestunderwood | W81: | 12/19/2025 | | X81: John - Investor Contacts!668 | Y81: Send next follow-up with traction + CTA | Z81: 7 | AA81: =IF(AC81="Archived",0,ROUND((IF(N81="Tier 1",35,IF(N81="Tier 2",20,8))+IF(C81="Financial Investor",15,IF(C81="Intermediary / Banker",12,8))+IF(L81="Term Sheet / Proposal",25,IF(L81="Engaged",20,IF(L81="Meeting Requested",18,IF(L81="Meeting Held",14,IF(L81="Follow Up",10,5)))))+MIN(Q81,30)+IF(S81="DUE",15,IF(S81="Next 3 Days",8,0))),0)) | AB81: =IF(AND(AC81="Active",OR(N81="Tier 1",N81="Tier 2"),OR(S81="DUE",S81="Next 3 Days")),"YES","") | AC81: =IF(L81="Passed","Archived","Active")
A82: EXOS-0081 | B82: John - Investor Contacts | C82: Financial Investor | D82: AIN Ventures | E82: Sherman Williams | G82: sherman@academyinvestor.com | J82: https://www.linkedin.com/in/sherman-williams/ | K82: John Quinn | L82: Follow Up | M82: Space / Defense / Aerospace / Advanced Manufacturing | N82: Tier 2 | O82: 45912 | P82: 45973 | Q82: =IF(P82="","",TODAY()-P82) | R82: =IF(OR(L82="Passed",Z82=""),"",P82+Z82) | S82: =IF(OR(R82="",L82="Passed"),"",IF(R82<=TODAY(),"DUE",IF(R82<=TODAY()+3,"Next 3 Days","Later"))) | U82: https://www.linkedin.com/in/sherman-williams/ | W82: | 12/19/2025 | | X82: John - Investor Contacts!670 | Y82: Send next follow-up with traction + CTA | Z82: 7 | AA82: =IF(AC82="Archived",0,ROUND((IF(N82="Tier 1",35,IF(N82="Tier 2",20,8))+IF(C82="Financial Investor",15,IF(C82="Intermediary / Banker",12,8))+IF(L82="Term Sheet / Proposal",25,IF(L82="Engaged",20,IF(L82="Meeting Requested",18,IF(L82="Meeting Held",14,IF(L82="Follow Up",10,5)))))+MIN(Q82,30)+IF(S82="DUE",15,IF(S82="Next 3 Days",8,0))),0)) | AB82: =IF(AND(AC82="Active",OR(N82="Tier 1",N82="Tier 2"),OR(S82="DUE",S82="Next 3 Days")),"YES","") | AC82: =IF(L82="Passed","Archived","Active")
A83: EXOS-0082 | B83: John - Investor Contacts | C83: Financial Investor | D83: APA Venture Partners | E83: Alex Kaufman | G83: alex@apavp.com | J83: https://www.linkedin.com/in/calexkaufman/ | K83: John Quinn | L83: Follow Up | M83: Space / Defense / Aerospace / Advanced Manufacturing | N83: Tier 2 | O83: 45929 | P83: 45973 | Q83: =IF(P83="","",TODAY()-P83) | R83: =IF(OR(L83="Passed",Z83=""),"",P83+Z83) | S83: =IF(OR(R83="",L83="Passed"),"",IF(R83<=TODAY(),"DUE",IF(R83<=TODAY()+3,"Next 3 Days","Later"))) | U83: https://www.linkedin.com/in/calexkaufman/ | W83: | 12/19/2025 | | X83: John - Investor Contacts!688 | Y83: Send next follow-up with traction + CTA | Z83: 7 | AA83: =IF(AC83="Archived",0,ROUND((IF(N83="Tier 1",35,IF(N83="Tier 2",20,8))+IF(C83="Financial Investor",15,IF(C83="Intermediary / Banker",12,8))+IF(L83="Term Sheet / Proposal",25,IF(L83="Engaged",20,IF(L83="Meeting Requested",18,IF(L83="Meeting Held",14,IF(L83="Follow Up",10,5)))))+MIN(Q83,30)+IF(S83="DUE",15,IF(S83="Next 3 Days",8,0))),0)) | AB83: =IF(AND(AC83="Active",OR(N83="Tier 1",N83="Tier 2"),OR(S83="DUE",S83="Next 3 Days")),"YES","") | AC83: =IF(L83="Passed","Archived","Active")
A84: EXOS-0083 | B84: John - Investor Contacts | C84: Financial Investor | D84: ATEM Capital | E84: Allan Gobbs | G84: ag@atemcap.com | J84: https://www.linkedin.com/in/gobbs/ | K84: John Quinn | L84: Follow Up | M84: Space / Defense / Aerospace / Advanced Manufacturing | N84: Tier 2 | O84: 45841 | P84: 45861 | Q84: =IF(P84="","",TODAY()-P84) | R84: =IF(OR(L84="Passed",Z84=""),"",P84+Z84) | S84: =IF(OR(R84="",L84="Passed"),"",IF(R84<=TODAY(),"DUE",IF(R84<=TODAY()+3,"Next 3 Days","Later"))) | U84: https://www.linkedin.com/in/gobbs/ | W84: | 12/26/2025 | | X84: John - Investor Contacts!343 | Y84: Send next follow-up with traction + CTA | Z84: 7 | AA84: =IF(AC84="Archived",0,ROUND((IF(N84="Tier 1",35,IF(N84="Tier 2",20,8))+IF(C84="Financial Investor",15,IF(C84="Intermediary / Banker",12,8))+IF(L84="Term Sheet / Proposal",25,IF(L84="Engaged",20,IF(L84="Meeting Requested",18,IF(L84="Meeting Held",14,IF(L84="Follow Up",10,5)))))+MIN(Q84,30)+IF(S84="DUE",15,IF(S84="Next 3 Days",8,0))),0)) | AB84: =IF(AND(AC84="Active",OR(N84="Tier 1",N84="Tier 2"),OR(S84="DUE",S84="Next 3 Days")),"YES","") | AC84: =IF(L84="Passed","Archived","Active")
A85: EXOS-0084 | B85: John - Investor Contacts | C85: Financial Investor | D85: ATEM Capital | E85: Elena Maley | G85: em@atemcap.com | J85: https://www.linkedin.com/in/elena-maley-96627914/ | K85: John Quinn | L85: Follow Up | M85: Space / Defense / Aerospace / Advanced Manufacturing | N85: Tier 2 | O85: 45841 | P85: 45861 | Q85: =IF(P85="","",TODAY()-P85) | R85: =IF(OR(L85="Passed",Z85=""),"",P85+Z85) | S85: =IF(OR(R85="",L85="Passed"),"",IF(R85<=TODAY(),"DUE",IF(R85<=TODAY()+3,"Next 3 Days","Later"))) | U85: https://www.linkedin.com/in/elena-maley-96627914/ | W85: | 12/26/2025 | | X85: John - Investor Contacts!344 | Y85: Send next follow-up with traction + CTA | Z85: 7 | AA85: =IF(AC85="Archived",0,ROUND((IF(N85="Tier 1",35,IF(N85="Tier 2",20,8))+IF(C85="Financial Investor",15,IF(C85="Intermediary / Banker",12,8))+IF(L85="Term Sheet / Proposal",25,IF(L85="Engaged",20,IF(L85="Meeting Requested",18,IF(L85="Meeting Held",14,IF(L85="Follow Up",10,5)))))+MIN(Q85,30)+IF(S85="DUE",15,IF(S85="Next 3 Days",8,0))),0)) | AB85: =IF(AND(AC85="Active",OR(N85="Tier 1",N85="Tier 2"),OR(S85="DUE",S85="Next 3 Days")),"YES","") | AC85: =IF(L85="Passed","Archived","Active")
A86: EXOS-0085 | B86: John - Investor Contacts | C86: Financial Investor | D86: AV8 Ventures | E86: Brett Battles | G86: brett@av8.vc | J86: https://www.linkedin.com/in/bbattles/ | K86: John Quinn | L86: Follow Up | M86: Space / Defense / Aerospace / Advanced Manufacturing | N86: Tier 2 | O86: 45839 | P86: 45861 | Q86: =IF(P86="","",TODAY()-P86) | R86: =IF(OR(L86="Passed",Z86=""),"",P86+Z86) | S86: =IF(OR(R86="",L86="Passed"),"",IF(R86<=TODAY(),"DUE",IF(R86<=TODAY()+3,"Next 3 Days","Later"))) | U86: https://www.linkedin.com/in/bbattles/ | W86: | 12/26/2025 | | X86: John - Investor Contacts!300 | Y86: Send next follow-up with traction + CTA | Z86: 7 | AA86: =IF(AC86="Archived",0,ROUND((IF(N86="Tier 1",35,IF(N86="Tier 2",20,8))+IF(C86="Financial Investor",15,IF(C86="Intermediary / Banker",12,8))+IF(L86="Term Sheet / Proposal",25,IF(L86="Engaged",20,IF(L86="Meeting Requested",18,IF(L86="Meeting Held",14,IF(L86="Follow Up",10,5)))))+MIN(Q86,30)+IF(S86="DUE",15,IF(S86="Next 3 Days",8,0))),0)) | AB86: =IF(AND(AC86="Active",OR(N86="Tier 1",N86="Tier 2"),OR(S86="DUE",S86="Next 3 Days")),"YES","") | AC86: =IF(L86="Passed","Archived","Active")
A87: EXOS-0086 | B87: John - Investor Contacts | C87: Financial Investor | D87: AV8 Ventures | E87: George Ugras | G87: george@av8.vc | J87: https://www.linkedin.com/in/ugras/ | K87: John Quinn | L87: Follow Up | M87: Space / Defense / Aerospace / Advanced Manufacturing | N87: Tier 2 | O87: 45839 | P87: 45861 | Q87: =IF(P87="","",TODAY()-P87) | R87: =IF(OR(L87="Passed",Z87=""),"",P87+Z87) | S87: =IF(OR(R87="",L87="Passed"),"",IF(R87<=TODAY(),"DUE",IF(R87<=TODAY()+3,"Next 3 Days","Later"))) | U87: https://www.linkedin.com/in/ugras/ | W87: | 12/26/2025 | | X87: John - Investor Contacts!299 | Y87: Send next follow-up with traction + CTA | Z87: 7 | AA87: =IF(AC87="Archived",0,ROUND((IF(N87="Tier 1",35,IF(N87="Tier 2",20,8))+IF(C87="Financial Investor",15,IF(C87="Intermediary / Banker",12,8))+IF(L87="Term Sheet / Proposal",25,IF(L87="Engaged",20,IF(L87="Meeting Requested",18,IF(L87="Meeting Held",14,IF(L87="Follow Up",10,5)))))+MIN(Q87,30)+IF(S87="DUE",15,IF(S87="Next 3 Days",8,0))),0)) | AB87: =IF(AND(AC87="Active",OR(N87="Tier 1",N87="Tier 2"),OR(S87="DUE",S87="Next 3 Days")),"YES","") | AC87: =IF(L87="Passed","Archived","Active")
A88: EXOS-0087 | B88: John - Investor Contacts | C88: Financial Investor | D88: AV8 Ventures | E88: Ruchita Sinha | G88: ruchita@av8.vc | J88: https://www.linkedin.com/in/ruchita-sinha/ | K88: John Quinn | L88: Follow Up | M88: Space / Defense / Aerospace / Advanced Manufacturing | N88: Tier 2 | O88: 45839 | P88: 45861 | Q88: =IF(P88="","",TODAY()-P88) | R88: =IF(OR(L88="Passed",Z88=""),"",P88+Z88) | S88: =IF(OR(R88="",L88="Passed"),"",IF(R88<=TODAY(),"DUE",IF(R88<=TODAY()+3,"Next 3 Days","Later"))) | U88: https://www.linkedin.com/in/ruchita-sinha/ | W88: | 12/26/2025 | | X88: John - Investor Contacts!302 | Y88: Send next follow-up with traction + CTA | Z88: 7 | AA88: =IF(AC88="Archived",0,ROUND((IF(N88="Tier 1",35,IF(N88="Tier 2",20,8))+IF(C88="Financial Investor",15,IF(C88="Intermediary / Banker",12,8))+IF(L88="Term Sheet / Proposal",25,IF(L88="Engaged",20,IF(L88="Meeting Requested",18,IF(L88="Meeting Held",14,IF(L88="Follow Up",10,5)))))+MIN(Q88,30)+IF(S88="DUE",15,IF(S88="Next 3 Days",8,0))),0)) | AB88: =IF(AND(AC88="Active",OR(N88="Tier 1",N88="Tier 2"),OR(S88="DUE",S88="Next 3 Days")),"YES","") | AC88: =IF(L88="Passed","Archived","Active")
A89: EXOS-0088 | B89: John - Investor Contacts | C89: Financial Investor | D89: AV8 Ventures | E89: Shawn Kung | G89: shawn@av8.vc | J89: https://www.linkedin.com/in/shawnkung/ | K89: John Quinn | L89: Follow Up | M89: Space / Defense / Aerospace / Advanced Manufacturing | N89: Tier 2 | O89: 45839 | P89: 45861 | Q89: =IF(P89="","",TODAY()-P89) | R89: =IF(OR(L89="Passed",Z89=""),"",P89+Z89) | S89: =IF(OR(R89="",L89="Passed"),"",IF(R89<=TODAY(),"DUE",IF(R89<=TODAY()+3,"Next 3 Days","Later"))) | U89: https://www.linkedin.com/in/shawnkung/ | W89: | 12/26/2025 | | X89: John - Investor Contacts!301 | Y89: Send next follow-up with traction + CTA | Z89: 7 | AA89: =IF(AC89="Archived",0,ROUND((IF(N89="Tier 1",35,IF(N89="Tier 2",20,8))+IF(C89="Financial Investor",15,IF(C89="Intermediary / Banker",12,8))+IF(L89="Term Sheet / Proposal",25,IF(L89="Engaged",20,IF(L89="Meeting Requested",18,IF(L89="Meeting Held",14,IF(L89="Follow Up",10,5)))))+MIN(Q89,30)+IF(S89="DUE",15,IF(S89="Next 3 Days",8,0))),0)) | AB89: =IF(AND(AC89="Active",OR(N89="Tier 1",N89="Tier 2"),OR(S89="DUE",S89="Next 3 Days")),"YES","") | AC89: =IF(L89="Passed","Archived","Active")
A90: EXOS-0089 | B90: John - Investor Contacts | C90: Financial Investor | D90: AVP (formerly AXA Venture Partners) | E90: Amy Rudersdorf | G90: amy@weareavp.com | K90: John Quinn | L90: Follow Up | M90: Space / Defense / Aerospace / Advanced Manufacturing | N90: Tier 2 | O90: 45847 | P90: 45861 | Q90: =IF(P90="","",TODAY()-P90) | R90: =IF(OR(L90="Passed",Z90=""),"",P90+Z90) | S90: =IF(OR(R90="",L90="Passed"),"",IF(R90<=TODAY(),"DUE",IF(R90<=TODAY()+3,"Next 3 Days","Later"))) | U90: linkedin.com/in/amyrudersdorf | W90: | 12/26/2025 | | X90: John - Investor Contacts!368 | Y90: Send next follow-up with traction + CTA | Z90: 7 | AA90: =IF(AC90="Archived",0,ROUND((IF(N90="Tier 1",35,IF(N90="Tier 2",20,8))+IF(C90="Financial Investor",15,IF(C90="Intermediary / Banker",12,8))+IF(L90="Term Sheet / Proposal",25,IF(L90="Engaged",20,IF(L90="Meeting Requested",18,IF(L90="Meeting Held",14,IF(L90="Follow Up",10,5)))))+MIN(Q90,30)+IF(S90="DUE",15,IF(S90="Next 3 Days",8,0))),0)) | AB90: =IF(AND(AC90="Active",OR(N90="Tier 1",N90="Tier 2"),OR(S90="DUE",S90="Next 3 Days")),"YES","") | AC90: =IF(L90="Passed","Archived","Active")
A91: EXOS-0090 | B91: John - Investor Contacts | C91: Financial Investor | D91: AVP (formerly AXA Venture Partners) | E91: Ethan Volk | G91: ethan.volk@axavp.com | K91: John Quinn | L91: Follow Up | M91: Space / Defense / Aerospace / Advanced Manufacturing | N91: Tier 2 | O91: 45847 | P91: 45861 | Q91: =IF(P91="","",TODAY()-P91) | R91: =IF(OR(L91="Passed",Z91=""),"",P91+Z91) | S91: =IF(OR(R91="",L91="Passed"),"",IF(R91<=TODAY(),"DUE",IF(R91<=TODAY()+3,"Next 3 Days","Later"))) | U91: linkedin.com/in/ethanvolk | W91: | 12/26/2025 | | X91: John - Investor Contacts!369 | Y91: Send next follow-up with traction + CTA | Z91: 7 | AA91: =IF(AC91="Archived",0,ROUND((IF(N91="Tier 1",35,IF(N91="Tier 2",20,8))+IF(C91="Financial Investor",15,IF(C91="Intermediary / Banker",12,8))+IF(L91="Term Sheet / Proposal",25,IF(L91="Engaged",20,IF(L91="Meeting Requested",18,IF(L91="Meeting Held",14,IF(L91="Follow Up",10,5)))))+MIN(Q91,30)+IF(S91="DUE",15,IF(S91="Next 3 Days",8,0))),0)) | AB91: =IF(AND(AC91="Active",OR(N91="Tier 1",N91="Tier 2"),OR(S91="DUE",S91="Next 3 Days")),"YES","") | AC91: =IF(L91="Passed","Archived","Active")
A92: EXOS-0091 | B92: John - Investor Contacts | C92: Financial Investor | D92: AVP (formerly AXA Venture Partners) | E92: Gregory Krisberg | G92: gregory.krisberg@axavp.com | K92: John Quinn | L92: Follow Up | M92: Space / Defense / Aerospace / Advanced Manufacturing | N92: Tier 2 | O92: 45847 | P92: 45861 | Q92: =IF(P92="","",TODAY()-P92) | R92: =IF(OR(L92="Passed",Z92=""),"",P92+Z92) | S92: =IF(OR(R92="",L92="Passed"),"",IF(R92<=TODAY(),"DUE",IF(R92<=TODAY()+3,"Next 3 Days","Later"))) | U92: linkedin.com/in/gregory-krisberg-90834b143 | W92: | 12/26/2025 | | X92: John - Investor Contacts!370 | Y92: Send next follow-up with traction + CTA | Z92: 7 | AA92: =IF(AC92="Archived",0,ROUND((IF(N92="Tier 1",35,IF(N92="Tier 2",20,8))+IF(C92="Financial Investor",15,IF(C92="Intermediary / Banker",12,8))+IF(L92="Term Sheet / Proposal",25,IF(L92="Engaged",20,IF(L92="Meeting Requested",18,IF(L92="Meeting Held",14,IF(L92="Follow Up",10,5)))))+MIN(Q92,30)+IF(S92="DUE",15,IF(S92="Next 3 Days",8,0))),0)) | AB92: =IF(AND(AC92="Active",OR(N92="Tier 1",N92="Tier 2"),OR(S92="DUE",S92="Next 3 Days")),"YES","") | AC92: =IF(L92="Passed","Archived","Active")
A93: EXOS-0092 | B93: John - Investor Contacts | C93: Financial Investor | D93: Accel | E93: Ben Fletcher | G93: bfletcher@accel.com | J93: https://www.linkedin.com/in/bfletch11/ | K93: John Quinn | L93: Follow Up | M93: Space / Defense / Aerospace / Advanced Manufacturing | N93: Tier 2 | O93: 45790 | P93: 45841 | Q93: =IF(P93="","",TODAY()-P93) | R93: =IF(OR(L93="Passed",Z93=""),"",P93+Z93) | S93: =IF(OR(R93="",L93="Passed"),"",IF(R93<=TODAY(),"DUE",IF(R93<=TODAY()+3,"Next 3 Days","Later"))) | U93: https://www.linkedin.com/in/bfletch11/ | W93: | | | X93: John - Investor Contacts!8 | Y93: Send next follow-up with traction + CTA | Z93: 7 | AA93: =IF(AC93="Archived",0,ROUND((IF(N93="Tier 1",35,IF(N93="Tier 2",20,8))+IF(C93="Financial Investor",15,IF(C93="Intermediary / Banker",12,8))+IF(L93="Term Sheet / Proposal",25,IF(L93="Engaged",20,IF(L93="Meeting Requested",18,IF(L93="Meeting Held",14,IF(L93="Follow Up",10,5)))))+MIN(Q93,30)+IF(S93="DUE",15,IF(S93="Next 3 Days",8,0))),0)) | AB93: =IF(AND(AC93="Active",OR(N93="Tier 1",N93="Tier 2"),OR(S93="DUE",S93="Next 3 Days")),"YES","") | AC93: =IF(L93="Passed","Archived","Active")
A94: EXOS-0093 | B94: John - Investor Contacts | C94: Financial Investor | D94: Accel | E94: Harry Nelis | G94: hnelis@accel.com | J94: https://www.linkedin.com/in/harry-nelis-429801/ | K94: John Quinn | L94: Follow Up | M94: Space / Defense / Aerospace / Advanced Manufacturing | N94: Tier 2 | O94: 45790 | P94: 45841 | Q94: =IF(P94="","",TODAY()-P94) | R94: =IF(OR(L94="Passed",Z94=""),"",P94+Z94) | S94: =IF(OR(R94="",L94="Passed"),"",IF(R94<=TODAY(),"DUE",IF(R94<=TODAY()+3,"Next 3 Days","Later"))) | U94: https://www.linkedin.com/in/harry-nelis-429801/ | W94: | | | X94: John - Investor Contacts!6 | Y94: Send next follow-up with traction + CTA | Z94: 7 | AA94: =IF(AC94="Archived",0,ROUND((IF(N94="Tier 1",35,IF(N94="Tier 2",20,8))+IF(C94="Financial Investor",15,IF(C94="Intermediary / Banker",12,8))+IF(L94="Term Sheet / Proposal",25,IF(L94="Engaged",20,IF(L94="Meeting Requested",18,IF(L94="Meeting Held",14,IF(L94="Follow Up",10,5)))))+MIN(Q94,30)+IF(S94="DUE",15,IF(S94="Next 3 Days",8,0))),0)) | AB94: =IF(AND(AC94="Active",OR(N94="Tier 1",N94="Tier 2"),OR(S94="DUE",S94="Next 3 Days")),"YES","") | AC94: =IF(L94="Passed","Archived","Active")
A95: EXOS-0094 | B95: John - Investor Contacts | C95: Financial Investor | D95: Accel | E95: Prashanth Prakash | G95: pprakash@accel.com | J95: https://www.linkedin.com/in/prakashprashanth/ | K95: John Quinn | L95: Follow Up | M95: Space / Defense / Aerospace / Advanced Manufacturing | N95: Tier 2 | O95: 45790 | P95: 45841 | Q95: =IF(P95="","",TODAY()-P95) | R95: =IF(OR(L95="Passed",Z95=""),"",P95+Z95) | S95: =IF(OR(R95="",L95="Passed"),"",IF(R95<=TODAY(),"DUE",IF(R95<=TODAY()+3,"Next 3 Days","Later"))) | U95: https://www.linkedin.com/in/prakashprashanth/ | W95: | | | X95: John - Investor Contacts!7 | Y95: Send next follow-up with traction + CTA | Z95: 7 | AA95: =IF(AC95="Archived",0,ROUND((IF(N95="Tier 1",35,IF(N95="Tier 2",20,8))+IF(C95="Financial Investor",15,IF(C95="Intermediary / Banker",12,8))+IF(L95="Term Sheet / Proposal",25,IF(L95="Engaged",20,IF(L95="Meeting Requested",18,IF(L95="Meeting Held",14,IF(L95="Follow Up",10,5)))))+MIN(Q95,30)+IF(S95="DUE",15,IF(S95="Next 3 Days",8,0))),0)) | AB95: =IF(AND(AC95="Active",OR(N95="Tier 1",N95="Tier 2"),OR(S95="DUE",S95="Next 3 Days")),"YES","") | AC95: =IF(L95="Passed","Archived","Active")
A96: EXOS-0095 | B96: John - Investor Contacts | OSC | C96: Financial Investor | D96: Acequia Capital | E96: Gregory Bernstein | G96: gregory@acecap.com | I96: 917.748.4052 | J96: https://www.linkedin.com/in/gregory-m-bernstein-34a2b4127/ | K96: John Quinn | L96: Follow Up | M96: Space / Defense / Aerospace / Advanced Manufacturing | N96: Tier 2 | O96: 45853 | P96: 45994 | Q96: =IF(P96="","",TODAY()-P96) | R96: =IF(OR(L96="Passed",Z96=""),"",P96+Z96) | S96: =IF(OR(R96="",L96="Passed"),"",IF(R96<=TODAY(),"DUE",IF(R96<=TODAY()+3,"Next 3 Days","Later"))) | U96: https://www.linkedin.com/in/gregory-m-bernstein-34a2b4127/ | W96: 12/30/2025 | X96: John - Investor Contacts!484 | OSC!12 | Y96: Send next follow-up with traction + CTA | Z96: 7 | AA96: =IF(AC96="Archived",0,ROUND((IF(N96="Tier 1",35,IF(N96="Tier 2",20,8))+IF(C96="Financial Investor",15,IF(C96="Intermediary / Banker",12,8))+IF(L96="Term Sheet / Proposal",25,IF(L96="Engaged",20,IF(L96="Meeting Requested",18,IF(L96="Meeting Held",14,IF(L96="Follow Up",10,5)))))+MIN(Q96,30)+IF(S96="DUE",15,IF(S96="Next 3 Days",8,0))),0)) | AB96: =IF(AND(AC96="Active",OR(N96="Tier 1",N96="Tier 2"),OR(S96="DUE",S96="Next 3 Days")),"YES","") | AC96: =IF(L96="Passed","Archived","Active")
A97: EXOS-0096 | B97: John - Investor Contacts | OSC | C97: Financial Investor | D97: Acequia Capital | E97: Hank Vigil | G97: hank@acecap.com | I97: 425.363.3954 | J97: https://www.linkedin.com/in/hank-vigil-447280160/ | K97: John Quinn | L97: Follow Up | M97: Space / Defense / Aerospace / Advanced Manufacturing | N97: Tier 2 | O97: 45853 | P97: 45994 | Q97: =IF(P97="","",TODAY()-P97) | R97: =IF(OR(L97="Passed",Z97=""),"",P97+Z97) | S97: =IF(OR(R97="",L97="Passed"),"",IF(R97<=TODAY(),"DUE",IF(R97<=TODAY()+3,"Next 3 Days","Later"))) | U97: https://www.linkedin.com/in/hank-vigil-447280160/ | W97: 12/30/2025 | X97: John - Investor Contacts!488 | OSC!16 | Y97: Send next follow-up with traction + CTA | Z97: 7 | AA97: =IF(AC97="Archived",0,ROUND((IF(N97="Tier 1",35,IF(N97="Tier 2",20,8))+IF(C97="Financial Investor",15,IF(C97="Intermediary / Banker",12,8))+IF(L97="Term Sheet / Proposal",25,IF(L97="Engaged",20,IF(L97="Meeting Requested",18,IF(L97="Meeting Held",14,IF(L97="Follow Up",10,5)))))+MIN(Q97,30)+IF(S97="DUE",15,IF(S97="Next 3 Days",8,0))),0)) | AB97: =IF(AND(AC97="Active",OR(N97="Tier 1",N97="Tier 2"),OR(S97="DUE",S97="Next 3 Days")),"YES","") | AC97: =IF(L97="Passed","Archived","Active")
A98: EXOS-0097 | B98: John - Investor Contacts | OSC | C98: Financial Investor | D98: Acequia Capital | E98: Investor Relations | G98: investor.relations@acecap.com | I98: 206.726.7886 | K98: John Quinn | L98: Follow Up | M98: Space / Defense / Aerospace / Advanced Manufacturing | N98: Tier 2 | O98: 45814 | P98: 45922 | Q98: =IF(P98="","",TODAY()-P98) | R98: =IF(OR(L98="Passed",Z98=""),"",P98+Z98) | S98: =IF(OR(R98="",L98="Passed"),"",IF(R98<=TODAY(),"DUE",IF(R98<=TODAY()+3,"Next 3 Days","Later"))) | X98: John - Investor Contacts!133 | OSC!2 | Y98: Send next follow-up with traction + CTA | Z98: 7 | AA98: =IF(AC98="Archived",0,ROUND((IF(N98="Tier 1",35,IF(N98="Tier 2",20,8))+IF(C98="Financial Investor",15,IF(C98="Intermediary / Banker",12,8))+IF(L98="Term Sheet / Proposal",25,IF(L98="Engaged",20,IF(L98="Meeting Requested",18,IF(L98="Meeting Held",14,IF(L98="Follow Up",10,5)))))+MIN(Q98,30)+IF(S98="DUE",15,IF(S98="Next 3 Days",8,0))),0)) | AB98: =IF(AND(AC98="Active",OR(N98="Tier 1",N98="Tier 2"),OR(S98="DUE",S98="Next 3 Days")),"YES","") | AC98: =IF(L98="Passed","Archived","Active")
A99: EXOS-0098 | B99: John - Investor Contacts | OSC | C99: Financial Investor | D99: Acequia Capital | E99: Leif Danielsen | G99: danielsen@acecap.com | J99: https://www.linkedin.com/in/leif-danielsen-35a56550/ | K99: John Quinn | L99: Follow Up | M99: Space / Defense / Aerospace / Advanced Manufacturing | N99: Tier 2 | O99: 45853 | P99: 45994 | Q99: =IF(P99="","",TODAY()-P99) | R99: =IF(OR(L99="Passed",Z99=""),"",P99+Z99) | S99: =IF(OR(R99="",L99="Passed"),"",IF(R99<=TODAY(),"DUE",IF(R99<=TODAY()+3,"Next 3 Days","Later"))) | U99: https://www.linkedin.com/in/leif-danielsen-35a56550/ | W99: 12/30/2025 | X99: John - Investor Contacts!487 | OSC!15 | Y99: Send next follow-up with traction + CTA | Z99: 7 | AA99: =IF(AC99="Archived",0,ROUND((IF(N99="Tier 1",35,IF(N99="Tier 2",20,8))+IF(C99="Financial Investor",15,IF(C99="Intermediary / Banker",12,8))+IF(L99="Term Sheet / Proposal",25,IF(L99="Engaged",20,IF(L99="Meeting Requested",18,IF(L99="Meeting Held",14,IF(L99="Follow Up",10,5)))))+MIN(Q99,30)+IF(S99="DUE",15,IF(S99="Next 3 Days",8,0))),0)) | AB99: =IF(AND(AC99="Active",OR(N99="Tier 1",N99="Tier 2"),OR(S99="DUE",S99="Next 3 Days")),"YES","") | AC99: =IF(L99="Passed","Archived","Active")
A100: EXOS-0099 | B100: John - Investor Contacts | OSC | C100: Financial Investor | D100: Acequia Capital | E100: Marc Jalabert | G100: marc@acecap.com | J100: https://www.linkedin.com/in/marcjalabert/ | K100: John Quinn | L100: Follow Up | M100: Space / Defense / Aerospace / Advanced Manufacturing | N100: Tier 2 | O100: 45853 | P100: 45994 | Q100: =IF(P100="","",TODAY()-P100) | R100: =IF(OR(L100="Passed",Z100=""),"",P100+Z100) | S100: =IF(OR(R100="",L100="Passed"),"",IF(R100<=TODAY(),"DUE",IF(R100<=TODAY()+3,"Next 3 Days","Later"))) | U100: https://www.linkedin.com/in/marcjalabert/ | W100: 12/30/2025 | X100: John - Investor Contacts!486 | OSC!14 | Y100: Send next follow-up with traction + CTA | Z100: 7 | AA100: =IF(AC100="Archived",0,ROUND((IF(N100="Tier 1",35,IF(N100="Tier 2",20,8))+IF(C100="Financial Investor",15,IF(C100="Intermediary / Banker",12,8))+IF(L100="Term Sheet / Proposal",25,IF(L100="Engaged",20,IF(L100="Meeting Requested",18,IF(L100="Meeting Held",14,IF(L100="Follow Up",10,5)))))+MIN(Q100,30)+IF(S100="DUE",15,IF(S100="Next 3 Days",8,0))),0)) | AB100: =IF(AND(AC100="Active",OR(N100="Tier 1",N100="Tier 2"),OR(S100="DUE",S100="Next 3 Days")),"YES","") | AC100: =IF(L100="Passed","Archived","Active")
...

Sheet Firm_Summary
A1: Company | B1: Category | C1: Best Stage | D1: Best Tier | E1: Contact Count | F1: Key Contacts | G1: Emails | H1: Last Touch | I1: Next Touch | J1: Due? | K1: Warm Intro | L1: Offer / Structure | M1: Notes
A2: AxisCades | B2: Financial Investor | C2: Term Sheet / Proposal | D2: Tier 1 | E2: 1 | F2: Suresh Babu Suryadevara | G2: suresh.s@axiscades.in | H2: 46055 | I2: =IF(OR(C2="Passed",H2="",ISBLANK(H2)),"",H2+2) | J2: =IF(I2="","",IF(I2<=TODAY(),"DUE",IF(I2<=TODAY()+3,"Next 3 Days","Later"))) | L2: Strategic Partnership- Equity deal | M2: Missed call toady at 08:30 - Follow-up framework shared outlining a phased, ITAR/EAR-compliant strategic partnership. Proposal includes AxisCades acquiring 51% of SSLC for $10M (phased capital), international sales support with commission structure, and long-term India-based manufacturing under TAA/MLA approvals. Discussions ongoing to confirm alignment on structure, valuation, and next steps. | toured SSLC on 2/16 | met in person at EXOS on 12/19, follow up set for onsite visit 1/19
A3: Bancroft Capital (Bancroft4Vets) | B3: Intermediary / Banker | C3: Term Sheet / Proposal | D3: Tier 1 | E3: 1 | F3: Jason Diamond | G3: jdiamond@bancroft4vets.com | I3: =IF(OR(C3="Passed",H3="",ISBLANK(H3)),"",H3+2) | J3: =IF(I3="","",IF(I3<=TODAY(),"DUE",IF(I3<=TODAY()+3,"Next 3 Days","Later"))) | L3: Investment Banking / Capital Raise | M3: Introduced via Kipton Cariaga. Terms/presentation shared. Defense- and veteran-focused investment bank. Logged for tracking and follow-up; no term sheet yet. Engaging BTIG 2-26-26 | 01/16/2026 | At their request, sent forward-ready cover email with high-level company overview and $10M raise summary, along with attached presentations. Materials prepared for direct circulation to IB partners and investor network (Jason forwarding internally). Awaiting feedback and/or investor introductions.
A4: Cerberus Capital Management | B4: Financial Investor | C4: Term Sheet / Proposal | D4: Tier 1 | E4: 3 | F4: Dan Quayle; Frank Bruno; Kent (Cerberus Ops) | G4: dquayle@cerberus.com; fbruno@cerberus.com; consult-klietzau@cerberusoperations.com | H4: 46023 | I4: =IF(OR(C4="Passed",H4="",ISBLANK(H4)),"",H4+2) | J4: =IF(I4="","",IF(I4<=TODAY(),"DUE",IF(I4<=TODAY()+3,"Next 3 Days","Later"))) | L4: Strategic Partner / Growth Capital | M4: 01/14/2026 | Introductory conversation held; John sent story deck, finance-focused deck, and one-pager today. Framed as strategic partner aligned with Scorpius acquisition, revenue expansion, and hypersonics / Golden Dome support. Added as potential strategic partner for board consideration. Awaiting response.
A5: Cloris Capital Group LLC | B5: Financial Investor | C5: Term Sheet / Proposal | D5: Tier 1 | E5: 1 | F5: Tahmina Khan | G5: tahmina.investing@gmail.com | I5: =IF(OR(C5="Passed",H5="",ISBLANK(H5)),"",H5+2) | J5: =IF(I5="","",IF(I5<=TODAY(),"DUE",IF(I5<=TODAY()+3,"Next 3 Days","Later"))) | K5: referred by Dereck | L5: Capital Partner (Equity / Strategic) 2% of transaction | M5: Completed discussions with both ETL and IronGate. No follow-up correspondence received to date. Awaiting next steps or investor feedback. | Investor requested documentation showing revenue for the past three years and indicated interest if trailing 12-month revenue reflects ~$1M. Financial documents sent by John. Awaiting response/feedback. | 11/24 call and materials sent
A6: Craft Capital | B6: Financial Investor | C6: Term Sheet / Proposal | D6: Tier 1 | E6: 1 | F6: Brandon Golenda | G6: bgolenda@craftcm.com | H6: 46020 | I6: =IF(OR(C6="Passed",H6="",ISBLANK(H6)),"",H6+2) | J6: =IF(I6="","",IF(I6<=TODAY(),"DUE",IF(I6<=TODAY()+3,"Next 3 Days","Later"))) | K6: referred by Dereck | L6: Advisory (Paid) Cost of finance: $30k fixed + 4–8% cash + 8% equity/warrants (if they introduce the capital) How to exclude other funding: The agreement already limits fees to Craft-introduced investors only, but You should formalize exclusions in writing immediately to avoid disputes. | M6: Advisory offer contingent on $30K fee. We chose not to proceed; parked. | $30K Investment bank enagement $10k/mo for 3 months advisor only. no funds.
A7: DelMorgan & Co | B7: Financial Investor | C7: Term Sheet / Proposal | D7: Tier 1 | E7: 1 | F7: RJ Mollen | G7: rjm@delmorganco.com | H7: 46037 | I7: =IF(OR(C7="Passed",H7="",ISBLANK(H7)),"",H7+2) | J7: =IF(I7="","",IF(I7<=TODAY(),"DUE",IF(I7<=TODAY()+3,"Next 3 Days","Later"))) | L7: Strategic Advisory / Infrastructure & Capital Access | M7: Talked and rejected offer- RJ proposed two alternative advisory paths outside the DelMorgan framework: (1) Fast Space infrastructure and asset monetization strategy, and (2) Gleam Consulting advisory + investor introductions tied to a $10M raise. Fee-based advisory with equity success bonuses. Not aligned with current priorities; documented for reference.
A8: InvestFortuna | B8: Financial Investor | C8: Term Sheet / Proposal | D8: Tier 1 | E8: 1 | F8: Sean Bromley | G8: sbromley@investfortuna.com | H8: 46023 | I8: =IF(OR(C8="Passed",H8="",ISBLANK(H8)),"",H8+2) | J8: =IF(I8="","",IF(I8<=TODAY(),"DUE",IF(I8<=TODAY()+3,"Next 3 Days","Later"))) | L8: Advisory + Bridge / IPO Path | M8: The .4 term sheet, as drafted, is not registrable, not exchange-compliant, and not defensible for directors. It can be salvaged only through structural changes that align it with industry norms that they rejected. | 01/15/2026 | Fortuna proposed an IPO-led advisory structure including a warrant offering, $5M minimum bridge financing (convertible at significant discount), and a $15M IPO financing, with substantial embedded dilution and control provisions. EXOS submitted a formal counter-term sheet replacing discounted instruments and automatic vesting with performance-based earn-out equity tied to post-IPO share price and market cap milestones, preserving a clean cap table and fiduciary compliance. Negotiations ongoing; awaiting Fortuna response.
A9: Pickwick Capital | B9: Financial Investor | C9: Term Sheet / Proposal | D9: Tier 1 | E9: 1 | F9: Crescent Varrone | G9: varronec@pickwickcapital.com; alvarezd@pickwickcapital.com | H9: 46031 | I9: =IF(OR(C9="Passed",H9="",ISBLANK(H9)),"",H9+2) | J9: =IF(I9="","",IF(I9<=TODAY(),"DUE",IF(I9<=TODAY()+3,"Next 3 Days","Later"))) | K9: varronec@pickwickcapital.com | L9: Capital Partner (Equity / Strategic) $15k/ mon 6 Months | M9: Active discussions underway. Pickwick has expressed interest; no term sheet yet. John had producitive meeting on 1/9. | 01/15/2026
A10: Sunbelt Dallas Metro | B10: Intermediary / Banker | C10: Term Sheet / Proposal | D10: Tier 1 | E10: 1 | F10: Bill Nicholson | G10: bnicholson@sunbeltnetwork.com | H10: 46083 | I10: =IF(OR(C10="Passed",H10="",ISBLANK(H10)),"",H10+2) | J10: =IF(I10="","",IF(I10<=TODAY(),"DUE",IF(I10<=TODAY()+3,"Next 3 Days","Later"))) | L10: Proposed intermediary engagement (retainer + success fee model under discussion; Board requesting performance-based structure) | M10: Sunbelt inquired about including a retainer amount in the Engagement Letter. John responded that the EXOS Board is unlikely to approve another open-ended retainer structure due to prior experiences with retainers that did not yield measurable outcomes. The Board is prioritizing: Clearly defined deliverables Performance-aligned compensation Objective execution milestones Defined transaction targets SEC-compliant structure (broker-dealer participation as required) John encouraged Sunbelt to propose a performance-based framework (reduced/deferred retainer, milestone-triggered payments, or primarily success-fee based on capital secured). Bill acknowledged and is coordinating internally to revise the proposal. He requested timing of the next Board meeting. Status: Awaiting revised engagement structure from Sunbelt for Board review. | sent email letting him know board doesn't want to pat retainer fees
A11: US Capital | B11: Financial Investor | C11: Term Sheet / Proposal | D11: Tier 1 | E11: 2 | F11: Ashley Curless; Mitch; Steve Wilburn; Charles Sims | G11: acurless@uscapital.com; mambe@uscapital.com | H11: 45986 | I11: =IF(OR(C11="Passed",H11="",ISBLANK(H11)),"",H11+2) | J11: =IF(I11="","",IF(I11<=TODAY(),"DUE",IF(I11<=TODAY()+3,"Next 3 Days","Later"))) | K11: referred by Dereck | L11: Capital Raise (Equity / Convertible) | M11: Terms shared; fee-heavy engagement model. $120K + 8% $920K | 01/15/2026 | Submitted formal equity financing proposal for up to $10M. Structure includes 8% cash banking fee, 8% warrant coverage, and $120K upfront compliance/diligence/distribution fees. Process is heavily intermediary-led with broad investor marketing and placement focus. High fees and limited strategic value relative to capital efficiency; not a preferred path at this stage.
A12: Black in Play | B12: Other / Review | C12: Engaged | D12: Tier 1 | E12: 0 | I12: =IF(OR(C12="Passed",H12="",ISBLANK(H12)),"",H12+5) | J12: =IF(I12="","",IF(I12<=TODAY(),"DUE",IF(I12<=TODAY()+3,"Next 3 Days","Later")))
A13: Blue under contract engagement | B13: Other / Review | C13: Engaged | D13: Tier 1 | E13: 0 | I13: =IF(OR(C13="Passed",H13="",ISBLANK(H13)),"",H13+5) | J13: =IF(I13="","",IF(I13<=TODAY(),"DUE",IF(I13<=TODAY()+3,"Next 3 Days","Later")))
A14: Concord Ventures | B14: Financial Investor | C14: Engaged | D14: Tier 1 | E14: 1 | F14: Salim Dada | G14: salim.d@concordventuresinc.com | H14: 45958 | I14: =IF(OR(C14="Passed",H14="",ISBLANK(H14)),"",H14+5) | J14: =IF(I14="","",IF(I14<=TODAY(),"DUE",IF(I14<=TODAY()+3,"Next 3 Days","Later"))) | K14: Salim Dada, Safia Dada | L14: Sell-Side / Marketing Advisory (Exclusive) | M14: Revised agreement sent; no follow-up since; inactive. | offer for $2500/month for 3 months plan | Offer for $2500/month to run program
A15: CounterFlow Solutions | B15: Other / Review | C15: Engaged | D15: Tier 1 | E15: 1 | F15: Dan Garretson | G15: dgarretson@counterflowsolutions.com | H15: 46024 | I15: =IF(OR(C15="Passed",H15="",ISBLANK(H15)),"",H15+5) | J15: =IF(I15="","",IF(I15<=TODAY(),"DUE",IF(I15<=TODAY()+3,"Next 3 Days","Later"))) | L15: Strategic Advisory (Narrative / Framing) | M15: Proposed short sprint to reframe EXOS + Scorpius narrative. Decision pending. | 12/23 john sent follow up reply | Costs for wrong scope
A16: CrossRoads Capital | B16: Financial Investor | C16: Engaged | D16: Tier 1 | E16: 2 | F16: Rchard Phillips; Andrew J. Buchholtz and David Ford | G16: andy@abuchholtz.com | H16: 46038 | I16: =IF(OR(C16="Passed",H16="",ISBLANK(H16)),"",H16+5) | J16: =IF(I16="","",IF(I16<=TODAY(),"DUE",IF(I16<=TODAY()+3,"Next 3 Days","Later"))) | K16: Richard Phillips | L16: CTD acquisition or JV opportunity | M16: have new 18,000 sf facility just North of Denver Co. $3-4M to scale | Sent you the ELA draft this morning — let me if you didn’t receive or if you have any questions. We can schedule another call if you’d like to review together. | had a call, sent deck
A17: DC Finance | B17: Financial Investor | C17: Engaged | D17: Tier 1 | E17: 1 | F17: Morris | I17: =IF(OR(C17="Passed",H17="",ISBLANK(H17)),"",H17+5) | J17: =IF(I17="","",IF(I17<=TODAY(),"DUE",IF(I17<=TODAY()+3,"Next 3 Days","Later"))) | L17: 10K or 30k to put you in a room with 12 Family offices
A18: Digital Asset Management | B18: Financial Investor | C18: Engaged | D18: Tier 1 | E18: 1 | F18: Juan Lorenzana | H18: 46059 | I18: =IF(OR(C18="Passed",H18="",ISBLANK(H18)),"",H18+5) | J18: =IF(I18="","",IF(I18<=TODAY(),"DUE",IF(I18<=TODAY()+3,"Next 3 Days","Later"))) | L18: no feedback on SEC filing AUM record | M18: $30K refundable. Fund with hedge of Gold metals real estate etc.
A19: Green- costs | B19: Other / Review | C19: Engaged | D19: Tier 1 | E19: 0 | I19: =IF(OR(C19="Passed",H19="",ISBLANK(H19)),"",H19+5) | J19: =IF(I19="","",IF(I19<=TODAY(),"DUE",IF(I19<=TODAY()+3,"Next 3 Days","Later")))
A20: Ivy Asset Management | B20: Other / Review | C20: Engaged | D20: Tier 1 | E20: 1 | F20: Chris Roberts "Christopher Virginia Roberts" | G20: chrisr@ivyassetmngmt.com | I20: =IF(OR(C20="Passed",H20="",ISBLANK(H20)),"",H20+5) | J20: =IF(I20="","",IF(I20<=TODAY(),"DUE",IF(I20<=TODAY()+3,"Next 3 Days","Later")))
A21: Odeon Capital | B21: Financial Investor | C21: Engaged | D21: Tier 1 | E21: 1 | F21: Eric Gomberg | G21: egomberg@odeoncap.com | H21: 46028 | I21: =IF(OR(C21="Passed",H21="",ISBLANK(H21)),"",H21+5) | J21: =IF(I21="","",IF(I21<=TODAY(),"DUE",IF(I21<=TODAY()+3,"Next 3 Days","Later"))) | L21: Capital Discussion | M21: MNDA + data room sent Dec 17. No response prior to year-end. Follow-up email sent today. | 01/15/2026 | 1. Reduced Retainer of $30,000 Upfront. 2. Success Fee of $400,000 at the back end. We will credit the $30K Retainer back at the end upon a successful completion. 3. Any reasonable travel authorized by the client in advance of any travel. Please let us know if this is okay, then we can proceed with the detailed proposal/engagement letter. Regards, Bill Bill Nicholson, MBA, M&AMI®, CM&AA®
A22: Red dropped | B22: Other / Review | C22: Engaged | D22: Tier 1 | E22: 0 | I22: =IF(OR(C22="Passed",H22="",ISBLANK(H22)),"",H22+5) | J22: =IF(I22="","",IF(I22<=TODAY(),"DUE",IF(I22<=TODAY()+3,"Next 3 Days","Later")))
A23: Ricci Global Partners | B23: Financial Investor | C23: Engaged | D23: Tier 1 | E23: 1 | F23: Riccardo Ricci | G23: riccardo@riccicapitalpartners.com; riccardo-ricci@ricciglobalpartners.com | H23: 46028 | I23: =IF(OR(C23="Passed",H23="",ISBLANK(H23)),"",H23+5) | J23: =IF(I23="","",IF(I23<=TODAY(),"DUE",IF(I23<=TODAY()+3,"Next 3 Days","Later"))) | K23: referred by Tom Wright | L23: Capital Partner (Equity / Strategic) | M23: MNDA executed and data room shared. Ricci requested finance working session and followed up again today to move forward | 01/15/2026 | 03/13/2026
A24: Screen with Visual Conmpliance | B24: Other / Review | C24: Engaged | D24: Tier 1 | E24: 0 | I24: =IF(OR(C24="Passed",H24="",ISBLANK(H24)),"",H24+5) | J24: =IF(I24="","",IF(I24<=TODAY(),"DUE",IF(I24<=TODAY()+3,"Next 3 Days","Later")))
A25: The Unity Group | B25: Other / Review | C25: Engaged | D25: Tier 1 | E25: 1 | F25: Alex Durie via Tahmina K | G25: alex@unity-group.com | I25: =IF(OR(C25="Passed",H25="",ISBLANK(H25)),"",H25+5) | J25: =IF(I25="","",IF(I25<=TODAY(),"DUE",IF(I25<=TODAY()+3,"Next 3 Days","Later")))
A26: Tristate Capital | B26: Intermediary / Banker | C26: Engaged | D26: Tier 1 | E26: 1 | F26: Sulaiman Sulaimani | G26: sulaiman@tristatecap.com | H26: 46054 | I26: =IF(OR(C26="Passed",H26="",ISBLANK(H26)),"",H26+5) | J26: =IF(I26="","",IF(I26<=TODAY(),"DUE",IF(I26<=TODAY()+3,"Next 3 Days","Later"))) | K26: referred by Dereck | L26: Capital Introduction (Success Fee + Equity) Cost of finance under Tristate: 2.0% cash + 1.0% non-voting equity Only on Tristate-sourced, closed capital | M26: https://www.irongatevc.com/ Contracted with Sulaiman Sulaimani ​John Quinn​ ​Neil Milburn​ John, I'm scheduled to speak with our strategic partner Ty McCoy tomorrow. He just emailed me a company now that appears to be a close contact of his as there is someone on their team that is former CIA. I think we found the right partner for you and your team. Please give me sometime as I work on this for you and your team. I'll be back in touch. Thanks for the call yesterday. I enjoyed speaking with you. I was able to connect with our strategic partner Ty McCoy with IronGate. He is available to speak with us next week at 12 pm CST on 2/10. I was also able to circle up with our clients from ETL. Hanshin Lee emailed me that he is interested in Exos Aerospace and speaking with us next week at 8 am CST on 2/10. If you can please send me calendar invites for both calls on 2/10 8 am CST with ETL, and 12 pm CST with IronGate. Once I receive both invites, I'll be sure to pass them along. | 01/15/2026 | 2/10 – Calls Held:
A27: Viking Mergers & Acquisitions | B27: Other / Review | C27: Engaged | D27: Tier 1 | E27: 1 | F27: A. Rehwinkel | G27: arehwinkel@vikingmergers.com | I27: =IF(OR(C27="Passed",H27="",ISBLANK(H27)),"",H27+5) | J27: =IF(I27="","",IF(I27<=TODAY(),"DUE",IF(I27<=TODAY()+3,"Next 3 Days","Later"))) | M27: Initial engagement underway; reviewing materials in data room.
A28: Collective Equity | B28: Financial Investor | C28: Meeting Requested | D28: Tier 1 | E28: 1 | F28: Mike Royston | G28: mike@collectiveequity.com | I28: =IF(OR(C28="Passed",H28="",ISBLANK(H28)),"",H28+2) | J28: =IF(I28="","",IF(I28<=TODAY(),"DUE",IF(I28<=TODAY()+3,"Next 3 Days","Later"))) | M28: meeting on 6/25 / follow up meeting in the works / ziyi@collectiveequity.com
A29: Gravitics | B29: Strategic / Corporate | C29: Meeting Requested | D29: Tier 1 | E29: 4 | F29: Scott Macklin; Bill Tandy; Colin Doughan; Jiral Shah | G29: smacklin@gravitics.com; btandy@gravitics.com; cdoughan@gravitics.com; jshah@gravitics.com | H29: 45744 | I29: =IF(OR(C29="Passed",H29="",ISBLANK(H29)),"",H29+2) | J29: =IF(I29="","",IF(I29<=TODAY(),"DUE",IF(I29<=TODAY()+3,"Next 3 Days","Later"))) | M29: meeting set for 4/3
A30: Investor Ready Capital | B30: Financial Investor | C30: Meeting Requested | D30: Tier 1 | E30: 1 | F30: Samuel Levitz | G30: samuel@investorreadycapital.com | I30: =IF(OR(C30="Passed",H30="",ISBLANK(H30)),"",H30+2) | J30: =IF(I30="","",IF(I30<=TODAY(),"DUE",IF(I30<=TODAY()+3,"Next 3 Days","Later"))) | M30: meeting held on 6/24 / follow up meeting on 6/27- Question replied to and followed up on 7-11
A31: One Bow River | B31: Financial Investor | C31: Meeting Requested | D31: Tier 1 | E31: 3 | F31: Stowe Faircloth; Kevin O'Neil; Steven Joanis | G31: shane.sherman@onebowriver.com; kevin.oneil@onebowriver.com; steven.joanis@onebowriver.com | H31: 45922 | I31: =IF(OR(C31="Passed",H31="",ISBLANK(H31)),"",H31+2) | J31: =IF(I31="","",IF(I31<=TODAY(),"DUE",IF(I31<=TODAY()+3,"Next 3 Days","Later"))) | K31: https://www.linkedin.com/in/shane-sherman/ | M31: 08/12/2025 | Stowe Faircloth <Stowe.faircloth@onebowriver.com>replied requesting a meeting on 9/22
A32: TEL Venture Capital | B32: Financial Investor | C32: Meeting Requested | D32: Tier 1 | E32: 1 | F32: Sergey Fedotov | G32: sergey.fedotov@tel.com | H32: 45912 | I32: =IF(OR(C32="Passed",H32="",ISBLANK(H32)),"",H32+2) | J32: =IF(I32="","",IF(I32<=TODAY(),"DUE",IF(I32<=TODAY()+3,"Next 3 Days","Later"))) | K32: https://www.linkedin.com/in/sergey-a-fedotov/ | M32: 9/24 - meeting set for 10/2
A33: referred by andy@abucholtz.com | B33: Financial Investor | C33: Meeting Requested | D33: Tier 1 | E33: 1 | F33: Richard Phillips | G33: phillips@crossroadscapitaldc.com | H33: 45903 | I33: =IF(OR(C33="Passed",H33="",ISBLANK(H33)),"",H33+2) | J33: =IF(I33="","",IF(I33<=TODAY(),"DUE",IF(I33<=TODAY()+3,"Next 3 Days","Later"))) | K33: phillips@crossroadscapitaldc.com | M33: meeting set 9/8/ NDA 9/12 | Suggested www.ctd.materials.com as a better fit and said he would schedule follow up meeting using your link | 9/17 – Richard sent draft ELA; John replied same day with detailed summary of requested revisions (removal of exclusivity, no retainer, Appendix D addition, clarified success fees). No reply since.
A34: Cerebro Capital | B34: Financial Investor | C34: Meeting Held | D34: Tier 1 | E34: 1 | F34: Steven Agathoklis | G34: sagathoklis@cerebrocapital.com | H34: 45951 | I34: =IF(OR(C34="Passed",H34="",ISBLANK(H34)),"",H34+5) | J34: =IF(I34="","",IF(I34<=TODAY(),"DUE",IF(I34<=TODAY()+3,"Next 3 Days","Later"))) | L34: Bridge Loan | M34: NDA signed; full financials provided. No response since; inactive. | meeting held on 10/16
A35: IPO Club | B35: Financial Investor | C35: Meeting Held | D35: Tier 1 | E35: 2 | F35: Edoardo Zarghetta; Jordan Yip | G35: edozar@gmail.com; jordan@preipo.club | H35: 46030 | I35: =IF(OR(C35="Passed",H35="",ISBLANK(H35)),"",H35+5) | J35: =IF(I35="","",IF(I35<=TODAY(),"DUE",IF(I35<=TODAY()+3,"Next 3 Days","Later"))) | K35: linkedin.com/in/edozar | linkedin.com/in/jordan-yip-zhu-ern | M35: meeting held on 1/13 - pitch deck sent for brother
A36: Noblis Ventures | B36: Financial Investor | C36: Meeting Held | D36: Tier 1 | E36: 3 | F36: Bill Collier; Matt Monaco; Matt Salter | G36: bill.collier@noblis.org; matthew.monaco@noblis.org; matt.salter@noblis.org | H36: 45972 | I36: =IF(OR(C36="Passed",H36="",ISBLANK(H36)),"",H36+5) | J36: =IF(I36="","",IF(I36<=TODAY(),"DUE",IF(I36<=TODAY()+3,"Next 3 Days","Later"))) | K36: https://www.linkedin.com/in/williammarcuscollier/ | https://www.linkedin.com/in/matthewkmonaco/ | M36: 12/5 follow up sent | meeting held and follow up emails sent. most recent follow up 12/5 | 12/05/2025
A37: Palm Drive Capital | B37: Financial Investor | C37: Meeting Held | D37: Tier 1 | E37: 1 | F37: Carter Dessommes | G37: carter@palmdrive.vc | H37: 45859 | I37: =IF(OR(C37="Passed",H37="",ISBLANK(H37)),"",H37+5) | J37: =IF(I37="","",IF(I37<=TODAY(),"DUE",IF(I37<=TODAY()+3,"Next 3 Days","Later"))) | M37: meeting held
A38: Prospect Capital | B38: Financial Investor | C38: Meeting Held | D38: Tier 1 | E38: 1 | F38: Sulaiman Sulaimani | H38: 46030 | I38: =IF(OR(C38="Passed",H38="",ISBLANK(H38)),"",H38+5) | J38: =IF(I38="","",IF(I38<=TODAY(),"DUE",IF(I38<=TODAY()+3,"Next 3 Days","Later"))) | K38: sulaiman@prospectcapital.com | M38: Introductory meeting held Jan 8. Prospect Capital operates through two distinct divisions; conversations are exploratory at this stage. Two divisions: core BDC credit and structured/special situations. EXOS aligns better with structured, event-driven capital vs traditional cash-flow lending.
A39: REI | B39: Financial Investor | C39: Meeting Held | D39: Tier 1 | E39: 0 | H39: 45917 | I39: =IF(OR(C39="Passed",H39="",ISBLANK(H39)),"",H39+5) | J39: =IF(I39="","",IF(I39<=TODAY(),"DUE",IF(I39<=TODAY()+3,"Next 3 Days","Later"))) | K39: Nick Book | M39: Choctaw nation investor group interested in Space investments. Requesting site tour on 9-26 If you could send me a new link for a warehouse visit over the next week or so I’d really like to continue to dig into this and see where or who we can fit in. Also, please send me the deck and anything else you would like me to consider.
A40: Rockfleet Financial | B40: Financial Investor | C40: Meeting Held | D40: Tier 1 | E40: 2 | F40: John Swift; Catherine Corrigan | G40: john.swift@rockfleetfinancial.com; catherine.corrigan@rockfleetfinancial.com | H40: 45831 | I40: =IF(OR(C40="Passed",H40="",ISBLANK(H40)),"",H40+5) | J40: =IF(I40="","",IF(I40<=TODAY(),"DUE",IF(I40<=TODAY()+3,"Next 3 Days","Later"))) | K40: linkedin.com/in/jr-swift | https://www.linkedin.com/in/catherine-corrigan-18992b12/ | M40: meeting held on 7/2 & NDA in process- Followed up 7-11
A41: (No Company) | B41: Financial Investor | C41: Follow Up | D41: Tier 2 | E41: 16 | F41: Clay; Drew Tulchin; EXOS + Plug & Play: Introductions; James Cameron; Jason Schwartz / Paul Gloyer GTL | G41: claysba1@gmail.com; drew@nmangels.com; jacob.reedy@trinet.com; james@visionaryleadership.co.nz; jason@leagueadvisors.com | H41: 46045 | I41: =IF(OR(C41="Passed",H41="",ISBLANK(H41)),"",H41+7) | J41: =IF(I41="","",IF(I41<=TODAY(),"DUE",IF(I41<=TODAY()+3,"Next 3 Days","Later"))) | K41: Tom referral | M41: not sure what to do with this one?? | dns fail | 12/05/2025
A42: .406 Ventures | B42: Financial Investor | C42: Follow Up | D42: Tier 2 | E42: 4 | F42: Graham Brooks; Greg Dracon; Liam Donohue; Payal Agrawal Divakaran | G42: gbrooks@406ventures.com; gdracon@406ventures.com; ldonohue@406ventures.com; payal@406ventures.com | H42: 45841 | I42: =IF(OR(C42="Passed",H42="",ISBLANK(H42)),"",H42+7) | J42: =IF(I42="","",IF(I42<=TODAY(),"DUE",IF(I42<=TODAY()+3,"Next 3 Days","Later"))) | K42: https://www.linkedin.com/in/grahambrooks/ | https://www.linkedin.com/in/gdracon/
A43: 137 Ventures | B43: Financial Investor | C43: Follow Up | D43: Tier 2 | E43: 5 | F43: Alexander Jacobson; Andrew Hansen; Christian Garrett; James Pardee; Justin Fishner-Wolfson | G43: alex@137ventures.com; andrew@137ventures.com; christian@137ventures.com; james@137ventures.com; justin@137ventures.com | H43: 45973 | I43: =IF(OR(C43="Passed",H43="",ISBLANK(H43)),"",H43+7) | J43: =IF(I43="","",IF(I43<=TODAY(),"DUE",IF(I43<=TODAY()+3,"Next 3 Days","Later"))) | K43: https://www.linkedin.com/in/jacobsonalex/ | https://www.linkedin.com/in/andrewhansen1/ | M43: 12/30/2025
A44: 1Up Ventures | B44: Financial Investor | C44: Follow Up | D44: Tier 2 | E44: 1 | F44: Ed Fries | G44: ed@1upfund.com | H44: 45973 | I44: =IF(OR(C44="Passed",H44="",ISBLANK(H44)),"",H44+7) | J44: =IF(I44="","",IF(I44<=TODAY(),"DUE",IF(I44<=TODAY()+3,"Next 3 Days","Later"))) | K44: https://www.linkedin.com/in/edfries/ | M44: 12/19/2025
A45: 3 Lines VC | B45: Financial Investor | C45: Follow Up | D45: Tier 2 | E45: 6 | F45: Hemant Elhence; Kamalesh Dwivedi; Krishna Kunapuli; Pallab K. Chatterjee; Rajiv Roy | G45: hemant@3lines.vc; kamalesh.dwivedi@3lines.vc; krishna.kunapuli@3lines.vc; pallab.chatterjee@3lines.vc; rajiv.roy@3lines.vc | H45: 45861 | I45: =IF(OR(C45="Passed",H45="",ISBLANK(H45)),"",H45+7) | J45: =IF(I45="","",IF(I45<=TODAY(),"DUE",IF(I45<=TODAY()+3,"Next 3 Days","Later"))) | K45: https://www.linkedin.com/in/hemantelhence/ | https://www.linkedin.com/in/krishna-kunapuli-3lines/ | M45: 12/26/2025 | online application: https://3lines.vc/appl
A46: 3LB Seed Capital | B46: Financial Investor | C46: Follow Up | D46: Tier 2 | E46: 1 | F46: Alberto Emprin | G46: a.emprin@3lbseed.com | H46: 46036 | I46: =IF(OR(C46="Passed",H46="",ISBLANK(H46)),"",H46+7) | J46: =IF(I46="","",IF(I46<=TODAY(),"DUE",IF(I46<=TODAY()+3,"Next 3 Days","Later"))) | K46: https://www.linkedin.com/in/albertoemprin/ | M46: 02/26/2026
A47: 4490 Ventures | B47: Financial Investor | C47: Follow Up | D47: Tier 2 | E47: 1 | F47: Dan Malven | G47: dm@4490ventures.com | H47: 45929 | I47: =IF(OR(C47="Passed",H47="",ISBLANK(H47)),"",H47+7) | J47: =IF(I47="","",IF(I47<=TODAY(),"DUE",IF(I47<=TODAY()+3,"Next 3 Days","Later"))) | K47: https://www.linkedin.com/in/danmalven | M47: 12/05/2025
A48: 776 Fund | B48: Financial Investor | C48: Follow Up | D48: Tier 2 | E48: 1 | F48: Alexis Ohanian | G48: alexis.ohanian@sevensevensix.com | H48: 45929 | I48: =IF(OR(C48="Passed",H48="",ISBLANK(H48)),"",H48+7) | J48: =IF(I48="","",IF(I48<=TODAY(),"DUE",IF(I48<=TODAY()+3,"Next 3 Days","Later"))) | K48: https://www.linkedin.com/in/alexisohanian/ | M48: 12/05/2025
A49: 8VC | B49: Financial Investor | C49: Follow Up | D49: Tier 2 | E49: 4 | F49: Alex Kolicich; Drew Oetting; Joe Lonsdale; Kimmy Scotti | G49: alex@8vc.com; drew@8vc.com; joe@8vc.com; kimmy@8vc.com | H49: 45985 | I49: =IF(OR(C49="Passed",H49="",ISBLANK(H49)),"",H49+7) | J49: =IF(I49="","",IF(I49<=TODAY(),"DUE",IF(I49<=TODAY()+3,"Next 3 Days","Later"))) | K49: linkedin.com/in/alex-kolicich-b71732a | linkedin.com/in/drew-oetting-52463337 | M49: 01/14/2026
A50: 97212 VC | B50: Financial Investor | C50: Follow Up | D50: Tier 2 | E50: 2 | F50: Eyal Bino; Ronie Lavi | G50: eyalbino@gmail.com; ronnie@97212.vc | H50: 45890 | I50: =IF(OR(C50="Passed",H50="",ISBLANK(H50)),"",H50+7) | J50: =IF(I50="","",IF(I50<=TODAY(),"DUE",IF(I50<=TODAY()+3,"Next 3 Days","Later"))) | K50: https://www.linkedin.com/in/eyal-bino/ | https://www.linkedin.com/in/ronnielavi/ | M50: 12/29/2025
A51: ACMI Group | B51: Financial Investor | C51: Follow Up | D51: Tier 2 | E51: 1 | F51: Kishen Raghunath | G51: kraghunath@acmigroup.com | I51: =IF(OR(C51="Passed",H51="",ISBLANK(H51)),"",H51+7) | J51: =IF(I51="","",IF(I51<=TODAY(),"DUE",IF(I51<=TODAY()+3,"Next 3 Days","Later"))) | M51: follow up email sent 5/27 // put you in contact with vboelscher@acmigroup.com // also talking to jbowling@acmigroup.com
A52: AIN Ventures | B52: Financial Investor | C52: Follow Up | D52: Tier 2 | E52: 3 | F52: Emily McMahan; Forrest Underwood; Sherman Williams | G52: emily@academyinvestor.com; forrest@academyinvestor.com; sherman@academyinvestor.com | H52: 45973 | I52: =IF(OR(C52="Passed",H52="",ISBLANK(H52)),"",H52+7) | J52: =IF(I52="","",IF(I52<=TODAY(),"DUE",IF(I52<=TODAY()+3,"Next 3 Days","Later"))) | K52: linkedin.com/in/emilymcmahan | https://www.linkedin.com/in/forrestunderwood | M52: 12/19/2025
A53: APA Venture Partners | B53: Financial Investor | C53: Follow Up | D53: Tier 2 | E53: 1 | F53: Alex Kaufman | G53: alex@apavp.com | H53: 45973 | I53: =IF(OR(C53="Passed",H53="",ISBLANK(H53)),"",H53+7) | J53: =IF(I53="","",IF(I53<=TODAY(),"DUE",IF(I53<=TODAY()+3,"Next 3 Days","Later"))) | K53: https://www.linkedin.com/in/calexkaufman/ | M53: 12/19/2025
A54: ATEM Capital | B54: Financial Investor | C54: Follow Up | D54: Tier 2 | E54: 2 | F54: Allan Gobbs; Elena Maley | G54: ag@atemcap.com; em@atemcap.com | H54: 45861 | I54: =IF(OR(C54="Passed",H54="",ISBLANK(H54)),"",H54+7) | J54: =IF(I54="","",IF(I54<=TODAY(),"DUE",IF(I54<=TODAY()+3,"Next 3 Days","Later"))) | K54: https://www.linkedin.com/in/gobbs/ | https://www.linkedin.com/in/elena-maley-96627914/ | M54: 12/26/2025
A55: AV8 Ventures | B55: Financial Investor | C55: Follow Up | D55: Tier 2 | E55: 4 | F55: Brett Battles; George Ugras; Ruchita Sinha; Shawn Kung | G55: brett@av8.vc; george@av8.vc; ruchita@av8.vc; shawn@av8.vc | H55: 45861 | I55: =IF(OR(C55="Passed",H55="",ISBLANK(H55)),"",H55+7) | J55: =IF(I55="","",IF(I55<=TODAY(),"DUE",IF(I55<=TODAY()+3,"Next 3 Days","Later"))) | K55: https://www.linkedin.com/in/bbattles/ | https://www.linkedin.com/in/ugras/ | M55: 12/26/2025
A56: AVP (formerly AXA Venture Partners) | B56: Financial Investor | C56: Follow Up | D56: Tier 2 | E56: 3 | F56: Amy Rudersdorf; Ethan Volk; Gregory Krisberg | G56: amy@weareavp.com; ethan.volk@axavp.com; gregory.krisberg@axavp.com | H56: 45861 | I56: =IF(OR(C56="Passed",H56="",ISBLANK(H56)),"",H56+7) | J56: =IF(I56="","",IF(I56<=TODAY(),"DUE",IF(I56<=TODAY()+3,"Next 3 Days","Later"))) | K56: linkedin.com/in/amyrudersdorf | linkedin.com/in/ethanvolk | M56: 12/26/2025
A57: Accel | B57: Financial Investor | C57: Follow Up | D57: Tier 2 | E57: 3 | F57: Ben Fletcher; Harry Nelis; Prashanth Prakash | G57: bfletcher@accel.com; hnelis@accel.com; pprakash@accel.com | H57: 45841 | I57: =IF(OR(C57="Passed",H57="",ISBLANK(H57)),"",H57+7) | J57: =IF(I57="","",IF(I57<=TODAY(),"DUE",IF(I57<=TODAY()+3,"Next 3 Days","Later"))) | K57: https://www.linkedin.com/in/bfletch11/ | https://www.linkedin.com/in/harry-nelis-429801/
A58: Acequia Capital | B58: Financial Investor | C58: Follow Up | D58: Tier 2 | E58: 6 | F58: Gregory Bernstein; Hank Vigil; Investor Relations; Leif Danielsen; Marc Jalabert | G58: gregory@acecap.com; hank@acecap.com; investor.relations@acecap.com; danielsen@acecap.com; marc@acecap.com | H58: 45994 | I58: =IF(OR(C58="Passed",H58="",ISBLANK(H58)),"",H58+7) | J58: =IF(I58="","",IF(I58<=TODAY(),"DUE",IF(I58<=TODAY()+3,"Next 3 Days","Later"))) | K58: https://www.linkedin.com/in/gregory-m-bernstein-34a2b4127/ | https://www.linkedin.com/in/hank-vigil-447280160/ | M58: 12/30/2025
A59: Acorn Pacific Ventures | B59: Financial Investor | C59: Follow Up | D59: Tier 2 | E59: 6 | F59: Benny Liao; David Wu; Derek Chau; Howard Chau; Peter Hsieh | G59: benny@acornpacific.ventures; david@acornpacific.ventures; derek@acornpacific.ventures; howard@acornpacific.ventures; peter@acornpacific.ventures | H59: 45890 | I59: =IF(OR(C59="Passed",H59="",ISBLANK(H59)),"",H59+7) | J59: =IF(I59="","",IF(I59<=TODAY(),"DUE",IF(I59<=TODAY()+3,"Next 3 Days","Later"))) | K59: https://www.linkedin.com/in/bliao999/ | https://www.linkedin.com/in/davidwutw-0b038855/ | M59: 12/29/2025
A60: Advance Ventures | B60: Financial Investor | C60: Follow Up | D60: Tier 2 | E60: 1 | F60: Ephraim Lindenbaum & Daria | G60: eph@advanceventures.com | H60: 46010 | I60: =IF(OR(C60="Passed",H60="",ISBLANK(H60)),"",H60+7) | J60: =IF(I60="","",IF(I60<=TODAY(),"DUE",IF(I60<=TODAY()+3,"Next 3 Days","Later"))) | K60: https://www.linkedin.com/in/ephraimlindenbaum/ | M60: sent pitch deck on 1/3 | 12/19/2025
A61: Aero Equity | B61: Financial Investor | C61: Follow Up | D61: Tier 2 | E61: 1 | F61: Lauren Graupman | G61: lgraupman@aeroequity.com | H61: 45881 | I61: =IF(OR(C61="Passed",H61="",ISBLANK(H61)),"",H61+7) | J61: =IF(I61="","",IF(I61<=TODAY(),"DUE",IF(I61<=TODAY()+3,"Next 3 Days","Later"))) | K61: https://www.linkedin.com/in/lauren-graupman
A62: Aero Equity / AE Industrial Parnters | B62: Financial Investor | C62: Follow Up | D62: Tier 2 | E62: 3 | F62: Brian Schettler; David Rowe; Kirk Konert | G62: bschettler@aeroequity.com; drowe@aeroequity.com; kkonert@aeroequity.com | H62: 45994 | I62: =IF(OR(C62="Passed",H62="",ISBLANK(H62)),"",H62+7) | J62: =IF(I62="","",IF(I62<=TODAY(),"DUE",IF(I62<=TODAY()+3,"Next 3 Days","Later"))) | K62: https://www.linkedin.com/in/brian-schettler-4ab87a5/ | https://www.linkedin.com/in/david-rowe-50018431/ | M62: 12/30/2025
A63: Allegory Capital | B63: Financial Investor | C63: Follow Up | D63: Tier 2 | E63: 1 | F63: Haider Alleg | G63: haider.alleg@allegory.capital | H63: 45973 | I63: =IF(OR(C63="Passed",H63="",ISBLANK(H63)),"",H63+7) | J63: =IF(I63="","",IF(I63<=TODAY(),"DUE",IF(I63<=TODAY()+3,"Next 3 Days","Later"))) | K63: https://www.linkedin.com/in/haideralleg/ | M63: 12/19/2025
A64: Allos Ventures | B64: Financial Investor | C64: Follow Up | D64: Tier 2 | E64: 1 | F64: David Kerr | G64: david@allosventures.com | H64: 45929 | I64: =IF(OR(C64="Passed",H64="",ISBLANK(H64)),"",H64+7) | J64: =IF(I64="","",IF(I64<=TODAY(),"DUE",IF(I64<=TODAY()+3,"Next 3 Days","Later"))) | K64: https://www.linkedin.com/in/david-kerr-9b0b501/ | M64: 12/05/2025
A65: Alsop Louie Partners | B65: Financial Investor | C65: Follow Up | D65: Tier 2 | E65: 2 | F65: Bill Crowell; Stewart Alsop | G65: wcrowell@alsop-louie.com; salsop@alsop-louie.com | H65: 45973 | I65: =IF(OR(C65="Passed",H65="",ISBLANK(H65)),"",H65+7) | J65: =IF(I65="","",IF(I65<=TODAY(),"DUE",IF(I65<=TODAY()+3,"Next 3 Days","Later"))) | K65: linkedin.com/in/william-crowell-65bb433a | https://www.linkedin.com/in/salsop/ | M65: 12/30/2025
A66: Alumni Venture Group | B66: Financial Investor | C66: Follow Up | D66: Tier 2 | E66: 1 | F66: Erik Hammer | G66: erik@av.vc | H66: 45929 | I66: =IF(OR(C66="Passed",H66="",ISBLANK(H66)),"",H66+7) | J66: =IF(I66="","",IF(I66<=TODAY(),"DUE",IF(I66<=TODAY()+3,"Next 3 Days","Later"))) | M66: 12/05/2025
A67: Alumni Ventures | B67: Financial Investor | C67: Follow Up | D67: Tier 2 | E67: 10 | F67: Brian Keil; David Beazley; Greg Baker; Matt Caspari; Carl Choi | G67: brian.keil@av.vc; david@av.vc; greg@av.vc; matt.caspari@av.vc; carl@av.vc | H67: 45973 | I67: =IF(OR(C67="Passed",H67="",ISBLANK(H67)),"",H67+7) | J67: =IF(I67="","",IF(I67<=TODAY(),"DUE",IF(I67<=TODAY()+3,"Next 3 Days","Later"))) | K67: https://www.linkedin.com/in/brianpkeil | https://www.linkedin.com/in/david-shapiro-2b328/ | M67: 12/30/2025 | 12/19/2025
A68: America's Fronteir | B68: Financial Investor | C68: Follow Up | D68: Tier 2 | E68: 3 | F68: Faran Nouri; Investor Relations; Jeff Karras | G68: faran@americasfrontier.org; investor.relations@americasfrontier.com; jkarras@altervp.com | H68: 45922 | I68: =IF(OR(C68="Passed",H68="",ISBLANK(H68)),"",H68+7) | J68: =IF(I68="","",IF(I68<=TODAY(),"DUE",IF(I68<=TODAY()+3,"Next 3 Days","Later")))
A69: American Capital Partners, LLC | B69: Financial Investor | C69: Follow Up | D69: Tier 2 | E69: 1 | F69: Lawrence | G69: ljust@acpweb.com | H69: 45841 | I69: =IF(OR(C69="Passed",H69="",ISBLANK(H69)),"",H69+7) | J69: =IF(I69="","",IF(I69<=TODAY(),"DUE",IF(I69<=TODAY()+3,"Next 3 Days","Later"))) | K69: Tom referral
A70: America’s Frontier Fund | B70: Financial Investor | C70: Follow Up | D70: Tier 2 | E70: 3 | F70: Brian Wilcove; Gilman Louie; Jordan Blashek | G70: brian@americasfrontier.org; gilman@americasfrontier.org; jordan@americasfrontier.org | H70: 45922 | I70: =IF(OR(C70="Passed",H70="",ISBLANK(H70)),"",H70+7) | J70: =IF(I70="","",IF(I70<=TODAY(),"DUE",IF(I70<=TODAY()+3,"Next 3 Days","Later"))) | K70: https://www.linkedin.com/in/brianwilcove/ | https://www.linkedin.com/in/gilmanlouie/
A71: Amplify Partners | B71: Financial Investor | C71: Follow Up | D71: Tier 2 | E71: 5 | F71: Grace Ge; Lenny Pruss; Mike Dauber; Sarah Catanzaro; Sunil Dhaliwal | G71: grace@amplifypartners.com; lenny@amplifypartners.com; mike@amplifypartners.com; sarah@amplifypartners.com; sunil@amplifypartners.com | H71: 45973 | I71: =IF(OR(C71="Passed",H71="",ISBLANK(H71)),"",H71+7) | J71: =IF(I71="","",IF(I71<=TODAY(),"DUE",IF(I71<=TODAY()+3,"Next 3 Days","Later"))) | K71: https://www.linkedin.com/in/gracewenge/ | https://www.linkedin.com/in/lennypruss/ | M71: 12/30/2025
A72: Andreessen Horowitz | B72: Financial Investor | C72: Follow Up | D72: Tier 2 | E72: 1 | F72: Katherine Boyle | G72: katherine@a16z.com | H72: 45841 | I72: =IF(OR(C72="Passed",H72="",ISBLANK(H72)),"",H72+7) | J72: =IF(I72="","",IF(I72<=TODAY(),"DUE",IF(I72<=TODAY()+3,"Next 3 Days","Later"))) | K72: https://www.linkedin.com/in/katherine-boyle-4531a67/
A73: Ansa | B73: Financial Investor | C73: Follow Up | D73: Tier 2 | E73: 3 | F73: Allan Jean-Baptiste; Josh Chin; Marco DeMeireles | G73: allan@ansa.co; josh@ansa.co; marco.demeireles@ansa.co | H73: 45923 | I73: =IF(OR(C73="Passed",H73="",ISBLANK(H73)),"",H73+7) | J73: =IF(I73="","",IF(I73<=TODAY(),"DUE",IF(I73<=TODAY()+3,"Next 3 Days","Later"))) | K73: linkedin.com/in/allanjeanbaptiste | https://www.linkedin.com/in/joshgwchin/ | M73: 12/03/2025
A74: Anthos Capital | B74: Financial Investor | C74: Follow Up | D74: Tier 2 | E74: 1 | F74: Roy Stigall | G74: rstigall@anthoscapital.com | H74: 45929 | I74: =IF(OR(C74="Passed",H74="",ISBLANK(H74)),"",H74+7) | J74: =IF(I74="","",IF(I74<=TODAY(),"DUE",IF(I74<=TODAY()+3,"Next 3 Days","Later"))) | K74: https://www.linkedin.com/in/roy-stigall-0b87a24a/ | M74: 12/05/2025
A75: Arbor Ventures | B75: Financial Investor | C75: Follow Up | D75: Tier 2 | E75: 6 | F75: Khaled Lababidi; Matt Dill; Melissa Cannon Guzy; Stephanie Baum‑Zepeda; Wei Hopeman | G75: khaled@arborventures.com; matt@arborventures.com; melissa@arborventures.com; stephanie@arborventures.com; whopeman@arborventures.com | H75: 45861 | I75: =IF(OR(C75="Passed",H75="",ISBLANK(H75)),"",H75+7) | J75: =IF(I75="","",IF(I75<=TODAY(),"DUE",IF(I75<=TODAY()+3,"Next 3 Days","Later"))) | K75: https://www.linkedin.com/in/khaled-lababidi-5793414/ | https://www.linkedin.com/in/melissa-c-guzy | M75: 12/26/2025
A76: Arcis Group | B76: Financial Investor | C76: Follow Up | D76: Tier 2 | E76: 5 | F76: Andrew Healey; Arnaud Isnard; David Coudray; Henri Isnard; Romain Bouché | G76: ahealey@arcisgroup.com; aisnard@arcisgroup.com; dcoudray@arcisgroup.com; hisnard@arcisgroup.com; rbouche@arcisgroup.com | H76: 45835 | I76: =IF(OR(C76="Passed",H76="",ISBLANK(H76)),"",H76+7) | J76: =IF(I76="","",IF(I76<=TODAY(),"DUE",IF(I76<=TODAY()+3,"Next 3 Days","Later"))) | K76: https://www.linkedin.com/in/andrew-healey-39a61125/ | https://www.linkedin.com/in/arnaud-isnard-929603/ | M76: 12/22/2025
A77: Arlington Capital | B77: Financial Investor | C77: Follow Up | D77: Tier 2 | E77: 4 | F77: David C Wodlinger; Matthew L Altman; Michael H Lustbader; Peter M Manos | G77: dwodlinger@arlingtoncap.com; maltman@arlingtoncap.com; mlustbader@arlingtoncap.com; pmanos@arlingtoncap.com | H77: 45986 | I77: =IF(OR(C77="Passed",H77="",ISBLANK(H77)),"",H77+7) | J77: =IF(I77="","",IF(I77<=TODAY(),"DUE",IF(I77<=TODAY()+3,"Next 3 Days","Later"))) | K77: https://www.linkedin.com/in/david-wodlinger-886b154/ | https://www.linkedin.com/in/matt-altman-34ab134/ | M77: 01/14/2026
A78: Asymmetric Capital Partners | B78: Financial Investor | C78: Follow Up | D78: Tier 2 | E78: 5 | F78: Michele Spitzer; Nancy Chou; Rob Biederman; Sam Clayman; Sarah Biggs | G78: michele@acp.vc; nancy@acp.vc; rob@acp.vc; sam@acp.vc; sarah@acp.vc | H78: 45835 | I78: =IF(OR(C78="Passed",H78="",ISBLANK(H78)),"",H78+7) | J78: =IF(I78="","",IF(I78<=TODAY(),"DUE",IF(I78<=TODAY()+3,"Next 3 Days","Later"))) | K78: https://www.linkedin.com/in/michelespitzer/ | https://www.linkedin.com/in/nancy-chou-b8496b29/ | M78: 12/23/2025
A79: Athenian VC | B79: Financial Investor | C79: Follow Up | D79: Tier 2 | E79: 1 | F79: Jason Mackey | G79: jason@athenian.vc | H79: 45973 | I79: =IF(OR(C79="Passed",H79="",ISBLANK(H79)),"",H79+7) | J79: =IF(I79="","",IF(I79<=TODAY(),"DUE",IF(I79<=TODAY()+3,"Next 3 Days","Later"))) | K79: https://www.linkedin.com/in/mackeyjasond/ | M79: 12/19/2025
A80: Augment Ventures | B80: Financial Investor | C80: Follow Up | D80: Tier 2 | E80: 5 | F80: Austin Churley; David Armstrong; Jeffrey Kontulis; Praachi Jain Mehta; Sonali Vijayavargiya | G80: austin@augmentventures.com; david@augmentventures.com; jeffrey@augmentventures.com; praachi@augmentventures.com; sonali@augmentventures.com | H80: 45924 | I80: =IF(OR(C80="Passed",H80="",ISBLANK(H80)),"",H80+7) | J80: =IF(I80="","",IF(I80<=TODAY(),"DUE",IF(I80<=TODAY()+3,"Next 3 Days","Later"))) | K80: https://www.linkedin.com/in/austinchurley/ | https://www.linkedin.com/in/david-armstrong-74b9a8b/ | M80: 12/04/2025
A81: Aureolis Ventures | B81: Financial Investor | C81: Follow Up | D81: Tier 2 | E81: 1 | F81: Arnav Mariwala | G81: arnav@aureolis.co.in | H81: 46010 | I81: =IF(OR(C81="Passed",H81="",ISBLANK(H81)),"",H81+7) | J81: =IF(I81="","",IF(I81<=TODAY(),"DUE",IF(I81<=TODAY()+3,"Next 3 Days","Later"))) | K81: linkedin.com/in/arnavmariwala
A82: Bain Capital | B82: Financial Investor | C82: Follow Up | D82: Tier 2 | E82: 4 | F82: Aaref Hilaly; Ajay Agarwal; Kevin Zhang; Merritt Hummer | G82: ahilaly@baincapital.com; ajay@baincapital.com; kzhang@baincapital.com; mhummer@baincapital.com | H82: 45985 | I82: =IF(OR(C82="Passed",H82="",ISBLANK(H82)),"",H82+7) | J82: =IF(I82="","",IF(I82<=TODAY(),"DUE",IF(I82<=TODAY()+3,"Next 3 Days","Later"))) | K82: https://www.linkedin.com/in/aarefhilaly/ | https://www.linkedin.com/in/ajay1agarwal | M82: 01/14/2026
A83: Bandera Capital | B83: Financial Investor | C83: Follow Up | D83: Tier 2 | E83: 3 | F83: David Solsky; Gabriel Reyna; Paul Bennett | G83: david@bandera.capital; gabriel@bandera.capital; paul@bandera.capital | H83: 45841 | I83: =IF(OR(C83="Passed",H83="",ISBLANK(H83)),"",H83+7) | J83: =IF(I83="","",IF(I83<=TODAY(),"DUE",IF(I83<=TODAY()+3,"Next 3 Days","Later"))) | K83: https://www.linkedin.com/in/davidsolsky/ | https://www.linkedin.com/in/gabriel-reyna/
A84: Battery Ventures | B84: Financial Investor | C84: Follow Up | D84: Tier 2 | E84: 5 | F84: Jesse Feldman; Michael Brown; Morad Elhafed; Neeraj Agrawal; Russell Fleischer | G84: jesse@battery.com; mbrown@battery.com; morad@battery.com; nagrawal@battery.com; rfleischer@battery.com | H84: 45841 | I84: =IF(OR(C84="Passed",H84="",ISBLANK(H84)),"",H84+7) | J84: =IF(I84="","",IF(I84<=TODAY(),"DUE",IF(I84<=TODAY()+3,"Next 3 Days","Later"))) | K84: https://www.linkedin.com/in/feldmanjesse/ | https://www.linkedin.com/in/michaelbrownvc/
A85: BayMed Venture Partners | B85: Financial Investor | C85: Follow Up | D85: Tier 2 | E85: 1 | F85: Gary Gershony | G85: gary@baymedvp.com | H85: 45973 | I85: =IF(OR(C85="Passed",H85="",ISBLANK(H85)),"",H85+7) | J85: =IF(I85="","",IF(I85<=TODAY(),"DUE",IF(I85<=TODAY()+3,"Next 3 Days","Later"))) | K85: linkedin.com/in/garygershony | M85: 12/19/2025
A86: Bessemer Venture | B86: Financial Investor | C86: Follow Up | D86: Tier 2 | E86: 1 | F86: Ed Colloton | G86: ed@bvp.com | H86: 45878 | I86: =IF(OR(C86="Passed",H86="",ISBLANK(H86)),"",H86+7) | J86: =IF(I86="","",IF(I86<=TODAY(),"DUE",IF(I86<=TODAY()+3,"Next 3 Days","Later"))) | M86: 12/26/2025
A87: Bessemer Venture Partners | B87: Financial Investor | C87: Follow Up | D87: Tier 2 | E87: 6 | F87: Byron Deeter; David Cowan; Kent Bennett; Ray O Johnson; Mick Mountz | G87: bdeeter@bvp.com; david@bvp.com; bennett@bvp.com; rjohnson@bvp.com; mmountz@bvp.com | H87: 45841 | I87: =IF(OR(C87="Passed",H87="",ISBLANK(H87)),"",H87+7) | J87: =IF(I87="","",IF(I87<=TODAY(),"DUE",IF(I87<=TODAY()+3,"Next 3 Days","Later"))) | K87: https://www.linkedin.com/in/byrondeeter/ | https://www.linkedin.com/in/davidjcowan/
A88: Blitzscaling Ventures | B88: Financial Investor | C88: Follow Up | D88: Tier 2 | E88: 4 | F88: Chris Yeh; Jeff Abbott; Jeremiah Owyang; Scott Johnson | G88: chris@blitzscalingventures.com; jeff@blitzscalingventures.com; jeremiah@blitzscalingventures.com; scott@blitzscalingventures.com | H88: 45835 | I88: =IF(OR(C88="Passed",H88="",ISBLANK(H88)),"",H88+7) | J88: =IF(I88="","",IF(I88<=TODAY(),"DUE",IF(I88<=TODAY()+3,"Next 3 Days","Later"))) | K88: linkedin.com/in/chrisyeh | linkedin.com/in/jeffreydabbott | M88: 12/22/2025 | "out of thesis - more focused on AI startups"
A89: Blue Delta Capital Partners | B89: Financial Investor | C89: Follow Up | D89: Tier 2 | E89: 3 | F89: Chris Torti; Kevin Robbins; Phil Nolan | G89: chris@bluedeltacapitalpartners.com; kevin@bluedeltacapitalpartners.com; phil@bluedeltacapitalpartners.com | H89: 45922 | I89: =IF(OR(C89="Passed",H89="",ISBLANK(H89)),"",H89+7) | J89: =IF(I89="","",IF(I89<=TODAY(),"DUE",IF(I89<=TODAY()+3,"Next 3 Days","Later")))
A90: Blue Startups | B90: Financial Investor | C90: Follow Up | D90: Tier 2 | E90: 1 | F90: Chenoa Farnsworth | G90: chenoa@bluestartups.com | H90: 45973 | I90: =IF(OR(C90="Passed",H90="",ISBLANK(H90)),"",H90+7) | J90: =IF(I90="","",IF(I90<=TODAY(),"DUE",IF(I90<=TODAY()+3,"Next 3 Days","Later"))) | K90: https://www.linkedin.com/in/chenoafarnsworth/ | M90: 12/19/2025
A91: Blue Stone | B91: Financial Investor | C91: Follow Up | D91: Tier 2 | E91: 5 | F91: Bill Strang; Eric Wolking; Joe Collins; John Allen; Mike Ivey | G91: bstrang@bluestoneinv.com; ewolking@bluestoneinv.com; jcollins@bluestoneinv.com; jallen@bluestoneinv.com; mivey@bluestoneinv.com | H91: 45922 | I91: =IF(OR(C91="Passed",H91="",ISBLANK(H91)),"",H91+7) | J91: =IF(I91="","",IF(I91<=TODAY(),"DUE",IF(I91<=TODAY()+3,"Next 3 Days","Later"))) | K91: https://www.linkedin.com/in/eric-wolking-29a6701/ | M91: outside area of expertise | asked to set meeting
A92: Blue Yard VC | B92: Financial Investor | C92: Follow Up | D92: Tier 2 | E92: 4 | F92: Chad Fowler; Ciaran O'Leary; David Byrd; Jason Whitmire | G92: legal@blueyard.com; chad@blueyard.com; ciaran@blueyard.com; david@blueyard.com; jason@blueyard.com | H92: 45922 | I92: =IF(OR(C92="Passed",H92="",ISBLANK(H92)),"",H92+7) | J92: =IF(I92="","",IF(I92<=TODAY(),"DUE",IF(I92<=TODAY()+3,"Next 3 Days","Later")))
A93: Bright Pixel Capital | B93: Financial Investor | C93: Follow Up | D93: Tier 2 | E93: 3 | F93: Eduardo Piedade; Fernando Martins; Filipa Costa | G93: eduardo.piedade@brpx.com; fernando.martins@brpx.com; filipa.costa@brpx.com | H93: 45973 | I93: =IF(OR(C93="Passed",H93="",ISBLANK(H93)),"",H93+7) | J93: =IF(I93="","",IF(I93<=TODAY(),"DUE",IF(I93<=TODAY()+3,"Next 3 Days","Later"))) | K93: https://www.linkedin.com/in/eduardopiedade/ | https://www.linkedin.com/in/fernandomartinscybersecurity | M93: 12/30/2025
A94: Brightstar Capital Partners | B94: Financial Investor | C94: Follow Up | D94: Tier 2 | E94: 5 | F94: Andrew Weinberg; Bruce Roberson; Kevin Deemer; Michael Singer; Shana Bochinis | G94: info@brightstarcp.com; andrew@brightstarcp.com; broberson@brightstarcp.com; kdeemer@brightstarcp.com; msinger@brightstarcp.com | H94: 45922 | I94: =IF(OR(C94="Passed",H94="",ISBLANK(H94)),"",H94+7) | J94: =IF(I94="","",IF(I94<=TODAY(),"DUE",IF(I94<=TODAY()+3,"Next 3 Days","Later")))
A95: BuildGroup | B95: Financial Investor | C95: Follow Up | D95: Tier 2 | E95: 5 | F95: Eric Levine; Jim Curry; Klee Kleber; Lanham Napier; Miguel Perez | G95: eric@buildgroup.com; jim@buildgroup.com; klee@buildgroup.com; lanham@buildgroup.com; miguel@buildgroup.com | H95: 45890 | I95: =IF(OR(C95="Passed",H95="",ISBLANK(H95)),"",H95+7) | J95: =IF(I95="","",IF(I95<=TODAY(),"DUE",IF(I95<=TODAY()+3,"Next 3 Days","Later"))) | K95: linkedin.com/in/eric-levine-740923a3 | linkedin.com/in/jimncurry | M95: 12/29/2025
A96: CEO | B96: Financial Investor | C96: Follow Up | D96: Tier 2 | E96: 2 | F96: Graeme Black; Mikael Lundman | G96: graeme.a.black.tu24@tuck.dartmouth.edu; mikael@exminvest.com | H96: 46037 | I96: =IF(OR(C96="Passed",H96="",ISBLANK(H96)),"",H96+7) | J96: =IF(I96="","",IF(I96<=TODAY(),"DUE",IF(I96<=TODAY()+3,"Next 3 Days","Later"))) | K96: https://www.linkedin.com/in/graeme-a-black/ | https://www.linkedin.com/in/mikaellundman/
A97: CEO/ Managing Partner - SENCO Hydrogen Capital | B97: Financial Investor | C97: Follow Up | D97: Tier 2 | E97: 1 | F97: Carsten Schmeding | G97: schmeding@senco-capital.com | H97: 46010 | I97: =IF(OR(C97="Passed",H97="",ISBLANK(H97)),"",H97+7) | J97: =IF(I97="","",IF(I97<=TODAY(),"DUE",IF(I97<=TODAY()+3,"Next 3 Days","Later"))) | K97: linkedin.com/in/carsten-schmeding-a351a5
A98: CFO | B98: Financial Investor | C98: Follow Up | D98: Tier 2 | E98: 2 | F98: Ben Tidd; Eillot Attie | G98: ben.tidd@hydrogenonecapital.com; elliot.attie@trilantic.com | H98: 46037 | I98: =IF(OR(C98="Passed",H98="",ISBLANK(H98)),"",H98+7) | J98: =IF(I98="","",IF(I98<=TODAY(),"DUE",IF(I98<=TODAY()+3,"Next 3 Days","Later"))) | K98: https://www.linkedin.com/in/ben-tidd/ | https://www.linkedin.com/in/elliot-attie-a5483b247/
A99: Candou Ventures | B99: Financial Investor | C99: Follow Up | D99: Tier 2 | E99: 1 | F99: Laleh Masnavi | G99: laleh@candouventures.com | H99: 46036 | I99: =IF(OR(C99="Passed",H99="",ISBLANK(H99)),"",H99+7) | J99: =IF(I99="","",IF(I99<=TODAY(),"DUE",IF(I99<=TODAY()+3,"Next 3 Days","Later"))) | K99: https://www.linkedin.com/in/laleh-masnavi-06b4347/
A100: Canvas Prime | B100: Financial Investor | C100: Follow Up | D100: Tier 2 | E100: 5 | F100: Gary Little; Harrison Lieberfarb; Justin Pirzadeh; Rebecca Lynn; Xan Wood | G100: glittle@canvas.vc; harrison@canvas.vc; jpirzadeh@canvas.vc; rebecca@canvas.vc; xan@canvas.vc | H100: 45929 | I100: =IF(OR(C100="Passed",H100="",ISBLANK(H100)),"",H100+7) | J100: =IF(I100="","",IF(I100<=TODAY(),"DUE",IF(I100<=TODAY()+3,"Next 3 Days","Later"))) | K100: linkedin.com/in/garylittle1 | linkedin.com/in/lieberfarb | M100: 12/04/2025 | 12/05/2025 | not a fit at this time
...

Sheet Today_Queue
A1: Rank | B1: Company | C1: Contact Name | D1: Category | E1: Stage | F1: Tier | G1: Last Touch | H1: Next Touch | I1: Due | J1: Priority Score | K1: Email | L1: Phone | M1: Next Action | N1: Notes
A2: 1 | B2: US Capital | C2: Ashley Curless | D2: Financial Investor | E2: Term Sheet / Proposal | F2: Tier 1 | G2: 45986 | H2: 45988 | I2: DUE | J2: 120 | K2: acurless@uscapital.com | M2: Review terms and push decision process | N2: Terms shared; fee-heavy engagement model. $120K + 8% $920K | 01/15/2026 | Submitted formal equity financing proposal for up to $10M. Structure includes 8% cash banking fee, 8% warrant coverage, and $120K upfront compliance/diligence/distribution fees. Process is heavily intermediary-led with broad investor marketing and placement focus. High fees and limited strategic value relative to capital efficiency; not a preferred path at this stage. | in data room ; sent terms but are they a strategic enough partner?
A3: 2 | B3: Craft Capital | C3: Brandon Golenda | D3: Financial Investor | E3: Term Sheet / Proposal | F3: Tier 1 | G3: 46020 | H3: 46022 | I3: DUE | J3: 120 | K3: bgolenda@craftcm.com | M3: Review terms and push decision process | N3: Advisory offer contingent on $30K fee. We chose not to proceed; parked. | $30K Investment bank enagement $10k/mo for 3 months advisor only. no funds.
A4: 3 | B4: Cerberus Capital Management | C4: Dan Quayle | D4: Financial Investor | E4: Term Sheet / Proposal | F4: Tier 1 | G4: 46023 | H4: 46025 | I4: DUE | J4: 120 | K4: dquayle@cerberus.com | M4: Review terms and push decision process | N4: 01/14/2026 | Introductory conversation held; John sent story deck, finance-focused deck, and one-pager today. Framed as strategic partner aligned with Scorpius acquisition, revenue expansion, and hypersonics / Golden Dome support. Added as potential strategic partner for board consideration. Awaiting response.
A5: 4 | B5: Cerberus Capital Management | C5: Frank Bruno | D5: Financial Investor | E5: Term Sheet / Proposal | F5: Tier 1 | G5: 46023 | H5: 46025 | I5: DUE | J5: 120 | K5: fbruno@cerberus.com | M5: Review terms and push decision process | N5: 01/14/2026 | Introductory conversation held; John sent story deck, finance-focused deck, and one-pager today. Framed as strategic partner aligned with Scorpius acquisition, revenue expansion, and hypersonics / Golden Dome support. Added as potential strategic partner for board consideration. Awaiting response.
A6: 5 | B6: Cerberus Capital Management | C6: Kent (Cerberus Ops) | D6: Financial Investor | E6: Term Sheet / Proposal | F6: Tier 1 | G6: 46023 | H6: 46025 | I6: DUE | J6: 120 | K6: consult-klietzau@cerberusoperations.com | M6: Review terms and push decision process | N6: Introductory conversation held; John sent story deck, finance-focused deck, and one-pager today. Framed as strategic partner aligned with Scorpius acquisition, revenue expansion, and hypersonics / Golden Dome support. Added as potential strategic partner for board consideration. Awaiting response.
A7: 6 | B7: InvestFortuna | C7: Sean Bromley | D7: Financial Investor | E7: Term Sheet / Proposal | F7: Tier 1 | G7: 46023 | H7: 46025 | I7: DUE | J7: 120 | K7: sbromley@investfortuna.com | M7: Review terms and push decision process | N7: The .4 term sheet, as drafted, is not registrable, not exchange-compliant, and not defensible for directors. It can be salvaged only through structural changes that align it with industry norms that they rejected. | 01/15/2026 | Fortuna proposed an IPO-led advisory structure including a warrant offering, $5M minimum bridge financing (convertible at significant discount), and a $15M IPO financing, with substantial embedded dilution and control provisions. EXOS submitted a formal counter-term sheet replacing discounted instruments and automatic vesting with performance-based earn-out equity tied to post-IPO share price and market cap milestones, preserving a clean cap table and fiduciary compliance. Negotiations ongoing; awaiting Fortuna response.
A8: 7 | B8: Pickwick Capital | C8: Crescent Varrone | D8: Financial Investor | E8: Term Sheet / Proposal | F8: Tier 1 | G8: 46031 | H8: 46033 | I8: DUE | J8: 120 | K8: varronec@pickwickcapital.com | M8: Review terms and push decision process | N8: Active discussions underway. Pickwick has expressed interest; no term sheet yet. John had producitive meeting on 1/9. | 01/15/2026
A9: 8 | B9: Pickwick Capital | C9: Crescent Varrone | D9: Financial Investor | E9: Term Sheet / Proposal | F9: Tier 1 | G9: 46031 | H9: 46033 | I9: DUE | J9: 120 | K9: alvarezd@pickwickcapital.com | L9: Capital Partner (Equity / Strategic) | M9: Review terms and push decision process | N9: Active discussions underway. Pickwick has expressed interest; no term sheet yet. John had producitive meeting on 1/9. | 01/15/2026
A10: 9 | B10: DelMorgan & Co | C10: RJ Mollen | D10: Financial Investor | E10: Term Sheet / Proposal | F10: Tier 1 | G10: 46037 | H10: 46039 | I10: DUE | J10: 120 | K10: rjm@delmorganco.com | M10: Review terms and push decision process | N10: Talked and rejected offer- RJ proposed two alternative advisory paths outside the DelMorgan framework: (1) Fast Space infrastructure and asset monetization strategy, and (2) Gleam Consulting advisory + investor introductions tied to a $10M raise. Fee-based advisory with equity success bonuses. Not aligned with current priorities; documented for reference.
A11: 10 | B11: AxisCades | C11: Suresh Babu Suryadevara | D11: Financial Investor | E11: Term Sheet / Proposal | F11: Tier 1 | G11: 46055 | H11: 46057 | I11: DUE | J11: 120 | K11: suresh.s@axiscades.in | M11: Review terms and push decision process | N11: Missed call toady at 08:30 - Follow-up framework shared outlining a phased, ITAR/EAR-compliant strategic partnership. Proposal includes AxisCades acquiring 51% of SSLC for $10M (phased capital), international sales support with commission structure, and long-term India-based manufacturing under TAA/MLA approvals. Discussions ongoing to confirm alignment on structure, valuation, and next steps. | toured SSLC on 2/16 | met in person at EXOS on 12/19, follow up set for onsite visit 1/19 | request for SSLC visit on hold pending establishment of basic term sheet.
A12: 11 | B12: US Capital | C12: Mitch; Steve Wilburn; Charles Sims | D12: Intermediary / Banker | E12: Term Sheet / Proposal | F12: Tier 1 | G12: 45986 | H12: 45988 | I12: DUE | J12: 117 | K12: mambe@uscapital.com | M12: Review terms and push decision process | N12: Terms shared; fee-heavy engagement model. $120K + 8% $920K | 01/15/2026 | Submitted formal equity financing proposal for up to $10M. Structure includes 8% cash banking fee, 8% warrant coverage, and $120K upfront compliance/diligence/distribution fees. Process is heavily intermediary-led with broad investor marketing and placement focus. High fees and limited strategic value relative to capital efficiency; not a preferred path at this stage.
A13: 12 | B13: Sunbelt Dallas Metro | C13: Bill Nicholson | D13: Intermediary / Banker | E13: Term Sheet / Proposal | F13: Tier 1 | G13: 46083 | H13: 46085 | I13: DUE | J13: 116 | K13: bnicholson@sunbeltnetwork.com | M13: Review terms and push decision process | N13: Sunbelt inquired about including a retainer amount in the Engagement Letter. John responded that the EXOS Board is unlikely to approve another open-ended retainer structure due to prior experiences with retainers that did not yield measurable outcomes. The Board is prioritizing: Clearly defined deliverables Performance-aligned compensation Objective execution milestones Defined transaction targets SEC-compliant structure (broker-dealer participation as required) John encouraged Sunbelt to propose a performance-based framework (reduced/deferred retainer, milestone-triggered payments, or primarily success-fee based on capital secured). Bill acknowledged and is coordinating internally to revise the proposal. He requested timing of the next Board meeting. Status: Awaiting revised engagement structure from Sunbelt for Board review. | sent email letting him know board doesn't want to pat retainer fees
A14: 13 | B14: Concord Ventures | C14: Salim Dada | D14: Financial Investor | E14: Engaged | F14: Tier 1 | G14: 45958 | H14: 45963 | I14: DUE | J14: 115 | K14: salim.d@concordventuresinc.com | M14: Advance diligence / proposal discussion | N14: Revised agreement sent; no follow-up since; inactive. | offer for $2500/month for 3 months plan | Offer for $2500/month to run program
A15: 14 | B15: Concord Ventures | C15: Salim Dada | D15: Financial Investor | E15: Engaged | F15: Tier 1 | G15: 45958 | H15: 45963 | I15: DUE | J15: 115 | M15: Advance diligence / proposal discussion | N15: Revised agreement sent; no follow-up since; inactive.
A16: 15 | B16: Odeon Capital | C16: Eric Gomberg | D16: Financial Investor | E16: Engaged | F16: Tier 1 | G16: 46028 | H16: 46033 | I16: DUE | J16: 115 | K16: egomberg@odeoncap.com | M16: Advance diligence / proposal discussion | N16: MNDA + data room sent Dec 17. No response prior to year-end. Follow-up email sent today. | 01/15/2026 | 1. Reduced Retainer of $30,000 Upfront. 2. Success Fee of $400,000 at the back end. We will credit the $30K Retainer back at the end upon a successful completion. 3. Any reasonable travel authorized by the client in advance of any travel. Please let us know if this is okay, then we can proceed with the detailed proposal/engagement letter. Regards, Bill Bill Nicholson, MBA, M&AMI®, CM&AA®
A17: 16 | B17: Ricci Global Partners | C17: Riccardo Ricci | D17: Financial Investor | E17: Engaged | F17: Tier 1 | G17: 46028 | H17: 46033 | I17: DUE | J17: 115 | K17: riccardo@riccicapitalpartners.com | M17: Advance diligence / proposal discussion | N17: MNDA executed and data room shared. Ricci requested finance working session and followed up again today to move forward | 01/15/2026 | 03/13/2026
A18: 17 | B18: Ricci Global Partners | C18: Riccardo Ricci | D18: Financial Investor | E18: Engaged | F18: Tier 1 | G18: 46028 | H18: 46033 | I18: DUE | J18: 115 | K18: riccardo-ricci@ricciglobalpartners.com | M18: Advance diligence / proposal discussion | N18: MNDA executed and data room shared. Ricci requested finance working session and followed up again today to move forward | 01/15/2026 | 03/13/2026
A19: 18 | B19: CrossRoads Capital | C19: Rchard Phillips | D19: Financial Investor | E19: Engaged | F19: Tier 1 | G19: 46038 | H19: 46043 | I19: DUE | J19: 115 | M19: Advance diligence / proposal discussion | N19: have new 18,000 sf facility just North of Denver Co. $3-4M to scale
A20: 19 | B20: Crossroads Capital | C20: Andrew J. Buchholtz and David Ford | D20: Financial Investor | E20: Engaged | F20: Tier 1 | G20: 46038 | H20: 46043 | I20: DUE | J20: 115 | K20: andy@abuchholtz.com | M20: Advance diligence / proposal discussion | N20: Sent you the ELA draft this morning — let me if you didn’t receive or if you have any questions. We can schedule another call if you’d like to review together. | have new 18,000 sf facility just North of Denver Co. $3-4M to scale | had a call, sent deck
A21: 20 | B21: Digital Asset Management | C21: Juan Lorenzana | D21: Financial Investor | E21: Engaged | F21: Tier 1 | G21: 46059 | H21: 46064 | I21: DUE | J21: 115 | M21: Advance diligence / proposal discussion | N21: $30K refundable. Fund with hedge of Gold metals real estate etc.
A22: 21 | B22: referred by andy@abucholtz.com | C22: Richard Phillips | D22: Financial Investor | E22: Meeting Requested | F22: Tier 1 | G22: 45903 | H22: 45905 | I22: DUE | J22: 113 | M22: Book call and send agenda/deck | N22: | meeting set 9/8/ NDA 9/12 |
A23: 22 | B23: TEL Venture Capital | C23: Sergey Fedotov | D23: Financial Investor | E23: Meeting Requested | F23: Tier 1 | G23: 45912 | H23: 45914 | I23: DUE | J23: 113 | K23: sergey.fedotov@tel.com | L23: 650.360.8669 | M23: Book call and send agenda/deck | N23: 9/24 - meeting set for 10/2
A24: 23 | B24: One Bow River | C24: Stowe Faircloth | D24: Financial Investor | E24: Meeting Requested | F24: Tier 1 | G24: 45922 | H24: 45924 | I24: DUE | J24: 113 | K24: shane.sherman@onebowriver.com | L24: 720.910.9483 | M24: Book call and send agenda/deck | N24: 08/12/2025 | Stowe Faircloth <Stowe.faircloth@onebowriver.com>replied requesting a meeting on 9/22
A25: 24 | B25: Tristate Capital | C25: Sulaiman Sulaimani | D25: Intermediary / Banker | E25: Engaged | F25: Tier 1 | G25: 46054 | H25: 46059 | I25: DUE | J25: 112 | K25: sulaiman@tristatecap.com | L25: 11/17 meeting held and follow up sent | M25: Advance diligence / proposal discussion | N25: https://www.irongatevc.com/ Contracted with Sulaiman Sulaimani ​John Quinn​ ​Neil Milburn​ John, I'm scheduled to speak with our strategic partner Ty McCoy tomorrow. He just emailed me a company now that appears to be a close contact of his as there is someone on their team that is former CIA. I think we found the right partner for you and your team. Please give me sometime as I work on this for you and your team. I'll be back in touch. Thanks for the call yesterday. I enjoyed speaking with you. I was able to connect with our strategic partner Ty McCoy with IronGate. He is available to speak with us next week at 12 pm CST on 2/10. I was also able to circle up with our clients from ETL. Hanshin Lee emailed me that he is interested in Exos Aerospace and speaking with us next week at 8 am CST on 2/10. If you can please send me calendar invites for both calls on 2/10 8 am CST with ETL, and 12 pm CST with IronGate. Once I receive both invites, I'll be sure to pass them along. | 01/15/2026 | 2/10 – Calls Held: | etl dean rx? match with portfolio co
A26: 25 | B26: Rockfleet Financial | C26: John Swift | D26: Financial Investor | E26: Meeting Held | F26: Tier 1 | G26: 45831 | H26: 45836 | I26: DUE | J26: 109 | K26: john.swift@rockfleetfinancial.com | M26: Send recap, materials, and next-step ask | N26: | meeting held on 7/2 & NDA in process- Followed up 7-11 |
A27: 26 | B27: Palm Drive Capital | C27: Carter Dessommes | D27: Financial Investor | E27: Meeting Held | F27: Tier 1 | G27: 45859 | H27: 45864 | I27: DUE | J27: 109 | K27: carter@palmdrive.vc | M27: Send recap, materials, and next-step ask | N27: | meeting held |
A28: 27 | B28: REI | D28: Financial Investor | E28: Meeting Held | F28: Tier 1 | G28: 45917 | H28: 45922 | I28: DUE | J28: 109 | M28: Send recap, materials, and next-step ask | N28: Choctaw nation investor group interested in Space investments. Requesting site tour on 9-26 If you could send me a new link for a warehouse visit over the next week or so I’d really like to continue to dig into this and see where or who we can fit in. Also, please send me the deck and anything else you would like me to consider. | |
A29: 28 | B29: Cerebro Capital | C29: Steven Agathoklis | D29: Financial Investor | E29: Meeting Held | F29: Tier 1 | G29: 45951 | H29: 45956 | I29: DUE | J29: 109 | K29: sagathoklis@cerebrocapital.com | M29: Send recap, materials, and next-step ask | N29: NDA signed; full financials provided. No response since; inactive. | meeting held on 10/16
A30: 29 | B30: Noblis Ventures | C30: Bill Collier | D30: Financial Investor | E30: Meeting Held | F30: Tier 1 | G30: 45972 | H30: 45977 | I30: DUE | J30: 109 | K30: bill.collier@noblis.org | L30: 09/03/2025 | M30: Send recap, materials, and next-step ask | N30: 12/5 follow up sent | meeting held and follow up emails sent. most recent follow up 12/5
A31: 30 | B31: IPO Club | C31: Edoardo Zarghetta | D31: Financial Investor | E31: Meeting Held | F31: Tier 1 | G31: 46030 | H31: 46035 | I31: DUE | J31: 109 | K31: edozar@gmail.com | M31: Send recap, materials, and next-step ask | N31: | meeting held on 1/13 - pitch deck sent for brother |
A32: 31 | B32: Prospect Capital | C32: Sulaiman Sulaimani | D32: Financial Investor | E32: Meeting Held | F32: Tier 1 | G32: 46030 | H32: 46035 | I32: DUE | J32: 109 | L32: Capital Partner (Debt / Structured Capital) | M32: Send recap, materials, and next-step ask | N32: Introductory meeting held Jan 8. Prospect Capital operates through two distinct divisions; conversations are exploratory at this stage. Two divisions: core BDC credit and structured/special situations. EXOS aligns better with structured, event-driven capital vs traditional cash-flow lending. |
A33: 32 | B33: Gravitics | C33: Scott Macklin | D33: Strategic / Corporate | E33: Meeting Requested | F33: Tier 1 | G33: 45744 | H33: 45746 | I33: DUE | J33: 106 | K33: smacklin@gravitics.com | M33: Book call and send agenda/deck | N33: meeting set for 4/3
A34: 33 | B34: CounterFlow Solutions | C34: Dan Garretson | D34: Other / Review | E34: Engaged | F34: Tier 1 | G34: 46024 | H34: 46029 | I34: DUE | J34: 104 | K34: dgarretson@counterflowsolutions.com | M34: Advance diligence / proposal discussion | N34: Proposed short sprint to reframe EXOS + Scorpius narrative. Decision pending. | 12/23 john sent follow up reply | Costs for wrong scope
A35: 34 | B35: Moonshots Capital | C35: LTC Brian Titus Noble | D35: Financial Investor | E35: Follow Up | F35: Tier 2 | G35: 45813 | H35: 45820 | I35: DUE | J35: 90 | K35: titus@moonshotscapital.com | M35: Send next follow-up with traction + CTA | N35: | |
A36: 35 | B36: Moonshots Capital | C36: Mac Hoffman | D36: Financial Investor | E36: Follow Up | F36: Tier 2 | G36: 45813 | H36: 45820 | I36: DUE | J36: 90 | K36: mac@moonshotscapital.com | M36: Send next follow-up with traction + CTA | N36: | Moonshots Application: https://www.moonshotscapital.com/submit-your-startup-for-early-stage-investment/ |
A37: 36 | B37: Khosla Ventures | C37: Alice Brooks | D37: Financial Investor | E37: Follow Up | F37: Tier 2 | G37: 45814 | H37: 45821 | I37: DUE | J37: 90 | K37: abrooks@khoslaventures.com | M37: Send next follow-up with traction + CTA | N37: | |
A38: 37 | B38: Khosla Ventures | C38: Jon Chu | D38: Financial Investor | E38: Follow Up | F38: Tier 2 | G38: 45814 | H38: 45821 | I38: DUE | J38: 90 | K38: jc@khoslaventures.com | M38: Send next follow-up with traction + CTA | N38: | |
A39: 38 | B39: Khosla Ventures | C39: Kanu Gulati | D39: Financial Investor | E39: Follow Up | F39: Tier 2 | G39: 45814 | H39: 45821 | I39: DUE | J39: 90 | K39: kg@khoslaventures.com | M39: Send next follow-up with traction + CTA | N39: | |
A40: 39 | B40: Khosla Ventures | C40: Rajesh Swaminathan | D40: Financial Investor | E40: Follow Up | F40: Tier 2 | G40: 45814 | H40: 45821 | I40: DUE | J40: 90 | K40: rs@khoslaventures.com | M40: Send next follow-up with traction + CTA | N40: asked for deck / 7/7 sent deck | Deck 7-7-25 |
A41: 40 | C41: James Cameron | D41: Financial Investor | E41: Follow Up | F41: Tier 2 | G41: 45821 | H41: 45828 | I41: DUE | J41: 90 | K41: james@visionaryleadership.co.nz | M41: Send next follow-up with traction + CTA | N41: | dns fail |
A42: 41 | C42: Jason Schwartz / Paul Gloyer GTL | D42: Financial Investor | E42: Follow Up | F42: Tier 2 | G42: 45821 | H42: 45828 | I42: DUE | J42: 90 | K42: jason@leagueadvisors.com | M42: Send next follow-up with traction + CTA | N42: | |
A43: 42 | B43: Moneta VC | C43: Aasim Hasan | D43: Financial Investor | E43: Follow Up | F43: Tier 2 | G43: 45821 | H43: 45828 | I43: DUE | J43: 90 | K43: ahasan@monetaventures.com | M43: Send next follow-up with traction + CTA | N43: | outside their scope |
A44: 43 | B44: Moneta VC | C44: Ashu Bhalla | D44: Financial Investor | E44: Follow Up | F44: Tier 2 | G44: 45821 | H44: 45828 | I44: DUE | J44: 90 | K44: ashu@moneta.vc | M44: Send next follow-up with traction + CTA | N44: | Moneta Application: https://moneta.vc/get-funding/ |
A45: 44 | B45: Moneta VC | C45: Brent Kelton | D45: Financial Investor | E45: Follow Up | F45: Tier 2 | G45: 45821 | H45: 45828 | I45: DUE | J45: 90 | K45: brent@moneta.vc | M45: Send next follow-up with traction + CTA | N45: | |
A46: 45 | B46: Moneta VC | C46: Lokesh Sikaria | D46: Financial Investor | E46: Follow Up | F46: Tier 2 | G46: 45821 | H46: 45828 | I46: DUE | J46: 90 | K46: lsikaria@monetaventures.com | M46: Send next follow-up with traction + CTA | N46: | |
A47: 46 | B47: Moneta VC | C47: Vaibhav Nadgauda | D47: Financial Investor | E47: Follow Up | F47: Tier 2 | G47: 45821 | H47: 45828 | I47: DUE | J47: 90 | K47: vnadgauda@monetaventures.com | M47: Send next follow-up with traction + CTA | N47: | |
A48: 47 | B48: Earl Grey Capital | C48: whole team | D48: Financial Investor | E48: Follow Up | F48: Tier 2 | G48: 45828 | H48: 45835 | I48: DUE | J48: 90 | K48: team@earlgrey.capital | M48: Send next follow-up with traction + CTA | N48: | |
A49: 48 | B49: Arcis Group | C49: Andrew Healey | D49: Financial Investor | E49: Follow Up | F49: Tier 2 | G49: 45835 | H49: 45842 | I49: DUE | J49: 90 | K49: ahealey@arcisgroup.com | M49: Send next follow-up with traction + CTA | N49: | 12/22/2025 |
A50: 49 | B50: Arcis Group | C50: Arnaud Isnard | D50: Financial Investor | E50: Follow Up | F50: Tier 2 | G50: 45835 | H50: 45842 | I50: DUE | J50: 90 | K50: aisnard@arcisgroup.com | M50: Send next follow-up with traction + CTA | N50: | 12/22/2025 |
A51: 50 | B51: Arcis Group | C51: David Coudray | D51: Financial Investor | E51: Follow Up | F51: Tier 2 | G51: 45835 | H51: 45842 | I51: DUE | J51: 90 | K51: dcoudray@arcisgroup.com | M51: Send next follow-up with traction + CTA | N51: | 12/22/2025 |
A52: 51 | B52: Arcis Group | C52: Henri Isnard | D52: Financial Investor | E52: Follow Up | F52: Tier 2 | G52: 45835 | H52: 45842 | I52: DUE | J52: 90 | K52: hisnard@arcisgroup.com | M52: Send next follow-up with traction + CTA | N52: | 12/22/2025 |
A53: 52 | B53: Arcis Group | C53: Romain Bouché | D53: Financial Investor | E53: Follow Up | F53: Tier 2 | G53: 45835 | H53: 45842 | I53: DUE | J53: 90 | K53: rbouche@arcisgroup.com | M53: Send next follow-up with traction + CTA | N53: | 12/22/2025 |
A54: 53 | B54: Asymmetric Capital Partners | C54: Michele Spitzer | D54: Financial Investor | E54: Follow Up | F54: Tier 2 | G54: 45835 | H54: 45842 | I54: DUE | J54: 90 | K54: michele@acp.vc | M54: Send next follow-up with traction + CTA | N54: | 12/23/2025 |
... A61: 60 | B61: Blitzscaling Ventures | C61: Jeremiah Owyang | D61: Financial Investor | E61: Follow Up | F61: Tier 2 | G61: 45835 | H61: 45842 | I61: DUE | J61: 90 | K61: jeremiah@blitzscalingventures.com | M61: Send next follow-up with traction + CTA | N61: | "out of thesis - more focused on AI startups" |

Sheet Fundraise_Guide
A1: Bot tasking guide: EXOS $10M Series A
A3: Mission | F3: Suggested stage moves
B4: • Primary goal: book 2–3 qualified investor calls per day. | F4: Research -> Contacted after first email goes out
B5: • System of record: CRM_Master. | F5: Contacted -> Follow Up after next touch is sent
B6: • Work order: Today_Queue first, then new research, then follow-ups. | F6: Follow Up -> Meeting Requested after positive reply / scheduling
F7: Meeting Requested -> Meeting Held after call completes
A8: Ideal investor profile | F8: Meeting Held -> Engaged when diligence, deck, NDA, or proposal is active
B9: • Space + defense industrial base + aerospace manufacturing + launch infrastructure. | F9: Engaged -> Term Sheet / Proposal when structured offer is on the table
B10: • U.S.-based investors or strategic partners comfortable with hard-tech / regulated businesses.
B11: • Targets able to participate in a $10M Series A and support follow-on capital.
B12: • Prefer funds or strategics with aerospace, defense, dual-use, launch, propulsion, ground systems, or advanced manufacturing relevance.
A14: Negative filters
B15: • Consumer-only, software-only, late-stage only, or check sizes too small to matter.
B16: • No scraping of private personal information; use public professional data only.
A18: Scoring rubric
B19: • Sector fit 25 | Check-size / stage fit 20 | Space / A&D relevance 20 | Lead potential 10 | Strategic value 10 | Warm intro 10 | Response likelihood 5
A21: Cadence
B22: • Day 0 initial email | Day 3 follow-up | Day 7 second follow-up | Day 12 bump | milestone re-engage later.
B23: • Pause after a clear pass. Update Last Touch, Notes, Stage, and Next Action every time.
A25: Scheduling rules
B26: • Offer only approved time blocks; prioritize Tier 1 then Tier 2.
B27: • No more than 3 external investor calls/day unless manually approved.
B28: • After positive reply, draft calendar invite + agenda + recap tasks.

Sheet JQ Follow Up
A1: red font = Lizi has a question for JQ | B1: blue highlight = NDA signed | C1: yellow highlight = a maybe | D1: green = JQ Follow Up ASAP
A2: NAME | B2: COMPANY | C2: LINKED IN | D2: EMAIL | E2: PHONE NUMBER | F2: FIRST CONTACT | G2: SECOND CONTACT | H2: NOTES | I2: Follow ups | L2: LAST ACTIVITY: | M2: NEXT STEP:
A4: Suresh Babu Suryadevara | B4: AxisCades | D4: suresh.s@axiscades.in ; arun.arumugam@axiscades.in ; rithvick.naidu@axiscades.in | F4: 12/10 meeting | G4: 12/18 NDA Signed | H4: met in person at EXOS on 12/19, follow up set for onsite visit 1/19 | I4: request for SSLC visit on hold pending establishment of basic term sheet.
A5: Jeremy Harbour | B5: Unity Group | C5: Tahmina Kahn referred | D5: jeremy@unity-group.com | F5: 3/3 zoom call, followed up with deck | H5: wants to take puclic in europe markets, unlisted - 2.5 mill - 3-4 steps, building to take puclic in a few years
