Workbook

Sheet Inputs
A1: SSLC year-end cash reality check: inputs
A2: Input | B2: Value | C2: Source / basis
A3: Starting cash (Oct 2, 2026) | B3: 198000 | C3: SSLC QuickBooks pull 10/2/2026
A4: Year-end target cash (Jim Wertz) | B4: 850000 | C4: Jim Wertz statement
A5: Weeks Oct 2 → Dec 31 | B5: 13 | C5: Calendar
A6: Weeks per tank (Markus Rufer) | B6: 3 | C6: Markus Rufer statement
A7: Price per tank ($) | B7: 250000 | C7: Markus Rufer statement
A8: Prepaid backlog already collected ($) | B8: 984000 | C8: SSLC QB 10/2: $864K billed ahead + $120K deposits. DISPUTED by John: tank start/billing not captured correctly
A9: Direct build cost (% of tank price) | B9: 0.52 | C9: Management assumption (actuals-anchored model COGS)
A10: Annual fixed overhead ($) | B10: 1340000 | C10: Derived: FY26 rev $1.925M × 48% GM + $416K op loss; mgmt assumption

Sheet Weekly Cash
A1: Week | B1: Tank delivered? | C1: Tank revenue ($) | D1: Best case: cash balance | E1: Per SSLC books (disputed): cash balance | F1: Wertz claim path | G1: Target $850K
A2: 0 | C2: 0 | D2: =Inputs!B3 | E2: =Inputs!B3 | F2: =Inputs!B3 | G2: =Inputs!B4
A3: 1 | B3: =IF(MOD(A3,Inputs!$B$6)=0,"Yes","") | C3: =IF(B3="Yes",Inputs!$B$7,0) | D3: =D2+C3-Inputs!$B$7*Inputs!$B$9/Inputs!$B$6-Inputs!$B$10/52 | E3: =E2+MAX(0,SUM($C$3:C3)-Inputs!$B$8)-MAX(0,SUM($C$3:C2)-Inputs!$B$8)-Inputs!$B$7*Inputs!$B$9/Inputs!$B$6-Inputs!$B$10/52 | F3: =Inputs!$B$3+(Inputs!$B$4-Inputs!$B$3)*A3/Inputs!$B$5 | G3: =Inputs!$B$4
A4: 2 | B4: =IF(MOD(A4,Inputs!$B$6)=0,"Yes","") | C4: =IF(B4="Yes",Inputs!$B$7,0) | D4: =D3+C4-Inputs!$B$7*Inputs!$B$9/Inputs!$B$6-Inputs!$B$10/52 | E4: =E3+MAX(0,SUM($C$3:C4)-Inputs!$B$8)-MAX(0,SUM($C$3:C3)-Inputs!$B$8)-Inputs!$B$7*Inputs!$B$9/Inputs!$B$6-Inputs!$B$10/52 | F4: =Inputs!$B$3+(Inputs!$B$4-Inputs!$B$3)*A4/Inputs!$B$5 | G4: =Inputs!$B$4
A5: 3 | B5: =IF(MOD(A5,Inputs!$B$6)=0,"Yes","") | C5: =IF(B5="Yes",Inputs!$B$7,0) | D5: =D4+C5-Inputs!$B$7*Inputs!$B$9/Inputs!$B$6-Inputs!$B$10/52 | E5: =E4+MAX(0,SUM($C$3:C5)-Inputs!$B$8)-MAX(0,SUM($C$3:C4)-Inputs!$B$8)-Inputs!$B$7*Inputs!$B$9/Inputs!$B$6-Inputs!$B$10/52 | F5: =Inputs!$B$3+(Inputs!$B$4-Inputs!$B$3)*A5/Inputs!$B$5 | G5: =Inputs!$B$4
A6: 4 | B6: =IF(MOD(A6,Inputs!$B$6)=0,"Yes","") | C6: =IF(B6="Yes",Inputs!$B$7,0) | D6: =D5+C6-Inputs!$B$7*Inputs!$B$9/Inputs!$B$6-Inputs!$B$10/52 | E6: =E5+MAX(0,SUM($C$3:C6)-Inputs!$B$8)-MAX(0,SUM($C$3:C5)-Inputs!$B$8)-Inputs!$B$7*Inputs!$B$9/Inputs!$B$6-Inputs!$B$10/52 | F6: =Inputs!$B$3+(Inputs!$B$4-Inputs!$B$3)*A6/Inputs!$B$5 | G6: =Inputs!$B$4
A7: 5 | B7: =IF(MOD(A7,Inputs!$B$6)=0,"Yes","") | C7: =IF(B7="Yes",Inputs!$B$7,0) | D7: =D6+C7-Inputs!$B$7*Inputs!$B$9/Inputs!$B$6-Inputs!$B$10/52 | E7: =E6+MAX(0,SUM($C$3:C7)-Inputs!$B$8)-MAX(0,SUM($C$3:C6)-Inputs!$B$8)-Inputs!$B$7*Inputs!$B$9/Inputs!$B$6-Inputs!$B$10/52 | F7: =Inputs!$B$3+(Inputs!$B$4-Inputs!$B$3)*A7/Inputs!$B$5 | G7: =Inputs!$B$4
A8: 6 | B8: =IF(MOD(A8,Inputs!$B$6)=0,"Yes","") | C8: =IF(B8="Yes",Inputs!$B$7,0) | D8: =D7+C8-Inputs!$B$7*Inputs!$B$9/Inputs!$B$6-Inputs!$B$10/52 | E8: =E7+MAX(0,SUM($C$3:C8)-Inputs!$B$8)-MAX(0,SUM($C$3:C7)-Inputs!$B$8)-Inputs!$B$7*Inputs!$B$9/Inputs!$B$6-Inputs!$B$10/52 | F8: =Inputs!$B$3+(Inputs!$B$4-Inputs!$B$3)*A8/Inputs!$B$5 | G8: =Inputs!$B$4
A9: 7 | B9: =IF(MOD(A9,Inputs!$B$6)=0,"Yes","") | C9: =IF(B9="Yes",Inputs!$B$7,0) | D9: =D8+C9-Inputs!$B$7*Inputs!$B$9/Inputs!$B$6-Inputs!$B$10/52 | E9: =E8+MAX(0,SUM($C$3:C9)-Inputs!$B$8)-MAX(0,SUM($C$3:C8)-Inputs!$B$8)-Inputs!$B$7*Inputs!$B$9/Inputs!$B$6-Inputs!$B$10/52 | F9: =Inputs!$B$3+(Inputs!$B$4-Inputs!$B$3)*A9/Inputs!$B$5 | G9: =Inputs!$B$4
A10: 8 | B10: =IF(MOD(A10,Inputs!$B$6)=0,"Yes","") | C10: =IF(B10="Yes",Inputs!$B$7,0) | D10: =D9+C10-Inputs!$B$7*Inputs!$B$9/Inputs!$B$6-Inputs!$B$10/52 | E10: =E9+MAX(0,SUM($C$3:C10)-Inputs!$B$8)-MAX(0,SUM($C$3:C9)-Inputs!$B$8)-Inputs!$B$7*Inputs!$B$9/Inputs!$B$6-Inputs!$B$10/52 | F10: =Inputs!$B$3+(Inputs!$B$4-Inputs!$B$3)*A10/Inputs!$B$5 | G10: =Inputs!$B$4
A11: 9 | B11: =IF(MOD(A11,Inputs!$B$6)=0,"Yes","") | C11: =IF(B11="Yes",Inputs!$B$7,0) | D11: =D10+C11-Inputs!$B$7*Inputs!$B$9/Inputs!$B$6-Inputs!$B$10/52 | E11: =E10+MAX(0,SUM($C$3:C11)-Inputs!$B$8)-MAX(0,SUM($C$3:C10)-Inputs!$B$8)-Inputs!$B$7*Inputs!$B$9/Inputs!$B$6-Inputs!$B$10/52 | F11: =Inputs!$B$3+(Inputs!$B$4-Inputs!$B$3)*A11/Inputs!$B$5 | G11: =Inputs!$B$4
A12: 10 | B12: =IF(MOD(A12,Inputs!$B$6)=0,"Yes","") | C12: =IF(B12="Yes",Inputs!$B$7,0) | D12: =D11+C12-Inputs!$B$7*Inputs!$B$9/Inputs!$B$6-Inputs!$B$10/52 | E12: =E11+MAX(0,SUM($C$3:C12)-Inputs!$B$8)-MAX(0,SUM($C$3:C11)-Inputs!$B$8)-Inputs!$B$7*Inputs!$B$9/Inputs!$B$6-Inputs!$B$10/52 | F12: =Inputs!$B$3+(Inputs!$B$4-Inputs!$B$3)*A12/Inputs!$B$5 | G12: =Inputs!$B$4
A13: 11 | B13: =IF(MOD(A13,Inputs!$B$6)=0,"Yes","") | C13: =IF(B13="Yes",Inputs!$B$7,0) | D13: =D12+C13-Inputs!$B$7*Inputs!$B$9/Inputs!$B$6-Inputs!$B$10/52 | E13: =E12+MAX(0,SUM($C$3:C13)-Inputs!$B$8)-MAX(0,SUM($C$3:C12)-Inputs!$B$8)-Inputs!$B$7*Inputs!$B$9/Inputs!$B$6-Inputs!$B$10/52 | F13: =Inputs!$B$3+(Inputs!$B$4-Inputs!$B$3)*A13/Inputs!$B$5 | G13: =Inputs!$B$4
A14: 12 | B14: =IF(MOD(A14,Inputs!$B$6)=0,"Yes","") | C14: =IF(B14="Yes",Inputs!$B$7,0) | D14: =D13+C14-Inputs!$B$7*Inputs!$B$9/Inputs!$B$6-Inputs!$B$10/52 | E14: =E13+MAX(0,SUM($C$3:C14)-Inputs!$B$8)-MAX(0,SUM($C$3:C13)-Inputs!$B$8)-Inputs!$B$7*Inputs!$B$9/Inputs!$B$6-Inputs!$B$10/52 | F14: =Inputs!$B$3+(Inputs!$B$4-Inputs!$B$3)*A14/Inputs!$B$5 | G14: =Inputs!$B$4
A15: 13 | B15: =IF(MOD(A15,Inputs!$B$6)=0,"Yes","") | C15: =IF(B15="Yes",Inputs!$B$7,0) | D15: =D14+C15-Inputs!$B$7*Inputs!$B$9/Inputs!$B$6-Inputs!$B$10/52 | E15: =E14+MAX(0,SUM($C$3:C15)-Inputs!$B$8)-MAX(0,SUM($C$3:C14)-Inputs!$B$8)-Inputs!$B$7*Inputs!$B$9/Inputs!$B$6-Inputs!$B$10/52 | F15: =Inputs!$B$3+(Inputs!$B$4-Inputs!$B$3)*A15/Inputs!$B$5 | G15: =Inputs!$B$4

Sheet Summary
A1: Year-end (Dec 31) result
A3: Tanks delivered by Dec 31 at 1 per 3 weeks | B3: =COUNTIF('Weekly Cash'!B3:B15,"Yes")
A4: Tank revenue by Dec 31 | B4: =SUM('Weekly Cash'!C3:C15)
A5: Best case year-end cash (all tanks = new cash) | B5: ='Weekly Cash'!D15
A6: Per SSLC books, if billed-ahead is accurate (DISPUTED) | B6: ='Weekly Cash'!E15
A7: Wertz claim | B7: =Inputs!B4
A8: Shortfall vs claim: best case | B8: =Inputs!B4-B5
A9: Shortfall vs claim: per SSLC books (disputed) | B9: =Inputs!B4-B6
A11: Reading: even if every tank is new cash, SSLC can't reach $850K by year-end from operations. The prepaid backlog means the next ~4 tanks were already paid for. Reaching $850K requires new customer deposits or financing, and each of those adds a delivery or repayment obligation.
A12: Management assumptions are marked on Inputs. Projection, not a statement of SSLC's actual results.
