Workbook

Sheet Index
B3: Date: | C3: =TODAY() -> 46171
A5: 1 | B5: Instructions
A6: =A5+1 -> 2 | B6: Dashboard
A7: =A6+1 -> 3 | B7: Controls
A8: =A7+1 -> 4 | B8: Revenue Asumptions
A9: =A8+1 -> 5 | B9: Expense Assumptions
A10: =A9+1 -> 6 | B10: Payroll Assumptions
A11: =A10+1 -> 7 | B11: Fixed Asset Schedules
A12: =A11+1 -> 8 | B12: Monthly P&L
A13: =A12+1 -> 9 | B13: Annual P&L
A14: =A13+1 -> 10 | B14: Monthly CFS
A15: =A14+1 -> 11 | B15: Annual CFS
A16: =A15+1 -> 12 | B16: Balance Sheet
A17: =A16+1 -> 13 | B17: Annual Balance Sheet
A18: =A16+1 -> 13 | B18: Funding Ask
A19: =A18+1 -> 14 | B19: Valuation

Sheet Instructions
A4: How this Model works
A6: A. | B6: Financial models are an attempt to present a "big picture" view of future financial performance. Many simplifying assumptions are made, and the model does not attempt to capture all financial details & nuances. Most simplifying assumptions will not have a material impact on the big picture - for example, the cash flow differences between leasing or purchasing a vehicle probably won't affect the big picture unless the company operates a massive fleet of vehicles. The model may also simplify issues such as the expensing vs. amortizing of startup expenses.
A7: B. | B7: The quality of any forecast is dependent on the quality of the assumptions and the quality of the cause-and-effect relationships incorporated into the model. The focus must be on the quality of the assumptions taken; and its cause-and-effect relationships.
A9: Colour Coding
C11: The Control Tab is the Input Tab for Assumptions.
C13: The tabs in Light Blue reflect the different of Assumptions taken in the model. These values are controlled by the values input in the Control Tab.
C15: Tabs in Light Green are output tabs, which display the information from the input tabs. Do not modify anything on the green tabs.
B17: 0 | C17: ONLY the BLUE cells containing texts in BLUE are Hard Coded and can be adjusted by the user without compromising the excel formulas.
B19: 0 | C19: Cells shaded Grey-Blue contain a dropdown list, and take values from the dropdown list only. Any other value inputed, will go on to show the user an error.
C21: Cells shaded Yellow contain instructions & explanations for the user to better understand the model, and the asumptions taken by the model

Sheet Dashboard
A1: Back To Index
B3: Overview | C3: 1 | D3: =+C3+1 -> 2 | E3: =+D3+1 -> 3 | F3: =+E3+1 -> 4 | G3: =+F3+1 -> 5
B5: Total Revenue | C5: ='Annual P&L'!B14/10^6 -> 8.86754 | D5: ='Annual P&L'!C14/10^6 -> 21.108525 | E5: ='Annual P&L'!D14/10^6 -> 43.092777 | F5: ='Annual P&L'!E14/10^6 -> 95.919145 | G5: ='Annual P&L'!F14/10^6 -> 179.18554
B6: Y.O.Y Growth % | D6: ='Annual P&L'!C15 -> 1.3804263 | E6: ='Annual P&L'!D15 -> 1.0414869 | F6: ='Annual P&L'!E15 -> 1.2258753 | G6: ='Annual P&L'!F15 -> 0.86808943
B8: Gross Profit | C8: ='Annual P&L'!B19/10^6 -> #N/A | D8: ='Annual P&L'!C19/10^6 -> #N/A | E8: ='Annual P&L'!D19/10^6 -> #N/A | F8: ='Annual P&L'!E19/10^6 -> #N/A | G8: ='Annual P&L'!F19/10^6 -> #N/A
B9: Gross Margins % | C9: ='Annual P&L'!B20 -> #N/A | D9: ='Annual P&L'!C20 -> #N/A | E9: ='Annual P&L'!D20 -> #N/A | F9: ='Annual P&L'!E20 -> #N/A | G9: ='Annual P&L'!F20 -> #N/A
B11: EBITDA | C11: ='Annual P&L'!B39/10^6 -> #N/A | D11: ='Annual P&L'!C39/10^6 -> #N/A | E11: ='Annual P&L'!D39/10^6 -> #N/A | F11: ='Annual P&L'!E39/10^6 -> #N/A | G11: ='Annual P&L'!F39/10^6 -> #N/A
B12: EBITDA Margin % | C12: ='Annual P&L'!B40 -> #N/A | D12: ='Annual P&L'!C40 -> #N/A | E12: ='Annual P&L'!D40 -> #N/A | F12: ='Annual P&L'!E40 -> #N/A | G12: ='Annual P&L'!F40 -> #N/A
B14: PAT | C14: ='Annual P&L'!B50/10^6 -> #N/A | D14: ='Annual P&L'!C50/10^6 -> #N/A | E14: ='Annual P&L'!D50/10^6 -> #N/A | F14: ='Annual P&L'!E50/10^6 -> #N/A | G14: ='Annual P&L'!F50/10^6 -> #N/A
B15: PAT Margin % | C15: ='Annual P&L'!B51 -> #N/A | D15: ='Annual P&L'!C51 -> #N/A | E15: ='Annual P&L'!D51 -> #N/A | F15: ='Annual P&L'!E51 -> #N/A | G15: ='Annual P&L'!F51 -> #N/A
S43: Product Devlopment | T43: 0.6
S44: Marketing | T44: 0.3
S45: Opex | T45: 0.1

Sheet Controls
A1: EXOS Aerospace | B1: Beginning Month: | C1: July | E1: NOTE: Month 1 = July 2025. Updated May 29, 2026. Includes entX LSA ($840K) + Second BLK3 Flight ($750K) + NASA Flight Opportunities IDIQ ($8M/yr steady state from Q3 2027). Exos is ONLY US FAA-licensed co. actively selling suborbital reusable payload services. Campaign model: 2 NASA + 1 commercial flight per quarter. Dual listing: Euronext Dublin + TXSE.
A2: Controls Sheet
A3: Amounts in USD | B3: Note: All the figures and assumptions are taken monthly
A4: Back To Index
A5: Assumptions for the Annual Period | B5: 1 | C5: =+B5+1 -> 2 | D5: =+C5+1 -> 3 | E5: =+D5+1 -> 4 | F5: =+E5+1 -> 5
A7: REVENUE ASSUMPTIONS
A9: BLK4 360kg LAUNCHER
A11: BLK4 360kg - Cost to Customer - Wet Lease (Commercial Flights) | B11: 3753756.3 | C11: 3753756.3 | D11: 3753756.3 | E11: 3753756.3 | F11: 3753756.3
A13: BLK4 360kg - Vehicle Launch | B13: 6000000 | C13: 6000000 | D13: 6000000 | E13: 6000000 | F13: 6000000
A15: PROPULSION SYSTEM SALES 5K 20K DESIGNS WITH TRIFDYNE PRESS.
A17: Propulsion System Cost to Customer | B17: 250000 | C17: 250000 | D17: 250000 | E17: 250000 | F17: 250000
A19: EXOS US BLK4 Wet Lease Launches
A21: Initial Outfit per Vessel | B21: 1
A23: EXOS US BLK4 Wet Lease Launches Cost to Customer | B23: 6000000 | C23: 6000000 | D23: 6000000 | E23: 6000000 | F23: 6000000
A25: Second Stage Sales
A27: Second Stage Price Per Unit | B27: 350000 | C27: 350000 | D27: 350000 | E27: 350000 | F27: 350000
A29: Scorpius Space Corp Tank Manufacture
A31: Linerless Carbon Fiber Composite Tanks | B31: 183000 | C31: =B31*(1+C32) -> 274500 | D31: =C31*(1+D32) -> 343125 | E31: =D31*(1+E32) -> 428906.25 | F31: =E31*(1+F32) -> 536132.81
A32: Annual Change % | C32: 0.5 | D32: 0.25 | E32: 0.25 | F32: 0.25
A34: Sarge Technology and Hardware Sales
A36: Contract Value | B36: 500000 | C36: =B36*(1+C37) -> 1000000 | D36: =C36*(1+D37) -> 1200000 | E36: =D36*(1+E37) -> 1440000 | F36: =E36*(1+F37) -> 1800000
A37: Annual Change % | C37: 1 | D37: 0.2 | E37: 0.2 | F37: 0.25
A40: OPEX
A42: COGS
A44: BLK4 360kg LAUNCHER - COGS - Wet Lease | B44: 3003005.1 | C44: 3003005.1 | D44: 3003005.1 | E44: 3003005.1 | F44: 3003005.1
A46: BLK4 360kg LAUNCHER - COGS - Vehicle Launch | B46: 4525325.6 | C46: 4525325.6 | D46: 4525325.6 | E46: 4525325.6 | F46: 2909137.9
A48: PROPULSION SYSTEM SALES 5K 20K DESIGNS WITH TRIFDYNE PRESS - COGS | B48: 0.5 | C48: 0.5 | D48: 0.5 | E48: 0.5 | F48: 0.5
A50: EXOS US BLK4 Wet Lease Launches - COGS | B50: 0.5 | C50: 0.5 | D50: 0.5 | E50: 0.5 | F50: 0.5
A52: Second Stage Sales - COGS | B52: 0.5 | C52: 0.5 | D52: 0.5 | E52: 0.5 | F52: 0.5
A54: Scorpius Space Corp Tank Manufacture - COGS | B54: 0.35 | C54: 0.35 | D54: 0.35 | E54: 0.3 | F54: 0.3
A56: Sarge Technology and Hardware Sales - COGS | B56: 0.5 | C56: 0.5 | D56: 0.5 | E56: 0.5 | F56: 0.5
A59: OPEX
A61: Internet and Phone | B61: ='Oper, Cap, Other Assum'!L15 -> 750 | C61: ='Oper, Cap, Other Assum'!G16 -> 772.5 | D61: ='Oper, Cap, Other Assum'!G17 -> 795.675 | E61: ='Oper, Cap, Other Assum'!G18 -> 1639.0905 | F61: ='Oper, Cap, Other Assum'!G19 -> 1688.2632
A63: Insurance | B63: ='Oper, Cap, Other Assum'!L22 -> 3000 | C63: ='Oper, Cap, Other Assum'!G23 -> 6180 | D63: ='Oper, Cap, Other Assum'!G24 -> 12180 | E63: ='Oper, Cap, Other Assum'!G25 -> 37930 | F63: ='Oper, Cap, Other Assum'!G26 -> 140180
A65: Professional Fees | B65: ='Oper, Cap, Other Assum'!L29 -> 3500 | C65: ='Oper, Cap, Other Assum'!G30 -> 3605 | D65: ='Oper, Cap, Other Assum'!G31 -> 3713.15 | E65: ='Oper, Cap, Other Assum'!G32 -> 3824.5445 | F65: ='Oper, Cap, Other Assum'!G33 -> 3939.2808
A67: Rent and Utility | B67: ='Oper, Cap, Other Assum'!M36 -> 40000 | C67: ='Oper, Cap, Other Assum'!G37 -> 41600 | D67: ='Oper, Cap, Other Assum'!G38 -> 43264 | E67: ='Oper, Cap, Other Assum'!G39 -> 89989.12 | F67: ='Oper, Cap, Other Assum'!G40 -> 93588.685
A69: Office and Other Expenses (per employee) | B69: 5000 | C69: =B69*(1+C70) -> 5150 | D69: =C69*(1+D70) -> 5304.5 | E69: =D69*(1+E70) -> 5463.635 | F69: =E69*(1+F70) -> 5627.5441
A70: Annual Change % | C70: 0.03 | D70: 0.03 | E70: 0.03 | F70: 0.03
A72: Marketing | B72: ='Oper, Cap, Other Assum'!G58 -> 15000 | C72: ='Oper, Cap, Other Assum'!G59 -> 16500 | D72: ='Oper, Cap, Other Assum'!G60 -> 18150 | E72: ='Oper, Cap, Other Assum'!G61 -> 19965 | F72: ='Oper, Cap, Other Assum'!G62 -> 21961.5
A74: Travel Expenses | B74: ='Oper, Cap, Other Assum'!G65 -> 20000 | C74: ='Oper, Cap, Other Assum'!G66 -> 20600 | D74: ='Oper, Cap, Other Assum'!G67 -> 21218 | E74: ='Oper, Cap, Other Assum'!G68 -> 21854.54 | F74: ='Oper, Cap, Other Assum'!G69 -> 22510.176
A76: Research and Development | B76: ='Oper, Cap, Other Assum'!G79 -> 5000 | C76: ='Oper, Cap, Other Assum'!G80 -> 20000 | D76: ='Oper, Cap, Other Assum'!G81 -> 20000 | E76: ='Oper, Cap, Other Assum'!G82 -> 20000 | F76: ='Oper, Cap, Other Assum'!G83 -> 20000
A79: PAYROLL ASSUMPTIONS
A81: President | B81: 135000 | C81: =B81*(1+C$125) -> 139050 | D81: =C81*(1+D$125) -> 143221.5 | E81: =D81*(1+E$125) -> 147518.14 | F81: =E81*(1+F$125) -> 151943.69
A82: CEO | B82: 236250 | C82: =B82*(1+C$125) -> 243337.5 | D82: =C82*(1+D$125) -> 250637.62 | E82: =D82*(1+E$125) -> 258156.75 | F82: =E82*(1+F$125) -> 265901.46
A83: COO | B83: 148500 | C83: =B83*(1+C$125) -> 152955 | D83: =C83*(1+D$125) -> 157543.65 | E83: =D83*(1+E$125) -> 162269.96 | F83: =E83*(1+F$125) -> 167138.06
A84: CTO | B84: 195750 | C84: =B84*(1+C$125) -> 201622.5 | D84: =C84*(1+D$125) -> 207671.18 | E84: =D84*(1+E$125) -> 213901.31 | F84: =E84*(1+F$125) -> 220318.35
A85: Instrumentation Controls Electrical Engineer | B85: 105975 | C85: =B85*(1+C$125) -> 109154.25 | D85: =C85*(1+D$125) -> 112428.88 | E85: =D85*(1+E$125) -> 115801.74 | F85: =E85*(1+F$125) -> 119275.8
A86: AS9100D & ITAR Compliance Officer | B86: 101250 | C86: =B86*(1+C$125) -> 104287.5 | D86: =C86*(1+D$125) -> 107416.12 | E86: =D86*(1+E$125) -> 110638.61 | F86: =E86*(1+F$125) -> 113957.77
A87: Staff (based on USD salaries) | B87: 0
A88: Administrative Assistant | B88: 60000 | C88: =B88*(1+C$125) -> 61800 | D88: =C88*(1+D$125) -> 63654 | E88: =D88*(1+E$125) -> 65563.62 | F88: =E88*(1+F$125) -> 67530.529
A89: Aero Modeling Engineer | B89: 101250 | C89: =B89*(1+C$125) -> 104287.5 | D89: =C89*(1+D$125) -> 107416.12 | E89: =D89*(1+E$125) -> 110638.61 | F89: =E89*(1+F$125) -> 113957.77
A90: Avionics Hardware Development Engineer | B90: 109305 | C90: =B90*(1+C$125) -> 112584.15 | D90: =C90*(1+D$125) -> 115961.67 | E90: =D90*(1+E$125) -> 119440.52 | F90: =E90*(1+F$125) -> 123023.74
A91: Contracts Administrator- PROGRAM MANAGER | B91: 121347 | C91: =B91*(1+C$125) -> 124987.41 | D91: =C91*(1+D$125) -> 128737.03 | E91: =D91*(1+E$125) -> 132599.14 | F91: =E91*(1+F$125) -> 136577.12
A92: Design Engineer (mech)- 12 Scorpius (average salary) | B92: 95550 | C92: =B92*(1+C$125) -> 98416.5 | D92: =C92*(1+D$125) -> 101368.99 | E92: =D92*(1+E$125) -> 104410.06 | F92: =E92*(1+F$125) -> 107542.37
A93: Engineering Internships- Admin | B93: 48859 | C93: =B93*(1+C$125) -> 50324.77 | D93: =C93*(1+D$125) -> 51834.513 | E93: =D93*(1+E$125) -> 53389.548 | F93: =E93*(1+F$125) -> 54991.235
A94: Guidance Navigation and Control Engineer | B94: 148500 | C94: =B94*(1+C$125) -> 152955 | D94: =C94*(1+D$125) -> 157543.65 | E94: =D94*(1+E$125) -> 162269.96 | F94: =E94*(1+F$125) -> 167138.06
A95: Junior RF Engineer | B95: 101250 | C95: =B95*(1+C$125) -> 104287.5 | D95: =C95*(1+D$125) -> 107416.12 | E95: =D95*(1+E$125) -> 110638.61 | F95: =E95*(1+F$125) -> 113957.77
A96: Launch Engineer | B96: 148500 | C96: =B96*(1+C$125) -> 152955 | D96: =C96*(1+D$125) -> 157543.65 | E96: =D96*(1+E$125) -> 162269.96 | F96: =E96*(1+F$125) -> 167138.06
A97: Mechanical Designer/Drafter/Technician | B97: 114750 | C97: =B97*(1+C$125) -> 118192.5 | D97: =C97*(1+D$125) -> 121738.28 | E97: =D97*(1+E$125) -> 125390.42 | F97: =E97*(1+F$125) -> 129152.14
A98: Mission Integration Engineer | B98: 148500 | C98: =B98*(1+C$125) -> 152955 | D98: =C98*(1+D$125) -> 157543.65 | E98: =D98*(1+E$125) -> 162269.96 | F98: =E98*(1+F$125) -> 167138.06
A99: Propulsion Development Engineer | B99: 165375 | C99: =B99*(1+C$125) -> 170336.25 | D99: =C99*(1+D$125) -> 175446.34 | E99: =D99*(1+E$125) -> 180709.73 | F99: =E99*(1+F$125) -> 186131.02
... A123: Please add Position | B123: 0 | C123: =B123*(1+C$125) -> 0 | D123: =C123*(1+D$125) -> 0 | E123: =D123*(1+E$125) -> 0 | F123: =E123*(1+F$125) -> 0
A125: Pay Raise | C125: 0.03 | D125: 0.03 | E125: 0.03 | F125: 0.03
A127: Payroll Tax + Incentives | B127: 0.3 | C127: 0.3 | D127: 0.3 | E127: 0.3 | F127: 0.3
A129: Taxation Assumptions
A131: Income Tax | B131: 0.21 | C131: 0.21 | D131: 0.21 | E131: 0.21 | F131: 0.21
A133: Net Working Capital Assumptions
A135: Current Liabilities Turnover (number of days) | B135: 30
A136: Current Assets Excluding Cash (number of days) | B136: 15
A137: Prepaid Expenses (% of Sales) | B137: 0.02
A138: Days in Inventory | B138: 30
A139: Other Current Assets (% of sales) | B139: 0.02
A140: Accrued Expenses (number of days) | B140: 30
A141: Other Current Liabilities (% of sales) | B141: 0.02
A142: Annual Interest on Line of Credit | B142: 0.06
A144: Rocket Build Assumptions
A146: Development of a reusable first stage of a two stage Hyperonsic/or LEO launcher | B146: Reusable 1st Stage Rocket Ser #J1-3 (3 years) | C146: Reusable 1st Stage Rocket Ser #J4-10 | D146: Reusable 1st Stage Rocket Ser #J11-21 | E146: Budget link to systems
A147: High Level Development Milestones | B147: First Vehicles | C147: Vehicles 4-10 | D147: Vehicles 11 onwards | E147: Budget section
A148: Number of Vehicles | B148: 3 | C148: 1 | D148: 1
A149: Engineering labor | B149: 35717393 | C149: 130215.36 | D149: 136663.06 | E149: Labor
A150: Vehicle Manufacturing and Operations Labor | B150: 0 | C150: 868102.38 | D150: 911087.07 | E150: Labor
A151: Licensing costs for reusable vehicles | B151: 750000 | C151: 1062130.6 | D151: 1367493.2 | E151: Labor
A152: Computer Section (CPU) | B152: =150000*$B$177*$B$148 -> 900000 | C152: 150000 | D152: 150000 | E152: Guidance Navigation and Control Development
A153: Self Reliant Condition Assessment System Scoprius model | B153: =50000*$B$177*$B$148 -> 300000 | C153: 50000 | D153: 50000 | E153: Guidance Navigation and Control Development
A154: onboard IMU / GPS / ANT | B154: =$B$177*$B$148*160000 -> 960000 | C154: 160000 | D154: 160000 | E154: Telemetry Hardware
A155: Propellant Tanks (flght set) | B155: =$B$177*$B$148*416666.666666667 -> 2500000 | C155: 750000 | D155: 750000 | E155: Propellant tanks and Staging
A156: Propellant Tanks (ASE stand set) | B156: =$B$177*$B$148*416666.666666667 -> 2500000 | C156: 0 | D156: 0 | E156: Propellant tanks and Staging
A157: Test stand GSA/ASE | B157: =$B$177*$B$148*116666.666666667 -> 700000 | C157: 50000 | D157: 50000 | E157: Assembly, Propulsio, and Vehicle Test Facilities
A158: Engine Bay | B158: =$B$177*$B$148*492000 -> 2952000 | C158: 600000 | D158: 600000 | E158: Propulsion Systems and Propellant Choice
A159: Engine R&D (Partner with NASA- SAA) | B159: =$B$177*$B$148*500000 -> 3000000 | C159: 150000 | D159: 150000 | E159: Propulsion Systems and Propellant Choice
A160: Flight Software mods (1st and 2nd stage) | B160: =$B$177*$B$148*666666.666666667 -> 4000000 | C160: 100000 | D160: 100000 | E160: Genera; Software
A161: Tanks pressurization system | B161: =$B$177*$B$148*575000 -> 3450000 | C161: 288000 | D161: 242000 | E161: Cryogenic dewar design
A162: Airframe Tubing - Al- Carbon Fiber | B162: =$B$177*$B$148*150000 -> 900000 | C162: 150000 | D162: 150000 | E162: Payload Aeroshell
A163: Bulkheads | B163: =$B$177*$B$148*75000 -> 450000 | C163: 75000 | D163: 75000 | E163: Payload Aeroshell
A164: Engine structures | B164: =$B$177*$B$148*85000 -> 510000 | C164: 85000 | D164: 85000 | E164: Propulsion Systems and Propellant Choice
A165: Helium Tank - Autogenous pressurization | B165: =$B$177*$B$148*150000 -> 900000 | C165: 150000 | D165: 150000 | E165: Pressurization Systems
A166: Wiring, Fittings & Hardware | B166: =$B$177*$B$148*140000 -> 840000 | C166: 140000 | D166: 140000 | E166: Guidance Navigation and Control Development
A167: Structures and UAD (Upper Aero Devices) | B167: =$B$177*$B$148*250000 -> 1500000 | C167: 250000 | D167: 250000 | E167: Aerodynamic Analysis
A168: Build of Second Stage | B168: 1000000 | C168: 175000 | D168: 175000 | E168: Payload Aeroshell
A169: Build of mobile Launcher- Fund uses | B169: 1000000 | C169: 0 | D169: 0 | E169: Launch System
...

Sheet Revenue Asumptions
A1: EXOS Aerospace
A2: Revenue Assumptions Sheet | B2: =Controls!C1 -> July | C2: =TEXT(DATE(2000, MATCH(B2, {"January","February","March","April","May","June","July","August","September","October","November","December"}, 0) + 1, 1), "mmmm") -> August | D2: =TEXT(DATE(2000, MATCH(C2, {"January","February","March","April","May","June","July","August","September","October","November","December"}, 0) + 1, 1), "mmmm") -> September | E2: =TEXT(DATE(2000, MATCH(D2, {"January","February","March","April","May","June","July","August","September","October","November","December"}, 0) + 1, 1), "mmmm") -> October | F2: =TEXT(DATE(2000, MATCH(E2, {"January","February","March","April","May","June","July","August","September","October","November","December"}, 0) + 1, 1), "mmmm") -> November | G2: =TEXT(DATE(2000, MATCH(F2, {"January","February","March","April","May","June","July","August","September","October","November","December"}, 0) + 1, 1), "mmmm") -> December | H2: =TEXT(DATE(2000, MATCH(G2, {"January","February","March","April","May","June","July","August","September","October","November","December"}, 0) + 1, 1), "mmmm") -> January | I2: =TEXT(DATE(2000, MATCH(H2, {"January","February","March","April","May","June","July","August","September","October","November","December"}, 0) + 1, 1), "mmmm") -> February | J2: =TEXT(DATE(2000, MATCH(I2, {"January","February","March","April","May","June","July","August","September","October","November","December"}, 0) + 1, 1), "mmmm") -> March | ... BI2: =TEXT(DATE(2000, MATCH(BH2, {"January","February","March","April","May","June","July","August","September","October","November","December"}, 0) + 1, 1), "mmmm") -> June
A3: Amounts in USD | B3: 1 | C3: =IF(MOD(B4,B5) = 0,B3+1,B3) -> 1 | D3: =IF(MOD(C4,C5) = 0,C3+1,C3) -> 1 | E3: =IF(MOD(D4,D5) = 0,D3+1,D3) -> 1 | F3: =IF(MOD(E4,E5) = 0,E3+1,E3) -> 1 | G3: =IF(MOD(F4,F5) = 0,F3+1,F3) -> 1 | H3: =IF(MOD(G4,G5) = 0,G3+1,G3) -> 1 | I3: =IF(MOD(H4,H5) = 0,H3+1,H3) -> 1 | J3: =IF(MOD(I4,I5) = 0,I3+1,I3) -> 1 | ... BI3: =IF(MOD(BH4,BH5) = 0,BH3+1,BH3) -> 5
A4: Back To Index | B4: 1 | C4: =B4+1 -> 2 | D4: =C4+1 -> 3 | E4: =D4+1 -> 4 | F4: =E4+1 -> 5 | G4: =F4+1 -> 6 | H4: =G4+1 -> 7 | I4: =H4+1 -> 8 | J4: =I4+1 -> 9 | ... BI4: =BH4+1 -> 60
A5: Assumptions for the Monthly Period | B5: 12 | C5: 12 | D5: 12 | E5: 12 | F5: 12 | G5: 12 | H5: 12 | I5: 12 | J5: 12 | K5: 12 | L5: 12 | M5: 12 | N5: 12 | O5: 12 | P5: 12 | Q5: 12 | R5: 12 | S5: 12 | T5: 12 | U5: 12 | V5: 12 | W5: 12 | X5: 12 | Y5: 12 | Z5: 12 | AA5: 12 | AB5: 12 | AC5: 12 | AD5: 12 | AE5: 12 | AF5: 12 | AG5: 12 | AH5: 12 | AI5: 12 | AJ5: 12 | AK5: 12 | AL5: 12 | AM5: 12 | AN5: 12 | AO5: 12 | AP5: 12 | AQ5: 12 | AR5: 12 | AS5: 12 | AT5: 12 | AU5: 12 | AV5: 12 | AW5: 12 | AX5: 12 | AY5: 12 | AZ5: 12 | BA5: 12 | BB5: 12 | BC5: 12 | BD5: 12 | BE5: 12 | BF5: 12 | BG5: 12 | BH5: 12 | BI5: 12
A7: BLK4 360kg launcher
A9: Wet Leases | B9: 0 | C9: 0 | D9: 0 | E9: 0 | F9: 0 | G9: 0 | H9: 0 | I9: 0 | J9: 0 | K9: 0 | L9: 0 | M9: 0 | N9: 0 | O9: 0 | P9: 0 | Q9: 0 | R9: 0 | S9: 0 | T9: 0 | U9: 0 | V9: 0 | W9: 0 | X9: 0 | Y9: 0 | Z9: 0 | AA9: 0 | AB9: 0 | AC9: 0 | AD9: 0 | AE9: 0 | AF9: 0 | AG9: 0 | AH9: 0 | AI9: 0 | AJ9: 0 | AK9: 0 | AL9: 0 | AM9: 0 | AN9: 0 | AO9: 0 | AP9: 0 | AQ9: 0 | AR9: 0 | AS9: 0 | AT9: 0 | AU9: 0 | AV9: 0 | AW9: 0 | AX9: 0 | AY9: 0 | AZ9: 0 | BA9: 0 | BB9: 0 | BC9: 0 | BD9: 0 | BE9: 0 | BF9: 0 | BG9: 0 | BH9: 0 | BI9: 0
A11: Vehicle Launches | B11: 0 | C11: 0 | D11: 0 | E11: 0 | F11: 0 | G11: 0 | H11: 0 | I11: 0 | J11: 0 | K11: 0 | L11: 0 | M11: 0 | N11: 0 | O11: 0 | P11: 0 | Q11: 0 | R11: 0 | S11: 0 | T11: 0 | U11: 0 | V11: 0 | W11: 0 | X11: 0 | Y11: 0 | Z11: 0 | AA11: 0 | AB11: 0 | AC11: 0 | AD11: 0 | AE11: 0 | AF11: 0 | AG11: 0 | AH11: 0 | AI11: 0 | AJ11: 0 | AK11: 0 | AL11: 0 | AM11: 0 | AN11: 0 | AO11: 0 | AP11: 0 | AQ11: 0 | AR11: 0 | AS11: 0 | AT11: 0 | AU11: 0 | AV11: 0 | AW11: 0 | AX11: 0 | AY11: 0 | AZ11: 0 | BA11: 0 | BB11: 0 | BC11: 0 | BD11: 0 | BE11: 0 | BF11: 0 | BG11: 0 | BH11: 0 | BI11: 0 | BJ11: 0 | BK11: 0 | BL11: 1 | BM11: 0 | BN11: 2 | BO11: 0 | BP11: 3 | BQ11: 0 | BR11: 4 | BS11: 0 | BT11: 4 | BU11: 0 | BV11: 4 | BW11: 0 | BX11: 4 | BY11: 0 | BZ11: 5 | CA11: 0 | CB11: 5 | CC11: 0 | CD11: 0 | CE11: 6 | CF11: 0 | CG11: 6 | CH11: 0 | CI11: 0 | CJ11: 6 | CK11: 0 | CL11: 6
A13: Revenue
A15: BLK4 360kg - Cost to Customer - Wet Lease (Commercial Flights) | B15: =((HLOOKUP(B$3,Controls!$A$5:$F$178,MATCH($A15,Controls!$A$5:$A$178,0),0))*B9)+(SUM(B17:B22)) -> 0 | C15: =((HLOOKUP(C$3,Controls!$A$5:$F$178,MATCH($A15,Controls!$A$5:$A$178,0),0))*C9)+(SUM(C17:C22)) -> 0 | D15: =((HLOOKUP(D$3,Controls!$A$5:$F$178,MATCH($A15,Controls!$A$5:$A$178,0),0))*D9)+(SUM(D17:D22)) -> 0 | E15: =((HLOOKUP(E$3,Controls!$A$5:$F$178,MATCH($A15,Controls!$A$5:$A$178,0),0))*E9)+(SUM(E17:E22)) -> 0 | F15: =((HLOOKUP(F$3,Controls!$A$5:$F$178,MATCH($A15,Controls!$A$5:$A$178,0),0))*F9)+(SUM(F17:F22)) -> 0 | G15: =((HLOOKUP(G$3,Controls!$A$5:$F$178,MATCH($A15,Controls!$A$5:$A$178,0),0))*G9)+(SUM(G17:G22)) -> 0 | H15: =((HLOOKUP(H$3,Controls!$A$5:$F$178,MATCH($A15,Controls!$A$5:$A$178,0),0))*H9)+(SUM(H17:H22)) -> 0 | I15: =((HLOOKUP(I$3,Controls!$A$5:$F$178,MATCH($A15,Controls!$A$5:$A$178,0),0))*I9)+(SUM(I17:I22)) -> 0 | ... BI15: =((HLOOKUP(BI$3,Controls!$A$5:$F$178,MATCH($A15,Controls!$A$5:$A$178,0),0))*BI9)+(SUM(BI17:BI22)) -> 6833332.8
A17: BLK4 360kg — Commercial Flight Revenue (Vehicle Sales & Wet Lease) | B17: 0 | C17: 0 | D17: 0 | E17: 0 | F17: 0 | G17: 0 | H17: 0 | I17: 0 | J17: 0 | K17: 0 | L17: 0 | M17: 0 | N17: 0 | O17: 0 | P17: 0 | Q17: 0 | R17: 0 | S17: 0 | T17: 0 | U17: 0 | V17: 0 | W17: 0 | X17: 0 | Y17: 0 | Z17: 0 | AA17: 0 | AB17: 0 | AC17: 0 | AD17: 0 | AE17: 0 | AF17: 0 | AG17: 0 | AH17: 0 | AI17: 1092592.3 | AJ17: 1092592.3 | AK17: 1092592.3 | AL17: 1092592.3 | AM17: 1092592.3 | AN17: 1092592.3 | AO17: 1092592.3 | AP17: 1092592.3 | AQ17: 1092592.3 | AR17: 2583333 | AS17: 2583333 | AT17: 2583333 | AU17: 2583333 | AV17: 2583333 | AW17: 2583333 | AX17: 2583333 | AY17: 2583333 | AZ17: 2583333 | BA17: 2583333 | BB17: 2583333 | BC17: 2583333 | BD17: 6833332.8 | BE17: 6833332.8 | BF17: 6833332.8 | BG17: 6833332.8 | BH17: 6833332.8 | BI17: 6833332.8
A18: Additional Revenue/Contract | B18: 0 | C18: 0 | D18: 0 | E18: 0 | F18: 0 | G18: 0 | H18: 0 | I18: 0 | J18: 0 | K18: 0 | L18: 0 | M18: 0 | N18: 0 | O18: 0 | P18: 0 | Q18: 0 | R18: 0 | S18: 0 | T18: 0 | U18: 0 | V18: 0 | W18: 0 | X18: 0 | Y18: 0 | Z18: 0 | AA18: 0 | AB18: 0 | AC18: 0 | AD18: 0 | AE18: 0 | AF18: 0 | AG18: 0 | AH18: 0 | AI18: 0 | AJ18: 0 | AK18: 0 | AL18: 0 | AM18: 0 | AN18: 0 | AO18: 0 | AP18: 0 | AQ18: 0 | AR18: 0 | AS18: 0 | AT18: 0 | AU18: 0 | AV18: 0 | AW18: 0 | AX18: 0 | AY18: 0 | AZ18: 0 | BA18: 0 | BB18: 0 | BC18: 0 | BD18: 0 | BE18: 0 | BF18: 0 | BG18: 0 | BH18: 0 | BI18: 0
A19: Additional Revenue/Contract | B19: 0 | C19: 0 | D19: 0 | E19: 0 | F19: 0 | G19: 0 | H19: 0 | I19: 0 | J19: 0 | K19: 0 | L19: 0 | M19: 0 | N19: 0 | O19: 0 | P19: 0 | Q19: 0 | R19: 0 | S19: 0 | T19: 0 | U19: 0 | V19: 0 | W19: 0 | X19: 0 | Y19: 0 | Z19: 0 | AA19: 0 | AB19: 0 | AC19: 0 | AD19: 0 | AE19: 0 | AF19: 0 | AG19: 0 | AH19: 0 | AI19: 0 | AJ19: 0 | AK19: 0 | AL19: 0 | AM19: 0 | AN19: 0 | AO19: 0 | AP19: 0 | AQ19: 0 | AR19: 0 | AS19: 0 | AT19: 0 | AU19: 0 | AV19: 0 | AW19: 0 | AX19: 0 | AY19: 0 | AZ19: 0 | BA19: 0 | BB19: 0 | BC19: 0 | BD19: 0 | BE19: 0 | BF19: 0 | BG19: 0 | BH19: 0 | BI19: 0
A20: Additional Revenue/Contract | B20: 0 | C20: 0 | D20: 0 | E20: 0 | F20: 0 | G20: 0 | H20: 0 | I20: 0 | J20: 0 | K20: 0 | L20: 0 | M20: 0 | N20: 0 | O20: 0 | P20: 0 | Q20: 0 | R20: 0 | S20: 0 | T20: 0 | U20: 0 | V20: 0 | W20: 0 | X20: 0 | Y20: 0 | Z20: 0 | AA20: 0 | AB20: 0 | AC20: 0 | AD20: 0 | AE20: 0 | AF20: 0 | AG20: 0 | AH20: 0 | AI20: 0 | AJ20: 0 | AK20: 0 | AL20: 0 | AM20: 0 | AN20: 0 | AO20: 0 | AP20: 0 | AQ20: 0 | AR20: 0 | AS20: 0 | AT20: 0 | AU20: 0 | AV20: 0 | AW20: 0 | AX20: 0 | AY20: 0 | AZ20: 0 | BA20: 0 | BB20: 0 | BC20: 0 | BD20: 0 | BE20: 0 | BF20: 0 | BG20: 0 | BH20: 0 | BI20: 0
A21: Additional Revenue/Contract | B21: 0 | C21: 0 | D21: 0 | E21: 0 | F21: 0 | G21: 0 | H21: 0 | I21: 0 | J21: 0 | K21: 0 | L21: 0 | M21: 0 | N21: 0 | O21: 0 | P21: 0 | Q21: 0 | R21: 0 | S21: 0 | T21: 0 | U21: 0 | V21: 0 | W21: 0 | X21: 0 | Y21: 0 | Z21: 0 | AA21: 0 | AB21: 0 | AC21: 0 | AD21: 0 | AE21: 0 | AF21: 0 | AG21: 0 | AH21: 0 | AI21: 0 | AJ21: 0 | AK21: 0 | AL21: 0 | AM21: 0 | AN21: 0 | AO21: 0 | AP21: 0 | AQ21: 0 | AR21: 0 | AS21: 0 | AT21: 0 | AU21: 0 | AV21: 0 | AW21: 0 | AX21: 0 | AY21: 0 | AZ21: 0 | BA21: 0 | BB21: 0 | BC21: 0 | BD21: 0 | BE21: 0 | BF21: 0 | BG21: 0 | BH21: 0 | BI21: 0
A22: Additional Revenue/Contract | B22: 0 | C22: 0 | D22: 0 | E22: 0 | F22: 0 | G22: 0 | H22: 0 | I22: 0 | J22: 0 | K22: 0 | L22: 0 | M22: 0 | N22: 0 | O22: 0 | P22: 0 | Q22: 0 | R22: 0 | S22: 0 | T22: 0 | U22: 0 | V22: 0 | W22: 0 | X22: 0 | Y22: 0 | Z22: 0 | AA22: 0 | AB22: 0 | AC22: 0 | AD22: 0 | AE22: 0 | AF22: 0 | AG22: 0 | AH22: 0 | AI22: 0 | AJ22: 0 | AK22: 0 | AL22: 0 | AM22: 0 | AN22: 0 | AO22: 0 | AP22: 0 | AQ22: 0 | AR22: 0 | AS22: 0 | AT22: 0 | AU22: 0 | AV22: 0 | AW22: 0 | AX22: 0 | AY22: 0 | AZ22: 0 | BA22: 0 | BB22: 0 | BC22: 0 | BD22: 0 | BE22: 0 | BF22: 0 | BG22: 0 | BH22: 0 | BI22: 0
A24: BLK4 360kg - Vehicle Launch | B24: =((HLOOKUP(B$3,Controls!$A$5:$F$217,MATCH($A24,Controls!$A$5:$A$217,0),0)*B11)+(SUM(B26:B31))) -> 0 | C24: =((HLOOKUP(C$3,Controls!$A$5:$F$217,MATCH($A24,Controls!$A$5:$A$217,0),0)*C11)+(SUM(C26:C31))) -> 0 | D24: =((HLOOKUP(D$3,Controls!$A$5:$F$217,MATCH($A24,Controls!$A$5:$A$217,0),0)*D11)+(SUM(D26:D31))) -> 0 | E24: =((HLOOKUP(E$3,Controls!$A$5:$F$217,MATCH($A24,Controls!$A$5:$A$217,0),0)*E11)+(SUM(E26:E31))) -> 0 | F24: =((HLOOKUP(F$3,Controls!$A$5:$F$217,MATCH($A24,Controls!$A$5:$A$217,0),0)*F11)+(SUM(F26:F31))) -> 0 | G24: =((HLOOKUP(G$3,Controls!$A$5:$F$217,MATCH($A24,Controls!$A$5:$A$217,0),0)*G11)+(SUM(G26:G31))) -> 0 | H24: =((HLOOKUP(H$3,Controls!$A$5:$F$217,MATCH($A24,Controls!$A$5:$A$217,0),0)*H11)+(SUM(H26:H31))) -> 0 | I24: =((HLOOKUP(I$3,Controls!$A$5:$F$217,MATCH($A24,Controls!$A$5:$A$217,0),0)*I11)+(SUM(I26:I31))) -> 0 | ... BI24: =((HLOOKUP(BI$3,Controls!$A$5:$F$217,MATCH($A24,Controls!$A$5:$A$217,0),0)*BI11)+(SUM(BI26:BI31))) -> 0
A26: Additional Revenue/Contract | B26: 0 | C26: 0 | D26: 0 | E26: 0 | F26: 0 | G26: 0 | H26: 0 | I26: 0 | J26: 0 | K26: 0 | L26: 0 | M26: 0 | N26: 0 | O26: 0 | P26: 0 | Q26: 0 | R26: 0 | S26: 0 | T26: 0 | U26: 0 | V26: 0 | W26: 0 | X26: 0 | Y26: 0 | Z26: 0 | AA26: 0 | AB26: 0 | AC26: 0 | AD26: 0 | AE26: 0 | AF26: 0 | AG26: 0 | AH26: 0 | AI26: 0 | AJ26: 0 | AK26: 0 | AL26: 0 | AM26: 0 | AN26: 0 | AO26: 0 | AP26: 0 | AQ26: 0 | AR26: 0 | AS26: 0 | AT26: 0 | AU26: 0 | AV26: 0 | AW26: 0 | AX26: 0 | AY26: 0 | AZ26: 0 | BA26: 0 | BB26: 0 | BC26: 0 | BD26: 0 | BE26: 0 | BF26: 0 | BG26: 0 | BH26: 0 | BI26: 0
A27: Additional Revenue/Contract | B27: 0 | C27: 0 | D27: 0 | E27: 0 | F27: 0 | G27: 0 | H27: 0 | I27: 0 | J27: 0 | K27: 0 | L27: 0 | M27: 0 | N27: 0 | O27: 0 | P27: 0 | Q27: 0 | R27: 0 | S27: 0 | T27: 0 | U27: 0 | V27: 0 | W27: 0 | X27: 0 | Y27: 0 | Z27: 0 | AA27: 0 | AB27: 0 | AC27: 0 | AD27: 0 | AE27: 0 | AF27: 0 | AG27: 0 | AH27: 0 | AI27: 0 | AJ27: 0 | AK27: 0 | AL27: 0 | AM27: 0 | AN27: 0 | AO27: 0 | AP27: 0 | AQ27: 0 | AR27: 0 | AS27: 0 | AT27: 0 | AU27: 0 | AV27: 0 | AW27: 0 | AX27: 0 | AY27: 0 | AZ27: 0 | BA27: 0 | BB27: 0 | BC27: 0 | BD27: 0 | BE27: 0 | BF27: 0 | BG27: 0 | BH27: 0 | BI27: 0
A28: Additional Revenue/Contract | B28: 0 | C28: 0 | D28: 0 | E28: 0 | F28: 0 | G28: 0 | H28: 0 | I28: 0 | J28: 0 | K28: 0 | L28: 0 | M28: 0 | N28: 0 | O28: 0 | P28: 0 | Q28: 0 | R28: 0 | S28: 0 | T28: 0 | U28: 0 | V28: 0 | W28: 0 | X28: 0 | Y28: 0 | Z28: 0 | AA28: 0 | AB28: 0 | AC28: 0 | AD28: 0 | AE28: 0 | AF28: 0 | AG28: 0 | AH28: 0 | AI28: 0 | AJ28: 0 | AK28: 0 | AL28: 0 | AM28: 0 | AN28: 0 | AO28: 0 | AP28: 0 | AQ28: 0 | AR28: 0 | AS28: 0 | AT28: 0 | AU28: 0 | AV28: 0 | AW28: 0 | AX28: 0 | AY28: 0 | AZ28: 0 | BA28: 0 | BB28: 0 | BC28: 0 | BD28: 0 | BE28: 0 | BF28: 0 | BG28: 0 | BH28: 0 | BI28: 0
A29: Additional Revenue/Contract | B29: 0 | C29: 0 | D29: 0 | E29: 0 | F29: 0 | G29: 0 | H29: 0 | I29: 0 | J29: 0 | K29: 0 | L29: 0 | M29: 0 | N29: 0 | O29: 0 | P29: 0 | Q29: 0 | R29: 0 | S29: 0 | T29: 0 | U29: 0 | V29: 0 | W29: 0 | X29: 0 | Y29: 0 | Z29: 0 | AA29: 0 | AB29: 0 | AC29: 0 | AD29: 0 | AE29: 0 | AF29: 0 | AG29: 0 | AH29: 0 | AI29: 0 | AJ29: 0 | AK29: 0 | AL29: 0 | AM29: 0 | AN29: 0 | AO29: 0 | AP29: 0 | AQ29: 0 | AR29: 0 | AS29: 0 | AT29: 0 | AU29: 0 | AV29: 0 | AW29: 0 | AX29: 0 | AY29: 0 | AZ29: 0 | BA29: 0 | BB29: 0 | BC29: 0 | BD29: 0 | BE29: 0 | BF29: 0 | BG29: 0 | BH29: 0 | BI29: 0
A30: Additional Revenue/Contract | B30: 0 | C30: 0 | D30: 0 | E30: 0 | F30: 0 | G30: 0 | H30: 0 | I30: 0 | J30: 0 | K30: 0 | L30: 0 | M30: 0 | N30: 0 | O30: 0 | P30: 0 | Q30: 0 | R30: 0 | S30: 0 | T30: 0 | U30: 0 | V30: 0 | W30: 0 | X30: 0 | Y30: 0 | Z30: 0 | AA30: 0 | AB30: 0 | AC30: 0 | AD30: 0 | AE30: 0 | AF30: 0 | AG30: 0 | AH30: 0 | AI30: 0 | AJ30: 0 | AK30: 0 | AL30: 0 | AM30: 0 | AN30: 0 | AO30: 0 | AP30: 0 | AQ30: 0 | AR30: 0 | AS30: 0 | AT30: 0 | AU30: 0 | AV30: 0 | AW30: 0 | AX30: 0 | AY30: 0 | AZ30: 0 | BA30: 0 | BB30: 0 | BC30: 0 | BD30: 0 | BE30: 0 | BF30: 0 | BG30: 0 | BH30: 0 | BI30: 0
A31: Additional Revenue/Contract | B31: 0 | C31: 0 | D31: 0 | E31: 0 | F31: 0 | G31: 0 | H31: 0 | I31: 0 | J31: 0 | K31: 0 | L31: 0 | M31: 0 | N31: 0 | O31: 0 | P31: 0 | Q31: 0 | R31: 0 | S31: 0 | T31: 0 | U31: 0 | V31: 0 | W31: 0 | X31: 0 | Y31: 0 | Z31: 0 | AA31: 0 | AB31: 0 | AC31: 0 | AD31: 0 | AE31: 0 | AF31: 0 | AG31: 0 | AH31: 0 | AI31: 0 | AJ31: 0 | AK31: 0 | AL31: 0 | AM31: 0 | AN31: 0 | AO31: 0 | AP31: 0 | AQ31: 0 | AR31: 0 | AS31: 0 | AT31: 0 | AU31: 0 | AV31: 0 | AW31: 0 | AX31: 0 | AY31: 0 | AZ31: 0 | BA31: 0 | BB31: 0 | BC31: 0 | BD31: 0 | BE31: 0 | BF31: 0 | BG31: 0 | BH31: 0 | BI31: 0
A33: Revenue from BLK4 360kg Launcher | B33: =B15+B24 -> 0 | C33: =C15+C24 -> 0 | D33: =D15+D24 -> 0 | E33: =E15+E24 -> 0 | F33: =F15+F24 -> 0 | G33: =G15+G24 -> 0 | H33: =H15+H24 -> 0 | I33: =I15+I24 -> 0 | ... BI33: =BI15+BI24 -> 6833332.8
A35: SYSTEMS SALES - CONTRACTING -
A37: Propulsion System Sales | B37: 0 | C37: 0 | D37: 0 | E37: 0 | F37: 0 | G37: 0 | H37: 0 | I37: 0 | J37: 0 | K37: 0 | L37: 0 | M37: 0 | N37: 0 | O37: 0 | P37: 0 | Q37: 0 | R37: 0 | S37: 0 | T37: 0 | U37: 0 | V37: 1 | W37: 0 | X37: 0 | Y37: 1 | Z37: 0 | AA37: 0 | AB37: 1 | AC37: 0 | AD37: 0 | AE37: 0 | AF37: 0 | AG37: 0 | AH37: 0 | AI37: 0 | AJ37: 0 | AK37: 1 | AL37: 0 | AM37: 1 | AN37: 0 | AO37: 1 | AP37: 0 | AQ37: 0 | AR37: 1 | AS37: 0 | AT37: 0 | AU37: 1 | AV37: 0 | AW37: 0 | AX37: 1 | AY37: 0 | AZ37: 0 | BA37: 1 | BB37: 0 | BC37: 0 | BD37: 1 | BE37: 0 | BF37: 0 | BG37: 1 | BH37: 0 | BI37: 1
A39: Suborbital Hover Vehicle-Reusable Rocket- DoD /DoW | B39: 0 | C39: 0 | D39: 250000 | E39: 100000 | F39: 250000 | G39: 250000 | H39: 250000 | I39: 250000 | J39: 150000 | K39: 150000 | L39: 150000 | M39: 100000 | N39: 0 | O39: 0 | P39: 0 | Q39: 0 | R39: 0 | S39: 0 | T39: 0 | U39: 0 | V39: 0 | W39: 0 | X39: 0 | Y39: 0 | Z39: 0 | AA39: 0 | AB39: 0 | AC39: 0 | AD39: 0 | AE39: 0 | AF39: 0 | AG39: 0 | AH39: 0 | AI39: 0 | AJ39: 0 | AK39: 0 | AL39: 0 | AM39: 0 | AN39: 0 | AO39: 0 | AP39: 0 | AQ39: 0 | AR39: 0 | AS39: 0 | AT39: 0 | AU39: 0 | AV39: 0 | AW39: 0 | AX39: 0 | AY39: 0 | AZ39: 0 | BA39: 0 | BB39: 0 | BC39: 0 | BD39: 0 | BE39: 0 | BF39: 0 | BG39: 0 | BH39: 0 | BI39: 0
A40: Scorpius Space Corp — Tank Manufacturing & Related Sales (Calendar Year) | B40: 0 | C40: 0 | D40: 0 | E40: 0 | F40: 0 | G40: 0 | H40: 150000 | I40: 150000 | J40: 150000 | K40: 150000 | L40: 150000 | M40: 150000 | N40: 291666.67 | O40: 291666.67 | P40: 291666.67 | Q40: 291666.67 | R40: 291666.67 | S40: 291666.67 | T40: 291666.67 | U40: 291666.67 | V40: 291666.67 | W40: 291666.67 | X40: 291666.67 | Y40: 291666.67 | Z40: 291666.67 | AA40: 291666.67 | AB40: 291666.67 | AC40: 291666.67 | AD40: 291666.67 | AE40: 291666.67 | AF40: 583333.33 | AG40: 583333.33 | AH40: 583333.33 | AI40: 583333.33 | AJ40: 583333.33 | AK40: 583333.33 | AL40: 583333.33 | AM40: 583333.33 | AN40: 583333.33 | AO40: 583333.33 | AP40: 583333.33 | AQ40: 583333.33 | AR40: 1166666.7 | AS40: 1166666.7 | AT40: 1166666.7 | AU40: 1166666.7 | AV40: 1166666.7 | AW40: 1166666.7 | AX40: 1166666.7 | AY40: 1166666.7 | AZ40: 1166666.7 | BA40: 1166666.7 | BB40: 1166666.7 | BC40: 1166666.7 | BD40: 2333333.3 | BE40: 2333333.3 | BF40: 2333333.3 | BG40: 2333333.3 | BH40: 2333333.3 | BI40: 2333333.3
A41: entX LSA — Project Lazarus RHU Flight Demo (BLK3.1) | B41: 0 | C41: 0 | D41: 0 | E41: 0 | F41: 0 | G41: 250000 | H41: 0 | I41: 0 | J41: 0 | K41: 0 | L41: 82000 | M41: 328000 | N41: 143000 | O41: 143000 | P41: 144000 | Q41: 0 | R41: 0 | S41: 0 | T41: 0 | U41: 0 | V41: 0 | W41: 0 | X41: 0 | Y41: 0 | Z41: 0 | AA41: 0 | AB41: 0 | AC41: 0 | AD41: 0 | AE41: 0 | AF41: 0 | AG41: 0 | AH41: 0 | AI41: 0 | AJ41: 0 | AK41: 0 | AL41: 0 | AM41: 0 | AN41: 0 | AO41: 0 | AP41: 0 | AQ41: 0 | AR41: 0 | AS41: 0 | AT41: 0 | AU41: 0 | AV41: 0 | AW41: 0 | AX41: 0 | AY41: 0 | AZ41: 0 | BA41: 0 | BB41: 0 | BC41: 0 | BD41: 0 | BE41: 0 | BF41: 0 | BG41: 0 | BH41: 0 | BI41: 0
A42: TACFI — RDRE Development Program ($2M DoD + $2M Match) | B42: 0 | C42: 0 | D42: 0 | E42: 0 | F42: 0 | G42: 0 | H42: 0 | I42: 0 | J42: 0 | K42: 0 | L42: 0 | M42: 0 | N42: 0 | O42: 0 | P42: 0 | Q42: 222222.22 | R42: 222222.22 | S42: 222222.22 | T42: 222222.22 | U42: 222222.22 | V42: 222222.22 | W42: 222222.22 | X42: 222222.22 | Y42: 222222.22 | Z42: 222222.22 | AA42: 222222.22 | AB42: 222222.22 | AC42: 222222.22 | AD42: 222222.22 | AE42: 222222.22 | AF42: 222222.22 | AG42: 222222.22 | AH42: 222222.22 | AI42: 0 | AJ42: 0 | AK42: 0 | AL42: 0 | AM42: 0 | AN42: 0 | AO42: 0 | AP42: 0 | AQ42: 0 | AR42: 0 | AS42: 0 | AT42: 0 | AU42: 0 | AV42: 0 | AW42: 0 | AX42: 0 | AY42: 0 | AZ42: 0 | BA42: 0 | BB42: 0 | BC42: 0 | BD42: 0 | BE42: 0 | BF42: 0 | BG42: 0 | BH42: 0 | BI42: 0
A43: STRATFI — RDRE Operational Engine Program ($30M over 36 months) | B43: 0 | C43: 0 | D43: 0 | E43: 0 | F43: 0 | G43: 0 | H43: 0 | I43: 0 | J43: 0 | K43: 0 | L43: 0 | M43: 0 | N43: 0 | O43: 0 | P43: 0 | Q43: 0 | R43: 0 | S43: 0 | T43: 0 | U43: 0 | V43: 0 | W43: 0 | X43: 0 | Y43: 0 | Z43: 0 | AA43: 0 | AB43: 0 | AC43: 0 | AD43: 0 | AE43: 0 | AF43: 0 | AG43: 0 | AH43: 0 | AI43: 833333.33 | AJ43: 833333.33 | AK43: 833333.33 | AL43: 833333.33 | AM43: 833333.33 | AN43: 833333.33 | AO43: 833333.33 | AP43: 833333.33 | AQ43: 833333.33 | AR43: 833333.33 | AS43: 833333.33 | AT43: 833333.33 | AU43: 833333.33 | AV43: 833333.33 | AW43: 833333.33 | AX43: 833333.33 | AY43: 833333.33 | AZ43: 833333.33 | BA43: 833333.33 | BB43: 833333.33 | BC43: 833333.33 | BD43: 833333.33 | BE43: 833333.33 | BF43: 833333.33 | BG43: 833333.33 | BH43: 833333.33 | BI43: 833333.33
A44: Note: STRATFI remaining 9 months ($7.5M) in FY2031 not shown | B44: 0 | C44: 0 | D44: 0 | E44: 0 | F44: 0 | G44: 0 | H44: 0 | I44: 0 | J44: 0 | K44: 0 | L44: 0 | M44: 0 | N44: 0 | O44: 0 | P44: 0 | Q44: 0 | R44: 0 | S44: 0 | T44: 0 | U44: 0 | V44: 0 | W44: 0 | X44: 0 | Y44: 0 | Z44: 0 | AA44: 0 | AB44: 0 | AC44: 0 | AD44: 0 | AE44: 0 | AF44: 0 | AG44: 0 | AH44: 0 | AI44: 0 | AJ44: 0 | AK44: 0 | AL44: 0 | AM44: 0 | AN44: 0 | AO44: 0 | AP44: 0 | AQ44: 0 | AR44: 0 | AS44: 0 | AT44: 0 | AU44: 0 | AV44: 0 | AW44: 0 | AX44: 0 | AY44: 0 | AZ44: 0 | BA44: 0 | BB44: 0 | BC44: 0 | BD44: 0 | BE44: 0 | BF44: 0 | BG44: 0 | BH44: 0 | BI44: 0
A46: Revenue from Propulsion System Sales | B46: =((HLOOKUP(B$3,Controls!$A$5:$F$217,MATCH(Controls!$A17,Controls!$A$5:$A$217,0),0)*B37))+(SUM(B39:B44)) -> 0 | C46: =((HLOOKUP(C$3,Controls!$A$5:$F$217,MATCH(Controls!$A17,Controls!$A$5:$A$217,0),0)*C37))+(SUM(C39:C44)) -> 0 | D46: =((HLOOKUP(D$3,Controls!$A$5:$F$217,MATCH(Controls!$A17,Controls!$A$5:$A$217,0),0)*D37))+(SUM(D39:D44)) -> 250000 | E46: =((HLOOKUP(E$3,Controls!$A$5:$F$217,MATCH(Controls!$A17,Controls!$A$5:$A$217,0),0)*E37))+(SUM(E39:E44)) -> 100000 | F46: =((HLOOKUP(F$3,Controls!$A$5:$F$217,MATCH(Controls!$A17,Controls!$A$5:$A$217,0),0)*F37))+(SUM(F39:F44)) -> 250000 | G46: =((HLOOKUP(G$3,Controls!$A$5:$F$217,MATCH(Controls!$A17,Controls!$A$5:$A$217,0),0)*G37))+(SUM(G39:G44)) -> 500000 | H46: =((HLOOKUP(H$3,Controls!$A$5:$F$217,MATCH(Controls!$A17,Controls!$A$5:$A$217,0),0)*H37))+(SUM(H39:H44)) -> 400000 | I46: =((HLOOKUP(I$3,Controls!$A$5:$F$217,MATCH(Controls!$A17,Controls!$A$5:$A$217,0),0)*I37))+(SUM(I39:I44)) -> 400000 | ... BI46: =((HLOOKUP(BI$3,Controls!$A$5:$F$217,MATCH(Controls!$A17,Controls!$A$5:$A$217,0),0)*BI37))+(SUM(BI39:BI44)) -> 3416666.7
A48: EXOS US BLK4 Wet Lease Launches
A50: EXOS US BLK4 Wet Lease Launches | B50: 0 | C50: 0 | D50: 0 | E50: 0 | F50: 0 | G50: 0 | H50: 0 | I50: 0 | J50: 0 | K50: 0 | L50: 0 | M50: 0 | N50: 0 | O50: 0 | P50: 0 | Q50: 0 | R50: 0 | S50: 0 | T50: 0 | U50: 0 | V50: 0 | W50: 0 | X50: 0 | Y50: 0 | Z50: 0 | AA50: 0 | AB50: 0 | AC50: 0 | AD50: 0 | AE50: 0 | AF50: 0 | AG50: 0 | AH50: 0 | AI50: 0 | AJ50: 0 | AK50: 0 | AL50: 0 | AM50: 0 | AN50: 0 | AO50: 0 | AP50: 0 | AQ50: 0 | AR50: 0 | AS50: 0 | AT50: 0 | AU50: 0 | AV50: 0 | AW50: 0 | AX50: 0 | AY50: 0 | AZ50: 0 | BA50: 0 | BB50: 0 | BC50: 0 | BD50: 0 | BE50: 0 | BF50: 0 | BG50: 0 | BH50: 0 | BI50: 0
A52: Recurring Orders | B52: 0 | C52: 0 | D52: 0 | E52: 0 | F52: 0 | G52: 0 | H52: 0 | I52: 0 | J52: 0 | K52: 0 | L52: 0 | M52: 0 | N52: 0 | O52: 0 | P52: 0 | Q52: 0 | R52: 0 | S52: 0 | T52: 0 | U52: 0 | V52: 0 | W52: 0 | X52: 0 | Y52: 0 | Z52: 0 | AA52: 0 | AB52: 0 | AC52: 0 | AD52: 0 | AE52: 0 | AF52: 0 | AG52: 0 | AH52: 0 | AI52: 0 | AJ52: 0 | AK52: 0 | AL52: 0 | AM52: 0.2 | AN52: 0 | AO52: 0 | AP52: 0 | AQ52: 0 | AR52: 0 | AS52: 0 | AT52: 0 | AU52: 0 | AV52: 0 | AW52: 0 | AX52: 0 | AY52: 0 | AZ52: 0.125 | BA52: 0 | BB52: 0.125 | BC52: 0 | BD52: 0.25 | BE52: 0 | BF52: 0 | BG52: 0 | BH52: 0.3 | BI52: 0
A54: NASA Flight Opportunities IDIQ — Suborbital Research Services ($1M/flight × 2 flights/qtr) | B54: 0 | C54: 0 | D54: 0 | E54: 0 | F54: 0 | G54: 0 | H54: 0 | I54: 0 | J54: 0 | K54: 0 | L54: 0 | M54: 0 | N54: 0 | O54: 0 | P54: 0 | Q54: 0 | R54: 0 | S54: 0 | T54: 0 | U54: 0 | V54: 0 | W54: 0 | X54: 0 | Y54: 0 | Z54: 0 | AA54: 0 | AB54: 0 | AC54: 0 | AD54: 0 | AE54: 0 | AF54: 0 | AG54: 0 | AH54: 0 | AI54: 0 | AJ54: 0 | AK54: 0 | AL54: 0 | AM54: 0 | AN54: 0 | AO54: 0 | AP54: 0 | AQ54: 0 | AR54: 0 | AS54: 0 | AT54: 0 | AU54: 0 | AV54: 0 | AW54: 0 | AX54: 0 | AY54: 0 | AZ54: 0 | BA54: 0 | BB54: 0 | BC54: 0 | BD54: 0 | BE54: 0 | BF54: 0 | BG54: 0 | BH54: 0 | BI54: 0
A55: Second BLK3 Flight — Commercial Payload Revenue ($750K) | B55: 0 | C55: 0 | D55: 0 | E55: 0 | F55: 0 | G55: 0 | H55: 0 | I55: 0 | J55: 0 | K55: 0 | L55: 0 | M55: 0 | N55: 0 | O55: 0 | P55: 0 | Q55: 0 | R55: 0 | S55: 0 | T55: 0 | U55: 0 | V55: 0 | W55: 0 | X55: 0 | Y55: 0 | Z55: 375000 | AA55: 375000 | AB55: 0 | AC55: 0 | AD55: 0 | AE55: 0 | AF55: 0 | AG55: 0 | AH55: 0 | AI55: 0 | AJ55: 0 | AK55: 0 | AL55: 0 | AM55: 0 | AN55: 0 | AO55: 0 | AP55: 0 | AQ55: 0 | AR55: 0 | AS55: 0 | AT55: 0 | AU55: 0 | AV55: 0 | AW55: 0 | AX55: 0 | AY55: 0 | AZ55: 0 | BA55: 0 | BB55: 0 | BC55: 0 | BD55: 0 | BE55: 0 | BF55: 0 | BG55: 0 | BH55: 0 | BI55: 0
A56: ANNUAL REVENUE TRAJECTORY — Projections start March 2026, scaling to $120M by CY2030 | B56: 0 | C56: 0 | D56: 0 | E56: 0 | F56: 0 | G56: 0 | H56: 0 | I56: 0 | J56: 0 | K56: 0 | L56: 0 | M56: 0 | N56: 0 | O56: 0 | P56: 0 | Q56: 0 | R56: 0 | S56: 0 | T56: 0 | U56: 0 | V56: 0 | W56: 0 | X56: 0 | Y56: 0 | Z56: 0 | AA56: 0 | AB56: 0 | AC56: 0 | AD56: 0 | AE56: 0 | AF56: 0 | AG56: 0 | AH56: 0 | AI56: 0 | AJ56: 0 | AK56: 0 | AL56: 0 | AM56: 0 | AN56: 0 | AO56: 0 | AP56: 0 | AQ56: 0 | AR56: 0 | AS56: 0 | AT56: 0 | AU56: 0 | AV56: 0 | AW56: 0 | AX56: 0 | AY56: 0 | AZ56: 0 | BA56: 0 | BB56: 0 | BC56: 0 | BD56: 0 | BE56: 0 | BF56: 0 | BG56: 0 | BH56: 0 | BI56: 0
A57: CY2025 Actual: $1,550,000 (base year — 4 consecutive years of doubling) | B57: 0 | C57: 0 | D57: 0 | E57: 0 | F57: 0 | G57: 0 | H57: 0 | I57: 0 | J57: 0 | K57: 0 | L57: 0 | M57: 0 | N57: 0 | O57: 0 | P57: 0 | Q57: 0 | R57: 0 | S57: 0 | T57: 0 | U57: 0 | V57: 0 | W57: 0 | X57: 0 | Y57: 0 | Z57: 0 | AA57: 0 | AB57: 0 | AC57: 0 | AD57: 0 | AE57: 0 | AF57: 0 | AG57: 0 | AH57: 0 | AI57: 0 | AJ57: 0 | AK57: 0 | AL57: 0 | AM57: 0 | AN57: 0 | AO57: 0 | AP57: 0 | AQ57: 0 | AR57: 0 | AS57: 0 | AT57: 0 | AU57: 0 | AV57: 0 | AW57: 0 | AX57: 0 | AY57: 0 | AZ57: 0 | BA57: 0 | BB57: 0 | BC57: 0 | BD57: 0 | BE57: 0 | BF57: 0 | BG57: 0 | BH57: 0 | BI57: 0
A58: CY2026: $4.86M — Scorpius $2.65M + HVRR + TACFI + entX $410K (no NASA IDIQ yet) | B58: 0 | C58: 0 | D58: 0 | E58: 0 | F58: 0 | G58: 0 | H58: 0 | I58: 0 | J58: 0 | K58: 0 | L58: 0 | M58: 0 | N58: 0 | O58: 0 | P58: 0 | Q58: 0 | R58: 0 | S58: 0 | T58: 0 | U58: 0 | V58: 0 | W58: 0 | X58: 0 | Y58: 0 | Z58: 0 | AA58: 0 | AB58: 0 | AC58: 0 | AD58: 0 | AE58: 0 | AF58: 0 | AG58: 0 | AH58: 0 | AI58: 0 | AJ58: 0 | AK58: 0 | AL58: 0 | AM58: 0 | AN58: 0 | AO58: 0 | AP58: 0 | AQ58: 0 | AR58: 0 | AS58: 0 | AT58: 0 | AU58: 0 | AV58: 0 | AW58: 0 | AX58: 0 | AY58: 0 | AZ58: 0 | BA58: 0 | BB58: 0 | BC58: 0 | BD58: 0 | BE58: 0 | BF58: 0 | BG58: 0 | BH58: 0 | BI58: 0
A59: CY2027: $9.38M — Scorpius $3.5M + TACFI $2.7M + entX/Commercial $1.18M + 2nd Flight $750K + NASA Flight Opps $2.0M (Q3-Q4 onramp) | B59: 0 | C59: 0 | D59: 0 | E59: 0 | F59: 0 | G59: 0 | H59: 0 | I59: 0 | J59: 0 | K59: 0 | L59: 0 | M59: 0 | N59: 0 | O59: 0 | P59: 0 | Q59: 0 | R59: 0 | S59: 0 | T59: 0 | U59: 0 | V59: 0 | W59: 0 | X59: 0 | Y59: 0 | Z59: 0 | AA59: 0 | AB59: 0 | AC59: 0 | AD59: 0 | AE59: 0 | AF59: 0 | AG59: 0 | AH59: 0 | AI59: 0 | AJ59: 0 | AK59: 0 | AL59: 0 | AM59: 0 | AN59: 0 | AO59: 0 | AP59: 0 | AQ59: 0 | AR59: 0 | AS59: 0 | AT59: 0 | AU59: 0 | AV59: 0 | AW59: 0 | AX59: 0 | AY59: 0 | AZ59: 0 | BA59: 0 | BB59: 0 | BC59: 0 | BD59: 0 | BE59: 0 | BF59: 0 | BG59: 0 | BH59: 0 | BI59: 0
A60: CY2028: $34M — BLK4 $9.8M + NASA $8M + Scorpius $7M + STRATFI $8.2M + Commercial $1M
A61: CY2029: $64M — BLK4 $31M + NASA $8M + Scorpius $14M + STRATFI $10M + Commercial $1M | B61: 0 | C61: 0 | D61: 0 | E61: 0 | F61: 0 | G61: 0 | H61: 0 | I61: 0 | J61: 0 | K61: 0 | L61: 0 | M61: 0 | N61: 0 | O61: 0 | P61: 0 | Q61: 0 | R61: 0 | S61: 0 | T61: 0 | U61: =((HLOOKUP(U$3,Controls!$A$5:$F$217,MATCH(Controls!$A23,Controls!$A$5:$A$217,0),0)*(U50+U52)*Controls!$B$21))+SUM(U54:U59) -> 0 | V61: =((HLOOKUP(V$3,Controls!$A$5:$F$217,MATCH(Controls!$A23,Controls!$A$5:$A$217,0),0)*(V50+V52)*Controls!$B$21))+SUM(V54:V59) -> 0 | W61: =((HLOOKUP(W$3,Controls!$A$5:$F$217,MATCH(Controls!$A23,Controls!$A$5:$A$217,0),0)*(W50+W52)*Controls!$B$21))+SUM(W54:W59) -> 0 | X61: =((HLOOKUP(X$3,Controls!$A$5:$F$217,MATCH(Controls!$A23,Controls!$A$5:$A$217,0),0)*(X50+X52)*Controls!$B$21))+SUM(X54:X59) -> 0 | Y61: =((HLOOKUP(Y$3,Controls!$A$5:$F$217,MATCH(Controls!$A23,Controls!$A$5:$A$217,0),0)*(Y50+Y52)*Controls!$B$21))+SUM(Y54:Y59) -> 0 | Z61: =((HLOOKUP(Z$3,Controls!$A$5:$F$217,MATCH(Controls!$A23,Controls!$A$5:$A$217,0),0)*(Z50+Z52)*Controls!$B$21))+SUM(Z54:Z59) -> 375000 | AA61: =((HLOOKUP(AA$3,Controls!$A$5:$F$217,MATCH(Controls!$A23,Controls!$A$5:$A$217,0),0)*(AA50+AA52)*Controls!$B$21))+SUM(AA54:AA59) -> 375000 | AB61: =((HLOOKUP(AB$3,Controls!$A$5:$F$217,MATCH(Controls!$A23,Controls!$A$5:$A$217,0),0)*(AB50+AB52)*Controls!$B$21))+SUM(AB54:AB59) -> 0 | ... BI61: =((HLOOKUP(BI$3,Controls!$A$5:$F$217,MATCH(Controls!$A23,Controls!$A$5:$A$217,0),0)*(BI50+BI52)*Controls!$B$21))+SUM(BI54:BI59) -> 0
A62: CY2030: $129M — BLK4 $82M + NASA $8M + Scorpius $28M + STRATFI $10M + Commercial $1M
A63: NOTE: $10M Series A enables this trajectory. Dual listing: Euronext Dublin (immediate) + TXSE (Year 2)
A65: ACTUALS: Jul 2025 — Feb 2026 (cols 2-9) | B65: 0 | C65: 0 | D65: 0 | E65: 0 | F65: 0 | G65: 0 | H65: 0 | I65: 0 | J65: 0 | K65: 0 | L65: 0 | M65: 0 | N65: 0 | O65: 0 | P65: 0 | Q65: 0 | R65: 0 | S65: 0 | T65: 0 | U65: 0 | V65: 0 | W65: 0 | X65: 0 | Y65: 0 | Z65: 0 | AA65: 0 | AB65: 0 | AC65: 0 | AD65: 0 | AE65: 0 | AF65: 0 | AG65: 0 | AH65: 0 | AI65: 0 | AJ65: 0 | AK65: 0 | AL65: 0 | AM65: 0 | AN65: 0 | AO65: 0 | AP65: 0 | AQ65: 0 | AR65: 0 | AS65: 0 | AT65: 0 | AU65: 0 | AV65: 0 | AW65: 0 | AX65: 0 | AY65: 0 | AZ65: 0 | BA65: 0 | BB65: 0 | BC65: 0 | BD65: 0 | BE65: 0 | BF65: 0 | BG65: 0 | BH65: 0 | BI65: 1 | BJ65: 0 | BK65: 0 | BL65: 0 | BM65: 0 | BN65: 0 | BO65: 0 | BP65: 0 | BQ65: 0 | BR65: 0 | BS65: 0 | BT65: 0 | BU65: 1 | BV65: 0 | BW65: 0 | BX65: 0 | BY65: 0 | BZ65: 0 | CA65: 0 | CB65: 0 | CC65: 0 | CD65: 0 | CE65: 0 | CF65: 1 | CG65: 0 | CH65: 1 | CI65: 0 | CJ65: 0 | CK65: 0 | CL65: 0 | CM65: 0 | CN65: 4 | CO65: 0 | CP65: 4 | CQ65: 0 | CR65: 0 | CS65: 0 | CT65: 4 | CU65: 0 | CV65: 0 | CW65: 0 | CX65: 0 | CY65: 0 | CZ65: 4 | DA65: 0 | DB65: 1 | DC65: 0 | DD65: 0
A66: PROJECTIONS: Mar 2026 onward (col 10+) | B66: 80000 | C66: 80000 | D66: 100000 | E66: 100000 | F66: 100000 | G66: 594652 | H66: 56000 | I66: 56000 | J66: 115000 | K66: 191017 | L66: 95000 | M66: 95000
A67: Recurring Sales | B67: 0 | C67: 0 | D67: 0 | E67: 0 | F67: 0 | G67: 0 | H67: 0 | I67: 0 | J67: 0 | K67: 0 | L67: 0 | M67: 0 | N67: 0 | O67: 0 | P67: 0 | Q67: 0 | R67: 0 | S67: 0 | T67: 0 | U67: 0 | V67: 0 | W67: 0 | X67: 0 | Y67: 0 | Z67: 0 | AA67: 0 | AB67: 0 | AC67: 0 | AD67: 0 | AE67: 0 | AF67: 0 | AG67: 0 | AH67: 0 | AI67: 0 | AJ67: 0 | AK67: 0 | AL67: 0 | AM67: 0 | AN67: 0 | AO67: 0 | AP67: 0 | AQ67: 0 | AR67: 0 | AS67: 0 | AT67: 0 | AU67: 0 | AV67: 0 | AW67: 0 | AX67: 0 | AY67: 0 | AZ67: 0 | BA67: 0 | BB67: 0 | BC67: 0 | BD67: 0 | BE67: 0 | BF67: 0 | BG67: 0 | BH67: 0 | BI67: 0
B69: 0 | C69: 0 | D69: 0 | E69: 0 | F69: 0 | G69: 0 | H69: 0 | I69: 0 | J69: 0 | K69: 0 | L69: 0 | M69: 0 | N69: 0 | O69: 0 | P69: 0 | Q69: 0 | R69: 0 | S69: 0 | T69: 0 | U69: 0 | V69: 0 | W69: 0 | X69: 0 | Y69: 0 | Z69: 0 | AA69: 0 | AB69: 0 | AC69: 0 | AD69: 0 | AE69: 0 | AF69: 0 | AG69: 0 | AH69: 0 | AI69: 0 | AJ69: 0 | AK69: 0 | AL69: 0 | AM69: 0 | AN69: 0 | AO69: 0 | AP69: 0 | AQ69: 0 | AR69: 0 | AS69: 0 | AT69: 0 | AU69: 0 | AV69: 0 | AW69: 0 | AX69: 0 | AY69: 0 | AZ69: 0 | BA69: 0 | BB69: 0 | BC69: 0 | BD69: 0 | BE69: 0 | BF69: 0 | BG69: 0 | BH69: 0 | BI69: 0
A70: This EXCEEDS investor deck projections ($25M base / $48M upside by 2030). | B70: 0 | C70: 0 | D70: 0 | E70: 0 | F70: 0 | G70: 0 | H70: 0 | I70: 0 | J70: 0 | K70: 0 | L70: 0 | M70: 0 | N70: 0 | O70: 0 | P70: 0 | Q70: 0 | R70: 0 | S70: 0 | T70: 0 | U70: 0 | V70: 0 | W70: 0 | X70: 0 | Y70: 0 | Z70: 0 | AA70: 0 | AB70: 0 | AC70: 0 | AD70: 0 | AE70: 0 | AF70: 0 | AG70: 0 | AH70: 0 | AI70: 0 | AJ70: 0 | AK70: 0 | AL70: 0 | AM70: 0 | AN70: 0 | AO70: 0 | AP70: 0 | AQ70: 0 | AR70: 0 | AS70: 0 | AT70: 0 | AU70: 0 | AV70: 0 | AW70: 0 | AX70: 0 | AY70: 0 | AZ70: 0 | BA70: 0 | BB70: 0 | BC70: 0 | BD70: 0 | BE70: 0 | BF70: 0 | BG70: 0 | BH70: 0 | BI70: 0
A71: Model now projects $120M by CY2030. Update deck accordingly. | B71: 0 | C71: 0 | D71: 0 | E71: 0 | F71: 0 | G71: 0 | H71: 0 | I71: 0 | J71: 0 | K71: 0 | L71: 0 | M71: 0 | N71: 0 | O71: 0 | P71: 0 | Q71: 0 | R71: 0 | S71: 0 | T71: 0 | U71: 0 | V71: 0 | W71: 0 | X71: 0 | Y71: 0 | Z71: 0 | AA71: 0 | AB71: 0 | AC71: 0 | AD71: 0 | AE71: 0 | AF71: 0 | AG71: 0 | AH71: 0 | AI71: 0 | AJ71: 0 | AK71: 0 | AL71: 0 | AM71: 0 | AN71: 0 | AO71: 0 | AP71: 0 | AQ71: 0 | AR71: 0 | AS71: 0 | AT71: 0 | AU71: 0 | AV71: 0 | AW71: 0 | AX71: 0 | AY71: 0 | AZ71: 0 | BA71: 0 | BB71: 0 | BC71: 0 | BD71: 0 | BE71: 0 | BF71: 0 | BG71: 0 | BH71: 0 | BI71: 0
A72: DECISION NEEDED: Reconcile deck to this model, or keep TACFI/STRATFI as upside in deck? | B72: 0 | C72: 0 | D72: 0 | E72: 0 | F72: 0 | G72: 0 | H72: 0 | I72: 0 | J72: 0 | K72: 0 | L72: 0 | M72: 0 | N72: 0 | O72: 0 | P72: 0 | Q72: 0 | R72: 0 | S72: 0 | T72: 0 | U72: 0 | V72: 0 | W72: 0 | X72: 0 | Y72: 0 | Z72: 0 | AA72: 0 | AB72: 0 | AC72: 0 | AD72: 0 | AE72: 0 | AF72: 0 | AG72: 0 | AH72: 0 | AI72: 0 | AJ72: 0 | AK72: 0 | AL72: 0 | AM72: 0 | AN72: 0 | AO72: 0 | AP72: 0 | AQ72: 0 | AR72: 0 | AS72: 0 | AT72: 0 | AU72: 0 | AV72: 0 | AW72: 0 | AX72: 0 | AY72: 0 | AZ72: 0 | BA72: 0 | BB72: 0 | BC72: 0 | BD72: 0 | BE72: 0 | BF72: 0 | BG72: 0 | BH72: 0 | BI72: 0
A73: Additional Revenue/Contract | B73: 0 | C73: 0 | D73: 0 | E73: 0 | F73: 0 | G73: 0 | H73: 0 | I73: 0 | J73: 0 | K73: 0 | L73: 0 | M73: 0 | N73: 0 | O73: 0 | P73: 0 | Q73: 0 | R73: 0 | S73: 0 | T73: 0 | U73: 0 | V73: 0 | W73: 0 | X73: 0 | Y73: 0 | Z73: 0 | AA73: 0 | AB73: 0 | AC73: 0 | AD73: 0 | AE73: 0 | AF73: 0 | AG73: 0 | AH73: 0 | AI73: 0 | AJ73: 0 | AK73: 0 | AL73: 0 | AM73: 0 | AN73: 0 | AO73: 0 | AP73: 0 | AQ73: 0 | AR73: 0 | AS73: 0 | AT73: 0 | AU73: 0 | AV73: 0 | AW73: 0 | AX73: 0 | AY73: 0 | AZ73: 0 | BA73: 0 | BB73: 0 | BC73: 0 | BD73: 0 | BE73: 0 | BF73: 0 | BG73: 0 | BH73: 0 | BI73: 0
A74: Additional Revenue/Contract | B74: 0 | C74: 0 | D74: 0 | E74: 0 | F74: 0 | G74: 0 | H74: 0 | I74: 0 | J74: 0 | K74: 0 | L74: 0 | M74: 0 | N74: 0 | O74: 0 | P74: 0 | Q74: 0 | R74: 0 | S74: 0 | T74: 0 | U74: 0 | V74: 0 | W74: 0 | X74: 0 | Y74: 0 | Z74: 0 | AA74: 0 | AB74: 0 | AC74: 0 | AD74: 0 | AE74: 0 | AF74: 0 | AG74: 0 | AH74: 0 | AI74: 0 | AJ74: 0 | AK74: 0 | AL74: 0 | AM74: 0 | AN74: 0 | AO74: 0 | AP74: 0 | AQ74: 0 | AR74: 0 | AS74: 0 | AT74: 0 | AU74: 0 | AV74: 0 | AW74: 0 | AX74: 0 | AY74: 0 | AZ74: 0 | BA74: 0 | BB74: 0 | BC74: 0 | BD74: 0 | BE74: 0 | BF74: 0 | BG74: 0 | BH74: 0 | BI74: 0
A76: Revenue from Second Stage Sales | B76: =(HLOOKUP(B$3,Controls!$A$5:$F$217,MATCH(Controls!$A27,Controls!$A$5:$A$217,0),0)*(B67+B65))+SUM(B69:B74) -> 0 | C76: =(HLOOKUP(C$3,Controls!$A$5:$F$217,MATCH(Controls!$A27,Controls!$A$5:$A$217,0),0)*(C67+C65))+SUM(C69:C74) -> 0 | D76: =(HLOOKUP(D$3,Controls!$A$5:$F$217,MATCH(Controls!$A27,Controls!$A$5:$A$217,0),0)*(D67+D65))+SUM(D69:D74) -> 0 | E76: =(HLOOKUP(E$3,Controls!$A$5:$F$217,MATCH(Controls!$A27,Controls!$A$5:$A$217,0),0)*(E67+E65))+SUM(E69:E74) -> 0 | F76: =(HLOOKUP(F$3,Controls!$A$5:$F$217,MATCH(Controls!$A27,Controls!$A$5:$A$217,0),0)*(F67+F65))+SUM(F69:F74) -> 0 | G76: =(HLOOKUP(G$3,Controls!$A$5:$F$217,MATCH(Controls!$A27,Controls!$A$5:$A$217,0),0)*(G67+G65))+SUM(G69:G74) -> 0 | H76: =(HLOOKUP(H$3,Controls!$A$5:$F$217,MATCH(Controls!$A27,Controls!$A$5:$A$217,0),0)*(H67+H65))+SUM(H69:H74) -> 0 | I76: =(HLOOKUP(I$3,Controls!$A$5:$F$217,MATCH(Controls!$A27,Controls!$A$5:$A$217,0),0)*(I67+I65))+SUM(I69:I74) -> 0 | ... BI76: =(HLOOKUP(BI$3,Controls!$A$5:$F$217,MATCH(Controls!$A27,Controls!$A$5:$A$217,0),0)*(BI67+BI65))+SUM(BI69:BI74) -> 350000
A77: `
A78: Scorpius Space Corp Tank Manufacture
A80: Scorpius Space Corp Tank Sales | N80: 1.5 | O80: 1.5 | P80: 2 | Q80: 2 | R80: 2.5 | S80: 2.5 | T80: 2.75 | U80: 3 | V80: 3 | W80: 3 | X80: 3.35 | Y80: 3.35 | Z80: 4 | AA80: 4 | AB80: 4.25 | AC80: 4.5 | AD80: 4.5 | AE80: 4.5 | AF80: 4.75 | AG80: 4.75 | AH80: 5 | AI80: 5.25 | AJ80: 5.25 | AK80: 5.25 | AL80: 5.5 | AM80: 5.75 | AN80: 5.75 | AO80: 6 | AP80: 6.25 | AQ80: 6.5 | AR80: 6.75 | AS80: 6.75 | AT80: 7 | AU80: 7.5 | AV80: 7.5 | AW80: 7.75 | AX80: 7.75 | AY80: 8 | AZ80: 8 | BA80: 8 | BB80: 8 | BC80: 8.5 | BD80: 8.75 | BE80: 9 | BF80: 9 | BG80: 9 | BH80: 9 | BI80: 9
A82: Nova B1-B6 | B82: 265600 | C82: 60300 | D82: 0 | E82: 0 | F82: 0 | G82: 0 | H82: 0 | I82: 0 | J82: 0 | K82: 0 | L82: 0 | M82: 0 | N82: 0 | O82: 0 | P82: 0 | Q82: 0 | R82: 0 | S82: 0 | T82: 0 | U82: 0 | V82: 0 | W82: 0 | X82: 0 | Y82: 0 | Z82: 0 | AA82: 0 | AB82: 0 | AC82: 0 | AD82: 0 | AE82: 0 | AF82: 0 | AG82: 0 | AH82: 0 | AI82: 0 | AJ82: 0 | AK82: 0 | AL82: 0 | AM82: 0 | AN82: 0 | AO82: 0 | AP82: 0 | AQ82: 0 | AR82: 0 | AS82: 0 | AT82: 0 | AU82: 0 | AV82: 0 | AW82: 0 | AX82: 0 | AY82: 0 | AZ82: 0 | BA82: 0 | BB82: 0 | BC82: 0 | BD82: 0 | BE82: 0 | BF82: 0 | BG82: 0 | BH82: 0 | BI82: 0
A83: Nova D 1-4 | B83: 0 | C83: 75000 | D83: 215000 | E83: 215000 | F83: 140000 | G83: 215000 | H83: 0 | I83: 0 | J83: 0 | K83: 0 | L83: 0 | M83: 0 | N83: 0 | O83: 0 | P83: 0 | Q83: 0 | R83: 0 | S83: 0 | T83: 0 | U83: 0 | V83: 0 | W83: 0 | X83: 0 | Y83: 0 | Z83: 0 | AA83: 0 | AB83: 0 | AC83: 0 | AD83: 0 | AE83: 0 | AF83: 0 | AG83: 0 | AH83: 0 | AI83: 0 | AJ83: 0 | AK83: 0 | AL83: 0 | AM83: 0 | AN83: 0 | AO83: 0 | AP83: 0 | AQ83: 0 | AR83: 0 | AS83: 0 | AT83: 0 | AU83: 0 | AV83: 0 | AW83: 0 | AX83: 0 | AY83: 0 | AZ83: 0 | BA83: 0 | BB83: 0 | BC83: 0 | BD83: 0 | BE83: 0 | BF83: 0 | BG83: 0 | BH83: 0 | BI83: 0
A84: Letara & Karman | B84: 0 | C84: 0 | D84: 0 | E84: 119180 | F84: 119180 | G84: 50000 | H84: 100000 | I84: 100000 | J84: 100000 | K84: 100000 | L84: 100000 | M84: 0 | N84: 0 | O84: 0 | P84: 0 | Q84: 0 | R84: 0 | S84: 0 | T84: 0 | U84: 0 | V84: 0 | W84: 0 | X84: 0 | Y84: 0 | Z84: 0 | AA84: 0 | AB84: 0 | AC84: 0 | AD84: 0 | AE84: 0 | AF84: 0 | AG84: 0 | AH84: 0 | AI84: 0 | AJ84: 0 | AK84: 0 | AL84: 0 | AM84: 0 | AN84: 0 | AO84: 0 | AP84: 0 | AQ84: 0 | AR84: 0 | AS84: 0 | AT84: 0 | AU84: 0 | AV84: 0 | AW84: 0 | AX84: 0 | AY84: 0 | AZ84: 0 | BA84: 0 | BB84: 0 | BC84: 0 | BD84: 0 | BE84: 0 | BF84: 0 | BG84: 0 | BH84: 0 | BI84: 0
A85: Vaya | B85: 0 | C85: 0 | D85: 0 | E85: 112500 | F85: 112500 | G85: 284600 | H85: 112500 | I85: 112500 | J85: 140000 | K85: 140000 | L85: 90000 | M85: 90000 | N85: 90000 | O85: 0 | P85: 0 | Q85: 0 | R85: 0 | S85: 0 | T85: 0 | U85: 0 | V85: 0 | W85: 0 | X85: 0 | Y85: 0 | Z85: 0 | AA85: 0 | AB85: 0 | AC85: 0 | AD85: 0 | AE85: 0 | AF85: 0 | AG85: 0 | AH85: 0 | AI85: 0 | AJ85: 0 | AK85: 0 | AL85: 0 | AM85: 0 | AN85: 0 | AO85: 0 | AP85: 0 | AQ85: 0 | AR85: 0 | AS85: 0 | AT85: 0 | AU85: 0 | AV85: 0 | AW85: 0 | AX85: 0 | AY85: 0 | AZ85: 0 | BA85: 0 | BB85: 0 | BC85: 0 | BD85: 0 | BE85: 0 | BF85: 0 | BG85: 0 | BH85: 0 | BI85: 0
A86: Exos | B86: 0 | C86: 0 | D86: 0 | E86: 95160 | F86: 206820 | G86: 0 | H86: 111700 | I86: 0 | J86: 0 | K86: 0 | L86: 0 | M86: 0 | N86: 0 | O86: 0 | P86: 0 | Q86: 0 | R86: 0 | S86: 0 | T86: 0 | U86: 0 | V86: 0 | W86: 0 | X86: 0 | Y86: 0 | Z86: 0 | AA86: 0 | AB86: 0 | AC86: 0 | AD86: 0 | AE86: 0 | AF86: 0 | AG86: 0 | AH86: 0 | AI86: 0 | AJ86: 0 | AK86: 0 | AL86: 0 | AM86: 0 | AN86: 0 | AO86: 0 | AP86: 0 | AQ86: 0 | AR86: 0 | AS86: 0 | AT86: 0 | AU86: 0 | AV86: 0 | AW86: 0 | AX86: 0 | AY86: 0 | AZ86: 0 | BA86: 0 | BB86: 0 | BC86: 0 | BD86: 0 | BE86: 0 | BF86: 0 | BG86: 0 | BH86: 0 | BI86: 0
A87: Toyota/Other | B87: 0 | C87: 0 | D87: 0 | E87: 0 | F87: 0 | G87: 0 | H87: 0 | I87: 325000 | J87: 375000 | K87: 365000 | L87: 130000 | M87: 130000 | N87: 130000 | O87: 50000 | P87: 50000 | Q87: 0 | R87: 0 | S87: 0 | T87: 0 | U87: 0 | V87: 0 | W87: 0 | X87: 0 | Y87: 0 | Z87: 0 | AA87: 0 | AB87: 0 | AC87: 0 | AD87: 0 | AE87: 0 | AF87: 0 | AG87: 0 | AH87: 0 | AI87: 0 | AJ87: 0 | AK87: 0 | AL87: 0 | AM87: 0 | AN87: 0 | AO87: 0 | AP87: 0 | AQ87: 0 | AR87: 0 | AS87: 0 | AT87: 0 | AU87: 0 | AV87: 0 | AW87: 0 | AX87: 0 | AY87: 0 | AZ87: 0 | BA87: 0 | BB87: 0 | BC87: 0 | BD87: 0 | BE87: 0 | BF87: 0 | BG87: 0 | BH87: 0 | BI87: 0
A89: Revenue from Scorpius Space Tank Sales | B89: =(HLOOKUP(B$3,Controls!$A$5:$F$217,MATCH(Controls!$A31,Controls!$A$5:$A$217,0),0)*(B80))+SUM(B82:B87) -> 265600 | C89: =(HLOOKUP(C$3,Controls!$A$5:$F$217,MATCH(Controls!$A31,Controls!$A$5:$A$217,0),0)*(C80))+SUM(C82:C87) -> 135300 | D89: =(HLOOKUP(D$3,Controls!$A$5:$F$217,MATCH(Controls!$A31,Controls!$A$5:$A$217,0),0)*(D80))+SUM(D82:D87) -> 215000 | E89: =(HLOOKUP(E$3,Controls!$A$5:$F$217,MATCH(Controls!$A31,Controls!$A$5:$A$217,0),0)*(E80))+SUM(E82:E87) -> 541840 | F89: =(HLOOKUP(F$3,Controls!$A$5:$F$217,MATCH(Controls!$A31,Controls!$A$5:$A$217,0),0)*(F80))+SUM(F82:F87) -> 578500 | G89: =(HLOOKUP(G$3,Controls!$A$5:$F$217,MATCH(Controls!$A31,Controls!$A$5:$A$217,0),0)*(G80))+SUM(G82:G87) -> 549600 | H89: =(HLOOKUP(H$3,Controls!$A$5:$F$217,MATCH(Controls!$A31,Controls!$A$5:$A$217,0),0)*(H80))+SUM(H82:H87) -> 324200 | I89: =(HLOOKUP(I$3,Controls!$A$5:$F$217,MATCH(Controls!$A31,Controls!$A$5:$A$217,0),0)*(I80))+SUM(I82:I87) -> 537500 | ... BI89: =(HLOOKUP(BI$3,Controls!$A$5:$F$217,MATCH(Controls!$A31,Controls!$A$5:$A$217,0),0)*(BI80))+SUM(BI82:BI87) -> 4825195.3
A91: Sarge Technology and Hardware
A93: Sarge Technology and Hardware Sales | B93: 0 | C93: 0 | D93: 0 | E93: 0 | F93: 0 | G93: 0 | H93: 0 | I93: 0 | J93: 0 | K93: 0 | L93: 0 | M93: 1 | N93: 0 | O93: 0 | P93: 0 | Q93: 2 | R93: 0 | S93: 0 | T93: 2 | U93: 0 | V93: 0 | W93: 2 | X93: 0 | Y93: 0 | Z93: 2 | AA93: 0 | AB93: 0 | AC93: 2 | AD93: 0 | AE93: 0 | AF93: 2 | AG93: 0 | AH93: 0 | AI93: 2 | AJ93: 0 | AK93: 0 | AL93: 3 | AM93: 0 | AN93: 0 | AO93: 3 | AP93: 0 | AQ93: 0 | AR93: 3 | AT93: 0 | AU93: 3 | AV93: 0 | AW93: 0 | AX93: 4 | AY93: 0 | AZ93: 0 | BA93: 4 | BB93: 0 | BC93: 0 | BD93: 4 | BE93: 0 | BF93: 0 | BG93: 5 | BH93: 0 | BI93: 0
A95: Additional Revenue/Contract | B95: 0 | C95: 0 | D95: 0 | E95: 0 | F95: 0 | G95: 0 | H95: 0 | I95: 0 | J95: 0 | K95: 0 | L95: 0 | M95: 0 | N95: 0 | O95: 0 | P95: 0 | Q95: 0 | R95: 0 | S95: 0 | T95: 0 | U95: 0 | V95: 0 | W95: 0 | X95: 0 | Y95: 0 | Z95: 0 | AA95: 0 | AB95: 0 | AC95: 0 | AD95: 0 | AE95: 0 | AF95: 0 | AG95: 0 | AH95: 0 | AI95: 0 | AJ95: 0 | AK95: 0 | AL95: 0 | AM95: 0 | AN95: 0 | AO95: 0 | AP95: 0 | AQ95: 0 | AR95: 0 | AS95: 0 | AT95: 0 | AU95: 0 | AV95: 0 | AW95: 0 | AX95: 0 | AY95: 0 | AZ95: 0 | BA95: 0 | BB95: 0 | BC95: 0 | BD95: 0 | BE95: 0 | BF95: 0 | BG95: 0 | BH95: 0 | BI95: 0
A96: Additional Revenue/Contract | B96: 0 | C96: 0 | D96: 0 | E96: 0 | F96: 0 | G96: 0 | H96: 0 | I96: 0 | J96: 0 | K96: 0 | L96: 0 | M96: 0 | N96: 0 | O96: 0 | P96: 0 | Q96: 0 | R96: 0 | S96: 0 | T96: 0 | U96: 0 | V96: 0 | W96: 0 | X96: 0 | Y96: 0 | Z96: 0 | AA96: 0 | AB96: 0 | AC96: 0 | AD96: 0 | AE96: 0 | AF96: 0 | AG96: 0 | AH96: 0 | AI96: 0 | AJ96: 0 | AK96: 0 | AL96: 0 | AM96: 0 | AN96: 0 | AO96: 0 | AP96: 0 | AQ96: 0 | AR96: 0 | AS96: 0 | AT96: 0 | AU96: 0 | AV96: 0 | AW96: 0 | AX96: 0 | AY96: 0 | AZ96: 0 | BA96: 0 | BB96: 0 | BC96: 0 | BD96: 0 | BE96: 0 | BF96: 0 | BG96: 0 | BH96: 0 | BI96: 0
A97: Additional Revenue/Contract | B97: 0 | C97: 0 | D97: 0 | E97: 0 | F97: 0 | G97: 0 | H97: 0 | I97: 0 | J97: 0 | K97: 0 | L97: 0 | M97: 0 | N97: 0 | O97: 0 | P97: 0 | Q97: 0 | R97: 0 | S97: 0 | T97: 0 | U97: 0 | V97: 0 | W97: 0 | X97: 0 | Y97: 0 | Z97: 0 | AA97: 0 | AB97: 0 | AC97: 0 | AD97: 0 | AE97: 0 | AF97: 0 | AG97: 0 | AH97: 0 | AI97: 0 | AJ97: 0 | AK97: 0 | AL97: 0 | AM97: 0 | AN97: 0 | AO97: 0 | AP97: 0 | AQ97: 0 | AR97: 0 | AS97: 0 | AT97: 0 | AU97: 0 | AV97: 0 | AW97: 0 | AX97: 0 | AY97: 0 | AZ97: 0 | BA97: 0 | BB97: 0 | BC97: 0 | BD97: 0 | BE97: 0 | BF97: 0 | BG97: 0 | BH97: 0 | BI97: 0
A98: Additional Revenue/Contract | B98: 0 | C98: 0 | D98: 0 | E98: 0 | F98: 0 | G98: 0 | H98: 0 | I98: 0 | J98: 0 | K98: 0 | L98: 0 | M98: 0 | N98: 0 | O98: 0 | P98: 0 | Q98: 0 | R98: 0 | S98: 0 | T98: 0 | U98: 0 | V98: 0 | W98: 0 | X98: 0 | Y98: 0 | Z98: 0 | AA98: 0 | AB98: 0 | AC98: 0 | AD98: 0 | AE98: 0 | AF98: 0 | AG98: 0 | AH98: 0 | AI98: 0 | AJ98: 0 | AK98: 0 | AL98: 0 | AM98: 0 | AN98: 0 | AO98: 0 | AP98: 0 | AQ98: 0 | AR98: 0 | AS98: 0 | AT98: 0 | AU98: 0 | AV98: 0 | AW98: 0 | AX98: 0 | AY98: 0 | AZ98: 0 | BA98: 0 | BB98: 0 | BC98: 0 | BD98: 0 | BE98: 0 | BF98: 0 | BG98: 0 | BH98: 0 | BI98: 0
A99: Additional Revenue/Contract | B99: 0 | C99: 0 | D99: 0 | E99: 0 | F99: 0 | G99: 0 | H99: 0 | I99: 0 | J99: 0 | K99: 0 | L99: 0 | M99: 0 | N99: 0 | O99: 0 | P99: 0 | Q99: 0 | R99: 0 | S99: 0 | T99: 0 | U99: 0 | V99: 0 | W99: 0 | X99: 0 | Y99: 0 | Z99: 0 | AA99: 0 | AB99: 0 | AC99: 0 | AD99: 0 | AE99: 0 | AF99: 0 | AG99: 0 | AH99: 0 | AI99: 0 | AJ99: 0 | AK99: 0 | AL99: 0 | AM99: 0 | AN99: 0 | AO99: 0 | AP99: 0 | AQ99: 0 | AR99: 0 | AS99: 0 | AT99: 0 | AU99: 0 | AV99: 0 | AW99: 0 | AX99: 0 | AY99: 0 | AZ99: 0 | BA99: 0 | BB99: 0 | BC99: 0 | BD99: 0 | BE99: 0 | BF99: 0 | BG99: 0 | BH99: 0 | BI99: 0
A100: Additional Revenue/Contract | B100: 0 | C100: 0 | D100: 0 | E100: 0 | F100: 0 | G100: 0 | H100: 0 | I100: 0 | J100: 0 | K100: 0 | L100: 0 | M100: 0 | N100: 0 | O100: 0 | P100: 0 | Q100: 0 | R100: 0 | S100: 0 | T100: 0 | U100: 0 | V100: 0 | W100: 0 | X100: 0 | Y100: 0 | Z100: 0 | AA100: 0 | AB100: 0 | AC100: 0 | AD100: 0 | AE100: 0 | AF100: 0 | AG100: 0 | AH100: 0 | AI100: 0 | AJ100: 0 | AK100: 0 | AL100: 0 | AM100: 0 | AN100: 0 | AO100: 0 | AP100: 0 | AQ100: 0 | AR100: 0 | AS100: 0 | AT100: 0 | AU100: 0 | AV100: 0 | AW100: 0 | AX100: 0 | AY100: 0 | AZ100: 0 | BA100: 0 | BB100: 0 | BC100: 0 | BD100: 0 | BE100: 0 | BF100: 0 | BG100: 0 | BH100: 0 | BI100: 0
A102: Revenue from Sarge Technology Sales | B102: =(HLOOKUP(B$3,Controls!$A$5:$F$217,MATCH(Controls!$A36,Controls!$A$5:$A$217,0),0)*(B93))+SUM(B95:B100) -> 0 | C102: =(HLOOKUP(C$3,Controls!$A$5:$F$217,MATCH(Controls!$A36,Controls!$A$5:$A$217,0),0)*(C93))+SUM(C95:C100) -> 0 | D102: =(HLOOKUP(D$3,Controls!$A$5:$F$217,MATCH(Controls!$A36,Controls!$A$5:$A$217,0),0)*(D93))+SUM(D95:D100) -> 0 | E102: =(HLOOKUP(E$3,Controls!$A$5:$F$217,MATCH(Controls!$A36,Controls!$A$5:$A$217,0),0)*(E93))+SUM(E95:E100) -> 0 | F102: =(HLOOKUP(F$3,Controls!$A$5:$F$217,MATCH(Controls!$A36,Controls!$A$5:$A$217,0),0)*(F93))+SUM(F95:F100) -> 0 | G102: =(HLOOKUP(G$3,Controls!$A$5:$F$217,MATCH(Controls!$A36,Controls!$A$5:$A$217,0),0)*(G93))+SUM(G95:G100) -> 0 | H102: =(HLOOKUP(H$3,Controls!$A$5:$F$217,MATCH(Controls!$A36,Controls!$A$5:$A$217,0),0)*(H93))+SUM(H95:H100) -> 0 | I102: =(HLOOKUP(I$3,Controls!$A$5:$F$217,MATCH(Controls!$A36,Controls!$A$5:$A$217,0),0)*(I93))+SUM(I95:I100) -> 0 | ... BI102: =(HLOOKUP(BI$3,Controls!$A$5:$F$217,MATCH(Controls!$A36,Controls!$A$5:$A$217,0),0)*(BI93))+SUM(BI95:BI100) -> 0
A105: Total Revenue | B105: =B102+B89+B76+B61+B46+B33 -> 265600 | C105: =C102+C89+C76+C61+C46+C33 -> 135300 | D105: =D102+D89+D76+D61+D46+D33 -> 465000 | E105: =E102+E89+E76+E61+E46+E33 -> 641840 | F105: =F102+F89+F76+F61+F46+F33 -> 828500 | G105: =G102+G89+G76+G61+G46+G33 -> 1049600 | H105: =H102+H89+H76+H61+H46+H33 -> 724200 | I105: =I102+I89+I76+I61+I46+I33 -> 937500 | ... BI105: =BI102+BI89+BI76+BI61+BI46+BI33 -> 15425195

Sheet Oper, Cap, Other Assum
B1: Series A Investment
B3: Assumptions | G3: M1 | H3: M2 | I3: M3 | J3: M4 | K3: M5 | L3: M6 | M3: M7 | N3: M8 | O3: M9 | P3: M10 | Q3: M11 | R3: M12 | S3: Annual
B5: General & Administrative Expenses
B7: Utilities | F7: Growth(y-o-y)
B8: Year 1 | F8: 0 | G8: 5000 | H8: 5000 | I8: 5000 | J8: 5000 | K8: 5000 | L8: 5000 | M8: 5000 | N8: 5000 | O8: 5000 | P8: 5000 | Q8: 5000 | R8: 5000 | S8: =SUM(G8:R8) -> 60000
B9: Year 2 | F9: 0.05 | G9: =R8+R8*F9 -> 5250 | H9: =G9 -> 5250 | I9: =H9 -> 5250 | J9: =I9 -> 5250 | K9: =J9 -> 5250 | L9: =K9 -> 5250 | M9: =L9 -> 5250 | N9: =M9 -> 5250 | O9: =N9 -> 5250 | ... R9: =Q9 -> 5250 | S9: =SUM(G9:R9) -> 63000
B10: Year 3 | F10: 0.05 | G10: =R9+R9*F10 -> 5512.5 | H10: =G10 -> 5512.5 | I10: =H10 -> 5512.5 | J10: =I10 -> 5512.5 | K10: =J10 -> 5512.5 | L10: =K10 -> 5512.5 | M10: =L10 -> 5512.5 | N10: =M10 -> 5512.5 | O10: =N10 -> 5512.5 | ... R10: =Q10 -> 5512.5 | S10: =SUM(G10:R10) -> 66150
B11: Year 4 | C11: Add manufacturing in Midland- Bldg by Midland EDC | F11: 0.05 | G11: =(R10+R10*F11)*4 -> 23152.5 | H11: =G11 -> 23152.5 | I11: =H11 -> 23152.5 | J11: =I11 -> 23152.5 | K11: =J11 -> 23152.5 | L11: =K11 -> 23152.5 | M11: =L11 -> 23152.5 | N11: =M11 -> 23152.5 | O11: =N11 -> 23152.5 | ... R11: =Q11 -> 23152.5 | S11: =SUM(G11:R11) -> 277830
B12: Year 5 | F12: 0.05 | G12: =R11+R11*F12 -> 24310.125 | H12: =G12 -> 24310.125 | I12: =H12 -> 24310.125 | J12: =I12 -> 24310.125 | K12: =J12 -> 24310.125 | L12: =K12 -> 24310.125 | M12: =L12 -> 24310.125 | N12: =M12 -> 24310.125 | O12: =N12 -> 24310.125 | ... R12: =Q12 -> 24310.125 | S12: =SUM(G12:R12) -> 291721.5
B14: Internet/Phone | F14: Growth(y-o-y)
B15: Year 1 | G15: 750 | H15: =G15 -> 750 | I15: =H15 -> 750 | J15: =I15 -> 750 | K15: =J15 -> 750 | L15: =K15 -> 750 | M15: =L15 -> 750 | N15: =M15 -> 750 | O15: =N15 -> 750 | ... R15: =Q15 -> 750 | S15: =SUM(G15:R15) -> 9000
B16: Year 2 | F16: 0.03 | G16: =R15*(1+$F16) -> 772.5 | H16: =G16 -> 772.5 | I16: =H16 -> 772.5 | J16: =I16 -> 772.5 | K16: =J16 -> 772.5 | L16: =K16 -> 772.5 | M16: =L16 -> 772.5 | N16: =M16 -> 772.5 | O16: =N16 -> 772.5 | ... R16: =Q16 -> 772.5 | S16: =SUM(G16:R16) -> 9270
B17: Year 3 | F17: 0.03 | G17: =R16*(1+$F17) -> 795.675 | H17: =G17 -> 795.675 | I17: =H17 -> 795.675 | J17: =I17 -> 795.675 | K17: =J17 -> 795.675 | L17: =K17 -> 795.675 | M17: =L17 -> 795.675 | N17: =M17 -> 795.675 | O17: =N17 -> 795.675 | ... R17: =Q17 -> 795.675 | S17: =SUM(G17:R17) -> 9548.1
B18: Year 4 | F18: 0.03 | G18: =(R17*(1+$F18))*2 -> 1639.0905 | H18: =G18 -> 1639.0905 | I18: =H18 -> 1639.0905 | J18: =I18 -> 1639.0905 | K18: =J18 -> 1639.0905 | L18: =K18 -> 1639.0905 | M18: =L18 -> 1639.0905 | N18: =M18 -> 1639.0905 | O18: =N18 -> 1639.0905 | ... R18: =Q18 -> 1639.0905 | S18: =SUM(G18:R18) -> 19669.086
B19: Year 5 | F19: 0.03 | G19: =R18*(1+$F19) -> 1688.2632 | H19: =G19 -> 1688.2632 | I19: =H19 -> 1688.2632 | J19: =I19 -> 1688.2632 | K19: =J19 -> 1688.2632 | L19: =K19 -> 1688.2632 | M19: =L19 -> 1688.2632 | N19: =M19 -> 1688.2632 | O19: =N19 -> 1688.2632 | ... R19: =Q19 -> 1688.2632 | S19: =SUM(G19:R19) -> 20259.159
B21: Insurance | F21: Growth(y-o-y)
B22: Year 1 | C22: Mission insurance accounted for as part of flight costs | G22: 3000 | H22: =G22 -> 3000 | I22: =H22 -> 3000 | J22: =I22 -> 3000 | K22: =J22 -> 3000 | L22: =K22 -> 3000 | M22: =L22 -> 3000 | N22: =M22 -> 3000 | O22: =N22*2 -> 6000 | P22: =O22 -> 6000 | Q22: =P22 -> 6000 | R22: =Q22 -> 6000 | S22: =SUM(G22:R22) -> 48000
B23: Year 2 | F23: 0.03 | G23: =R22*(1+$F23) -> 6180 | H23: 89430 | I23: 21000 | J23: 6000 | K23: 6000 | L23: 6000 | M23: 6000 | N23: 6000 | O23: 6000 | P23: 6000 | Q23: 6000 | R23: 6000 | S23: =SUM(G23:R23) -> 170610
B24: Year 3 | F24: 0.03 | G24: 12180 | H24: 194274 | I24: 31000 | J24: 6000 | K24: 6000 | L24: 6000 | M24: 6000 | N24: 6000 | O24: 6000 | P24: 6000 | Q24: 6000 | R24: 31000 | S24: =SUM(G24:R24) -> 316454
B25: Year 4 | F25: 0.03 | G25: 37930 | H25: 356947 | I25: 6000 | J25: 31000 | K25: 6000 | L25: 6000 | M25: 6000 | N25: 6000 | O25: 6000 | P25: 106000 | Q25: 6000 | R25: 106000 | S25: =SUM(G25:R25) -> 679877
B26: Year 5 | F26: 0.03 | G26: 140180 | H26: 706274 | I26: 6000 | J26: 106000 | K26: 6000 | L26: 6000 | M26: 6000 | N26: 6000 | O26: 6000 | P26: 106000 | Q26: 6000 | R26: 31000 | S26: =SUM(G26:R26) -> 1131454
B28: Professional Fees (consulting, legal, accounting, etc) | F28: Growth(y-o-y)
B29: Year 1 | G29: 3500 | H29: =G29 -> 3500 | I29: =H29 -> 3500 | J29: =I29 -> 3500 | K29: =J29 -> 3500 | L29: =K29 -> 3500 | M29: =L29 -> 3500 | N29: =M29 -> 3500 | O29: =N29 -> 3500 | ... R29: =Q29 -> 3500 | S29: =SUM(G29:R29) -> 42000
B30: Year 2 | F30: 0.03 | G30: =R29*(1+$F30) -> 3605 | H30: =G30 -> 3605 | I30: =H30 -> 3605 | J30: =I30 -> 3605 | K30: =J30 -> 3605 | L30: =K30 -> 3605 | M30: =L30 -> 3605 | N30: =M30 -> 3605 | O30: =N30 -> 3605 | ... R30: =Q30 -> 3605 | S30: =SUM(G30:R30) -> 43260
B31: Year 3 | F31: 0.03 | G31: =R30*(1+$F31) -> 3713.15 | H31: =G31 -> 3713.15 | I31: =H31 -> 3713.15 | J31: =I31 -> 3713.15 | K31: =J31 -> 3713.15 | L31: =K31 -> 3713.15 | M31: =L31 -> 3713.15 | N31: =M31 -> 3713.15 | O31: =N31 -> 3713.15 | ... R31: =Q31 -> 3713.15 | S31: =SUM(G31:R31) -> 44557.8
B32: Year 4 | F32: 0.03 | G32: =R31*(1+$F32) -> 3824.5445 | H32: =G32 -> 3824.5445 | I32: =H32 -> 3824.5445 | J32: =I32 -> 3824.5445 | K32: =J32 -> 3824.5445 | L32: =K32 -> 3824.5445 | M32: =L32 -> 3824.5445 | N32: =M32 -> 3824.5445 | O32: =N32 -> 3824.5445 | ... R32: =Q32 -> 3824.5445 | S32: =SUM(G32:R32) -> 45894.534
B33: Year 5 | F33: 0.03 | G33: =R32*(1+$F33) -> 3939.2808 | H33: =G33 -> 3939.2808 | I33: =H33 -> 3939.2808 | J33: =I33 -> 3939.2808 | K33: =J33 -> 3939.2808 | L33: =K33 -> 3939.2808 | M33: =L33 -> 3939.2808 | N33: =M33 -> 3939.2808 | O33: =N33 -> 3939.2808 | ... R33: =Q33 -> 3939.2808 | S33: =SUM(G33:R33) -> 47271.37 | T33: Torrence California Monthly lease Expense $33,000 plus personnel (included in Headcount)
F34: Buy 310 Wilmeth Basis | G34: 75000 sqft | H34: build out | I34: AC 75Ksf | J34: Insulation | K34: power | L34: Total for occ | M34: Credit | N34: Total | O34: Monthly rent NNN | P34: Monthly Taxes | Q34: Maintenance and power | R34: Total/month | T34: 75215.536
B35: Rent /Lease / Equipment/ Electricity | F35: Growth(y-o-y) | G35: office costs | H35: =20000*125 -> 2500000 | I35: =75000*8 -> 600000 | J35: =75000*3 -> 225000 | K35: 500000 | L35: =SUM(H35:K35) -> 3825000 | M35: =75000*8 -> 600000 | N35: =L35-M35 -> 3225000 | O35: =(7.75*75000)/12 -> 48437.5 | P35: =(3.25*75000)/12 -> 20312.5 | Q35: =((1*75000)/12)+6500 -> 12750 | R35: =SUM(O35:Q35) -> 81500
B36: Year 1 | G36: 40000 | H36: 40000 | I36: 40000 | J36: 40000 | K36: 40000 | L36: 40000 | M36: 40000 | N36: 40000 | O36: 40000 | P36: 40000 | Q36: 40000 | R36: 40000 | S36: =SUM(G36:R36) -> 480000
B37: Year 2 | F37: 0.04 | G37: =$R$36*(1+$F$37) -> 41600 | H37: =$R$36*(1+$F$37) -> 41600 | I37: =$R$36*(1+$F$37) -> 41600 | J37: =$R$36*(1+$F$37) -> 41600 | K37: =$R$36*(1+$F$37) -> 41600 | L37: =$R$36*(1+$F$37) -> 41600 | M37: =$R$36*(1+$F$37) -> 41600 | N37: =$R$36*(1+$F$37) -> 41600 | ... R37: =$R$36*(1+$F$37) -> 41600 | S37: =SUM(G37:R37) -> 499200
B38: Year 3 | F38: 0.04 | G38: =R37*(1+$F$37) -> 43264 | H38: =G38 -> 43264 | I38: =H38 -> 43264 | J38: =I38 -> 43264 | K38: =J38 -> 43264 | L38: =K38 -> 43264 | M38: =L38 -> 43264 | N38: =M38 -> 43264 | O38: =N38 -> 43264 | ... R38: =Q38 -> 43264 | S38: =SUM(G38:R38) -> 519168
B39: Year 4 | F39: 0.04 | G39: =R38*(1+$F$37)*2 -> 89989.12 | H39: =G39 -> 89989.12 | I39: =H39 -> 89989.12 | J39: =I39 -> 89989.12 | K39: =J39 -> 89989.12 | L39: =K39 -> 89989.12 | M39: =L39 -> 89989.12 | N39: =M39 -> 89989.12 | O39: =N39 -> 89989.12 | ... R39: =Q39 -> 89989.12 | S39: =SUM(G39:R39) -> 1079869.4
B40: Year 5 | F40: 0.04 | G40: =R39*(1+$F$37) -> 93588.685 | H40: =G40 -> 93588.685 | I40: =H40 -> 93588.685 | J40: =I40 -> 93588.685 | K40: =J40 -> 93588.685 | L40: =K40 -> 93588.685 | M40: =L40 -> 93588.685 | N40: =M40 -> 93588.685 | O40: =N40 -> 93588.685 | ... R40: =Q40 -> 93588.685 | S40: =SUM(G40:R40) -> 1123064.2
B42: Office Setup / Network / Computers / Software - Licensing | F42: Growth(y-o-y)
B43: Year 1 | G43: 5000 | H43: =G43 -> 5000 | I43: =H43 -> 5000 | J43: =I43 -> 5000 | K43: =J43 -> 5000 | L43: =K43 -> 5000 | M43: =L43 -> 5000 | N43: 10000 | O43: 10000 | P43: 5000 | Q43: 15000 | R43: 5000 | S43: =SUM(G43:R43) -> 80000
B44: Year 2 | F44: 0.03 | G44: 25000 | H44: 10000 | I44: 5000 | J44: 5000 | K44: 30000 | L44: 15000 | M44: 10000 | N44: 10000 | O44: 5000 | P44: 15000 | Q44: 5000 | R44: 30000 | S44: =SUM(G44:R44) -> 165000
B45: Year 3 | F45: 0.03 | G45: 30000 | H45: 35000 | I45: 0 | J45: 0 | K45: 0 | L45: 0 | M45: 5000 | N45: 5000 | O45: 5000 | P45: 5000 | Q45: 5000 | R45: 20000 | S45: =SUM(G45:R45) -> 110000
B46: Year 4 | F46: 0.03 | G46: 150000 | H46: 12640 | I46: 12640 | J46: 12640 | K46: 12640 | L46: 12640 | M46: 12640 | N46: 12640 | O46: 12640 | P46: 12640 | Q46: 12640 | R46: 12640 | S46: =SUM(G46:R46) -> 289040
B47: Year 5 | F47: 0.03 | G47: 15550 | H47: 15550 | I47: 15550 | J47: 15550 | K47: 15550 | L47: 15550 | M47: 15550 | N47: 15550 | O47: 15550 | P47: 15550 | Q47: 15550 | R47: 15550 | S47: =SUM(G47:R47) -> 186600
B49: Blank | F49: Growth(y-o-y)
B50: Year 1 | G50: 0 | H50: =G50 -> 0 | I50: =H50 -> 0 | J50: =I50 -> 0 | K50: =J50 -> 0 | L50: =K50 -> 0 | M50: =L50 -> 0 | N50: =M50 -> 0 | O50: =N50 -> 0 | ... R50: =Q50 -> 0 | S50: =SUM(G50:R50) -> 0
B51: Year 2 | F51: 0.02 | G51: =R50*(1+$F51) -> 0 | H51: =G51 -> 0 | I51: =H51 -> 0 | J51: =I51 -> 0 | K51: =J51 -> 0 | L51: =K51 -> 0 | M51: =L51 -> 0 | N51: =M51 -> 0 | O51: =N51 -> 0 | ... R51: =Q51 -> 0 | S51: =SUM(G51:R51) -> 0
B52: Year 3 | F52: 0.02 | G52: =R51*(1+$F52) -> 0 | H52: =G52 -> 0 | I52: =H52 -> 0 | J52: =I52 -> 0 | K52: =J52 -> 0 | L52: =K52 -> 0 | M52: =L52 -> 0 | N52: =M52 -> 0 | O52: =N52 -> 0 | ... R52: =Q52 -> 0 | S52: =SUM(G52:R52) -> 0
B53: Year 4 | F53: 0.02 | G53: =R52*(1+$F53) -> 0 | H53: =G53 -> 0 | I53: =H53 -> 0 | J53: =I53 -> 0 | K53: =J53 -> 0 | L53: =K53 -> 0 | M53: =L53 -> 0 | N53: =M53 -> 0 | O53: =N53 -> 0 | ... R53: =Q53 -> 0 | S53: =SUM(G53:R53) -> 0
B54: Year 5 | F54: 0.02 | G54: =R53*(1+$F54) -> 0 | H54: =G54 -> 0 | I54: =H54 -> 0 | J54: =I54 -> 0 | K54: =J54 -> 0 | L54: =K54 -> 0 | M54: =L54 -> 0 | N54: =M54 -> 0 | O54: =N54 -> 0 | ... R54: =Q54 -> 0 | S54: =SUM(G54:R54) -> 0
B57: Marketing | F57: Growth(y-o-y)
B58: Year 1 | G58: 15000 | H58: =G58 -> 15000 | I58: =H58 -> 15000 | J58: =I58 -> 15000 | K58: =J58 -> 15000 | L58: =K58 -> 15000 | M58: =L58 -> 15000 | N58: =M58 -> 15000 | O58: =N58 -> 15000 | ... R58: =Q58 -> 15000 | S58: =SUM(G58:R58) -> 180000
B59: Year 2 | F59: 0.1 | G59: =R58*(1+F59) -> 16500 | H59: =G59 -> 16500 | I59: =H59 -> 16500 | J59: =I59 -> 16500 | K59: =J59 -> 16500 | L59: =K59 -> 16500 | M59: =L59 -> 16500 | N59: =M59 -> 16500 | O59: =N59 -> 16500 | ... R59: =Q59 -> 16500 | S59: =SUM(G59:R59) -> 198000
B60: Year 3 | F60: 0.1 | G60: =R59*(1+F60) -> 18150 | H60: =G60 -> 18150 | I60: =H60 -> 18150 | J60: =I60 -> 18150 | K60: =J60 -> 18150 | L60: =K60 -> 18150 | M60: =L60 -> 18150 | N60: =M60 -> 18150 | O60: =N60 -> 18150 | ... R60: =Q60 -> 18150 | S60: =SUM(G60:R60) -> 217800
B61: Year 4 | F61: 0.1 | G61: =R60*(1+F61) -> 19965 | H61: =G61 -> 19965 | I61: =H61 -> 19965 | J61: =I61 -> 19965 | K61: =J61 -> 19965 | L61: =K61 -> 19965 | M61: =L61 -> 19965 | N61: =M61 -> 19965 | O61: =N61 -> 19965 | ... R61: =Q61 -> 19965 | S61: =SUM(G61:R61) -> 239580
B62: Year 5 | F62: 0.1 | G62: =R61*(1+F62) -> 21961.5 | H62: =G62 -> 21961.5 | I62: =H62 -> 21961.5 | J62: =I62 -> 21961.5 | K62: =J62 -> 21961.5 | L62: =K62 -> 21961.5 | M62: =L62 -> 21961.5 | N62: =M62 -> 21961.5 | O62: =N62 -> 21961.5 | ... R62: =Q62 -> 21961.5 | S62: =SUM(G62:R62) -> 263538
F63: Company Confidential
B64: Travel Expenses | F64: Growth(y-o-y)
B65: Year 1 | G65: 20000 | H65: =G65 -> 20000 | I65: =H65 -> 20000 | J65: =I65 -> 20000 | K65: =J65 -> 20000 | L65: =K65 -> 20000 | M65: =L65 -> 20000 | N65: =M65 -> 20000 | O65: =N65 -> 20000 | P65: =N65 -> 20000 | Q65: =P65 -> 20000 | R65: =Q65 -> 20000 | S65: =SUM(G65:R65) -> 240000
B66: Year 2 | E66: FOR SALES ONLY | F66: 1.03 | G66: =G65*F66 -> 20600 | H66: =G66 -> 20600 | I66: =H66 -> 20600 | J66: =I66 -> 20600 | K66: =J66 -> 20600 | L66: =K66 -> 20600 | M66: =L66 -> 20600 | N66: =M66 -> 20600 | O66: =N66 -> 20600 | ... R66: =Q66 -> 20600 | S66: =SUM(G66:R66) -> 247200
B67: Year 3 | F67: 0.03 | G67: =R66*(1+$F67) -> 21218 | H67: =G67 -> 21218 | I67: =H67 -> 21218 | J67: =I67 -> 21218 | K67: =J67 -> 21218 | L67: =K67 -> 21218 | M67: =L67 -> 21218 | N67: =M67 -> 21218 | O67: =N67 -> 21218 | ... R67: =Q67 -> 21218 | S67: =SUM(G67:R67) -> 254616
B68: Year 4 | F68: 0.03 | G68: =R67*(1+$F68) -> 21854.54 | H68: =G68 -> 21854.54 | I68: =H68 -> 21854.54 | J68: =I68 -> 21854.54 | K68: =J68 -> 21854.54 | L68: =K68 -> 21854.54 | M68: =L68 -> 21854.54 | N68: =M68 -> 21854.54 | O68: =N68 -> 21854.54 | ... R68: =Q68 -> 21854.54 | S68: =SUM(G68:R68) -> 262254.48
B69: Year 5 | F69: 0.03 | G69: =R68*(1+$F69) -> 22510.176 | H69: =G69 -> 22510.176 | I69: =H69 -> 22510.176 | J69: =I69 -> 22510.176 | K69: =J69 -> 22510.176 | L69: =K69 -> 22510.176 | M69: =L69 -> 22510.176 | N69: =M69 -> 22510.176 | O69: =N69 -> 22510.176 | ... R69: =Q69 -> 22510.176 | S69: =SUM(G69:R69) -> 270122.11
B71: Debt Service
B72: Year 1 | E72: 0 | F72: 0 | G72: 10000 | H72: 10000 | I72: 10000 | J72: 10000 | K72: 10000 | L72: 10000 | M72: 10000 | N72: 10000 | O72: 10000 | P72: 10000 | Q72: 10000 | R72: 10000 | S72: =SUM(G72:R72) -> 120000
B73: Year 2 | E73: 0 | F73: 0 | G73: 10000 | H73: 10000 | I73: 10000 | J73: 10000 | K73: 10000 | L73: 10000 | M73: 10000 | N73: 10000 | O73: 10000 | P73: 10000 | Q73: 10000 | R73: 10000 | S73: =SUM(G73:R73) -> 120000
B74: Year 3 | E74: 0 | F74: 0 | G74: 10000 | H74: 10000 | I74: 10000 | J74: 10000 | K74: 10000 | L74: 10000 | M74: 10000 | N74: 10000 | O74: 10000 | P74: 10000 | Q74: 10000 | R74: 10000 | S74: =SUM(G74:R74) -> 120000
B75: Year 4 | E75: 0 | F75: 0 | G75: 0 | H75: 0 | I75: 0 | J75: 0 | K75: 0 | L75: 0 | M75: 0 | N75: 0 | O75: 0 | P75: 0 | Q75: 0 | R75: 0 | S75: =SUM(G75:R75) -> 0
B76: Year 5 | E76: 0 | F76: 0 | G76: 0 | H76: 0 | I76: 0 | J76: 0 | K76: 0 | L76: 0 | M76: 0 | N76: 0 | O76: 0 | P76: 0 | Q76: 0 | R76: 0 | S76: =SUM(G76:R76) -> 0
B78: RESEARCH AND DEVELOPMENT | D78: non capital | F78: Growth(y-o-y)
B79: Year 1 | C79: testing hardware non capital R&D | G79: 5000 | H79: =G79 -> 5000 | I79: =H79 -> 5000 | J79: =I79 -> 5000 | K79: =J79 -> 5000 | L79: =K79 -> 5000 | M79: =L79 -> 5000 | N79: =M79 -> 5000 | O79: =N79 -> 5000 | ... R79: =Q79 -> 5000 | S79: =SUM(G79:R79) -> 60000
B80: Year 2 | C80: testing hardware non capital R&D | F80: 0.03 | G80: 20000 | H80: =G80 -> 20000 | I80: =H80 -> 20000 | J80: =I80 -> 20000 | K80: =J80 -> 20000 | L80: =K80 -> 20000 | M80: =L80 -> 20000 | N80: =M80 -> 20000 | O80: =N80 -> 20000 | ... R80: =Q80 -> 20000 | S80: =SUM(G80:R80) -> 240000
B81: Year 3 | C81: testing hardware non capital R&D | F81: 0.03 | G81: 20000 | H81: =G81 -> 20000 | I81: =H81 -> 20000 | J81: =I81 -> 20000 | K81: =J81 -> 20000 | L81: =K81 -> 20000 | M81: =L81 -> 20000 | N81: =M81 -> 20000 | O81: =N81 -> 20000 | ... R81: =Q81 -> 20000 | S81: =SUM(G81:R81) -> 240000
B82: Year 4 | C82: testing hardware non capital R&D | F82: 0.03 | G82: 20000 | H82: =G82 -> 20000 | I82: =H82 -> 20000 | J82: =I82 -> 20000 | K82: =J82 -> 20000 | L82: =K82 -> 20000 | M82: =L82 -> 20000 | N82: =M82 -> 20000 | O82: =N82 -> 20000 | ... R82: =Q82 -> 20000 | S82: =SUM(G82:R82) -> 240000
B83: Year 5 | C83: testing hardware non capital R&D | F83: 0.03 | G83: 20000 | H83: =G83 -> 20000 | I83: =H83 -> 20000 | J83: =I83 -> 20000 | K83: =J83 -> 20000 | L83: =K83 -> 20000 | M83: =L83 -> 20000 | N83: =M83 -> 20000 | O83: =N83 -> 20000 | ... R83: =Q83 -> 20000 | S83: =SUM(G83:R83) -> 240000
B85: Total Research and Development Expense
B86: Year 1 | G86: =G8+G15+G22+G29+G36+G43++G50+G58+G65+G79 -> 97250 | H86: =H8+H15+H22+H29+H36+H43++H50+H58+H65+H79 -> 97250 | I86: =I8+I15+I22+I29+I36+I43++I50+I58+I65+I79 -> 97250 | J86: =J8+J15+J22+J29+J36+J43++J50+J58+J65+J79 -> 97250 | K86: =K8+K15+K22+K29+K36+K43++K50+K58+K65+K79 -> 97250 | L86: =L8+L15+L22+L29+L36+L43++L50+L58+L65+L79 -> 97250 | M86: =M8+M15+M22+M29+M36+M43++M50+M58+M65+M79 -> 97250 | N86: =N8+N15+N22+N29+N36+N43++N50+N58+N65+N79 -> 102250 | ... S86: =S8+S15+S22+S29+S36+S43++S50+S58+S65+S79 -> 1199000
B87: Year 2 | G87: =G9+G16+G23+G30+G37+G44++G51+G59+G66+G80 -> 139507.5 | H87: =H9+H16+H23+H30+H37+H44++H51+H59+H66+H80 -> 207757.5 | I87: =I9+I16+I23+I30+I37+I44++I51+I59+I66+I80 -> 134327.5 | J87: =J9+J16+J23+J30+J37+J44++J51+J59+J66+J80 -> 119327.5 | K87: =K9+K16+K23+K30+K37+K44++K51+K59+K66+K80 -> 144327.5 | L87: =L9+L16+L23+L30+L37+L44++L51+L59+L66+L80 -> 129327.5 | M87: =M9+M16+M23+M30+M37+M44++M51+M59+M66+M80 -> 124327.5 | N87: =N9+N16+N23+N30+N37+N44++N51+N59+N66+N80 -> 124327.5 | ... S87: =S9+S16+S23+S30+S37+S44++S51+S59+S66+S80 -> 1635540
B88: Year 3 | G88: =G10+G17+G24+G31+G38+G45++G52+G60+G67+G81 -> 154833.33 | H88: =H10+H17+H24+H31+H38+H45++H52+H60+H67+H81 -> 341927.32 | I88: =I10+I17+I24+I31+I38+I45++I52+I60+I67+I81 -> 143653.33 | J88: =J10+J17+J24+J31+J38+J45++J52+J60+J67+J81 -> 118653.32 | K88: =K10+K17+K24+K31+K38+K45++K52+K60+K67+K81 -> 118653.32 | L88: =L10+L17+L24+L31+L38+L45++L52+L60+L67+L81 -> 118653.32 | M88: =M10+M17+M24+M31+M38+M45++M52+M60+M67+M81 -> 123653.32 | N88: =N10+N17+N24+N31+N38+N45++N52+N60+N67+N81 -> 123653.32 | ... S88: =S10+S17+S24+S31+S38+S45++S52+S60+S67+S81 -> 1778293.9
B89: Year 4 | G89: =G11+G18+G25+G32+G39+G46++G53+G61+G68+G82 -> 368354.79 | H89: =H11+H18+H25+H32+H39+H46++H53+H61+H68+H82 -> 550011.8 | I89: =I11+I18+I25+I32+I39+I46++I53+I61+I68+I82 -> 199064.8 | J89: =J11+J18+J25+J32+J39+J46++J53+J61+J68+J82 -> 224064.8 | K89: =K11+K18+K25+K32+K39+K46++K53+K61+K68+K82 -> 199064.8 | L89: =L11+L18+L25+L32+L39+L46++L53+L61+L68+L82 -> 199064.8 | M89: =M11+M18+M25+M32+M39+M46++M53+M61+M68+M82 -> 199064.8 | N89: =N11+N18+N25+N32+N39+N46++N53+N61+N68+N82 -> 199064.8 | ... S89: =S11+S18+S25+S32+S39+S46++S53+S61+S68+S82 -> 3134014.5
B90: Year 5 | G90: =G12+G19+G26+G33+G40+G47++G54+G62+G69+G83 -> 343728.03 | H90: =H12+H19+H26+H33+H40+H47++H54+H62+H69+H83 -> 909822.03 | I90: =I12+I19+I26+I33+I40+I47++I54+I62+I69+I83 -> 209548.03 | J90: =J12+J19+J26+J33+J40+J47++J54+J62+J69+J83 -> 309548.03 | K90: =K12+K19+K26+K33+K40+K47++K54+K62+K69+K83 -> 209548.03 | L90: =L12+L19+L26+L33+L40+L47++L54+L62+L69+L83 -> 209548.03 | M90: =M12+M19+M26+M33+M40+M47++M54+M62+M69+M83 -> 209548.03 | N90: =N12+N19+N26+N33+N40+N47++N54+N62+N69+N83 -> 209548.03 | ... S90: =S12+S19+S26+S33+S40+S47++S54+S62+S69+S83 -> 3574030.4
B92: Tax Rate | D92: 0.21
B95: Balance Sheet Assumptions
B96: Current Liabilities Turnover (number of days) | D96: 30 | E96: Of total expenses
B97: Current Assets Excluding Cash (number of days) | D97: 15 | E97: Of total revenue
B98: Prepaid Expenses (% of Sales) | D98: 0.02 | E98: of Net Sales
B99: Days in Inventory | D99: 30 | E99: days
B100: Other Current Assets (% of sales) | D100: 0.02 | E100: of Net sales
B101: Accrued Expenses (number of days) | D101: 30 | E101: days
B102: Other Current Liabilities (% of sales) | D102: 0.02 | E102: of Net Sales

Sheet Expense Assumptions
A1: EXOS Aerospace
A2: Expense Assumptions Sheet | B2: =Controls!C1 -> July | C2: =TEXT(DATE(2000, MATCH(B2, {"January","February","March","April","May","June","July","August","September","October","November","December"}, 0) + 1, 1), "mmmm") -> August | D2: =TEXT(DATE(2000, MATCH(C2, {"January","February","March","April","May","June","July","August","September","October","November","December"}, 0) + 1, 1), "mmmm") -> September | E2: =TEXT(DATE(2000, MATCH(D2, {"January","February","March","April","May","June","July","August","September","October","November","December"}, 0) + 1, 1), "mmmm") -> October | F2: =TEXT(DATE(2000, MATCH(E2, {"January","February","March","April","May","June","July","August","September","October","November","December"}, 0) + 1, 1), "mmmm") -> November | G2: =TEXT(DATE(2000, MATCH(F2, {"January","February","March","April","May","June","July","August","September","October","November","December"}, 0) + 1, 1), "mmmm") -> December | H2: =TEXT(DATE(2000, MATCH(G2, {"January","February","March","April","May","June","July","August","September","October","November","December"}, 0) + 1, 1), "mmmm") -> January | I2: =TEXT(DATE(2000, MATCH(H2, {"January","February","March","April","May","June","July","August","September","October","November","December"}, 0) + 1, 1), "mmmm") -> February | J2: =TEXT(DATE(2000, MATCH(I2, {"January","February","March","April","May","June","July","August","September","October","November","December"}, 0) + 1, 1), "mmmm") -> March | ... BI2: =TEXT(DATE(2000, MATCH(BH2, {"January","February","March","April","May","June","July","August","September","October","November","December"}, 0) + 1, 1), "mmmm") -> June
A3: Amounts in USD | B3: 1 | C3: =IF(MOD(B4,B5) = 0,B3+1,B3) -> 1 | D3: =IF(MOD(C4,C5) = 0,C3+1,C3) -> 1 | E3: =IF(MOD(D4,D5) = 0,D3+1,D3) -> 1 | F3: =IF(MOD(E4,E5) = 0,E3+1,E3) -> 1 | G3: =IF(MOD(F4,F5) = 0,F3+1,F3) -> 1 | H3: =IF(MOD(G4,G5) = 0,G3+1,G3) -> 1 | I3: =IF(MOD(H4,H5) = 0,H3+1,H3) -> 1 | J3: =IF(MOD(I4,I5) = 0,I3+1,I3) -> 1 | ... BI3: =IF(MOD(BH4,BH5) = 0,BH3+1,BH3) -> 5
A4: Back To Index | B4: 1 | C4: =B4+1 -> 2 | D4: =C4+1 -> 3 | E4: =D4+1 -> 4 | F4: =E4+1 -> 5 | G4: =F4+1 -> 6 | H4: =G4+1 -> 7 | I4: =H4+1 -> 8 | J4: =I4+1 -> 9 | ... BI4: =BH4+1 -> 60
A5: Assumptions for the Monthly Period | B5: 12 | C5: 12 | D5: 12 | E5: 12 | F5: 12 | G5: 12 | H5: 12 | I5: 12 | J5: 12 | K5: 12 | L5: 12 | M5: 12 | N5: 12 | O5: 12 | P5: 12 | Q5: 12 | R5: 12 | S5: 12 | T5: 12 | U5: 12 | V5: 12 | W5: 12 | X5: 12 | Y5: 12 | Z5: 12 | AA5: 12 | AB5: 12 | AC5: 12 | AD5: 12 | AE5: 12 | AF5: 12 | AG5: 12 | AH5: 12 | AI5: 12 | AJ5: 12 | AK5: 12 | AL5: 12 | AM5: 12 | AN5: 12 | AO5: 12 | AP5: 12 | AQ5: 12 | AR5: 12 | AS5: 12 | AT5: 12 | AU5: 12 | AV5: 12 | AW5: 12 | AX5: 12 | AY5: 12 | AZ5: 12 | BA5: 12 | BB5: 12 | BC5: 12 | BD5: 12 | BE5: 12 | BF5: 12 | BG5: 12 | BH5: 12 | BI5: 12
A7: Cost of Sale (COS)
A9: BLK4 360kg LAUNCHER - COGS - Wet Lease | B9: =HLOOKUP(B$3,Controls!$A$5:$F$96,MATCH('Expense Assumptions'!$A9,Controls!$A$5:$A$96,0),0)*'Revenue Asumptions'!B9 -> 0 | C9: =HLOOKUP(C$3,Controls!$A$5:$F$96,MATCH('Expense Assumptions'!$A9,Controls!$A$5:$A$96,0),0)*'Revenue Asumptions'!C9 -> 0 | D9: =HLOOKUP(D$3,Controls!$A$5:$F$96,MATCH('Expense Assumptions'!$A9,Controls!$A$5:$A$96,0),0)*'Revenue Asumptions'!D9 -> 0 | E9: =HLOOKUP(E$3,Controls!$A$5:$F$96,MATCH('Expense Assumptions'!$A9,Controls!$A$5:$A$96,0),0)*'Revenue Asumptions'!E9 -> 0 | F9: =HLOOKUP(F$3,Controls!$A$5:$F$96,MATCH('Expense Assumptions'!$A9,Controls!$A$5:$A$96,0),0)*'Revenue Asumptions'!F9 -> 0 | G9: =HLOOKUP(G$3,Controls!$A$5:$F$96,MATCH('Expense Assumptions'!$A9,Controls!$A$5:$A$96,0),0)*'Revenue Asumptions'!G9 -> 0 | H9: =HLOOKUP(H$3,Controls!$A$5:$F$96,MATCH('Expense Assumptions'!$A9,Controls!$A$5:$A$96,0),0)*'Revenue Asumptions'!H9 -> 0 | I9: =HLOOKUP(I$3,Controls!$A$5:$F$96,MATCH('Expense Assumptions'!$A9,Controls!$A$5:$A$96,0),0)*'Revenue Asumptions'!I9 -> 0 | ... BI9: =HLOOKUP(BI$3,Controls!$A$5:$F$96,MATCH('Expense Assumptions'!$A9,Controls!$A$5:$A$96,0),0)*'Revenue Asumptions'!BI9 -> 0
A10: BLK4 360kg LAUNCHER - COGS - Vehicle Launch | B10: =HLOOKUP(B$3,Controls!$A$5:$F$96,MATCH('Expense Assumptions'!$A10,Controls!$A$5:$A$96,0),0)*'Revenue Asumptions'!B11 -> 0 | C10: =HLOOKUP(C$3,Controls!$A$5:$F$96,MATCH('Expense Assumptions'!$A10,Controls!$A$5:$A$96,0),0)*'Revenue Asumptions'!C11 -> 0 | D10: =HLOOKUP(D$3,Controls!$A$5:$F$96,MATCH('Expense Assumptions'!$A10,Controls!$A$5:$A$96,0),0)*'Revenue Asumptions'!D11 -> 0 | E10: =HLOOKUP(E$3,Controls!$A$5:$F$96,MATCH('Expense Assumptions'!$A10,Controls!$A$5:$A$96,0),0)*'Revenue Asumptions'!E11 -> 0 | F10: =HLOOKUP(F$3,Controls!$A$5:$F$96,MATCH('Expense Assumptions'!$A10,Controls!$A$5:$A$96,0),0)*'Revenue Asumptions'!F11 -> 0 | G10: =HLOOKUP(G$3,Controls!$A$5:$F$96,MATCH('Expense Assumptions'!$A10,Controls!$A$5:$A$96,0),0)*'Revenue Asumptions'!G11 -> 0 | H10: =HLOOKUP(H$3,Controls!$A$5:$F$96,MATCH('Expense Assumptions'!$A10,Controls!$A$5:$A$96,0),0)*'Revenue Asumptions'!H11 -> 0 | I10: =HLOOKUP(I$3,Controls!$A$5:$F$96,MATCH('Expense Assumptions'!$A10,Controls!$A$5:$A$96,0),0)*'Revenue Asumptions'!I11 -> 0 | ... BI10: =HLOOKUP(BI$3,Controls!$A$5:$F$96,MATCH('Expense Assumptions'!$A10,Controls!$A$5:$A$96,0),0)*'Revenue Asumptions'!BI11 -> 0
A11: PROPULSION SYSTEM SALES 5K 20K DESIGNS WITH TRIFDYNE PRESS - COGS | B11: =HLOOKUP(B$3,Controls!$A$5:$F$96,MATCH('Expense Assumptions'!$A11,Controls!$A$5:$A$96,0),0)*'Revenue Asumptions'!B46 -> 0 | C11: =HLOOKUP(C$3,Controls!$A$5:$F$96,MATCH('Expense Assumptions'!$A11,Controls!$A$5:$A$96,0),0)*'Revenue Asumptions'!C46 -> 0 | D11: =HLOOKUP(D$3,Controls!$A$5:$F$96,MATCH('Expense Assumptions'!$A11,Controls!$A$5:$A$96,0),0)*'Revenue Asumptions'!D46 -> 125000 | E11: =HLOOKUP(E$3,Controls!$A$5:$F$96,MATCH('Expense Assumptions'!$A11,Controls!$A$5:$A$96,0),0)*'Revenue Asumptions'!E46 -> 50000 | F11: =HLOOKUP(F$3,Controls!$A$5:$F$96,MATCH('Expense Assumptions'!$A11,Controls!$A$5:$A$96,0),0)*'Revenue Asumptions'!F46 -> 125000 | G11: =HLOOKUP(G$3,Controls!$A$5:$F$96,MATCH('Expense Assumptions'!$A11,Controls!$A$5:$A$96,0),0)*'Revenue Asumptions'!G46 -> 250000 | H11: =HLOOKUP(H$3,Controls!$A$5:$F$96,MATCH('Expense Assumptions'!$A11,Controls!$A$5:$A$96,0),0)*'Revenue Asumptions'!H46 -> 200000 | I11: =HLOOKUP(I$3,Controls!$A$5:$F$96,MATCH('Expense Assumptions'!$A11,Controls!$A$5:$A$96,0),0)*'Revenue Asumptions'!I46 -> 200000 | ... BI11: =HLOOKUP(BI$3,Controls!$A$5:$F$96,MATCH('Expense Assumptions'!$A11,Controls!$A$5:$A$96,0),0)*'Revenue Asumptions'!BI46 -> 1708333.3
A12: EXOS US BLK4 Wet Lease Launches - COGS | B12: =HLOOKUP(B$3,Controls!$A$5:$F$96,MATCH('Expense Assumptions'!$A12,Controls!$A$5:$A$96,0),0)*'Revenue Asumptions'!B61 -> 0 | C12: =HLOOKUP(C$3,Controls!$A$5:$F$96,MATCH('Expense Assumptions'!$A12,Controls!$A$5:$A$96,0),0)*'Revenue Asumptions'!C61 -> 0 | D12: =HLOOKUP(D$3,Controls!$A$5:$F$96,MATCH('Expense Assumptions'!$A12,Controls!$A$5:$A$96,0),0)*'Revenue Asumptions'!D61 -> 0 | E12: =HLOOKUP(E$3,Controls!$A$5:$F$96,MATCH('Expense Assumptions'!$A12,Controls!$A$5:$A$96,0),0)*'Revenue Asumptions'!E61 -> 0 | F12: =HLOOKUP(F$3,Controls!$A$5:$F$96,MATCH('Expense Assumptions'!$A12,Controls!$A$5:$A$96,0),0)*'Revenue Asumptions'!F61 -> 0 | G12: =HLOOKUP(G$3,Controls!$A$5:$F$96,MATCH('Expense Assumptions'!$A12,Controls!$A$5:$A$96,0),0)*'Revenue Asumptions'!G61 -> 0 | H12: =HLOOKUP(H$3,Controls!$A$5:$F$96,MATCH('Expense Assumptions'!$A12,Controls!$A$5:$A$96,0),0)*'Revenue Asumptions'!H61 -> 0 | I12: =HLOOKUP(I$3,Controls!$A$5:$F$96,MATCH('Expense Assumptions'!$A12,Controls!$A$5:$A$96,0),0)*'Revenue Asumptions'!I61 -> 0 | ... BI12: =HLOOKUP(BI$3,Controls!$A$5:$F$96,MATCH('Expense Assumptions'!$A12,Controls!$A$5:$A$96,0),0)*'Revenue Asumptions'!BI61 -> 0
A13: ='Revenue Asumptions'!A63 -> NOTE: $10M Series A enables this trajectory. Dual listing: Euronext Dublin (immediate) + TXSE (Year 2) | B13: =HLOOKUP(B$3,Controls!$A$5:$F$96,MATCH('Expense Assumptions'!$A13,Controls!$A$5:$A$96,0),0)*'Revenue Asumptions'!B76 -> #N/A | C13: =HLOOKUP(C$3,Controls!$A$5:$F$96,MATCH('Expense Assumptions'!$A13,Controls!$A$5:$A$96,0),0)*'Revenue Asumptions'!C76 -> #N/A | D13: =HLOOKUP(D$3,Controls!$A$5:$F$96,MATCH('Expense Assumptions'!$A13,Controls!$A$5:$A$96,0),0)*'Revenue Asumptions'!D76 -> #N/A | E13: =HLOOKUP(E$3,Controls!$A$5:$F$96,MATCH('Expense Assumptions'!$A13,Controls!$A$5:$A$96,0),0)*'Revenue Asumptions'!E76 -> #N/A | F13: =HLOOKUP(F$3,Controls!$A$5:$F$96,MATCH('Expense Assumptions'!$A13,Controls!$A$5:$A$96,0),0)*'Revenue Asumptions'!F76 -> #N/A | G13: =HLOOKUP(G$3,Controls!$A$5:$F$96,MATCH('Expense Assumptions'!$A13,Controls!$A$5:$A$96,0),0)*'Revenue Asumptions'!G76 -> #N/A | H13: =HLOOKUP(H$3,Controls!$A$5:$F$96,MATCH('Expense Assumptions'!$A13,Controls!$A$5:$A$96,0),0)*'Revenue Asumptions'!H76 -> #N/A | I13: =HLOOKUP(I$3,Controls!$A$5:$F$96,MATCH('Expense Assumptions'!$A13,Controls!$A$5:$A$96,0),0)*'Revenue Asumptions'!I76 -> #N/A | ... BI13: =HLOOKUP(BI$3,Controls!$A$5:$F$96,MATCH('Expense Assumptions'!$A13,Controls!$A$5:$A$96,0),0)*'Revenue Asumptions'!BI76 -> #N/A
A14: Scorpius Space Corp Tank Manufacture - COGS | B14: =HLOOKUP(B$3,Controls!$A$5:$F$96,MATCH('Expense Assumptions'!$A14,Controls!$A$5:$A$96,0),0)*('Revenue Asumptions'!B89) -> 92960 | C14: =HLOOKUP(C$3,Controls!$A$5:$F$96,MATCH('Expense Assumptions'!$A14,Controls!$A$5:$A$96,0),0)*('Revenue Asumptions'!C89) -> 47355 | D14: =HLOOKUP(D$3,Controls!$A$5:$F$96,MATCH('Expense Assumptions'!$A14,Controls!$A$5:$A$96,0),0)*('Revenue Asumptions'!D89) -> 75250 | E14: =HLOOKUP(E$3,Controls!$A$5:$F$96,MATCH('Expense Assumptions'!$A14,Controls!$A$5:$A$96,0),0)*('Revenue Asumptions'!E89) -> 189644 | F14: =HLOOKUP(F$3,Controls!$A$5:$F$96,MATCH('Expense Assumptions'!$A14,Controls!$A$5:$A$96,0),0)*('Revenue Asumptions'!F89) -> 202475 | G14: =HLOOKUP(G$3,Controls!$A$5:$F$96,MATCH('Expense Assumptions'!$A14,Controls!$A$5:$A$96,0),0)*('Revenue Asumptions'!G89) -> 192360 | H14: =HLOOKUP(H$3,Controls!$A$5:$F$96,MATCH('Expense Assumptions'!$A14,Controls!$A$5:$A$96,0),0)*('Revenue Asumptions'!H89) -> 113470 | I14: =HLOOKUP(I$3,Controls!$A$5:$F$96,MATCH('Expense Assumptions'!$A14,Controls!$A$5:$A$96,0),0)*('Revenue Asumptions'!I89) -> 188125 | ... BI14: =HLOOKUP(BI$3,Controls!$A$5:$F$96,MATCH('Expense Assumptions'!$A14,Controls!$A$5:$A$96,0),0)*('Revenue Asumptions'!BI89) -> 1447558.6
A15: Sarge Technology and Hardware Sales - COGS | B15: =HLOOKUP(B$3,Controls!$A$5:$F$96,MATCH('Expense Assumptions'!$A15,Controls!$A$5:$A$96,0),0)*('Revenue Asumptions'!B102) -> 0 | C15: =HLOOKUP(C$3,Controls!$A$5:$F$96,MATCH('Expense Assumptions'!$A15,Controls!$A$5:$A$96,0),0)*('Revenue Asumptions'!C102) -> 0 | D15: =HLOOKUP(D$3,Controls!$A$5:$F$96,MATCH('Expense Assumptions'!$A15,Controls!$A$5:$A$96,0),0)*('Revenue Asumptions'!D102) -> 0 | E15: =HLOOKUP(E$3,Controls!$A$5:$F$96,MATCH('Expense Assumptions'!$A15,Controls!$A$5:$A$96,0),0)*('Revenue Asumptions'!E102) -> 0 | F15: =HLOOKUP(F$3,Controls!$A$5:$F$96,MATCH('Expense Assumptions'!$A15,Controls!$A$5:$A$96,0),0)*('Revenue Asumptions'!F102) -> 0 | G15: =HLOOKUP(G$3,Controls!$A$5:$F$96,MATCH('Expense Assumptions'!$A15,Controls!$A$5:$A$96,0),0)*('Revenue Asumptions'!G102) -> 0 | H15: =HLOOKUP(H$3,Controls!$A$5:$F$96,MATCH('Expense Assumptions'!$A15,Controls!$A$5:$A$96,0),0)*('Revenue Asumptions'!H102) -> 0 | I15: =HLOOKUP(I$3,Controls!$A$5:$F$96,MATCH('Expense Assumptions'!$A15,Controls!$A$5:$A$96,0),0)*('Revenue Asumptions'!I102) -> 0 | ... BI15: =HLOOKUP(BI$3,Controls!$A$5:$F$96,MATCH('Expense Assumptions'!$A15,Controls!$A$5:$A$96,0),0)*('Revenue Asumptions'!BI102) -> 0
A16: TACFI/STRATFI RDRE Program COGS (est. 70% of revenue) | B16: 0 | C16: 0 | D16: 0 | E16: 0 | F16: 0 | G16: 0 | H16: 0 | I16: 0 | J16: 0 | K16: 0 | L16: 0 | M16: 0 | N16: 0 | O16: 0 | P16: 0 | Q16: 155555.55 | R16: 155555.55 | S16: 155555.55 | T16: 155555.55 | U16: 155555.55 | V16: 155555.55 | W16: 155555.55 | X16: 155555.55 | Y16: 155555.55 | Z16: 155555.55 | AA16: 155555.55 | AB16: 155555.55 | AC16: 155555.55 | AD16: 155555.55 | AE16: 155555.55 | AF16: 155555.55 | AG16: 155555.55 | AH16: 155555.55 | AI16: 583333.33 | AJ16: 583333.33 | AK16: 583333.33 | AL16: 583333.33 | AM16: 583333.33 | AN16: 583333.33 | AO16: 583333.33 | AP16: 583333.33 | AQ16: 583333.33 | AR16: 583333.33 | AS16: 583333.33 | AT16: 583333.33 | AU16: 583333.33 | AV16: 583333.33 | AW16: 583333.33 | AX16: 583333.33 | AY16: 583333.33 | AZ16: 583333.33 | BA16: 583333.33 | BB16: 583333.33 | BC16: 583333.33 | BD16: 583333.33 | BE16: 583333.33 | BF16: 583333.33 | BG16: 583333.33 | BH16: 583333.33 | BI16: 583333.33
A17: Scorpius Tank Manufacturing COGS (est. 55% of revenue) | T17: 137500 | U17: 137500 | V17: 137500 | W17: 137500 | X17: 137500 | Y17: 137500 | Z17: 137500 | AA17: 137500 | AB17: 137500 | AC17: 137500 | AD17: 137500 | AE17: 137500 | AF17: 229166.85 | AG17: 229166.85 | AH17: 229166.85 | AI17: 229166.85 | AJ17: 229166.85 | AK17: 229166.85 | AL17: 229166.85 | AM17: 229166.85 | AN17: 229166.85 | AO17: 229166.85 | AP17: 229166.85 | AQ17: 229166.85 | AR17: 366666.85 | AS17: 366666.85 | AT17: 366666.85 | AU17: 366666.85 | AV17: 366666.85 | AW17: 366666.85 | AX17: 366666.85 | AY17: 366666.85 | AZ17: 366666.85 | BA17: 366666.85 | BB17: 366666.85 | BC17: 366666.85 | BD17: 504166.85 | BE17: 504166.85 | BF17: 504166.85 | BG17: 504166.85 | BH17: 504166.85 | BI17: 504166.85
A18: Total Cost of Sale (COS) | B18: =SUM(B9:B16) -> #N/A | C18: =SUM(C9:C16) -> #N/A | D18: =SUM(D9:D16) -> #N/A | E18: =SUM(E9:E16) -> #N/A | F18: =SUM(F9:F16) -> #N/A | G18: =SUM(G9:G16) -> #N/A | H18: =SUM(H9:H16) -> #N/A | I18: =SUM(I9:I16) -> #N/A | ... BI18: =SUM(BI9:BI16) -> #N/A
A20: Operating Expenses (OPEX)
A22: Internet and Phone | B22: =HLOOKUP(B$3,Controls!$A$5:$F$96,MATCH('Expense Assumptions'!$A22,Controls!$A$5:$A$96,0),0) -> 750 | C22: =HLOOKUP(C$3,Controls!$A$5:$F$96,MATCH('Expense Assumptions'!$A22,Controls!$A$5:$A$96,0),0) -> 750 | D22: =HLOOKUP(D$3,Controls!$A$5:$F$96,MATCH('Expense Assumptions'!$A22,Controls!$A$5:$A$96,0),0) -> 750 | E22: =HLOOKUP(E$3,Controls!$A$5:$F$96,MATCH('Expense Assumptions'!$A22,Controls!$A$5:$A$96,0),0) -> 750 | F22: =HLOOKUP(F$3,Controls!$A$5:$F$96,MATCH('Expense Assumptions'!$A22,Controls!$A$5:$A$96,0),0) -> 750 | G22: =HLOOKUP(G$3,Controls!$A$5:$F$96,MATCH('Expense Assumptions'!$A22,Controls!$A$5:$A$96,0),0) -> 750 | H22: =HLOOKUP(H$3,Controls!$A$5:$F$96,MATCH('Expense Assumptions'!$A22,Controls!$A$5:$A$96,0),0) -> 750 | I22: =HLOOKUP(I$3,Controls!$A$5:$F$96,MATCH('Expense Assumptions'!$A22,Controls!$A$5:$A$96,0),0) -> 750 | ... BI22: =HLOOKUP(BI$3,Controls!$A$5:$F$96,MATCH('Expense Assumptions'!$A22,Controls!$A$5:$A$96,0),0) -> 1688.2632
A23: Insurance | B23: =HLOOKUP(B$3,Controls!$A$5:$F$96,MATCH('Expense Assumptions'!$A23,Controls!$A$5:$A$96,0),0) -> 3000 | C23: =HLOOKUP(C$3,Controls!$A$5:$F$96,MATCH('Expense Assumptions'!$A23,Controls!$A$5:$A$96,0),0) -> 3000 | D23: =HLOOKUP(D$3,Controls!$A$5:$F$96,MATCH('Expense Assumptions'!$A23,Controls!$A$5:$A$96,0),0) -> 3000 | E23: =HLOOKUP(E$3,Controls!$A$5:$F$96,MATCH('Expense Assumptions'!$A23,Controls!$A$5:$A$96,0),0) -> 3000 | F23: =HLOOKUP(F$3,Controls!$A$5:$F$96,MATCH('Expense Assumptions'!$A23,Controls!$A$5:$A$96,0),0) -> 3000 | G23: =HLOOKUP(G$3,Controls!$A$5:$F$96,MATCH('Expense Assumptions'!$A23,Controls!$A$5:$A$96,0),0) -> 3000 | H23: =HLOOKUP(H$3,Controls!$A$5:$F$96,MATCH('Expense Assumptions'!$A23,Controls!$A$5:$A$96,0),0) -> 3000 | I23: =HLOOKUP(I$3,Controls!$A$5:$F$96,MATCH('Expense Assumptions'!$A23,Controls!$A$5:$A$96,0),0) -> 3000 | ... BI23: =HLOOKUP(BI$3,Controls!$A$5:$F$96,MATCH('Expense Assumptions'!$A23,Controls!$A$5:$A$96,0),0) -> 140180
A24: Professional Fees | B24: =HLOOKUP(B$3,Controls!$A$5:$F$96,MATCH('Expense Assumptions'!$A24,Controls!$A$5:$A$96,0),0) -> 3500 | C24: =HLOOKUP(C$3,Controls!$A$5:$F$96,MATCH('Expense Assumptions'!$A24,Controls!$A$5:$A$96,0),0) -> 3500 | D24: =HLOOKUP(D$3,Controls!$A$5:$F$96,MATCH('Expense Assumptions'!$A24,Controls!$A$5:$A$96,0),0) -> 3500 | E24: =HLOOKUP(E$3,Controls!$A$5:$F$96,MATCH('Expense Assumptions'!$A24,Controls!$A$5:$A$96,0),0) -> 3500 | F24: =HLOOKUP(F$3,Controls!$A$5:$F$96,MATCH('Expense Assumptions'!$A24,Controls!$A$5:$A$96,0),0) -> 3500 | G24: =HLOOKUP(G$3,Controls!$A$5:$F$96,MATCH('Expense Assumptions'!$A24,Controls!$A$5:$A$96,0),0) -> 3500 | H24: =HLOOKUP(H$3,Controls!$A$5:$F$96,MATCH('Expense Assumptions'!$A24,Controls!$A$5:$A$96,0),0) -> 3500 | I24: =HLOOKUP(I$3,Controls!$A$5:$F$96,MATCH('Expense Assumptions'!$A24,Controls!$A$5:$A$96,0),0) -> 3500 | ... BI24: =HLOOKUP(BI$3,Controls!$A$5:$F$96,MATCH('Expense Assumptions'!$A24,Controls!$A$5:$A$96,0),0) -> 3939.2808
A25: Rent and Utility | B25: =HLOOKUP(B$3,Controls!$A$5:$F$96,MATCH('Expense Assumptions'!$A25,Controls!$A$5:$A$96,0),0) -> 40000 | C25: =HLOOKUP(C$3,Controls!$A$5:$F$96,MATCH('Expense Assumptions'!$A25,Controls!$A$5:$A$96,0),0) -> 40000 | D25: =HLOOKUP(D$3,Controls!$A$5:$F$96,MATCH('Expense Assumptions'!$A25,Controls!$A$5:$A$96,0),0) -> 40000 | E25: =HLOOKUP(E$3,Controls!$A$5:$F$96,MATCH('Expense Assumptions'!$A25,Controls!$A$5:$A$96,0),0) -> 40000 | F25: =HLOOKUP(F$3,Controls!$A$5:$F$96,MATCH('Expense Assumptions'!$A25,Controls!$A$5:$A$96,0),0) -> 40000 | G25: =HLOOKUP(G$3,Controls!$A$5:$F$96,MATCH('Expense Assumptions'!$A25,Controls!$A$5:$A$96,0),0) -> 40000 | H25: =HLOOKUP(H$3,Controls!$A$5:$F$96,MATCH('Expense Assumptions'!$A25,Controls!$A$5:$A$96,0),0) -> 40000 | I25: =HLOOKUP(I$3,Controls!$A$5:$F$96,MATCH('Expense Assumptions'!$A25,Controls!$A$5:$A$96,0),0) -> 40000 | ... BI25: =HLOOKUP(BI$3,Controls!$A$5:$F$96,MATCH('Expense Assumptions'!$A25,Controls!$A$5:$A$96,0),0) -> 93588.685
A26: Office and Other Expenses (per employee) | B26: 10000 | C26: 0 | D26: =HLOOKUP(D$3,Controls!$A$5:$F$96,MATCH('Expense Assumptions'!$A26,Controls!$A$5:$A$96,0),0)*('Payroll Assumptions'!D54-'Payroll Assumptions'!C54) -> 0 | E26: =HLOOKUP(E$3,Controls!$A$5:$F$96,MATCH('Expense Assumptions'!$A26,Controls!$A$5:$A$96,0),0)*('Payroll Assumptions'!E54-'Payroll Assumptions'!D54) -> 70000 | F26: =HLOOKUP(F$3,Controls!$A$5:$F$96,MATCH('Expense Assumptions'!$A26,Controls!$A$5:$A$96,0),0)*('Payroll Assumptions'!F54-'Payroll Assumptions'!E54) -> 0 | G26: =HLOOKUP(G$3,Controls!$A$5:$F$96,MATCH('Expense Assumptions'!$A26,Controls!$A$5:$A$96,0),0)*('Payroll Assumptions'!G54-'Payroll Assumptions'!F54) -> 16825 | H26: =HLOOKUP(H$3,Controls!$A$5:$F$96,MATCH('Expense Assumptions'!$A26,Controls!$A$5:$A$96,0),0)*('Payroll Assumptions'!H54-'Payroll Assumptions'!G54) -> 0 | I26: =HLOOKUP(I$3,Controls!$A$5:$F$96,MATCH('Expense Assumptions'!$A26,Controls!$A$5:$A$96,0),0)*('Payroll Assumptions'!I54-'Payroll Assumptions'!H54) -> 5000 | J26: =HLOOKUP(J$3,Controls!$A$5:$F$96,MATCH('Expense Assumptions'!$A26,Controls!$A$5:$A$96,0),0)*('Payroll Assumptions'!J54-'Payroll Assumptions'!I54) -> 0 | K26: =HLOOKUP(K$3,Controls!$A$5:$F$96,MATCH('Expense Assumptions'!$A26,Controls!$A$5:$A$96,0),0)*('Payroll Assumptions'!K54-'Payroll Assumptions'!J54) -> 5000 | ... AK26: =HLOOKUP(AK$3,Controls!$A$5:$F$96,MATCH('Expense Assumptions'!$A26,Controls!$A$5:$A$96,0),0)*('Payroll Assumptions'!AK54-'Payroll Assumptions'!AJ54) -> 0 | AL26: =HLOOKUP(AL$3,Controls!$A$5:$F$96,MATCH('Expense Assumptions'!$A26,Controls!$A$5:$A$96,0),0)*('Payroll Assumptions'!AL54-'Payroll Assumptions'!AK54)/12 -> 0 | AM26: =AL26 -> 0 | AN26: =AM26 -> 0 | AO26: =AN26 -> 0 | AP26: =AO26 -> 0 | AQ26: =AP26 -> 0 | AR26: =AQ26 -> 0 | AS26: =AR26 -> 0 | AT26: =AS26 -> 0 | ... AW26: =AV26 -> 0 | AX26: =HLOOKUP(AX$3,Controls!$A$5:$F$96,MATCH('Expense Assumptions'!$A26,Controls!$A$5:$A$96,0),0)*('Payroll Assumptions'!AX54-'Payroll Assumptions'!AW54)/12 -> 1406.886 | AY26: =AX26 -> 1406.886 | AZ26: =AY26 -> 1406.886 | BA26: =AZ26 -> 1406.886 | BB26: =BA26 -> 1406.886 | BC26: =BB26 -> 1406.886 | BD26: =BC26 -> 1406.886 | BE26: =BD26 -> 1406.886 | BF26: =BE26 -> 1406.886 | ... BI26: =BH26 -> 1406.886
A27: Marketing | B27: 1500 | C27: 1500 | D27: 1500 | E27: 1500 | F27: 1500 | G27: =HLOOKUP(G$3,Controls!$A$5:$F$96,MATCH('Expense Assumptions'!$A27,Controls!$A$5:$A$96,0),0) -> 15000 | H27: =HLOOKUP(H$3,Controls!$A$5:$F$96,MATCH('Expense Assumptions'!$A27,Controls!$A$5:$A$96,0),0) -> 15000 | I27: =HLOOKUP(I$3,Controls!$A$5:$F$96,MATCH('Expense Assumptions'!$A27,Controls!$A$5:$A$96,0),0) -> 15000 | J27: =HLOOKUP(J$3,Controls!$A$5:$F$96,MATCH('Expense Assumptions'!$A27,Controls!$A$5:$A$96,0),0) -> 15000 | K27: =HLOOKUP(K$3,Controls!$A$5:$F$96,MATCH('Expense Assumptions'!$A27,Controls!$A$5:$A$96,0),0) -> 15000 | L27: =HLOOKUP(L$3,Controls!$A$5:$F$96,MATCH('Expense Assumptions'!$A27,Controls!$A$5:$A$96,0),0) -> 15000 | M27: =HLOOKUP(M$3,Controls!$A$5:$F$96,MATCH('Expense Assumptions'!$A27,Controls!$A$5:$A$96,0),0) -> 15000 | N27: =HLOOKUP(N$3,Controls!$A$5:$F$96,MATCH('Expense Assumptions'!$A27,Controls!$A$5:$A$96,0),0) -> 16500 | ... BI27: =HLOOKUP(BI$3,Controls!$A$5:$F$96,MATCH('Expense Assumptions'!$A27,Controls!$A$5:$A$96,0),0) -> 21961.5
A28: Travel Expenses | B28: 3000 | C28: 5000 | D28: 5000 | E28: 10000 | F28: 10000 | G28: 10000 | H28: =HLOOKUP(H$3,Controls!$A$5:$F$96,MATCH('Expense Assumptions'!$A28,Controls!$A$5:$A$96,0),0) -> 20000 | I28: =HLOOKUP(I$3,Controls!$A$5:$F$96,MATCH('Expense Assumptions'!$A28,Controls!$A$5:$A$96,0),0) -> 20000 | J28: =HLOOKUP(J$3,Controls!$A$5:$F$96,MATCH('Expense Assumptions'!$A28,Controls!$A$5:$A$96,0),0) -> 20000 | K28: =HLOOKUP(K$3,Controls!$A$5:$F$96,MATCH('Expense Assumptions'!$A28,Controls!$A$5:$A$96,0),0) -> 20000 | L28: =HLOOKUP(L$3,Controls!$A$5:$F$96,MATCH('Expense Assumptions'!$A28,Controls!$A$5:$A$96,0),0) -> 20000 | M28: =HLOOKUP(M$3,Controls!$A$5:$F$96,MATCH('Expense Assumptions'!$A28,Controls!$A$5:$A$96,0),0) -> 20000 | N28: =HLOOKUP(N$3,Controls!$A$5:$F$96,MATCH('Expense Assumptions'!$A28,Controls!$A$5:$A$96,0),0) -> 20600 | O28: =HLOOKUP(O$3,Controls!$A$5:$F$96,MATCH('Expense Assumptions'!$A28,Controls!$A$5:$A$96,0),0) -> 20600 | ... BI28: =HLOOKUP(BI$3,Controls!$A$5:$F$96,MATCH('Expense Assumptions'!$A28,Controls!$A$5:$A$96,0),0) -> 22510.176
A29: Research and Development | B29: 1000 | C29: 1000 | D29: 1000 | E29: 1000 | F29: 1000 | G29: =HLOOKUP(G$3,Controls!$A$5:$F$96,MATCH('Expense Assumptions'!$A29,Controls!$A$5:$A$96,0),0) -> 5000 | H29: =HLOOKUP(H$3,Controls!$A$5:$F$96,MATCH('Expense Assumptions'!$A29,Controls!$A$5:$A$96,0),0) -> 5000 | I29: =HLOOKUP(I$3,Controls!$A$5:$F$96,MATCH('Expense Assumptions'!$A29,Controls!$A$5:$A$96,0),0) -> 5000 | J29: =HLOOKUP(J$3,Controls!$A$5:$F$96,MATCH('Expense Assumptions'!$A29,Controls!$A$5:$A$96,0),0) -> 5000 | K29: =HLOOKUP(K$3,Controls!$A$5:$F$96,MATCH('Expense Assumptions'!$A29,Controls!$A$5:$A$96,0),0) -> 5000 | L29: =HLOOKUP(L$3,Controls!$A$5:$F$96,MATCH('Expense Assumptions'!$A29,Controls!$A$5:$A$96,0),0) -> 5000 | M29: =HLOOKUP(M$3,Controls!$A$5:$F$96,MATCH('Expense Assumptions'!$A29,Controls!$A$5:$A$96,0),0) -> 5000 | N29: =HLOOKUP(N$3,Controls!$A$5:$F$96,MATCH('Expense Assumptions'!$A29,Controls!$A$5:$A$96,0),0) -> 20000 | ... BI29: =HLOOKUP(BI$3,Controls!$A$5:$F$96,MATCH('Expense Assumptions'!$A29,Controls!$A$5:$A$96,0),0) -> 20000
A31: Total Expenses | B31: =SUM(B22:B29) -> 62750 | C31: =SUM(C22:C29) -> 54750 | D31: =SUM(D22:D29) -> 54750 | E31: =SUM(E22:E29) -> 129750 | F31: =SUM(F22:F29) -> 59750 | G31: =SUM(G22:G29) -> 94075 | H31: =SUM(H22:H29) -> 87250 | I31: =SUM(I22:I29) -> 92250 | ... BI31: =SUM(BI22:BI29) -> 305274.79

Sheet Payroll Assumptions
A1: EXOS Aerospace
A2: Payroll Assumptions Sheet | B2: =Controls!C1 -> July | C2: =TEXT(DATE(2000, MATCH(B2, {"January","February","March","April","May","June","July","August","September","October","November","December"}, 0) + 1, 1), "mmmm") -> August | D2: =TEXT(DATE(2000, MATCH(C2, {"January","February","March","April","May","June","July","August","September","October","November","December"}, 0) + 1, 1), "mmmm") -> September | E2: =TEXT(DATE(2000, MATCH(D2, {"January","February","March","April","May","June","July","August","September","October","November","December"}, 0) + 1, 1), "mmmm") -> October | F2: =TEXT(DATE(2000, MATCH(E2, {"January","February","March","April","May","June","July","August","September","October","November","December"}, 0) + 1, 1), "mmmm") -> November | G2: =TEXT(DATE(2000, MATCH(F2, {"January","February","March","April","May","June","July","August","September","October","November","December"}, 0) + 1, 1), "mmmm") -> December | H2: =TEXT(DATE(2000, MATCH(G2, {"January","February","March","April","May","June","July","August","September","October","November","December"}, 0) + 1, 1), "mmmm") -> January | I2: =TEXT(DATE(2000, MATCH(H2, {"January","February","March","April","May","June","July","August","September","October","November","December"}, 0) + 1, 1), "mmmm") -> February | J2: =TEXT(DATE(2000, MATCH(I2, {"January","February","March","April","May","June","July","August","September","October","November","December"}, 0) + 1, 1), "mmmm") -> March | ... BI2: =TEXT(DATE(2000, MATCH(BH2, {"January","February","March","April","May","June","July","August","September","October","November","December"}, 0) + 1, 1), "mmmm") -> June
A3: Amounts in USD | B3: 1 | C3: =IF(MOD(B4,B5) = 0,B3+1,B3) -> 1 | D3: =IF(MOD(C4,C5) = 0,C3+1,C3) -> 1 | E3: =IF(MOD(D4,D5) = 0,D3+1,D3) -> 1 | F3: =IF(MOD(E4,E5) = 0,E3+1,E3) -> 1 | G3: =IF(MOD(F4,F5) = 0,F3+1,F3) -> 1 | H3: =IF(MOD(G4,G5) = 0,G3+1,G3) -> 1 | I3: =IF(MOD(H4,H5) = 0,H3+1,H3) -> 1 | J3: =IF(MOD(I4,I5) = 0,I3+1,I3) -> 1 | ... BI3: =IF(MOD(BH4,BH5) = 0,BH3+1,BH3) -> 5
A4: Back To Index | B4: 1 | C4: =B4+1 -> 2 | D4: =C4+1 -> 3 | E4: =D4+1 -> 4 | F4: =E4+1 -> 5 | G4: =F4+1 -> 6 | H4: =G4+1 -> 7 | I4: =H4+1 -> 8 | J4: =I4+1 -> 9 | ... BI4: =BH4+1 -> 60
A5: Assumptions for the Monthly Period | B5: 12 | C5: 12 | D5: 12 | E5: 12 | F5: 12 | G5: 12 | H5: 12 | I5: 12 | J5: 12 | K5: 12 | L5: 12 | M5: 12 | N5: 12 | O5: 12 | P5: 12 | Q5: 12 | R5: 12 | S5: 12 | T5: 12 | U5: 12 | V5: 12 | W5: 12 | X5: 12 | Y5: 12 | Z5: 12 | AA5: 12 | AB5: 12 | AC5: 12 | AD5: 12 | AE5: 12 | AF5: 12 | AG5: 12 | AH5: 12 | AI5: 12 | AJ5: 12 | AK5: 12 | AL5: 12 | AM5: 12 | AN5: 12 | AO5: 12 | AP5: 12 | AQ5: 12 | AR5: 12 | AS5: 12 | AT5: 12 | AU5: 12 | AV5: 12 | AW5: 12 | AX5: 12 | AY5: 12 | AZ5: 12 | BA5: 12 | BB5: 12 | BC5: 12 | BD5: 12 | BE5: 12 | BF5: 12 | BG5: 12 | BH5: 12 | BI5: 12
A7: No. of Employees
A9: Corporate Team
A10: President | B10: 0.85 | C10: 0.85 | D10: 0.85 | E10: 0.85 | F10: 0.85 | G10: 0.85 | H10: 0.85 | I10: 0.85 | J10: 0.85 | K10: 0.85 | L10: 0.85 | M10: 0.85 | N10: 1 | O10: 1 | P10: 1 | Q10: 1 | R10: 1 | S10: 1 | T10: 1 | U10: 1 | V10: 1 | W10: 1 | X10: 1 | Y10: 1 | Z10: 1 | AA10: 1 | AB10: 1 | AC10: 1 | AD10: 1 | AE10: 1 | AF10: 1 | AG10: 1 | AH10: 1 | AI10: 1 | AJ10: 1 | AK10: 1 | AL10: 1 | AM10: 1 | AN10: 1 | AO10: 1 | AP10: 1 | AQ10: 1 | AR10: 1 | AS10: 1 | AT10: 1 | AU10: 1 | AV10: 1 | AW10: 1 | AX10: 1 | AY10: 1 | AZ10: 1 | BA10: 1 | BB10: 1 | BC10: 1 | BD10: 1 | BE10: 1 | BF10: 1 | BG10: 1 | BH10: 1 | BI10: 1
A11: CEO | B11: 0.85 | C11: 0.85 | D11: 0.85 | E11: 0.85 | F11: 0.85 | G11: 0.85 | H11: 0.85 | I11: 0.85 | J11: 0.85 | K11: 0.85 | L11: 0.85 | M11: 0.85 | N11: 1 | O11: 1 | P11: 1 | Q11: 1 | R11: 1 | S11: 1 | T11: 1 | U11: 1 | V11: 1 | W11: 1 | X11: 1 | Y11: 1 | Z11: 1 | AA11: 1 | AB11: 1 | AC11: 1 | AD11: 1 | AE11: 1 | AF11: 1 | AG11: 1 | AH11: 1 | AI11: 1 | AJ11: 1 | AK11: 1 | AL11: 2 | AM11: 2 | AN11: 2 | AO11: 2 | AP11: 2 | AQ11: 2 | AR11: 2 | AS11: 2 | AT11: 2 | AU11: 2 | AV11: 2 | AW11: 2 | AX11: 2 | AY11: 2 | AZ11: 2 | BA11: 2 | BB11: 2 | BC11: 2 | BD11: 2 | BE11: 2 | BF11: 2 | BG11: 2 | BH11: 2 | BI11: 2
A12: COO | B12: 0.85 | C12: 0.85 | D12: 0.85 | E12: 0.85 | F12: 0.85 | G12: 0.85 | H12: 0.85 | I12: 0.85 | J12: 0.85 | K12: 0.85 | L12: 0.85 | M12: 0.85 | N12: 1 | O12: 1 | P12: 1 | Q12: 1 | R12: 1 | S12: 1 | T12: 1 | U12: 1 | V12: 1 | W12: 1 | X12: 1 | Y12: 1 | Z12: 2 | AA12: 2 | AB12: 2 | AC12: 2 | AD12: 2 | AE12: 2 | AF12: 2 | AG12: 2 | AH12: 2 | AI12: 2 | AJ12: 2 | AK12: 2 | AL12: 2 | AM12: 2 | AN12: 2 | AO12: 2 | AP12: 2 | AQ12: 2 | AR12: 2 | AS12: 2 | AT12: 2 | AU12: 2 | AV12: 2 | AW12: 2 | AX12: 2 | AY12: 2 | AZ12: 2 | BA12: 2 | BB12: 2 | BC12: 2 | BD12: 2 | BE12: 2 | BF12: 2 | BG12: 2 | BH12: 2 | BI12: 2
A13: CTO | B13: 0.85 | C13: 0.85 | D13: 0.85 | E13: 0.85 | F13: 0.85 | G13: 0.85 | H13: 0.85 | I13: 0.85 | J13: 0.85 | K13: 0.85 | L13: 0.85 | M13: 0.85 | N13: 2 | O13: 2 | P13: 2 | Q13: 2 | R13: 2 | S13: 2 | T13: 2 | U13: 2 | V13: 2 | W13: 2 | X13: 2 | Y13: 2 | Z13: 2 | AA13: 2 | AB13: 2 | AC13: 2 | AD13: 2 | AE13: 2 | AF13: 2 | AG13: 2 | AH13: 2 | AI13: 2 | AJ13: 2 | AK13: 2 | AL13: 2 | AM13: 2 | AN13: 2 | AO13: 2 | AP13: 2 | AQ13: 2 | AR13: 2 | AS13: 2 | AT13: 2 | AU13: 2 | AV13: 2 | AW13: 2 | AX13: 2 | AY13: 2 | AZ13: 2 | BA13: 2 | BB13: 2 | BC13: 2 | BD13: 2 | BE13: 2 | BF13: 2 | BG13: 2 | BH13: 2 | BI13: 2
A14: Instrumentation Controls Electrical Engineer | B14: 0 | C14: 0 | D14: 0 | E14: 0 | F14: 0 | G14: 0 | H14: 0 | I14: 0 | J14: 0 | K14: 0 | L14: 0 | M14: 0 | N14: 0 | O14: 0 | P14: 0 | Q14: 0 | R14: 0 | S14: 0 | T14: 0 | U14: 0 | V14: 0 | W14: 0 | X14: 0 | Y14: 0 | Z14: 0 | AA14: 0 | AB14: 0 | AC14: 0 | AD14: 0 | AE14: 0 | AF14: 0 | AG14: 0 | AH14: 0 | AI14: 0 | AJ14: 0 | AK14: 0 | AL14: 6 | AM14: 6 | AN14: 6 | AO14: 6 | AP14: 6 | AQ14: 6 | AR14: 6 | AS14: 6 | AT14: 6 | AU14: 6 | AV14: 6 | AW14: 6 | AX14: 7.5 | AY14: 7.5 | AZ14: 7.5 | BA14: 7.5 | BB14: 7.5 | BC14: 7.5 | BD14: 7.5 | BE14: 7.5 | BF14: 7.5 | BG14: 7.5 | BH14: 7.5 | BI14: 7.5
A15: AS9100D & ITAR Compliance Officer | B15: 0 | C15: 0 | D15: 0 | E15: 0 | F15: 0 | G15: 0 | M15: 1 | N15: 1 | O15: 1 | P15: 1 | Q15: 1 | R15: 1 | S15: 1 | T15: 1 | U15: 1 | V15: 1 | W15: 1 | X15: 1 | Y15: 1 | Z15: 2 | AA15: 2 | AB15: 2 | AC15: 2 | AD15: 2 | AE15: 2 | AF15: 2 | AG15: 2 | AH15: 2 | AI15: 2 | AJ15: 2 | AK15: 2 | AL15: 2.4 | AM15: 2.4 | AN15: 2.4 | AO15: 2.4 | AP15: 2.4 | AQ15: 2.4 | AR15: 2.4 | AS15: 2.4 | AT15: 2.4 | AU15: 2.4 | AV15: 2.4 | AW15: 2.4 | AX15: 3 | AY15: 3 | AZ15: 3 | BA15: 3 | BB15: 3 | BC15: 3 | BD15: 3 | BE15: 3 | BF15: 3 | BG15: 3 | BH15: 3 | BI15: 3
A16: Staff (based on USD salaries)
A17: Administrative Assistant | B17: 0.85 | C17: 0.85 | D17: 0.85 | E17: 0.85 | F17: 0.85 | G17: 0.85 | H17: 0.85 | I17: 0.85 | J17: 0.85 | K17: 0.85 | L17: 0.85 | M17: 0.85 | N17: 1 | O17: 1 | P17: 1 | Q17: 1 | R17: 1 | S17: 1 | T17: 1 | U17: 1 | V17: 1 | W17: 1 | X17: 1 | Y17: 1 | Z17: 1 | AA17: 1 | AB17: 1 | AC17: 1 | AD17: 1 | AE17: 1 | AF17: 1 | AG17: 1 | AH17: 1 | AI17: 1 | AJ17: 1 | AK17: 1 | AL17: 1 | AM17: 1 | AN17: 1 | AO17: 1 | AP17: 1 | AQ17: 1 | AR17: 1 | AS17: 1 | AT17: 1 | AU17: 1 | AV17: 1 | AW17: 1 | AX17: 2 | AY17: 2 | AZ17: 2 | BA17: 2 | BB17: 2 | BC17: 2 | BD17: 2 | BE17: 2 | BF17: 2 | BG17: 2 | BH17: 2 | BI17: 2
A18: Aero Modeling Engineer | B18: 0 | C18: 0 | D18: 0 | E18: 0 | F18: 0 | G18: 0 | H18: 0 | I18: 0 | J18: 0 | K18: 0 | L18: 0 | M18: 0 | N18: 0 | O18: 0 | P18: 0 | Q18: 0 | R18: 0 | S18: 0 | T18: 0 | U18: 0 | V18: 0 | W18: 0 | X18: 0 | Y18: 0 | Z18: 0 | AA18: 0 | AB18: 0 | AC18: 0 | AD18: 0 | AE18: 0 | AF18: 0 | AG18: 0 | AH18: 0 | AI18: 0 | AJ18: 0 | AK18: 1 | AL18: 1.2 | AM18: 1.2 | AN18: 1.2 | AO18: 1.2 | AP18: 1.2 | AQ18: 1.2 | AR18: 1.2 | AS18: 1.2 | AT18: 1.2 | AU18: 1.2 | AV18: 1.2 | AW18: 1.2 | AX18: 1.5 | AY18: 1.5 | AZ18: 1.5 | BA18: 1.5 | BB18: 1.5 | BC18: 1.5 | BD18: 1.5 | BE18: 1.5 | BF18: 1.5 | BG18: 1.5 | BH18: 1.5 | BI18: 1.5
A19: Avionics Hardware Development Engineer | B19: 0 | C19: 0 | D19: 0 | E19: 0 | F19: 0 | G19: 0 | H19: 0 | I19: 0 | J19: 0 | K19: 0 | L19: 0 | M19: 0 | N19: 0 | O19: 0 | P19: 0 | Q19: 0 | R19: 0 | S19: 0 | T19: 0 | U19: 0 | V19: 0 | W19: 0 | X19: 0 | Y19: 0 | Z19: 0 | AA19: 0 | AB19: 0 | AC19: 0 | AD19: 0 | AE19: 0 | AF19: 0 | AG19: 0 | AH19: 0 | AI19: 0 | AJ19: 0 | AK19: 0 | AL19: 1.2 | AM19: 1.2 | AN19: 1.2 | AO19: 1.2 | AP19: 1.2 | AQ19: 1.2 | AR19: 1.2 | AS19: 1.2 | AT19: 1.2 | AU19: 1.2 | AV19: 1.2 | AW19: 1.2 | AX19: 1.5 | AY19: 1.5 | AZ19: 1.5 | BA19: 1.5 | BB19: 1.5 | BC19: 1.5 | BD19: 1.5 | BE19: 1.5 | BF19: 1.5 | BG19: 1.5 | BH19: 1.5 | BI19: 1.5
A20: Contracts Administrator- PROGRAM MANAGER | B20: 0 | C20: 0 | D20: 0 | E20: 0 | F20: 0 | G20: 0 | H20: 0 | I20: 0 | J20: 0 | K20: 0 | L20: 0 | M20: 0 | N20: 0 | O20: 0 | P20: 0 | Q20: 0 | R20: 0 | S20: 0 | T20: 0 | U20: 0 | V20: 0 | W20: 0 | X20: 0 | Y20: 0 | Z20: 0 | AA20: 0 | AB20: 0 | AC20: 0 | AD20: 0 | AE20: 0 | AF20: 0 | AG20: 0 | AH20: 0 | AI20: 0 | AJ20: 0 | AK20: 0 | AL20: 1.2 | AM20: 1.2 | AN20: 1.2 | AO20: 1.2 | AP20: 1.2 | AQ20: 1.2 | AR20: 1.2 | AS20: 1.2 | AT20: 1.2 | AU20: 1.2 | AV20: 1.2 | AW20: 1.2 | AX20: 1.5 | AY20: 1.5 | AZ20: 1.5 | BA20: 1.5 | BB20: 1.5 | BC20: 1.5 | BD20: 1.5 | BE20: 1.5 | BF20: 1.5 | BG20: 1.5 | BH20: 1.5 | BI20: 1.5
A21: Design Engineer (mech)- 12 Scorpius (average salary) | B21: 1 | C21: 1 | D21: 1 | E21: 15 | F21: 15 | G21: 15 | H21: 15 | I21: 15 | J21: 15 | K21: 15 | L21: 15 | M21: 15 | N21: 15 | O21: 15 | P21: 15 | Q21: 15 | R21: 15 | S21: 15 | T21: 16 | U21: 17 | V21: 18 | W21: 19 | X21: 20 | Y21: 20 | Z21: 20 | AA21: 20 | AB21: 20 | AC21: 20 | AD21: 20 | AE21: 20 | AF21: 20 | AG21: 20 | AH21: 20 | AI21: 20 | AJ21: 20 | AK21: 20 | AL21: 20 | AM21: 20 | AN21: 20 | AO21: 20 | AP21: 20 | AQ21: 20 | AR21: 20 | AS21: 20 | AT21: 20 | AU21: 20 | AV21: 20 | AW21: 20 | AX21: 20 | AY21: 20 | AZ21: 20 | BA21: 20 | BB21: 20 | BC21: 20 | BD21: 20 | BE21: 20 | BF21: 20 | BG21: 20 | BH21: 20 | BI21: 20
A22: Engineering Internships- Admin | B22: 0 | C22: 0 | D22: 0 | E22: 0 | F22: 0 | G22: 0 | H22: 0 | I22: 0 | J22: 0 | K22: 0 | L22: 0 | M22: 0 | N22: 0 | O22: 0 | P22: 0 | Q22: 0 | R22: 0 | S22: 0 | T22: 0 | U22: 0 | V22: 0 | W22: 0 | X22: 0 | Y22: 0 | Z22: 0 | AA22: 0 | AB22: 0 | AC22: 0 | AD22: 0 | AE22: 0 | AF22: 0 | AG22: 0 | AH22: 0 | AI22: 0 | AJ22: 0 | AK22: 0 | AL22: 3.6 | AM22: 3.6 | AN22: 3.6 | AO22: 3.6 | AP22: 3.6 | AQ22: 3.6 | AR22: 3.6 | AS22: 3.6 | AT22: 3.6 | AU22: 3.6 | AV22: 3.6 | AW22: 3.6 | AX22: 3.6 | AY22: 3.6 | AZ22: 3.6 | BA22: 3.6 | BB22: 3.6 | BC22: 3.6 | BD22: 3.6 | BE22: 3.6 | BF22: 3.6 | BG22: 3.6 | BH22: 3.6 | BI22: 3.6
A23: Guidance Navigation and Control Engineer | B23: 0 | C23: 0 | D23: 0 | E23: 0 | F23: 0 | G23: 0 | H23: 0 | I23: 0 | J23: 0 | K23: 0 | L23: 0 | M23: 0 | N23: 0 | O23: 0 | P23: 0 | Q23: 0 | R23: 0 | S23: 0 | T23: 0 | U23: 0 | V23: 0 | W23: 0 | X23: 0 | Y23: 0 | Z23: 0 | AA23: 0 | AB23: 0 | AC23: 0 | AD23: 0 | AE23: 0 | AF23: 0 | AG23: 0 | AH23: 0 | AI23: 0 | AJ23: 0 | AK23: 0 | AL23: 1 | AM23: 1 | AN23: 1 | AO23: 1 | AP23: 1 | AQ23: 1 | AR23: 1 | AS23: 1 | AT23: 1 | AU23: 1 | AV23: 1 | AW23: 1 | AX23: 1 | AY23: 1 | AZ23: 1 | BA23: 1 | BB23: 1 | BC23: 1 | BD23: 1 | BE23: 1 | BF23: 1 | BG23: 1 | BH23: 1 | BI23: 1
A24: Junior RF Engineer | B24: 0 | C24: 0 | D24: 0 | E24: 0 | F24: 0 | G24: 0 | H24: 0 | I24: 0 | J24: 0 | K24: 0 | L24: 0 | M24: 0 | N24: 0 | O24: 0 | P24: 0 | Q24: 0 | R24: 0 | S24: 0 | T24: 0 | U24: 0 | V24: 0 | W24: 0 | X24: 0 | Y24: 0 | Z24: 0 | AA24: 0 | AB24: 0 | AC24: 0 | AD24: 0 | AE24: 0 | AF24: 0 | AG24: 0 | AH24: 0 | AI24: 0 | AJ24: 0 | AK24: 0 | AL24: 1 | AM24: 1 | AN24: 1 | AO24: 1 | AP24: 1 | AQ24: 1 | AR24: 1 | AS24: 1 | AT24: 1 | AU24: 1 | AV24: 1 | AW24: 1 | AX24: 1 | AY24: 1 | AZ24: 1 | BA24: 1 | BB24: 1 | BC24: 1 | BD24: 1 | BE24: 1 | BF24: 1 | BG24: 1 | BH24: 1 | BI24: 1
A25: Launch Engineer | B25: 0 | C25: 0 | D25: 0 | E25: 0 | F25: 0 | G25: 0 | H25: 0 | I25: 0 | J25: 0 | K25: 0 | L25: 0 | M25: 0 | N25: 0 | O25: 0 | P25: 0 | Q25: 0 | R25: 0 | S25: 0 | T25: 0 | U25: 0 | V25: 0 | W25: 0 | X25: 0 | Y25: 0 | Z25: 0 | AA25: 0 | AB25: 0 | AC25: 0 | AD25: 0 | AE25: 0 | AF25: 0 | AG25: 0 | AH25: 0 | AI25: 0 | AJ25: 0 | AK25: 0 | AL25: 1 | AM25: 1 | AN25: 1 | AO25: 1 | AP25: 1 | AQ25: 1 | AR25: 1 | AS25: 1 | AT25: 1 | AU25: 1 | AV25: 1 | AW25: 1 | AX25: 1 | AY25: 1 | AZ25: 1 | BA25: 1 | BB25: 1 | BC25: 1 | BD25: 1 | BE25: 1 | BF25: 1 | BG25: 1 | BH25: 1 | BI25: 1
A26: Mechanical Designer/Drafter/Technician | B26: 0 | C26: 0 | D26: 0 | E26: 0 | F26: 0 | G26: 0 | H26: 0 | I26: 0 | J26: 0 | K26: 0 | L26: 0 | M26: 0 | N26: 0 | O26: 0 | P26: 0 | Q26: 0 | R26: 0 | S26: 0 | T26: 0 | U26: 0 | V26: 0 | W26: 0 | X26: 0 | Y26: 0 | Z26: 0 | AA26: 0 | AB26: 0 | AC26: 0 | AD26: 0 | AE26: 0 | AF26: 0 | AG26: 0 | AH26: 0 | AI26: 0 | AJ26: 0 | AK26: 0 | AL26: 1 | AM26: 1 | AN26: 1 | AO26: 1 | AP26: 1 | AQ26: 1 | AR26: 1 | AS26: 1 | AT26: 1 | AU26: 1 | AV26: 1 | AW26: 1 | AX26: 1 | AY26: 1 | AZ26: 1 | BA26: 1 | BB26: 1 | BC26: 1 | BD26: 1 | BE26: 1 | BF26: 1 | BG26: 1 | BH26: 1 | BI26: 1
A27: Mission Integration Engineer | B27: 0 | C27: 0 | D27: 0 | E27: 0 | F27: 0 | G27: 0 | H27: 0 | I27: 0 | J27: 0 | K27: 0 | L27: 0 | M27: 0 | N27: 0 | O27: 0 | P27: 0 | Q27: 0 | R27: 0 | S27: 0 | T27: 0 | U27: 0 | V27: 0 | W27: 0 | X27: 0 | Y27: 0 | Z27: 0 | AA27: 0 | AB27: 0 | AC27: 0 | AD27: 0 | AE27: 0 | AF27: 0 | AG27: 0 | AH27: 0 | AI27: 0 | AJ27: 0 | AK27: 0 | AL27: 1 | AM27: 1 | AN27: 1 | AO27: 1 | AP27: 1 | AQ27: 1 | AR27: 1 | AS27: 1 | AT27: 1 | AU27: 1 | AV27: 1 | AW27: 1 | AX27: 1 | AY27: 1 | AZ27: 1 | BA27: 1 | BB27: 1 | BC27: 1 | BD27: 1 | BE27: 1 | BF27: 1 | BG27: 1 | BH27: 1 | BI27: 1
A28: Propulsion Development Engineer | B28: 0 | C28: 0 | D28: 0 | E28: 0 | F28: 0 | G28: 0 | H28: 0 | I28: 0 | J28: 0 | K28: 0 | L28: 0 | M28: 0 | N28: 0 | O28: 0 | P28: 0 | Q28: 0 | R28: 0 | S28: 0 | T28: 0 | U28: 0 | V28: 0 | W28: 0 | X28: 0 | Y28: 0 | Z28: 0 | AA28: 0 | AB28: 0 | AC28: 0 | AD28: 0 | AE28: 0 | AF28: 0 | AG28: 0 | AH28: 0 | AI28: 0 | AJ28: 0 | AK28: 0 | AL28: 1 | AM28: 1 | AN28: 1 | AO28: 1 | AP28: 1 | AQ28: 1 | AR28: 1 | AS28: 1 | AT28: 1 | AU28: 1 | AV28: 1 | AW28: 1 | AX28: 1 | AY28: 1 | AZ28: 1 | BA28: 1 | BB28: 1 | BC28: 1 | BD28: 1 | BE28: 1 | BF28: 1 | BG28: 1 | BH28: 1 | BI28: 1
... A41: Instument Control Electrical- ICE Technicians - OPS | B41: 1 | C41: 1 | D41: 1 | E41: 1 | F41: 1 | G41: 2 | H41: 2 | I41: 2 | J41: 2 | K41: 2 | L41: 2 | M41: 3 | N41: 4 | O41: 4 | P41: 4 | Q41: 4 | R41: 4 | S41: 4 | T41: 4 | U41: 4 | V41: 4 | W41: 4 | X41: 4 | Y41: 4 | Z41: 4 | AA41: 5 | AB41: 5 | AC41: 5 | AD41: 5 | AE41: 5 | AF41: 5 | AG41: 5 | AH41: 5 | AI41: 5 | AJ41: 5 | AK41: 5 | AL41: 7 | AM41: 7 | AN41: 7 | AO41: 7 | AP41: 7 | AQ41: 7 | AR41: 7 | AS41: 7 | AT41: 7 | AU41: 7 | AV41: 7 | AW41: 7 | AX41: 7 | AY41: 6 | AZ41: 6 | BA41: 6 | BB41: 6 | BC41: 6 | BD41: 6 | BE41: 6 | BF41: 6 | BG41: 6 | BH41: 6 | BI41: 6
A42: Humanoid robots | B42: 0 | C42: 0 | D42: 0 | E42: 0 | F42: 0 | G42: 0 | H42: 0 | I42: 0 | J42: 0 | K42: 0 | L42: 0 | M42: 0 | N42: 0 | O42: 0 | P42: 0 | Q42: 0 | R42: 0 | S42: =S40 -> 3 | T42: =T40 -> 3 | U42: =U40 -> 3 | V42: =V40 -> 3 | W42: =W40 -> 3 | X42: =X40 -> 3 | Y42: =Y40 -> 3 | Z42: =Z40 -> 3 | AA42: 6 | AB42: 6 | AC42: 6 | AD42: 6 | AE42: 6 | AF42: 6 | AG42: 6 | AH42: 9 | AI42: 9 | AJ42: 9 | AK42: 9 | AL42: 12 | AM42: 12 | AN42: 12 | AO42: 12 | AP42: 12 | AQ42: 12 | AR42: 12 | AS42: 16 | AT42: 16 | AU42: 16 | AV42: 16 | AW42: 16 | AX42: 24 | AY42: 24 | AZ42: 24 | BA42: 24 | BB42: 24 | BC42: 24 | BD42: 24 | BE42: 24 | BF42: 24 | BG42: 24 | BH42: 24 | BI42: 24
A43: General Council and International Law consultancy | B43: 0 | C43: 0 | D43: 0 | E43: 0 | F43: 0 | G43: 0 | H43: 0 | I43: 0 | J43: 0 | K43: 0 | L43: 0 | M43: 0 | N43: 1 | O43: 1 | P43: 1 | Q43: 1 | R43: 1 | S43: 1 | T43: 1 | U43: 1 | V43: 1 | W43: 1 | X43: 1 | Y43: 1 | Z43: 1 | AA43: 1 | AB43: 1 | AC43: 1 | AD43: 1 | AE43: 1 | AF43: 1 | AG43: 1 | AH43: 1 | AI43: 1 | AJ43: 1 | AK43: 1 | AL43: 1 | AM43: 1 | AN43: 1 | AO43: 1 | AP43: 1 | AQ43: 1 | AR43: 1 | AS43: 1 | AT43: 1 | AU43: 1 | AV43: 1 | AW43: 1 | AX43: 1 | AY43: 1 | AZ43: 1 | BA43: 1 | BB43: 1 | BC43: 1 | BD43: 1 | BE43: 1 | BF43: 1 | BG43: 1 | BH43: 1 | BI43: 1
A44: CFO Accounting GAAP Audit | B44: 0.355 | C44: 0.355 | D44: 0.355 | E44: 0.355 | F44: 0.355 | G44: 0.72 | H44: 0.72 | I44: 0.72 | J44: 0.72 | K44: 0.72 | L44: 0.72 | M44: 0.72 | N44: 0.72 | O44: 0.72 | P44: 0.72 | Q44: 0.72 | R44: 1 | S44: 1 | T44: 1 | U44: 1 | V44: 1 | W44: 1 | X44: 1 | Y44: 1 | Z44: 1 | AA44: 1 | AB44: 1 | AC44: 1 | AD44: 1 | AE44: 1 | AF44: 1 | AG44: 1 | AH44: 1 | AI44: 1 | AJ44: 1 | AK44: 1 | AL44: 1 | AM44: 1 | AN44: 1 | AO44: 1 | AP44: 1 | AQ44: 1 | AR44: 1 | AS44: 1 | AT44: 1 | AU44: 1 | AV44: 1 | AW44: 1 | AX44: 1 | AY44: 1 | AZ44: 1 | BA44: 1 | BB44: 1 | BC44: 1 | BD44: 1 | BE44: 1 | BF44: 1 | BG44: 1 | BH44: 1 | BI44: 1
A45: =Controls!A116 -> Please add Position | B45: 0 | C45: 0 | D45: 0 | E45: 0 | F45: 0 | G45: 0 | H45: 0 | I45: 0 | J45: 0 | K45: 0 | L45: 0 | M45: 0 | N45: 0 | O45: 0 | P45: 0 | Q45: 0 | R45: 0 | S45: 0 | T45: 0 | U45: 0 | V45: 0 | W45: 0 | X45: 0 | Y45: 0 | Z45: 0 | AA45: 0 | AB45: 0 | AC45: 0 | AD45: 0 | AE45: 0 | AF45: 0 | AG45: 0 | AH45: 0 | AI45: 0 | AJ45: 0 | AK45: 0 | AL45: 0 | AM45: 0 | AN45: 0 | AO45: 0 | AP45: 0 | AQ45: 0 | AR45: 0 | AS45: 0 | AT45: 0 | AU45: 0 | AV45: 0 | AW45: 0 | AX45: 0 | AY45: 0 | AZ45: 0 | BA45: 0 | BB45: 0 | BC45: 0 | BD45: 0 | BE45: 0 | BF45: 0 | BG45: 0 | BH45: 0 | BI45: 0
A46: =Controls!A117 -> Please add Position | B46: 0 | C46: 0 | D46: 0 | E46: 0 | F46: 0 | G46: 0 | H46: 0 | I46: 0 | J46: 0 | K46: 0 | L46: 0 | M46: 0 | N46: 0 | O46: 0 | P46: 0 | Q46: 0 | R46: 0 | S46: 0 | T46: 0 | U46: 0 | V46: 0 | W46: 0 | X46: 0 | Y46: 0 | Z46: 0 | AA46: 0 | AB46: 0 | AC46: 0 | AD46: 0 | AE46: 0 | AF46: 0 | AG46: 0 | AH46: 0 | AI46: 0 | AJ46: 0 | AK46: 0 | AL46: 0 | AM46: 0 | AN46: 0 | AO46: 0 | AP46: 0 | AQ46: 0 | AR46: 0 | AS46: 0 | AT46: 0 | AU46: 0 | AV46: 0 | AW46: 0 | AX46: 0 | AY46: 0 | AZ46: 0 | BA46: 0 | BB46: 0 | BC46: 0 | BD46: 0 | BE46: 0 | BF46: 0 | BG46: 0 | BH46: 0 | BI46: 0
A47: =Controls!A118 -> Please add Position | B47: 0 | C47: 0 | D47: 0 | E47: 0 | F47: 0 | G47: 0 | H47: 0 | I47: 0 | J47: 0 | K47: 0 | L47: 0 | M47: 0 | N47: 0 | O47: 0 | P47: 0 | Q47: 0 | R47: 0 | S47: 0 | T47: 0 | U47: 0 | V47: 0 | W47: 0 | X47: 0 | Y47: 0 | Z47: 0 | AA47: 0 | AB47: 0 | AC47: 0 | AD47: 0 | AE47: 0 | AF47: 0 | AG47: 0 | AH47: 0 | AI47: 0 | AJ47: 0 | AK47: 0 | AL47: 0 | AM47: 0 | AN47: 0 | AO47: 0 | AP47: 0 | AQ47: 0 | AR47: 0 | AS47: 0 | AT47: 0 | AU47: 0 | AV47: 0 | AW47: 0 | AX47: 0 | AY47: 0 | AZ47: 0 | BA47: 0 | BB47: 0 | BC47: 0 | BD47: 0 | BE47: 0 | BF47: 0 | BG47: 0 | BH47: 0 | BI47: 0
A48: =Controls!A119 -> Please add Position | B48: 0 | C48: 0 | D48: 0 | E48: 0 | F48: 0 | G48: 0 | H48: 0 | I48: 0 | J48: 0 | K48: 0 | L48: 0 | M48: 0 | N48: 0 | O48: 0 | P48: 0 | Q48: 0 | R48: 0 | S48: 0 | T48: 0 | U48: 0 | V48: 0 | W48: 0 | X48: 0 | Y48: 0 | Z48: 0 | AA48: 0 | AB48: 0 | AC48: 0 | AD48: 0 | AE48: 0 | AF48: 0 | AG48: 0 | AH48: 0 | AI48: 0 | AJ48: 0 | AK48: 0 | AL48: 0 | AM48: 0 | AN48: 0 | AO48: 0 | AP48: 0 | AQ48: 0 | AR48: 0 | AS48: 0 | AT48: 0 | AU48: 0 | AV48: 0 | AW48: 0 | AX48: 0 | AY48: 0 | AZ48: 0 | BA48: 0 | BB48: 0 | BC48: 0 | BD48: 0 | BE48: 0 | BF48: 0 | BG48: 0 | BH48: 0 | BI48: 0
A49: =Controls!A120 -> Please add Position | B49: 0 | C49: 0 | D49: 0 | E49: 0 | F49: 0 | G49: 0 | H49: 0 | I49: 0 | J49: 0 | K49: 0 | L49: 0 | M49: 0 | N49: 0 | O49: 0 | P49: 0 | Q49: 0 | R49: 0 | S49: 0 | T49: 0 | U49: 0 | V49: 0 | W49: 0 | X49: 0 | Y49: 0 | Z49: 0 | AA49: 0 | AB49: 0 | AC49: 0 | AD49: 0 | AE49: 0 | AF49: 0 | AG49: 0 | AH49: 0 | AI49: 0 | AJ49: 0 | AK49: 0 | AL49: 0 | AM49: 0 | AN49: 0 | AO49: 0 | AP49: 0 | AQ49: 0 | AR49: 0 | AS49: 0 | AT49: 0 | AU49: 0 | AV49: 0 | AW49: 0 | AX49: 0 | AY49: 0 | AZ49: 0 | BA49: 0 | BB49: 0 | BC49: 0 | BD49: 0 | BE49: 0 | BF49: 0 | BG49: 0 | BH49: 0 | BI49: 0
A50: =Controls!A121 -> Please add Position | B50: 0 | C50: 0 | D50: 0 | E50: 0 | F50: 0 | G50: 0 | H50: 0 | I50: 0 | J50: 0 | K50: 0 | L50: 0 | M50: 0 | N50: 0 | O50: 0 | P50: 0 | Q50: 0 | R50: 0 | S50: 0 | T50: 0 | U50: 0 | V50: 0 | W50: 0 | X50: 0 | Y50: 0 | Z50: 0 | AA50: 0 | AB50: 0 | AC50: 0 | AD50: 0 | AE50: 0 | AF50: 0 | AG50: 0 | AH50: 0 | AI50: 0 | AJ50: 0 | AK50: 0 | AL50: 0 | AM50: 0 | AN50: 0 | AO50: 0 | AP50: 0 | AQ50: 0 | AR50: 0 | AS50: 0 | AT50: 0 | AU50: 0 | AV50: 0 | AW50: 0 | AX50: 0 | AY50: 0 | AZ50: 0 | BA50: 0 | BB50: 0 | BC50: 0 | BD50: 0 | BE50: 0 | BF50: 0 | BG50: 0 | BH50: 0 | BI50: 0
A51: =Controls!A122 -> Please add Position | B51: 0 | C51: 0 | D51: 0 | E51: 0 | F51: 0 | G51: 0 | H51: 0 | I51: 0 | J51: 0 | K51: 0 | L51: 0 | M51: 0 | N51: 0 | O51: 0 | P51: 0 | Q51: 0 | R51: 0 | S51: 0 | T51: 0 | U51: 0 | V51: 0 | W51: 0 | X51: 0 | Y51: 0 | Z51: 0 | AA51: 0 | AB51: 0 | AC51: 0 | AD51: 0 | AE51: 0 | AF51: 0 | AG51: 0 | AH51: 0 | AI51: 0 | AJ51: 0 | AK51: 0 | AL51: 0 | AM51: 0 | AN51: 0 | AO51: 0 | AP51: 0 | AQ51: 0 | AR51: 0 | AS51: 0 | AT51: 0 | AU51: 0 | AV51: 0 | AW51: 0 | AX51: 0 | AY51: 0 | AZ51: 0 | BA51: 0 | BB51: 0 | BC51: 0 | BD51: 0 | BE51: 0 | BF51: 0 | BG51: 0 | BH51: 0 | BI51: 0
A52: TACFI/STRATFI Program Staff (Placeholder) | B52: 0 | C52: 0 | D52: 0 | E52: 0 | F52: 0 | G52: 0 | H52: 0 | I52: 0 | J52: 0 | K52: 0 | L52: 0 | M52: 0 | N52: 0 | O52: 0 | P52: 0 | Q52: 0 | R52: 0 | S52: 0 | T52: 0 | U52: 0 | V52: 0 | W52: 0 | X52: 0 | Y52: 0 | Z52: 0 | AA52: 0 | AB52: 0 | AC52: 0 | AD52: 0 | AE52: 0 | AF52: 0 | AG52: 0 | AH52: 0 | AI52: 0 | AJ52: 0 | AK52: 0 | AL52: 0 | AM52: 0 | AN52: 0 | AO52: 0 | AP52: 0 | AQ52: 0 | AR52: 0 | AS52: 0 | AT52: 0 | AU52: 0 | AV52: 0 | AW52: 0 | AX52: 0 | AY52: 0 | AZ52: 0 | BA52: 0 | BB52: 0 | BC52: 0 | BD52: 0 | BE52: 0 | BF52: 0 | BG52: 0 | BH52: 0 | BI52: 0
A53: RDRE Propulsion Engineers (TACFI-funded) | Q53: 3 | R53: 3 | S53: 3 | T53: 3 | U53: 3 | V53: 3 | W53: 3 | X53: 3 | Y53: 3 | Z53: 3 | AA53: 3 | AB53: 3 | AC53: 3 | AD53: 3 | AE53: 3 | AF53: 3 | AG53: 3 | AH53: 3
A54: RDRE Program Engineers (STRATFI-funded) | B54: =SUM(B10:B52) -> 7.605 | C54: =SUM(C10:C52) -> 7.605 | D54: =SUM(D10:D52) -> 7.605 | E54: =SUM(E10:E52) -> 21.605 | F54: =SUM(F10:F52) -> 21.605 | G54: =SUM(G10:G52) -> 24.97 | H54: =SUM(H10:H52) -> 24.97 | I54: =SUM(I10:I52) -> 25.97 | ... AH54: =SUM(AH10:AH52) -> 53 | AI54: 5 | AJ54: 5 | AK54: 5 | AL54: 5 | AM54: 5 | AN54: 5 | AO54: 5 | AP54: 5 | AQ54: 5 | AR54: 5 | AS54: 5 | AT54: 5 | AU54: 5 | AV54: 5 | AW54: 5 | AX54: 8 | AY54: 8 | AZ54: 8 | BA54: 8 | BB54: 8 | BC54: 8 | BD54: 8 | BE54: 8 | BF54: 8 | BG54: 8 | BH54: 8 | BI54: 8
A55: Scorpius Manufacturing Staff | S55: 6.45 | T55: 4 | U55: 4 | V55: 4 | W55: 4 | X55: 4 | Y55: 4 | Z55: 4 | AA55: 4 | AB55: 4 | AC55: 4 | AD55: 4 | AE55: 4 | AF55: 4 | AG55: 4 | AH55: 4 | AI55: 4 | AJ55: 4 | AK55: 4 | AL55: 6 | AM55: 6 | AN55: 6 | AO55: 6 | AP55: 6 | AQ55: 6 | AR55: 6 | AS55: 6 | AT55: 6 | AU55: 6 | AV55: 6 | AW55: 6 | AX55: 8 | AY55: 8 | AZ55: 8 | BA55: 8 | BB55: 8 | BC55: 8 | BD55: 8 | BE55: 8 | BF55: 8 | BG55: 8 | BH55: 8 | BI55: 8
A56: Total traditional headcount | B56: =SUM(B54+B55) -> 7.605 | C56: =SUM(C54+C55) -> 7.605 | D56: =SUM(D54+D55) -> 7.605 | E56: =SUM(E54+E55) -> 21.605 | F56: =SUM(F54+F55) -> 21.605 | G56: =SUM(G54+G55) -> 24.97 | H56: =SUM(H54+H55) -> 24.97 | I56: =SUM(I54+I55) -> 25.97 | ... BI56: =SUM(BI54+BI55) -> 16
A57: Monthly Compensation
A59: Corporate Team
A60: President | B60: =HLOOKUP(B$3,Controls!$A$5:$F$153,MATCH($A60,Controls!$A$5:$A$153,0),0)*B10/12 -> 9562.5 | C60: =HLOOKUP(C$3,Controls!$A$5:$F$153,MATCH($A60,Controls!$A$5:$A$153,0),0)*C10/12 -> 9562.5 | D60: =HLOOKUP(D$3,Controls!$A$5:$F$153,MATCH($A60,Controls!$A$5:$A$153,0),0)*D10/12 -> 9562.5 | E60: =HLOOKUP(E$3,Controls!$A$5:$F$153,MATCH($A60,Controls!$A$5:$A$153,0),0)*E10/12 -> 9562.5 | F60: =HLOOKUP(F$3,Controls!$A$5:$F$153,MATCH($A60,Controls!$A$5:$A$153,0),0)*F10/12 -> 9562.5 | G60: =HLOOKUP(G$3,Controls!$A$5:$F$153,MATCH($A60,Controls!$A$5:$A$153,0),0)*G10/12 -> 9562.5 | H60: =HLOOKUP(H$3,Controls!$A$5:$F$153,MATCH($A60,Controls!$A$5:$A$153,0),0)*H10/12 -> 9562.5 | I60: =HLOOKUP(I$3,Controls!$A$5:$F$153,MATCH($A60,Controls!$A$5:$A$153,0),0)*I10/12 -> 9562.5 | ... BI60: =HLOOKUP(BI$3,Controls!$A$5:$F$153,MATCH($A60,Controls!$A$5:$A$153,0),0)*BI10/12 -> 12661.974
A61: CEO | B61: =HLOOKUP(B$3,Controls!$A$5:$F$153,MATCH($A61,Controls!$A$5:$A$153,0),0)*B11/12 -> 16734.375 | C61: =HLOOKUP(C$3,Controls!$A$5:$F$153,MATCH($A61,Controls!$A$5:$A$153,0),0)*C11/12 -> 16734.375 | D61: =HLOOKUP(D$3,Controls!$A$5:$F$153,MATCH($A61,Controls!$A$5:$A$153,0),0)*D11/12 -> 16734.375 | E61: =HLOOKUP(E$3,Controls!$A$5:$F$153,MATCH($A61,Controls!$A$5:$A$153,0),0)*E11/12 -> 16734.375 | F61: =HLOOKUP(F$3,Controls!$A$5:$F$153,MATCH($A61,Controls!$A$5:$A$153,0),0)*F11/12 -> 16734.375 | G61: =HLOOKUP(G$3,Controls!$A$5:$F$153,MATCH($A61,Controls!$A$5:$A$153,0),0)*G11/12 -> 16734.375 | H61: =HLOOKUP(H$3,Controls!$A$5:$F$153,MATCH($A61,Controls!$A$5:$A$153,0),0)*H11/12 -> 16734.375 | I61: =HLOOKUP(I$3,Controls!$A$5:$F$153,MATCH($A61,Controls!$A$5:$A$153,0),0)*I11/12 -> 16734.375 | ... BI61: =HLOOKUP(BI$3,Controls!$A$5:$F$153,MATCH($A61,Controls!$A$5:$A$153,0),0)*BI11/12 -> 44316.909
A62: COO | B62: =HLOOKUP(B$3,Controls!$A$5:$F$153,MATCH($A62,Controls!$A$5:$A$153,0),0)*B12/12 -> 10518.75 | C62: =HLOOKUP(C$3,Controls!$A$5:$F$153,MATCH($A62,Controls!$A$5:$A$153,0),0)*C12/12 -> 10518.75 | D62: =HLOOKUP(D$3,Controls!$A$5:$F$153,MATCH($A62,Controls!$A$5:$A$153,0),0)*D12/12 -> 10518.75 | E62: =HLOOKUP(E$3,Controls!$A$5:$F$153,MATCH($A62,Controls!$A$5:$A$153,0),0)*E12/12 -> 10518.75 | F62: =HLOOKUP(F$3,Controls!$A$5:$F$153,MATCH($A62,Controls!$A$5:$A$153,0),0)*F12/12 -> 10518.75 | G62: =HLOOKUP(G$3,Controls!$A$5:$F$153,MATCH($A62,Controls!$A$5:$A$153,0),0)*G12/12 -> 10518.75 | H62: =HLOOKUP(H$3,Controls!$A$5:$F$153,MATCH($A62,Controls!$A$5:$A$153,0),0)*H12/12 -> 10518.75 | I62: =HLOOKUP(I$3,Controls!$A$5:$F$153,MATCH($A62,Controls!$A$5:$A$153,0),0)*I12/12 -> 10518.75 | ... BI62: =HLOOKUP(BI$3,Controls!$A$5:$F$153,MATCH($A62,Controls!$A$5:$A$153,0),0)*BI12/12 -> 27856.343
A63: CTO | B63: =HLOOKUP(B$3,Controls!$A$5:$F$153,MATCH($A63,Controls!$A$5:$A$153,0),0)*B13/12 -> 13865.625 | C63: =HLOOKUP(C$3,Controls!$A$5:$F$153,MATCH($A63,Controls!$A$5:$A$153,0),0)*C13/12 -> 13865.625 | D63: =HLOOKUP(D$3,Controls!$A$5:$F$153,MATCH($A63,Controls!$A$5:$A$153,0),0)*D13/12 -> 13865.625 | E63: =HLOOKUP(E$3,Controls!$A$5:$F$153,MATCH($A63,Controls!$A$5:$A$153,0),0)*E13/12 -> 13865.625 | F63: =HLOOKUP(F$3,Controls!$A$5:$F$153,MATCH($A63,Controls!$A$5:$A$153,0),0)*F13/12 -> 13865.625 | G63: =HLOOKUP(G$3,Controls!$A$5:$F$153,MATCH($A63,Controls!$A$5:$A$153,0),0)*G13/12 -> 13865.625 | H63: =HLOOKUP(H$3,Controls!$A$5:$F$153,MATCH($A63,Controls!$A$5:$A$153,0),0)*H13/12 -> 13865.625 | I63: =HLOOKUP(I$3,Controls!$A$5:$F$153,MATCH($A63,Controls!$A$5:$A$153,0),0)*I13/12 -> 13865.625 | ... BI63: =HLOOKUP(BI$3,Controls!$A$5:$F$153,MATCH($A63,Controls!$A$5:$A$153,0),0)*BI13/12 -> 36719.725
A64: Instrumentation Controls Electrical Engineer | B64: =HLOOKUP(B$3,Controls!$A$5:$F$153,MATCH($A64,Controls!$A$5:$A$153,0),0)*B14/12 -> 0 | C64: =HLOOKUP(C$3,Controls!$A$5:$F$153,MATCH($A64,Controls!$A$5:$A$153,0),0)*C14/12 -> 0 | D64: =HLOOKUP(D$3,Controls!$A$5:$F$153,MATCH($A64,Controls!$A$5:$A$153,0),0)*D14/12 -> 0 | E64: =HLOOKUP(E$3,Controls!$A$5:$F$153,MATCH($A64,Controls!$A$5:$A$153,0),0)*E14/12 -> 0 | F64: =HLOOKUP(F$3,Controls!$A$5:$F$153,MATCH($A64,Controls!$A$5:$A$153,0),0)*F14/12 -> 0 | G64: =HLOOKUP(G$3,Controls!$A$5:$F$153,MATCH($A64,Controls!$A$5:$A$153,0),0)*G14/12 -> 0 | H64: =HLOOKUP(H$3,Controls!$A$5:$F$153,MATCH($A64,Controls!$A$5:$A$153,0),0)*H14/12 -> 0 | I64: =HLOOKUP(I$3,Controls!$A$5:$F$153,MATCH($A64,Controls!$A$5:$A$153,0),0)*I14/12 -> 0 | ... BI64: =HLOOKUP(BI$3,Controls!$A$5:$F$153,MATCH($A64,Controls!$A$5:$A$153,0),0)*BI14/12 -> 74547.373
A65: AS9100D & ITAR Compliance Officer | B65: =HLOOKUP(B$3,Controls!$A$5:$F$153,MATCH($A65,Controls!$A$5:$A$153,0),0)*B15/12 -> 0 | C65: =HLOOKUP(C$3,Controls!$A$5:$F$153,MATCH($A65,Controls!$A$5:$A$153,0),0)*C15/12 -> 0 | D65: =HLOOKUP(D$3,Controls!$A$5:$F$153,MATCH($A65,Controls!$A$5:$A$153,0),0)*D15/12 -> 0 | E65: =HLOOKUP(E$3,Controls!$A$5:$F$153,MATCH($A65,Controls!$A$5:$A$153,0),0)*E15/12 -> 0 | F65: =HLOOKUP(F$3,Controls!$A$5:$F$153,MATCH($A65,Controls!$A$5:$A$153,0),0)*F15/12 -> 0 | G65: =HLOOKUP(G$3,Controls!$A$5:$F$153,MATCH($A65,Controls!$A$5:$A$153,0),0)*G15/12 -> 0 | H65: =HLOOKUP(H$3,Controls!$A$5:$F$153,MATCH($A65,Controls!$A$5:$A$153,0),0)*H15/12 -> 0 | I65: =HLOOKUP(I$3,Controls!$A$5:$F$153,MATCH($A65,Controls!$A$5:$A$153,0),0)*I15/12 -> 0 | ... BI65: =HLOOKUP(BI$3,Controls!$A$5:$F$153,MATCH($A65,Controls!$A$5:$A$153,0),0)*BI15/12 -> 28489.442
A67: Staff (based on USD salaries)
A69: Administrative Assistant | B69: =HLOOKUP(B$3,Controls!$A$5:$F$153,MATCH($A69,Controls!$A$5:$A$153,0),0)*B17/12 -> 4250 | C69: =HLOOKUP(C$3,Controls!$A$5:$F$153,MATCH($A69,Controls!$A$5:$A$153,0),0)*C17/12 -> 4250 | D69: =HLOOKUP(D$3,Controls!$A$5:$F$153,MATCH($A69,Controls!$A$5:$A$153,0),0)*D17/12 -> 4250 | E69: =HLOOKUP(E$3,Controls!$A$5:$F$153,MATCH($A69,Controls!$A$5:$A$153,0),0)*E17/12 -> 4250 | F69: =HLOOKUP(F$3,Controls!$A$5:$F$153,MATCH($A69,Controls!$A$5:$A$153,0),0)*F17/12 -> 4250 | G69: =HLOOKUP(G$3,Controls!$A$5:$F$153,MATCH($A69,Controls!$A$5:$A$153,0),0)*G17/12 -> 4250 | H69: =HLOOKUP(H$3,Controls!$A$5:$F$153,MATCH($A69,Controls!$A$5:$A$153,0),0)*H17/12 -> 4250 | I69: =HLOOKUP(I$3,Controls!$A$5:$F$153,MATCH($A69,Controls!$A$5:$A$153,0),0)*I17/12 -> 4250 | ... BI69: =HLOOKUP(BI$3,Controls!$A$5:$F$153,MATCH($A69,Controls!$A$5:$A$153,0),0)*BI17/12 -> 11255.088
A70: Aero Modeling Engineer | B70: =HLOOKUP(B$3,Controls!$A$5:$F$153,MATCH($A70,Controls!$A$5:$A$153,0),0)*B18/12 -> 0 | C70: =HLOOKUP(C$3,Controls!$A$5:$F$153,MATCH($A70,Controls!$A$5:$A$153,0),0)*C18/12 -> 0 | D70: =HLOOKUP(D$3,Controls!$A$5:$F$153,MATCH($A70,Controls!$A$5:$A$153,0),0)*D18/12 -> 0 | E70: =HLOOKUP(E$3,Controls!$A$5:$F$153,MATCH($A70,Controls!$A$5:$A$153,0),0)*E18/12 -> 0 | F70: =HLOOKUP(F$3,Controls!$A$5:$F$153,MATCH($A70,Controls!$A$5:$A$153,0),0)*F18/12 -> 0 | G70: =HLOOKUP(G$3,Controls!$A$5:$F$153,MATCH($A70,Controls!$A$5:$A$153,0),0)*G18/12 -> 0 | H70: =HLOOKUP(H$3,Controls!$A$5:$F$153,MATCH($A70,Controls!$A$5:$A$153,0),0)*H18/12 -> 0 | I70: =HLOOKUP(I$3,Controls!$A$5:$F$153,MATCH($A70,Controls!$A$5:$A$153,0),0)*I18/12 -> 0 | ... BI70: =HLOOKUP(BI$3,Controls!$A$5:$F$153,MATCH($A70,Controls!$A$5:$A$153,0),0)*BI18/12 -> 14244.721
A71: Avionics Hardware Development Engineer | B71: =HLOOKUP(B$3,Controls!$A$5:$F$153,MATCH($A71,Controls!$A$5:$A$153,0),0)*B19/12 -> 0 | C71: =HLOOKUP(C$3,Controls!$A$5:$F$153,MATCH($A71,Controls!$A$5:$A$153,0),0)*C19/12 -> 0 | D71: =HLOOKUP(D$3,Controls!$A$5:$F$153,MATCH($A71,Controls!$A$5:$A$153,0),0)*D19/12 -> 0 | E71: =HLOOKUP(E$3,Controls!$A$5:$F$153,MATCH($A71,Controls!$A$5:$A$153,0),0)*E19/12 -> 0 | F71: =HLOOKUP(F$3,Controls!$A$5:$F$153,MATCH($A71,Controls!$A$5:$A$153,0),0)*F19/12 -> 0 | G71: =HLOOKUP(G$3,Controls!$A$5:$F$153,MATCH($A71,Controls!$A$5:$A$153,0),0)*G19/12 -> 0 | H71: =HLOOKUP(H$3,Controls!$A$5:$F$153,MATCH($A71,Controls!$A$5:$A$153,0),0)*H19/12 -> 0 | I71: =HLOOKUP(I$3,Controls!$A$5:$F$153,MATCH($A71,Controls!$A$5:$A$153,0),0)*I19/12 -> 0 | ... BI71: =HLOOKUP(BI$3,Controls!$A$5:$F$153,MATCH($A71,Controls!$A$5:$A$153,0),0)*BI19/12 -> 15377.968
A72: Contracts Administrator- PROGRAM MANAGER | B72: =HLOOKUP(B$3,Controls!$A$5:$F$153,MATCH($A72,Controls!$A$5:$A$153,0),0)*B20/12 -> 0 | C72: =HLOOKUP(C$3,Controls!$A$5:$F$153,MATCH($A72,Controls!$A$5:$A$153,0),0)*C20/12 -> 0 | D72: =HLOOKUP(D$3,Controls!$A$5:$F$153,MATCH($A72,Controls!$A$5:$A$153,0),0)*D20/12 -> 0 | E72: =HLOOKUP(E$3,Controls!$A$5:$F$153,MATCH($A72,Controls!$A$5:$A$153,0),0)*E20/12 -> 0 | F72: =HLOOKUP(F$3,Controls!$A$5:$F$153,MATCH($A72,Controls!$A$5:$A$153,0),0)*F20/12 -> 0 | G72: =HLOOKUP(G$3,Controls!$A$5:$F$153,MATCH($A72,Controls!$A$5:$A$153,0),0)*G20/12 -> 0 | H72: =HLOOKUP(H$3,Controls!$A$5:$F$153,MATCH($A72,Controls!$A$5:$A$153,0),0)*H20/12 -> 0 | I72: =HLOOKUP(I$3,Controls!$A$5:$F$153,MATCH($A72,Controls!$A$5:$A$153,0),0)*I20/12 -> 0 | ... BI72: =HLOOKUP(BI$3,Controls!$A$5:$F$153,MATCH($A72,Controls!$A$5:$A$153,0),0)*BI20/12 -> 17072.14
A73: Design Engineer (mech)- 12 Scorpius (average salary) | B73: =HLOOKUP(B$3,Controls!$A$5:$F$153,MATCH($A73,Controls!$A$5:$A$153,0),0)*B21/12 -> 7962.5 | C73: =HLOOKUP(C$3,Controls!$A$5:$F$153,MATCH($A73,Controls!$A$5:$A$153,0),0)*C21/12 -> 7962.5 | D73: =HLOOKUP(D$3,Controls!$A$5:$F$153,MATCH($A73,Controls!$A$5:$A$153,0),0)*D21/12 -> 7962.5 | E73: =HLOOKUP(E$3,Controls!$A$5:$F$153,MATCH($A73,Controls!$A$5:$A$153,0),0)*E21/12 -> 119437.5 | F73: =HLOOKUP(F$3,Controls!$A$5:$F$153,MATCH($A73,Controls!$A$5:$A$153,0),0)*F21/12 -> 119437.5 | G73: =HLOOKUP(G$3,Controls!$A$5:$F$153,MATCH($A73,Controls!$A$5:$A$153,0),0)*G21/12 -> 119437.5 | H73: =HLOOKUP(H$3,Controls!$A$5:$F$153,MATCH($A73,Controls!$A$5:$A$153,0),0)*H21/12 -> 119437.5 | I73: =HLOOKUP(I$3,Controls!$A$5:$F$153,MATCH($A73,Controls!$A$5:$A$153,0),0)*I21/12 -> 119437.5 | ... BI73: =HLOOKUP(BI$3,Controls!$A$5:$F$153,MATCH($A73,Controls!$A$5:$A$153,0),0)*BI21/12 -> 179237.28
A74: Engineering Internships- Admin | B74: =HLOOKUP(B$3,Controls!$A$5:$F$153,MATCH($A74,Controls!$A$5:$A$153,0),0)*B22/12 -> 0 | C74: =HLOOKUP(C$3,Controls!$A$5:$F$153,MATCH($A74,Controls!$A$5:$A$153,0),0)*C22/12 -> 0 | D74: =HLOOKUP(D$3,Controls!$A$5:$F$153,MATCH($A74,Controls!$A$5:$A$153,0),0)*D22/12 -> 0 | E74: =HLOOKUP(E$3,Controls!$A$5:$F$153,MATCH($A74,Controls!$A$5:$A$153,0),0)*E22/12 -> 0 | F74: =HLOOKUP(F$3,Controls!$A$5:$F$153,MATCH($A74,Controls!$A$5:$A$153,0),0)*F22/12 -> 0 | G74: =HLOOKUP(G$3,Controls!$A$5:$F$153,MATCH($A74,Controls!$A$5:$A$153,0),0)*G22/12 -> 0 | H74: =HLOOKUP(H$3,Controls!$A$5:$F$153,MATCH($A74,Controls!$A$5:$A$153,0),0)*H22/12 -> 0 | I74: =HLOOKUP(I$3,Controls!$A$5:$F$153,MATCH($A74,Controls!$A$5:$A$153,0),0)*I22/12 -> 0 | ... BI74: =HLOOKUP(BI$3,Controls!$A$5:$F$153,MATCH($A74,Controls!$A$5:$A$153,0),0)*BI22/12 -> 16497.37
A75: Guidance Navigation and Control Engineer | B75: =HLOOKUP(B$3,Controls!$A$5:$F$153,MATCH($A75,Controls!$A$5:$A$153,0),0)*B23/12 -> 0 | C75: =HLOOKUP(C$3,Controls!$A$5:$F$153,MATCH($A75,Controls!$A$5:$A$153,0),0)*C23/12 -> 0 | D75: =HLOOKUP(D$3,Controls!$A$5:$F$153,MATCH($A75,Controls!$A$5:$A$153,0),0)*D23/12 -> 0 | E75: =HLOOKUP(E$3,Controls!$A$5:$F$153,MATCH($A75,Controls!$A$5:$A$153,0),0)*E23/12 -> 0 | F75: =HLOOKUP(F$3,Controls!$A$5:$F$153,MATCH($A75,Controls!$A$5:$A$153,0),0)*F23/12 -> 0 | G75: =HLOOKUP(G$3,Controls!$A$5:$F$153,MATCH($A75,Controls!$A$5:$A$153,0),0)*G23/12 -> 0 | H75: =HLOOKUP(H$3,Controls!$A$5:$F$153,MATCH($A75,Controls!$A$5:$A$153,0),0)*H23/12 -> 0 | I75: =HLOOKUP(I$3,Controls!$A$5:$F$153,MATCH($A75,Controls!$A$5:$A$153,0),0)*I23/12 -> 0 | ... BI75: =HLOOKUP(BI$3,Controls!$A$5:$F$153,MATCH($A75,Controls!$A$5:$A$153,0),0)*BI23/12 -> 13928.172
A76: Junior RF Engineer | B76: =HLOOKUP(B$3,Controls!$A$5:$F$153,MATCH($A76,Controls!$A$5:$A$153,0),0)*B24/12 -> 0 | C76: =HLOOKUP(C$3,Controls!$A$5:$F$153,MATCH($A76,Controls!$A$5:$A$153,0),0)*C24/12 -> 0 | D76: =HLOOKUP(D$3,Controls!$A$5:$F$153,MATCH($A76,Controls!$A$5:$A$153,0),0)*D24/12 -> 0 | E76: =HLOOKUP(E$3,Controls!$A$5:$F$153,MATCH($A76,Controls!$A$5:$A$153,0),0)*E24/12 -> 0 | F76: =HLOOKUP(F$3,Controls!$A$5:$F$153,MATCH($A76,Controls!$A$5:$A$153,0),0)*F24/12 -> 0 | G76: =HLOOKUP(G$3,Controls!$A$5:$F$153,MATCH($A76,Controls!$A$5:$A$153,0),0)*G24/12 -> 0 | H76: =HLOOKUP(H$3,Controls!$A$5:$F$153,MATCH($A76,Controls!$A$5:$A$153,0),0)*H24/12 -> 0 | I76: =HLOOKUP(I$3,Controls!$A$5:$F$153,MATCH($A76,Controls!$A$5:$A$153,0),0)*I24/12 -> 0 | ... BI76: =HLOOKUP(BI$3,Controls!$A$5:$F$153,MATCH($A76,Controls!$A$5:$A$153,0),0)*BI24/12 -> 9496.4806
A77: Launch Engineer | B77: =HLOOKUP(B$3,Controls!$A$5:$F$153,MATCH($A77,Controls!$A$5:$A$153,0),0)*B25/12 -> 0 | C77: =HLOOKUP(C$3,Controls!$A$5:$F$153,MATCH($A77,Controls!$A$5:$A$153,0),0)*C25/12 -> 0 | D77: =HLOOKUP(D$3,Controls!$A$5:$F$153,MATCH($A77,Controls!$A$5:$A$153,0),0)*D25/12 -> 0 | E77: =HLOOKUP(E$3,Controls!$A$5:$F$153,MATCH($A77,Controls!$A$5:$A$153,0),0)*E25/12 -> 0 | F77: =HLOOKUP(F$3,Controls!$A$5:$F$153,MATCH($A77,Controls!$A$5:$A$153,0),0)*F25/12 -> 0 | G77: =HLOOKUP(G$3,Controls!$A$5:$F$153,MATCH($A77,Controls!$A$5:$A$153,0),0)*G25/12 -> 0 | H77: =HLOOKUP(H$3,Controls!$A$5:$F$153,MATCH($A77,Controls!$A$5:$A$153,0),0)*H25/12 -> 0 | I77: =HLOOKUP(I$3,Controls!$A$5:$F$153,MATCH($A77,Controls!$A$5:$A$153,0),0)*I25/12 -> 0 | ... BI77: =HLOOKUP(BI$3,Controls!$A$5:$F$153,MATCH($A77,Controls!$A$5:$A$153,0),0)*BI25/12 -> 13928.172
A78: Mechanical Designer/Drafter/Technician | B78: =HLOOKUP(B$3,Controls!$A$5:$F$153,MATCH($A78,Controls!$A$5:$A$153,0),0)*B26/12 -> 0 | C78: =HLOOKUP(C$3,Controls!$A$5:$F$153,MATCH($A78,Controls!$A$5:$A$153,0),0)*C26/12 -> 0 | D78: =HLOOKUP(D$3,Controls!$A$5:$F$153,MATCH($A78,Controls!$A$5:$A$153,0),0)*D26/12 -> 0 | E78: =HLOOKUP(E$3,Controls!$A$5:$F$153,MATCH($A78,Controls!$A$5:$A$153,0),0)*E26/12 -> 0 | F78: =HLOOKUP(F$3,Controls!$A$5:$F$153,MATCH($A78,Controls!$A$5:$A$153,0),0)*F26/12 -> 0 | G78: =HLOOKUP(G$3,Controls!$A$5:$F$153,MATCH($A78,Controls!$A$5:$A$153,0),0)*G26/12 -> 0 | H78: =HLOOKUP(H$3,Controls!$A$5:$F$153,MATCH($A78,Controls!$A$5:$A$153,0),0)*H26/12 -> 0 | I78: =HLOOKUP(I$3,Controls!$A$5:$F$153,MATCH($A78,Controls!$A$5:$A$153,0),0)*I26/12 -> 0 | ... BI78: =HLOOKUP(BI$3,Controls!$A$5:$F$153,MATCH($A78,Controls!$A$5:$A$153,0),0)*BI26/12 -> 10762.678
A79: Mission Integration Engineer | B79: =HLOOKUP(B$3,Controls!$A$5:$F$153,MATCH($A79,Controls!$A$5:$A$153,0),0)*B27/12 -> 0 | C79: =HLOOKUP(C$3,Controls!$A$5:$F$153,MATCH($A79,Controls!$A$5:$A$153,0),0)*C27/12 -> 0 | D79: =HLOOKUP(D$3,Controls!$A$5:$F$153,MATCH($A79,Controls!$A$5:$A$153,0),0)*D27/12 -> 0 | E79: =HLOOKUP(E$3,Controls!$A$5:$F$153,MATCH($A79,Controls!$A$5:$A$153,0),0)*E27/12 -> 0 | F79: =HLOOKUP(F$3,Controls!$A$5:$F$153,MATCH($A79,Controls!$A$5:$A$153,0),0)*F27/12 -> 0 | G79: =HLOOKUP(G$3,Controls!$A$5:$F$153,MATCH($A79,Controls!$A$5:$A$153,0),0)*G27/12 -> 0 | H79: =HLOOKUP(H$3,Controls!$A$5:$F$153,MATCH($A79,Controls!$A$5:$A$153,0),0)*H27/12 -> 0 | I79: =HLOOKUP(I$3,Controls!$A$5:$F$153,MATCH($A79,Controls!$A$5:$A$153,0),0)*I27/12 -> 0 | ... BI79: =HLOOKUP(BI$3,Controls!$A$5:$F$153,MATCH($A79,Controls!$A$5:$A$153,0),0)*BI27/12 -> 13928.172
A80: Propulsion Development Engineer | B80: =HLOOKUP(B$3,Controls!$A$5:$F$153,MATCH($A80,Controls!$A$5:$A$153,0),0)*B28/12 -> 0 | C80: =HLOOKUP(C$3,Controls!$A$5:$F$153,MATCH($A80,Controls!$A$5:$A$153,0),0)*C28/12 -> 0 | D80: =HLOOKUP(D$3,Controls!$A$5:$F$153,MATCH($A80,Controls!$A$5:$A$153,0),0)*D28/12 -> 0 | E80: =HLOOKUP(E$3,Controls!$A$5:$F$153,MATCH($A80,Controls!$A$5:$A$153,0),0)*E28/12 -> 0 | F80: =HLOOKUP(F$3,Controls!$A$5:$F$153,MATCH($A80,Controls!$A$5:$A$153,0),0)*F28/12 -> 0 | G80: =HLOOKUP(G$3,Controls!$A$5:$F$153,MATCH($A80,Controls!$A$5:$A$153,0),0)*G28/12 -> 0 | H80: =HLOOKUP(H$3,Controls!$A$5:$F$153,MATCH($A80,Controls!$A$5:$A$153,0),0)*H28/12 -> 0 | I80: =HLOOKUP(I$3,Controls!$A$5:$F$153,MATCH($A80,Controls!$A$5:$A$153,0),0)*I28/12 -> 0 | ... BI80: =HLOOKUP(BI$3,Controls!$A$5:$F$153,MATCH($A80,Controls!$A$5:$A$153,0),0)*BI28/12 -> 15510.918
... A93: Instument Control Electrical- ICE Technicians - OPS | B93: =HLOOKUP(B$3,Controls!$A$5:$F$153,MATCH($A93,Controls!$A$5:$A$153,0),0)*B41/12 -> 8437.5 | C93: =HLOOKUP(C$3,Controls!$A$5:$F$153,MATCH($A93,Controls!$A$5:$A$153,0),0)*C41/12 -> 8437.5 | D93: =HLOOKUP(D$3,Controls!$A$5:$F$153,MATCH($A93,Controls!$A$5:$A$153,0),0)*D41/12 -> 8437.5 | E93: =HLOOKUP(E$3,Controls!$A$5:$F$153,MATCH($A93,Controls!$A$5:$A$153,0),0)*E41/12 -> 8437.5 | F93: =HLOOKUP(F$3,Controls!$A$5:$F$153,MATCH($A93,Controls!$A$5:$A$153,0),0)*F41/12 -> 8437.5 | G93: =HLOOKUP(G$3,Controls!$A$5:$F$153,MATCH($A93,Controls!$A$5:$A$153,0),0)*G41/12 -> 16875 | H93: =HLOOKUP(H$3,Controls!$A$5:$F$153,MATCH($A93,Controls!$A$5:$A$153,0),0)*H41/12 -> 16875 | I93: =HLOOKUP(I$3,Controls!$A$5:$F$153,MATCH($A93,Controls!$A$5:$A$153,0),0)*I41/12 -> 16875 | ... BI93: =HLOOKUP(BI$3,Controls!$A$5:$F$153,MATCH($A93,Controls!$A$5:$A$153,0),0)*BI41/12 -> 56978.884
A94: =A42 -> Humanoid robots | R94: =HLOOKUP(R$3,Controls!$A$5:$F$153,MATCH($A92,Controls!$A$5:$A$153,0),0)*R42/12 -> 0 | S94: =HLOOKUP(S$3,Controls!$A$5:$F$153,MATCH($A92,Controls!$A$5:$A$153,0),0)*S42/12 -> 26071.875 | T94: =HLOOKUP(T$3,Controls!$A$5:$F$153,MATCH($A92,Controls!$A$5:$A$153,0),0)*T42/12 -> 26071.875 | U94: =HLOOKUP(U$3,Controls!$A$5:$F$153,MATCH($A92,Controls!$A$5:$A$153,0),0)*U42/12 -> 26071.875 | V94: =HLOOKUP(V$3,Controls!$A$5:$F$153,MATCH($A92,Controls!$A$5:$A$153,0),0)*V42/12 -> 26071.875 | W94: =HLOOKUP(W$3,Controls!$A$5:$F$153,MATCH($A92,Controls!$A$5:$A$153,0),0)*W42/12 -> 26071.875 | X94: =HLOOKUP(X$3,Controls!$A$5:$F$153,MATCH($A92,Controls!$A$5:$A$153,0),0)*X42/12 -> 26071.875 | Y94: =HLOOKUP(Y$3,Controls!$A$5:$F$153,MATCH($A92,Controls!$A$5:$A$153,0),0)*Y42/12 -> 26071.875 | ... BI94: =HLOOKUP(BI$3,Controls!$A$5:$F$153,MATCH($A92,Controls!$A$5:$A$153,0),0)*BI42/12 -> 227915.53
A95: General Council and International Law consultancy | B95: =HLOOKUP(B$3,Controls!$A$5:$F$153,MATCH($A95,Controls!$A$5:$A$153,0),0)*B43/12 -> 0 | C95: =HLOOKUP(C$3,Controls!$A$5:$F$153,MATCH($A95,Controls!$A$5:$A$153,0),0)*C43/12 -> 0 | D95: =HLOOKUP(D$3,Controls!$A$5:$F$153,MATCH($A95,Controls!$A$5:$A$153,0),0)*D43/12 -> 0 | E95: =HLOOKUP(E$3,Controls!$A$5:$F$153,MATCH($A95,Controls!$A$5:$A$153,0),0)*E43/12 -> 0 | F95: =HLOOKUP(F$3,Controls!$A$5:$F$153,MATCH($A95,Controls!$A$5:$A$153,0),0)*F43/12 -> 0 | G95: =HLOOKUP(G$3,Controls!$A$5:$F$153,MATCH($A95,Controls!$A$5:$A$153,0),0)*G43/12 -> 0 | H95: =HLOOKUP(H$3,Controls!$A$5:$F$153,MATCH($A95,Controls!$A$5:$A$153,0),0)*H43/12 -> 0 | I95: =HLOOKUP(I$3,Controls!$A$5:$F$153,MATCH($A95,Controls!$A$5:$A$153,0),0)*I43/12 -> 0 | ... BI95: =HLOOKUP(BI$3,Controls!$A$5:$F$153,MATCH($A95,Controls!$A$5:$A$153,0),0)*BI43/12 -> 5627.544
A96: CFO Accounting GAAP Audit | B96: =HLOOKUP(B$3,Controls!$A$5:$F$153,MATCH($A96,Controls!$A$5:$A$153,0),0)*B44/12 -> 1775 | C96: =HLOOKUP(C$3,Controls!$A$5:$F$153,MATCH($A96,Controls!$A$5:$A$153,0),0)*C44/12 -> 1775 | D96: =HLOOKUP(D$3,Controls!$A$5:$F$153,MATCH($A96,Controls!$A$5:$A$153,0),0)*D44/12 -> 1775 | E96: =HLOOKUP(E$3,Controls!$A$5:$F$153,MATCH($A96,Controls!$A$5:$A$153,0),0)*E44/12 -> 1775 | F96: =HLOOKUP(F$3,Controls!$A$5:$F$153,MATCH($A96,Controls!$A$5:$A$153,0),0)*F44/12 -> 1775 | G96: =HLOOKUP(G$3,Controls!$A$5:$F$153,MATCH($A96,Controls!$A$5:$A$153,0),0)*G44/12 -> 3600 | H96: =HLOOKUP(H$3,Controls!$A$5:$F$153,MATCH($A96,Controls!$A$5:$A$153,0),0)*H44/12 -> 3600 | I96: =HLOOKUP(I$3,Controls!$A$5:$F$153,MATCH($A96,Controls!$A$5:$A$153,0),0)*I44/12 -> 3600 | ... BI96: =HLOOKUP(BI$3,Controls!$A$5:$F$153,MATCH($A96,Controls!$A$5:$A$153,0),0)*BI44/12 -> 5627.544
A97: =A45 -> Please add Position | B97: =HLOOKUP(B$3,Controls!$A$5:$F$153,MATCH($A97,Controls!$A$5:$A$153,0),0)*B45/12 -> 0 | C97: =HLOOKUP(C$3,Controls!$A$5:$F$153,MATCH($A97,Controls!$A$5:$A$153,0),0)*C45/12 -> 0 | D97: =HLOOKUP(D$3,Controls!$A$5:$F$153,MATCH($A97,Controls!$A$5:$A$153,0),0)*D45/12 -> 0 | E97: =HLOOKUP(E$3,Controls!$A$5:$F$153,MATCH($A97,Controls!$A$5:$A$153,0),0)*E45/12 -> 0 | F97: =HLOOKUP(F$3,Controls!$A$5:$F$153,MATCH($A97,Controls!$A$5:$A$153,0),0)*F45/12 -> 0 | G97: =HLOOKUP(G$3,Controls!$A$5:$F$153,MATCH($A97,Controls!$A$5:$A$153,0),0)*G45/12 -> 0 | H97: =HLOOKUP(H$3,Controls!$A$5:$F$153,MATCH($A97,Controls!$A$5:$A$153,0),0)*H45/12 -> 0 | I97: =HLOOKUP(I$3,Controls!$A$5:$F$153,MATCH($A97,Controls!$A$5:$A$153,0),0)*I45/12 -> 0 | ... BI97: =HLOOKUP(BI$3,Controls!$A$5:$F$153,MATCH($A97,Controls!$A$5:$A$153,0),0)*BI45/12 -> 0
A98: =A46 -> Please add Position | B98: =HLOOKUP(B$3,Controls!$A$5:$F$153,MATCH($A98,Controls!$A$5:$A$153,0),0)*B46/12 -> 0 | C98: =HLOOKUP(C$3,Controls!$A$5:$F$153,MATCH($A98,Controls!$A$5:$A$153,0),0)*C46/12 -> 0 | D98: =HLOOKUP(D$3,Controls!$A$5:$F$153,MATCH($A98,Controls!$A$5:$A$153,0),0)*D46/12 -> 0 | E98: =HLOOKUP(E$3,Controls!$A$5:$F$153,MATCH($A98,Controls!$A$5:$A$153,0),0)*E46/12 -> 0 | F98: =HLOOKUP(F$3,Controls!$A$5:$F$153,MATCH($A98,Controls!$A$5:$A$153,0),0)*F46/12 -> 0 | G98: =HLOOKUP(G$3,Controls!$A$5:$F$153,MATCH($A98,Controls!$A$5:$A$153,0),0)*G46/12 -> 0 | H98: =HLOOKUP(H$3,Controls!$A$5:$F$153,MATCH($A98,Controls!$A$5:$A$153,0),0)*H46/12 -> 0 | I98: =HLOOKUP(I$3,Controls!$A$5:$F$153,MATCH($A98,Controls!$A$5:$A$153,0),0)*I46/12 -> 0 | ... BI98: =HLOOKUP(BI$3,Controls!$A$5:$F$153,MATCH($A98,Controls!$A$5:$A$153,0),0)*BI46/12 -> 0
A99: =A47 -> Please add Position | B99: =HLOOKUP(B$3,Controls!$A$5:$F$153,MATCH($A99,Controls!$A$5:$A$153,0),0)*B47/12 -> 0 | C99: =HLOOKUP(C$3,Controls!$A$5:$F$153,MATCH($A99,Controls!$A$5:$A$153,0),0)*C47/12 -> 0 | D99: =HLOOKUP(D$3,Controls!$A$5:$F$153,MATCH($A99,Controls!$A$5:$A$153,0),0)*D47/12 -> 0 | E99: =HLOOKUP(E$3,Controls!$A$5:$F$153,MATCH($A99,Controls!$A$5:$A$153,0),0)*E47/12 -> 0 | F99: =HLOOKUP(F$3,Controls!$A$5:$F$153,MATCH($A99,Controls!$A$5:$A$153,0),0)*F47/12 -> 0 | G99: =HLOOKUP(G$3,Controls!$A$5:$F$153,MATCH($A99,Controls!$A$5:$A$153,0),0)*G47/12 -> 0 | H99: =HLOOKUP(H$3,Controls!$A$5:$F$153,MATCH($A99,Controls!$A$5:$A$153,0),0)*H47/12 -> 0 | I99: =HLOOKUP(I$3,Controls!$A$5:$F$153,MATCH($A99,Controls!$A$5:$A$153,0),0)*I47/12 -> 0 | ... BI99: =HLOOKUP(BI$3,Controls!$A$5:$F$153,MATCH($A99,Controls!$A$5:$A$153,0),0)*BI47/12 -> 0
A100: =A48 -> Please add Position | B100: =HLOOKUP(B$3,Controls!$A$5:$F$153,MATCH($A100,Controls!$A$5:$A$153,0),0)*B48/12 -> 0 | C100: =HLOOKUP(C$3,Controls!$A$5:$F$153,MATCH($A100,Controls!$A$5:$A$153,0),0)*C48/12 -> 0 | D100: =HLOOKUP(D$3,Controls!$A$5:$F$153,MATCH($A100,Controls!$A$5:$A$153,0),0)*D48/12 -> 0 | E100: =HLOOKUP(E$3,Controls!$A$5:$F$153,MATCH($A100,Controls!$A$5:$A$153,0),0)*E48/12 -> 0 | F100: =HLOOKUP(F$3,Controls!$A$5:$F$153,MATCH($A100,Controls!$A$5:$A$153,0),0)*F48/12 -> 0 | G100: =HLOOKUP(G$3,Controls!$A$5:$F$153,MATCH($A100,Controls!$A$5:$A$153,0),0)*G48/12 -> 0 | H100: =HLOOKUP(H$3,Controls!$A$5:$F$153,MATCH($A100,Controls!$A$5:$A$153,0),0)*H48/12 -> 0 | I100: =HLOOKUP(I$3,Controls!$A$5:$F$153,MATCH($A100,Controls!$A$5:$A$153,0),0)*I48/12 -> 0 | ... BI100: =HLOOKUP(BI$3,Controls!$A$5:$F$153,MATCH($A100,Controls!$A$5:$A$153,0),0)*BI48/12 -> 0
A101: =A49 -> Please add Position | B101: =HLOOKUP(B$3,Controls!$A$5:$F$153,MATCH($A101,Controls!$A$5:$A$153,0),0)*B49/12 -> 0 | C101: =HLOOKUP(C$3,Controls!$A$5:$F$153,MATCH($A101,Controls!$A$5:$A$153,0),0)*C49/12 -> 0 | D101: =HLOOKUP(D$3,Controls!$A$5:$F$153,MATCH($A101,Controls!$A$5:$A$153,0),0)*D49/12 -> 0 | E101: =HLOOKUP(E$3,Controls!$A$5:$F$153,MATCH($A101,Controls!$A$5:$A$153,0),0)*E49/12 -> 0 | F101: =HLOOKUP(F$3,Controls!$A$5:$F$153,MATCH($A101,Controls!$A$5:$A$153,0),0)*F49/12 -> 0 | G101: =HLOOKUP(G$3,Controls!$A$5:$F$153,MATCH($A101,Controls!$A$5:$A$153,0),0)*G49/12 -> 0 | H101: =HLOOKUP(H$3,Controls!$A$5:$F$153,MATCH($A101,Controls!$A$5:$A$153,0),0)*H49/12 -> 0 | I101: =HLOOKUP(I$3,Controls!$A$5:$F$153,MATCH($A101,Controls!$A$5:$A$153,0),0)*I49/12 -> 0 | ... BI101: =HLOOKUP(BI$3,Controls!$A$5:$F$153,MATCH($A101,Controls!$A$5:$A$153,0),0)*BI49/12 -> 0
A102: =A50 -> Please add Position | B102: =HLOOKUP(B$3,Controls!$A$5:$F$153,MATCH($A102,Controls!$A$5:$A$153,0),0)*B50/12 -> 0 | C102: =HLOOKUP(C$3,Controls!$A$5:$F$153,MATCH($A102,Controls!$A$5:$A$153,0),0)*C50/12 -> 0 | D102: =HLOOKUP(D$3,Controls!$A$5:$F$153,MATCH($A102,Controls!$A$5:$A$153,0),0)*D50/12 -> 0 | E102: =HLOOKUP(E$3,Controls!$A$5:$F$153,MATCH($A102,Controls!$A$5:$A$153,0),0)*E50/12 -> 0 | F102: =HLOOKUP(F$3,Controls!$A$5:$F$153,MATCH($A102,Controls!$A$5:$A$153,0),0)*F50/12 -> 0 | G102: =HLOOKUP(G$3,Controls!$A$5:$F$153,MATCH($A102,Controls!$A$5:$A$153,0),0)*G50/12 -> 0 | H102: =HLOOKUP(H$3,Controls!$A$5:$F$153,MATCH($A102,Controls!$A$5:$A$153,0),0)*H50/12 -> 0 | I102: =HLOOKUP(I$3,Controls!$A$5:$F$153,MATCH($A102,Controls!$A$5:$A$153,0),0)*I50/12 -> 0 | ... BI102: =HLOOKUP(BI$3,Controls!$A$5:$F$153,MATCH($A102,Controls!$A$5:$A$153,0),0)*BI50/12 -> 0
A103: =A51 -> Please add Position | B103: =HLOOKUP(B$3,Controls!$A$5:$F$153,MATCH($A103,Controls!$A$5:$A$153,0),0)*B51/12 -> 0 | C103: =HLOOKUP(C$3,Controls!$A$5:$F$153,MATCH($A103,Controls!$A$5:$A$153,0),0)*C51/12 -> 0 | D103: =HLOOKUP(D$3,Controls!$A$5:$F$153,MATCH($A103,Controls!$A$5:$A$153,0),0)*D51/12 -> 0 | E103: =HLOOKUP(E$3,Controls!$A$5:$F$153,MATCH($A103,Controls!$A$5:$A$153,0),0)*E51/12 -> 0 | F103: =HLOOKUP(F$3,Controls!$A$5:$F$153,MATCH($A103,Controls!$A$5:$A$153,0),0)*F51/12 -> 0 | G103: =HLOOKUP(G$3,Controls!$A$5:$F$153,MATCH($A103,Controls!$A$5:$A$153,0),0)*G51/12 -> 0 | H103: =HLOOKUP(H$3,Controls!$A$5:$F$153,MATCH($A103,Controls!$A$5:$A$153,0),0)*H51/12 -> 0 | I103: =HLOOKUP(I$3,Controls!$A$5:$F$153,MATCH($A103,Controls!$A$5:$A$153,0),0)*I51/12 -> 0 | ... BI103: =HLOOKUP(BI$3,Controls!$A$5:$F$153,MATCH($A103,Controls!$A$5:$A$153,0),0)*BI51/12 -> 0
A104: =A52 -> TACFI/STRATFI Program Staff (Placeholder) | B104: =HLOOKUP(B$3,Controls!$A$5:$F$153,MATCH($A104,Controls!$A$5:$A$153,0),0)*B52/12 -> #N/A | C104: =HLOOKUP(C$3,Controls!$A$5:$F$153,MATCH($A104,Controls!$A$5:$A$153,0),0)*C52/12 -> #N/A | D104: =HLOOKUP(D$3,Controls!$A$5:$F$153,MATCH($A104,Controls!$A$5:$A$153,0),0)*D52/12 -> #N/A | E104: =HLOOKUP(E$3,Controls!$A$5:$F$153,MATCH($A104,Controls!$A$5:$A$153,0),0)*E52/12 -> #N/A | F104: =HLOOKUP(F$3,Controls!$A$5:$F$153,MATCH($A104,Controls!$A$5:$A$153,0),0)*F52/12 -> #N/A | G104: =HLOOKUP(G$3,Controls!$A$5:$F$153,MATCH($A104,Controls!$A$5:$A$153,0),0)*G52/12 -> #N/A | H104: =HLOOKUP(H$3,Controls!$A$5:$F$153,MATCH($A104,Controls!$A$5:$A$153,0),0)*H52/12 -> #N/A | I104: =HLOOKUP(I$3,Controls!$A$5:$F$153,MATCH($A104,Controls!$A$5:$A$153,0),0)*I52/12 -> #N/A | ... BI104: =HLOOKUP(BI$3,Controls!$A$5:$F$153,MATCH($A104,Controls!$A$5:$A$153,0),0)*BI52/12 -> #N/A
A106: Payroll Tax + Incentives | B106: =SUM(B60:B104)*HLOOKUP(B$3,Controls!$A$5:$F$153,MATCH($A106,Controls!$A$5:$A$153,0),0) -> #N/A | C106: =SUM(C60:C104)*HLOOKUP(C$3,Controls!$A$5:$F$153,MATCH($A106,Controls!$A$5:$A$153,0),0) -> #N/A | D106: =SUM(D60:D104)*HLOOKUP(D$3,Controls!$A$5:$F$153,MATCH($A106,Controls!$A$5:$A$153,0),0) -> #N/A | E106: =SUM(E60:E104)*HLOOKUP(E$3,Controls!$A$5:$F$153,MATCH($A106,Controls!$A$5:$A$153,0),0) -> #N/A | F106: =SUM(F60:F104)*HLOOKUP(F$3,Controls!$A$5:$F$153,MATCH($A106,Controls!$A$5:$A$153,0),0) -> #N/A | G106: =SUM(G60:G104)*HLOOKUP(G$3,Controls!$A$5:$F$153,MATCH($A106,Controls!$A$5:$A$153,0),0) -> #N/A | H106: =SUM(H60:H104)*HLOOKUP(H$3,Controls!$A$5:$F$153,MATCH($A106,Controls!$A$5:$A$153,0),0) -> #N/A | I106: =SUM(I60:I104)*HLOOKUP(I$3,Controls!$A$5:$F$153,MATCH($A106,Controls!$A$5:$A$153,0),0) -> #N/A | ... BI106: =SUM(BI60:BI104)*HLOOKUP(BI$3,Controls!$A$5:$F$153,MATCH($A106,Controls!$A$5:$A$153,0),0) -> #N/A
A107: Robtot Equavalent Salary | AA107: 100000 | AH107: 80000
A108: Total Monthly Compensation | B108: =SUM(B60:B106) -> #N/A | C108: =SUM(C60:C106) -> #N/A | D108: =SUM(D60:D106) -> #N/A | E108: =SUM(E60:E106) -> #N/A | F108: =SUM(F60:F106) -> #N/A | G108: =SUM(G60:G106) -> #N/A | H108: =SUM(H60:H106) -> #N/A | I108: =SUM(I60:I106) -> #N/A | ... BI108: =SUM(BI60:BI106) -> #N/A

Sheet Robot Economics
A1: Parameter | B1: Value | C1: Notes | D1: FTE Displaced | E1: Labor Savings | F1: Net EBITDA
A2: Discount Rate (WACC) | B2: 0.08 | C2: Used for NPV | D2: 2 | E2: 240000 | F2: 165000
A3: Initial Robot Price (Year 0) | B3: 150000 | C3: Optimistic 2027 price | D3: 2.15 | E3: 258000 | F3: 198000
A4: Annual Price Decline Rate | B4: 0.2 | C4: Scale/learning curve | D4: 2.3 | E4: 276000 | F4: 228000
A5: Annual Fully Loaded Cost Factor | B5: 0.5 | C5: Annual cost ≈ factor × that year's robot price | D5: 2.45 | E5: 294000 | F5: 255600
A6: Labor Cost per FTE (fully burdened) | B6: 120000 | C6: Aerospace manufacturing operator baseline | D6: 2.6 | E6: 312000 | F6: 281280
A7: FTE Displaced - Year 1 | B7: 2 | C7: Per robot impact | D7: 2.75 | E7: 330000 | F7: 305424
A8: FTE Displaced - Year 5 | B8: 2.75 | C8: Per robot impact
A9: Analysis Horizon (years) | B9: 5 | C9: 5 years
A10: Residual Value % at Year 5 | B10: 0.2 | C10: Applied to Year-5 price
A11: Annual Lease Payment (per robot) | B11: 40000 | C11: Placeholder; replace with vendor quote
A14: Year | B14: Robot Price | C14: Annual Robot Cost | D14: FTE Displaced | E14: Labor Savings | F14: Net EBITDA | G14: Cumulative Net Cash Flow (Buy)
A15: 1 | B15: 150000 | C15: 75000 | D15: 2 | E15: 240000 | F15: 165000 | G15: 15000
A16: 2 | B16: 120000 | C16: 60000 | D16: 2.1875 | E16: 262500 | F16: 202500 | G16: 217500
A17: 3 | B17: 96000 | C17: 48000 | D17: 2.375 | E17: 285000 | F17: 237000 | G17: 454500
A18: 4 | B18: 76800 | C18: 38400 | D18: 2.5625 | E18: 307500 | F18: 269100 | G18: 723600
A19: 5 | B19: 61440 | C19: 30720 | D19: 2.75 | E19: 330000 | F19: 299280 | G19: 1022880

Sheet Fixed Asset Schedules
A1: EXOS Aerospace
A2: Fixed Assets Assumptions Sheet | B2: =Controls!C1 -> July | C2: =TEXT(DATE(2000, MATCH(B2, {"January","February","March","April","May","June","July","August","September","October","November","December"}, 0) + 1, 1), "mmmm") -> August | D2: =TEXT(DATE(2000, MATCH(C2, {"January","February","March","April","May","June","July","August","September","October","November","December"}, 0) + 1, 1), "mmmm") -> September | E2: =TEXT(DATE(2000, MATCH(D2, {"January","February","March","April","May","June","July","August","September","October","November","December"}, 0) + 1, 1), "mmmm") -> October | F2: =TEXT(DATE(2000, MATCH(E2, {"January","February","March","April","May","June","July","August","September","October","November","December"}, 0) + 1, 1), "mmmm") -> November | G2: =TEXT(DATE(2000, MATCH(F2, {"January","February","March","April","May","June","July","August","September","October","November","December"}, 0) + 1, 1), "mmmm") -> December | H2: =TEXT(DATE(2000, MATCH(G2, {"January","February","March","April","May","June","July","August","September","October","November","December"}, 0) + 1, 1), "mmmm") -> January | I2: =TEXT(DATE(2000, MATCH(H2, {"January","February","March","April","May","June","July","August","September","October","November","December"}, 0) + 1, 1), "mmmm") -> February | J2: =TEXT(DATE(2000, MATCH(I2, {"January","February","March","April","May","June","July","August","September","October","November","December"}, 0) + 1, 1), "mmmm") -> March | ... BI2: =TEXT(DATE(2000, MATCH(BH2, {"January","February","March","April","May","June","July","August","September","October","November","December"}, 0) + 1, 1), "mmmm") -> June
A3: Amounts in USD | B3: 1 | C3: =IF(MOD(B4,B5) = 0,B3+1,B3) -> 1 | D3: =IF(MOD(C4,C5) = 0,C3+1,C3) -> 1 | E3: =IF(MOD(D4,D5) = 0,D3+1,D3) -> 1 | F3: =IF(MOD(E4,E5) = 0,E3+1,E3) -> 1 | G3: =IF(MOD(F4,F5) = 0,F3+1,F3) -> 1 | H3: =IF(MOD(G4,G5) = 0,G3+1,G3) -> 1 | I3: =IF(MOD(H4,H5) = 0,H3+1,H3) -> 1 | J3: =IF(MOD(I4,I5) = 0,I3+1,I3) -> 1 | ... BI3: =IF(MOD(BH4,BH5) = 0,BH3+1,BH3) -> 5
A4: Back To Index | B4: 1 | C4: =B4+1 -> 2 | D4: =C4+1 -> 3 | E4: =D4+1 -> 4 | F4: =E4+1 -> 5 | G4: =F4+1 -> 6 | H4: =G4+1 -> 7 | I4: =H4+1 -> 8 | J4: =I4+1 -> 9 | ... BI4: =BH4+1 -> 60
A5: Assumptions for the Monthly Period | B5: 12 | C5: 12 | D5: 12 | E5: 12 | F5: 12 | G5: 12 | H5: 12 | I5: 12 | J5: 12 | K5: 12 | L5: 12 | M5: 12 | N5: 12 | O5: 12 | P5: 12 | Q5: 12 | R5: 12 | S5: 12 | T5: 12 | U5: 12 | V5: 12 | W5: 12 | X5: 12 | Y5: 12 | Z5: 12 | AA5: 12 | AB5: 12 | AC5: 12 | AD5: 12 | AE5: 12 | AF5: 12 | AG5: 12 | AH5: 12 | AI5: 12 | AJ5: 12 | AK5: 12 | AL5: 12 | AM5: 12 | AN5: 12 | AO5: 12 | AP5: 12 | AQ5: 12 | AR5: 12 | AS5: 12 | AT5: 12 | AU5: 12 | AV5: 12 | AW5: 12 | AX5: 12 | AY5: 12 | AZ5: 12 | BA5: 12 | BB5: 12 | BC5: 12 | BD5: 12 | BE5: 12 | BF5: 12 | BG5: 12 | BH5: 12 | BI5: 12
A6: Fixed Assets
A8: PPE
A9: Monthly Depreciation | B9: 0.0061
A11: Opening Balance | B11: =3009000-429000 -> 2580000 | C11: =+B14 -> 2564262 | D11: =+C14 -> 2548524 | E11: =+D14 -> 2532786 | F11: =+E14 -> 3924708.6 | G11: =+F14 -> 3900331.1 | H11: =+G14 -> 3875953.7 | I11: =+H14 -> 4440462 | J11: =+I14 -> 4412470.3 | ... BI11: =+BH14 -> 55067479
A12: Additions | B12: =D50-D47 -> 0 | C12: 0 | D12: 0 | E12: =E50 -> 1416300 | F12: 0 | G12: 0 | H12: =F50 -> 592500 | I12: 0 | J12: 0 | K12: =G50 -> 92500 | L12: 0 | M12: 0 | N12: =H50 -> 5157813 | O12: 0 | P12: 0 | Q12: =I50 -> 177813 | R12: 0 | S12: 0 | T12: =J50 -> 27813 | U12: 0 | V12: 0 | W12: =K50 -> 27813 | X12: 0 | Y12: 0 | Z12: =L50 -> 207813 | AA12: 0 | AB12: 0 | AC12: =M50 -> 27813 | AD12: 0 | AE12: 0 | AF12: =N50 -> 27813 | AG12: 0 | AH12: 0 | AI12: =O50 -> 27813 | AJ12: 0 | AK12: 0 | AL12: =P50 -> 6892060.7 | AM12: 0 | AN12: 0 | AO12: =Q50 -> 5692060.7 | AP12: 0 | AQ12: 0 | AR12: =R50 -> 3492060.7 | AS12: 0 | AT12: 0 | AU12: =S50 -> 11423912 | AV12: 0 | AW12: 0 | AX12: =T50 -> 6116933.8 | AY12: 0 | AZ12: 0 | BA12: =U50 -> 6116933.8 | BB12: 0 | BC12: 0 | BD12: =V50 -> 6116933.8 | BE12: 0 | BF12: 0 | BG12: =W50 -> 6052373.2 | BH12: 0 | BI12: 0
A13: Depreciation | B13: =+(B11+B12)*$B9 -> 15738 | C13: =IF(C12=0,B13,B13+(C12*$B$9)) -> 15738 | D13: =IF(D12=0,C13,C13+(D12*$B$9)) -> 15738 | E13: =IF(E12=0,D13,D13+(E12*$B$9)) -> 24377.43 | F13: =IF(F12=0,E13,E13+(F12*$B$9)) -> 24377.43 | G13: =IF(G12=0,F13,F13+(G12*$B$9)) -> 24377.43 | H13: =IF(H12=0,G13,G13+(H12*$B$9)) -> 27991.68 | I13: =IF(I12=0,H13,H13+(I12*$B$9)) -> 27991.68 | J13: =IF(J12=0,I13,I13+(J12*$B$9)) -> 27991.68 | ... BI13: =IF(BI12=0,BH13,BH13+(BI12*$B$9)) -> 379829.14
A14: Closing Balance | B14: =+B11+B12-B13 -> 2564262 | C14: =+C11+C12-C13 -> 2548524 | D14: =+D11+D12-D13 -> 2532786 | E14: =+E11+E12-E13 -> 3924708.6 | F14: =+F11+F12-F13 -> 3900331.1 | G14: =+G11+G12-G13 -> 3875953.7 | H14: =+H11+H12-H13 -> 4440462 | I14: =+I11+I12-I13 -> 4412470.3 | ... BI14: =+BI11+BI12-BI13 -> 54687649
A16: Intangible Assets
A17: Monthly Depreciation | B17: 0.0056
A19: Opening Balance | B19: 11785800 | C19: =+B22 -> 17570650 | D19: =+C22 -> 17471700 | E19: =+D22 -> 17372751 | F19: =+E22 -> 17273801 | G19: =+F22 -> 17174851 | H19: =+G22 -> 17075901 | I19: =+H22 -> 16976952 | J19: =+I22 -> 16878002 | ... BI19: =+BH22 -> 11831564
A20: Additions | B20: =D47+C47+E47 -> 5883800 | C20: 0 | D20: 0 | E20: 0 | F20: 0 | G20: 0 | H20: 0 | I20: 0 | J20: 0 | K20: 0 | L20: 0 | M20: 0 | N20: 0 | O20: 0 | P20: 0 | Q20: 0 | R20: 0 | S20: 0 | T20: 0 | U20: 0 | V20: 0 | W20: 0 | X20: 0 | Y20: 0 | Z20: 0 | AA20: 0 | AB20: 0 | AC20: 0 | AD20: 0 | AE20: 0 | AF20: 0 | AG20: 0 | AH20: 0 | AI20: 0 | AJ20: 0 | AK20: 0 | AL20: 0 | AM20: 0 | AN20: 0 | AO20: 0 | AP20: 0 | AQ20: 0 | AR20: 0 | AS20: 0 | AT20: 0 | AU20: 0 | AV20: 0 | AW20: 0 | AX20: 0 | AY20: 0 | AZ20: 0 | BA20: 0 | BB20: 0 | BC20: 0 | BD20: 0 | BE20: 0 | BF20: 0 | BG20: 0 | BH20: 0 | BI20: 0
A21: Depreciation | B21: =+(B19+B20)*$B17 -> 98949.76 | C21: =IF(C20=0,B21,B21+(C20*$B$17)) -> 98949.76 | D21: =IF(D20=0,C21,C21+(D20*$B$17)) -> 98949.76 | E21: =IF(E20=0,D21,D21+(E20*$B$17)) -> 98949.76 | F21: =IF(F20=0,E21,E21+(F20*$B$17)) -> 98949.76 | G21: =IF(G20=0,F21,F21+(G20*$B$17)) -> 98949.76 | H21: =IF(H20=0,G21,G21+(H20*$B$17)) -> 98949.76 | I21: =IF(I20=0,H21,H21+(I20*$B$17)) -> 98949.76 | J21: =IF(J20=0,I21,I21+(J20*$B$17)) -> 98949.76 | ... BI21: =IF(BI20=0,BH21,BH21+(BI20*$B$17)) -> 98949.76
A22: Closing Balance | B22: =+B19+B20-B21 -> 17570650 | C22: =+C19+C20-C21 -> 17471700 | D22: =+D19+D20-D21 -> 17372751 | E22: =+E19+E20-E21 -> 17273801 | F22: =+F19+F20-F21 -> 17174851 | G22: =+G19+G20-G21 -> 17075901 | H22: =+H19+H20-H21 -> 16976952 | I22: =+I19+I20-I21 -> 16878002 | ... BI22: =+BI19+BI20-BI21 -> 11732614
C36: R&D phase | D36: 2025 | H36: FY 2 | L36: FY 3 | P36: FY 4 | T36: FY 5 | X36: FY 6
C37: Month 0 | D37: Q1 FY1 post raise | E37: Q2 FY1 | F37: Q3 FY1 | G37: Q4 FY1 | H37: Q1 FY2 | I37: Q2 FY2 | J37: Q3 FY2 | K37: Q4 FY2 | L37: Q1 FY3 | M37: Q2 FY3 | N37: Q3 FY3 | O37: Q4 FY3 | P37: Q1 FY1 | Q37: Q2 FY1 | R37: Q3 FY1 | S37: Q4 FY1 | T37: Q1 FY2 | U37: Q2 FY2 | V37: Q3 FY2 | W37: Q4 FY2 | X37: Q1 FY3 | Y37: Q2 FY3 | Z37: Q3 FY3 | AA37: Q4 FY3
A39: CAPITAL EXPENDITURES | D39: 2 | E39: 6 | G39: 4 | H39: 4 | I39: 9 | J39: 8
C40: 0 | D40: 0 | E40: 0 | F40: 0 | G40: 0 | H40: 0 | I40: 0 | J40: 0 | K40: 0 | L40: 0 | M40: 0 | N40: 0 | O40: 0 | P40: 29560.663 | Q40: 3029560.7 | R40: 3029560.7 | S40: 6059121.3 | T40: 6059121.3 | U40: 6059121.3 | V40: 6059121.3 | W40: 3029560.7 | X40: 750000 | Y40: 750000 | Z40: 750000 | AA40: 750000
B41: Manufacturing facility, parts storage, offices, rocket staging area buildout | C41: 0 | D41: 0 | E41: 20000 | F41: 20000 | G41: 20000 | H41: 5000000 | I41: 20000 | J41: 20000 | K41: 20000 | L41: 200000 | M41: 20000 | N41: 20000 | O41: 20000 | P41: 3825000 | Q41: 150000 | R41: 50000 | S41: 50000 | T41: 50000 | U41: 50000 | V41: 50000 | W41: 50000 | X41: 20000050 | Y41: 50000 | Z41: 50000 | AA41: 50000
B42: ASE /GSE Manufacturing process setups | C42: 0 | D42: 0 | E42: 22500 | F42: 22500 | G42: 22500 | H42: 7813 | I42: 7813 | J42: 7813 | K42: 7813 | L42: 7813 | M42: 7813 | N42: 7813 | O42: 7813 | P42: 62500 | Q42: 62500 | R42: 62500 | S42: 62500 | T42: 7812.5 | U42: 7812.5 | V42: 7812.5 | W42: 7812.5 | X42: 7812.5 | Y42: 7812.5 | Z42: 7812.5 | AA42: 7812.5
B43: Ground Comm mobile Antenna M0 & Build of BLK3 3 stages / Operations training | C43: 0 | D43: 0 | E43: 750000 | F43: 500000 | G43: 0 | H43: 0 | I43: 0 | J43: 0 | K43: 0 | L43: 0 | M43: 0 | N43: 0 | O43: 0 | P43: 2275000 | S43: 1275000 | T43: 0 | U43: 0 | V43: 0 | W43: 1965000 | X43: 0 | Y43: 0 | Z43: 0 | AA43: 900000
B44: ERP/MRP program & AS9000D system setup | C44: 0 | D44: 0 | E44: 0 | F44: 0 | G44: 0 | H44: 150000 | I44: 150000 | J44: 0 | K44: 0 | L44: 0 | M44: 0 | N44: 0 | O44: 0 | P44: 100000 | Q44: 100000 | R44: 0 | S44: 0 | T44: 0 | U44: 0 | V44: 0 | W44: 0 | X44: 0 | Y44: 0 | Z44: 0 | AA44: 0
B45: Launch System and Test pad- clean room ground launch trailers | C45: 0 | D45: 0 | E45: 0 | F45: 0 | G45: 0 | H45: 0 | I45: 0 | J45: 0 | K45: 0 | L45: 0 | M45: 0 | N45: 0 | O45: 0 | P45: 350000 | Q45: 350000 | R45: 350000 | S45: 350000 | T45: 0 | U45: 0 | V45: 0 | W45: 0 | X45: 0 | Y45: 0 | Z45: 0 | AA45: 0
B46: Launch support equipment research and dev & ground transport=- | C46: 0 | D46: 0 | E46: 50000 | F46: 0 | G46: 0 | H46: 0 | I46: 0 | J46: 0 | K46: 0 | L46: 0 | M46: 0 | N46: 0 | O46: 0 | P46: 250000 | Q46: 2000000 | R46: 0 | S46: 0 | T46: 0 | U46: 0 | V46: 0 | W46: 1000000 | X46: 0 | Y46: 0 | Z46: 0 | AA46: 0
B47: Capital manufacturing eqiupment / Acquisition M0/BLK3 program buildout | C47: 790000 | D47: 4570000 | E47: 523800 | F47: 0 | G47: 0 | H47: 0 | I47: 0 | J47: 0 | K47: 0 | L47: 0 | M47: 0 | N47: 0 | O47: 0 | P47: 0 | Q47: 0 | R47: 0 | S47: 0 | T47: 0 | U47: 0 | V47: 0 | W47: 0 | X47: 0 | Y47: 0 | Z47: 0 | AA47: 0
B48: Cutting tables and equipment | C48: 0 | D48: 0 | E48: 50000 | F48: 50000 | G48: 50000 | H48: 0 | I48: 0 | J48: 0 | K48: 0 | L48: 0 | M48: 0 | N48: 0 | O48: 0 | P48: 0 | Q48: 0 | R48: 0 | S48: 0 | T48: 0 | U48: 0 | V48: 0 | W48: 0 | X48: 0 | Y48: 0 | Z48: 0 | AA48: 0
B49: CNC lathes - buyout of affiliation with MST | C49: 250000 | D49: 0 | E49: 0 | F49: 0 | G49: 0 | H49: 0 | I49: 0 | J49: 0 | K49: 0 | L49: 0 | M49: 0 | N49: 0 | O49: 0 | P49: 0 | Q49: 0 | R49: 0 | S49: 3627290.2 | T49: 0 | U49: 0 | V49: 0 | W49: 0 | X49: 0 | Y49: 0 | Z49: 0 | AA49: 0
A50: TOTAL CAPEX | C50: =SUM(C40:C49) -> 1040000 | D50: =SUM(D40:D49) -> 4570000 | E50: =SUM(E40:E49) -> 1416300 | F50: =SUM(F40:F49) -> 592500 | G50: =SUM(G40:G49) -> 92500 | H50: =SUM(H40:H49) -> 5157813 | I50: =SUM(I40:I49) -> 177813 | J50: =SUM(J40:J49) -> 27813 | ... AA50: =SUM(AA40:AA49) -> 1707812.5

Sheet Net Working Capital Changes
A1: EXOS Aerospace
A2: Net Working Capital Changes | B2: =Controls!C1 -> July | C2: =TEXT(DATE(2000, MATCH(B2, {"January","February","March","April","May","June","July","August","September","October","November","December"}, 0) + 1, 1), "mmmm") -> August | D2: =TEXT(DATE(2000, MATCH(C2, {"January","February","March","April","May","June","July","August","September","October","November","December"}, 0) + 1, 1), "mmmm") -> September | E2: =TEXT(DATE(2000, MATCH(D2, {"January","February","March","April","May","June","July","August","September","October","November","December"}, 0) + 1, 1), "mmmm") -> October | F2: =TEXT(DATE(2000, MATCH(E2, {"January","February","March","April","May","June","July","August","September","October","November","December"}, 0) + 1, 1), "mmmm") -> November | G2: =TEXT(DATE(2000, MATCH(F2, {"January","February","March","April","May","June","July","August","September","October","November","December"}, 0) + 1, 1), "mmmm") -> December | H2: =TEXT(DATE(2000, MATCH(G2, {"January","February","March","April","May","June","July","August","September","October","November","December"}, 0) + 1, 1), "mmmm") -> January | I2: =TEXT(DATE(2000, MATCH(H2, {"January","February","March","April","May","June","July","August","September","October","November","December"}, 0) + 1, 1), "mmmm") -> February | J2: =TEXT(DATE(2000, MATCH(I2, {"January","February","March","April","May","June","July","August","September","October","November","December"}, 0) + 1, 1), "mmmm") -> March | ... BI2: =TEXT(DATE(2000, MATCH(BH2, {"January","February","March","April","May","June","July","August","September","October","November","December"}, 0) + 1, 1), "mmmm") -> June
A3: Amounts in USD | B3: 1 | C3: =IF(MOD(B4,B5) = 0,B3+1,B3) -> 1 | D3: =IF(MOD(C4,C5) = 0,C3+1,C3) -> 1 | E3: =IF(MOD(D4,D5) = 0,D3+1,D3) -> 1 | F3: =IF(MOD(E4,E5) = 0,E3+1,E3) -> 1 | G3: =IF(MOD(F4,F5) = 0,F3+1,F3) -> 1 | H3: =IF(MOD(G4,G5) = 0,G3+1,G3) -> 1 | I3: =IF(MOD(H4,H5) = 0,H3+1,H3) -> 1 | J3: =IF(MOD(I4,I5) = 0,I3+1,I3) -> 1 | ... BI3: =IF(MOD(BH4,BH5) = 0,BH3+1,BH3) -> 5
A4: Back To Index | B4: 1 | C4: =B4+1 -> 2 | D4: =C4+1 -> 3 | E4: =D4+1 -> 4 | F4: =E4+1 -> 5 | G4: =F4+1 -> 6 | H4: =G4+1 -> 7 | I4: =H4+1 -> 8 | J4: =I4+1 -> 9 | ... BI4: =BH4+1 -> 60
A5: Assumptions for the Monthly Period | B5: 12 | C5: 12 | D5: 12 | E5: 12 | F5: 12 | G5: 12 | H5: 12 | I5: 12 | J5: 12 | K5: 12 | L5: 12 | M5: 12 | N5: 12 | O5: 12 | P5: 12 | Q5: 12 | R5: 12 | S5: 12 | T5: 12 | U5: 12 | V5: 12 | W5: 12 | X5: 12 | Y5: 12 | Z5: 12 | AA5: 12 | AB5: 12 | AC5: 12 | AD5: 12 | AE5: 12 | AF5: 12 | AG5: 12 | AH5: 12 | AI5: 12 | AJ5: 12 | AK5: 12 | AL5: 12 | AM5: 12 | AN5: 12 | AO5: 12 | AP5: 12 | AQ5: 12 | AR5: 12 | AS5: 12 | AT5: 12 | AU5: 12 | AV5: 12 | AW5: 12 | AX5: 12 | AY5: 12 | AZ5: 12 | BA5: 12 | BB5: 12 | BC5: 12 | BD5: 12 | BE5: 12 | BF5: 12 | BG5: 12 | BH5: 12 | BI5: 12
A9: Net Working Capital Changes
A11: Assets
A13: Accounts Receivable | B13: =' Balance Sheet'!D10-' Balance Sheet'!C10 -> -30200 | C13: =' Balance Sheet'!E10-' Balance Sheet'!D10 -> 0 | D13: =' Balance Sheet'!F10-' Balance Sheet'!E10 -> 0 | E13: =' Balance Sheet'!G10-' Balance Sheet'!F10 -> 0 | F13: =' Balance Sheet'!H10-' Balance Sheet'!G10 -> 0 | G13: =' Balance Sheet'!I10-' Balance Sheet'!H10 -> 0 | H13: =' Balance Sheet'!J10-' Balance Sheet'!I10 -> 0 | I13: =' Balance Sheet'!K10-' Balance Sheet'!J10 -> 0 | ... BI13: =' Balance Sheet'!BK10-' Balance Sheet'!BJ10 -> 0
A15: Prepaid Expenses | B15: =' Balance Sheet'!D11-' Balance Sheet'!C11 -> 0 | C15: =' Balance Sheet'!E11-' Balance Sheet'!D11 -> 0 | D15: =' Balance Sheet'!F11-' Balance Sheet'!E11 -> 0 | E15: =' Balance Sheet'!G11-' Balance Sheet'!F11 -> 0 | F15: =' Balance Sheet'!H11-' Balance Sheet'!G11 -> 0 | G15: =' Balance Sheet'!I11-' Balance Sheet'!H11 -> 0 | H15: =' Balance Sheet'!J11-' Balance Sheet'!I11 -> 0 | I15: =' Balance Sheet'!K11-' Balance Sheet'!J11 -> 0 | ... BI15: =' Balance Sheet'!BK11-' Balance Sheet'!BJ11 -> 0
A17: Inventory | B17: =' Balance Sheet'!D9-' Balance Sheet'!C9 -> #N/A | C17: =' Balance Sheet'!E9-' Balance Sheet'!D9 -> #N/A | D17: =' Balance Sheet'!F9-' Balance Sheet'!E9 -> #N/A | E17: =' Balance Sheet'!G9-' Balance Sheet'!F9 -> #N/A | F17: =' Balance Sheet'!H9-' Balance Sheet'!G9 -> #N/A | G17: =' Balance Sheet'!I9-' Balance Sheet'!H9 -> #N/A | H17: =' Balance Sheet'!J9-' Balance Sheet'!I9 -> #N/A | I17: =' Balance Sheet'!K9-' Balance Sheet'!J9 -> #N/A | ... BI17: =' Balance Sheet'!BK9-' Balance Sheet'!BJ9 -> #N/A
A19: Other Current Assets | B19: =' Balance Sheet'!D12-' Balance Sheet'!C12 -> 0 | C19: =' Balance Sheet'!E12-' Balance Sheet'!D12 -> 0 | D19: =' Balance Sheet'!F12-' Balance Sheet'!E12 -> 0 | E19: =' Balance Sheet'!G12-' Balance Sheet'!F12 -> 0 | F19: =' Balance Sheet'!H12-' Balance Sheet'!G12 -> 0 | G19: =' Balance Sheet'!I12-' Balance Sheet'!H12 -> 0 | H19: =' Balance Sheet'!J12-' Balance Sheet'!I12 -> 0 | I19: =' Balance Sheet'!K12-' Balance Sheet'!J12 -> 0 | ... BI19: =' Balance Sheet'!BK12-' Balance Sheet'!BJ12 -> 0
A21: Liabilities
A23: Accounts Payable | B23: =' Balance Sheet'!D24-' Balance Sheet'!C24 -> #N/A | C23: =' Balance Sheet'!E24-' Balance Sheet'!D24 -> #N/A | D23: =' Balance Sheet'!F24-' Balance Sheet'!E24 -> #N/A | E23: =' Balance Sheet'!G24-' Balance Sheet'!F24 -> #N/A | F23: =' Balance Sheet'!H24-' Balance Sheet'!G24 -> #N/A | G23: =' Balance Sheet'!I24-' Balance Sheet'!H24 -> #N/A | H23: =' Balance Sheet'!J24-' Balance Sheet'!I24 -> #N/A | I23: =' Balance Sheet'!K24-' Balance Sheet'!J24 -> #N/A | ... BI23: =' Balance Sheet'!BK24-' Balance Sheet'!BJ24 -> #N/A
A25: Accrued Expenses & Payroll Taxes Payable | B25: =' Balance Sheet'!D25-' Balance Sheet'!C25 -> #N/A | C25: =' Balance Sheet'!E25-' Balance Sheet'!D25 -> #N/A | D25: =' Balance Sheet'!F25-' Balance Sheet'!E25 -> #N/A | E25: =' Balance Sheet'!G25-' Balance Sheet'!F25 -> #N/A | F25: =' Balance Sheet'!H25-' Balance Sheet'!G25 -> #N/A | G25: =' Balance Sheet'!I25-' Balance Sheet'!H25 -> #N/A | H25: =' Balance Sheet'!J25-' Balance Sheet'!I25 -> #N/A | I25: =' Balance Sheet'!K25-' Balance Sheet'!J25 -> #N/A | ... BI25: =' Balance Sheet'!BK25-' Balance Sheet'!BJ25 -> #N/A
A27: Other Current Liabilities | B27: =' Balance Sheet'!D27-' Balance Sheet'!C27 -> 0 | C27: =' Balance Sheet'!E27-' Balance Sheet'!D27 -> 0 | D27: =' Balance Sheet'!F27-' Balance Sheet'!E27 -> 0 | E27: =' Balance Sheet'!G27-' Balance Sheet'!F27 -> 0 | F27: =' Balance Sheet'!H27-' Balance Sheet'!G27 -> 0 | G27: =' Balance Sheet'!I27-' Balance Sheet'!H27 -> 0 | H27: =' Balance Sheet'!J27-' Balance Sheet'!I27 -> 0 | I27: =' Balance Sheet'!K27-' Balance Sheet'!J27 -> 0 | ... BI27: =' Balance Sheet'!BK27-' Balance Sheet'!BJ27 -> 0
A29: Changes in Net Working Capital | B29: =SUM(B13:B19)-SUM(B23:B27) -> #N/A | C29: =SUM(C13:C19)-SUM(C23:C27) -> #N/A | D29: =SUM(D13:D19)-SUM(D23:D27) -> #N/A | E29: =SUM(E13:E19)-SUM(E23:E27) -> #N/A | F29: =SUM(F13:F19)-SUM(F23:F27) -> #N/A | G29: =SUM(G13:G19)-SUM(G23:G27) -> #N/A | H29: =SUM(H13:H19)-SUM(H23:H27) -> #N/A | I29: =SUM(I13:I19)-SUM(I23:I27) -> #N/A | ... BH29: =SUM(BH13:BH19)-SUM(BH23:BH27) -> #N/A

Sheet Monthly P&L
A1: EXOS Aerospace
A2: Monthly Profit & Loss | B2: =Controls!C1 -> July | C2: =TEXT(DATE(2000, MATCH(B2, {"January","February","March","April","May","June","July","August","September","October","November","December"}, 0) + 1, 1), "mmmm") -> August | D2: =TEXT(DATE(2000, MATCH(C2, {"January","February","March","April","May","June","July","August","September","October","November","December"}, 0) + 1, 1), "mmmm") -> September | E2: =TEXT(DATE(2000, MATCH(D2, {"January","February","March","April","May","June","July","August","September","October","November","December"}, 0) + 1, 1), "mmmm") -> October | F2: =TEXT(DATE(2000, MATCH(E2, {"January","February","March","April","May","June","July","August","September","October","November","December"}, 0) + 1, 1), "mmmm") -> November | G2: =TEXT(DATE(2000, MATCH(F2, {"January","February","March","April","May","June","July","August","September","October","November","December"}, 0) + 1, 1), "mmmm") -> December | H2: =TEXT(DATE(2000, MATCH(G2, {"January","February","March","April","May","June","July","August","September","October","November","December"}, 0) + 1, 1), "mmmm") -> January | I2: =TEXT(DATE(2000, MATCH(H2, {"January","February","March","April","May","June","July","August","September","October","November","December"}, 0) + 1, 1), "mmmm") -> February | J2: =TEXT(DATE(2000, MATCH(I2, {"January","February","March","April","May","June","July","August","September","October","November","December"}, 0) + 1, 1), "mmmm") -> March | ... BI2: =TEXT(DATE(2000, MATCH(BH2, {"January","February","March","April","May","June","July","August","September","October","November","December"}, 0) + 1, 1), "mmmm") -> June
A3: Amounts in USD | B3: 1 | C3: =IF(MOD(B4,B5) = 0,B3+1,B3) -> 1 | D3: =IF(MOD(C4,C5) = 0,C3+1,C3) -> 1 | E3: =IF(MOD(D4,D5) = 0,D3+1,D3) -> 1 | F3: =IF(MOD(E4,E5) = 0,E3+1,E3) -> 1 | G3: =IF(MOD(F4,F5) = 0,F3+1,F3) -> 1 | H3: =IF(MOD(G4,G5) = 0,G3+1,G3) -> 1 | I3: =IF(MOD(H4,H5) = 0,H3+1,H3) -> 1 | J3: =IF(MOD(I4,I5) = 0,I3+1,I3) -> 1 | ... BI3: =IF(MOD(BH4,BH5) = 0,BH3+1,BH3) -> 5
A4: Back To Index | B4: 1 | C4: =B4+1 -> 2 | D4: =C4+1 -> 3 | E4: =D4+1 -> 4 | F4: =E4+1 -> 5 | G4: =F4+1 -> 6 | H4: =G4+1 -> 7 | I4: =H4+1 -> 8 | J4: =I4+1 -> 9 | ... BI4: =BH4+1 -> 60
A5: Assumptions for the Monthly Period | B5: 12 | C5: 12 | D5: 12 | E5: 12 | F5: 12 | G5: 12 | H5: 12 | I5: 12 | J5: 12 | K5: 12 | L5: 12 | M5: 12 | N5: 12 | O5: 12 | P5: 12 | Q5: 12 | R5: 12 | S5: 12 | T5: 12 | U5: 12 | V5: 12 | W5: 12 | X5: 12 | Y5: 12 | Z5: 12 | AA5: 12 | AB5: 12 | AC5: 12 | AD5: 12 | AE5: 12 | AF5: 12 | AG5: 12 | AH5: 12 | AI5: 12 | AJ5: 12 | AK5: 12 | AL5: 12 | AM5: 12 | AN5: 12 | AO5: 12 | AP5: 12 | AQ5: 12 | AR5: 12 | AS5: 12 | AT5: 12 | AU5: 12 | AV5: 12 | AW5: 12 | AX5: 12 | AY5: 12 | AZ5: 12 | BA5: 12 | BB5: 12 | BC5: 12 | BD5: 12 | BE5: 12 | BF5: 12 | BG5: 12 | BH5: 12 | BI5: 12
A7: Revenue from BLK4 360kg Launcher | B7: ='Revenue Asumptions'!B33 -> 0 | C7: ='Revenue Asumptions'!C33 -> 0 | D7: ='Revenue Asumptions'!D33 -> 0 | E7: ='Revenue Asumptions'!E33 -> 0 | F7: ='Revenue Asumptions'!F33 -> 0 | G7: ='Revenue Asumptions'!G33 -> 0 | H7: ='Revenue Asumptions'!H33 -> 0 | I7: ='Revenue Asumptions'!I33 -> 0 | ... BI7: ='Revenue Asumptions'!BI33 -> 6833332.8
A8: Revenue from Propulsion System Sales | B8: ='Revenue Asumptions'!B46 -> 0 | C8: ='Revenue Asumptions'!C46 -> 0 | D8: ='Revenue Asumptions'!D46 -> 250000 | E8: ='Revenue Asumptions'!E46 -> 100000 | F8: ='Revenue Asumptions'!F46 -> 250000 | G8: ='Revenue Asumptions'!G46 -> 500000 | H8: ='Revenue Asumptions'!H46 -> 400000 | I8: ='Revenue Asumptions'!I46 -> 400000 | ... BI8: ='Revenue Asumptions'!BI46 -> 3416666.7
A9: Revenue from EXOS US BLK4 Wet Lease Launches | B9: ='Revenue Asumptions'!B61 -> 0 | C9: ='Revenue Asumptions'!C61 -> 0 | D9: ='Revenue Asumptions'!D61 -> 0 | E9: ='Revenue Asumptions'!E61 -> 0 | F9: ='Revenue Asumptions'!F61 -> 0 | G9: ='Revenue Asumptions'!G61 -> 0 | H9: ='Revenue Asumptions'!H61 -> 0 | I9: ='Revenue Asumptions'!I61 -> 0 | ... BI9: ='Revenue Asumptions'!BI61 -> 0
A10: Revenue from Second Stage Sales | B10: ='Revenue Asumptions'!B76 -> 0 | C10: ='Revenue Asumptions'!C76 -> 0 | D10: ='Revenue Asumptions'!D76 -> 0 | E10: ='Revenue Asumptions'!E76 -> 0 | F10: ='Revenue Asumptions'!F76 -> 0 | G10: ='Revenue Asumptions'!G76 -> 0 | H10: ='Revenue Asumptions'!H76 -> 0 | I10: ='Revenue Asumptions'!I76 -> 0 | ... BI10: ='Revenue Asumptions'!BI76 -> 350000
A11: Revenue from Scorpius Space Tank Sales | B11: ='Revenue Asumptions'!B89 -> 265600 | C11: ='Revenue Asumptions'!C89 -> 135300 | D11: ='Revenue Asumptions'!D89 -> 215000 | E11: ='Revenue Asumptions'!E89 -> 541840 | F11: ='Revenue Asumptions'!F89 -> 578500 | G11: ='Revenue Asumptions'!G89 -> 549600 | H11: ='Revenue Asumptions'!H89 -> 324200 | I11: ='Revenue Asumptions'!I89 -> 537500 | ... BI11: ='Revenue Asumptions'!BI89 -> 4825195.3
A12: Revenue from Sarge Technology Sales | B12: ='Revenue Asumptions'!B102 -> 0 | C12: ='Revenue Asumptions'!C102 -> 0 | D12: ='Revenue Asumptions'!D102 -> 0 | E12: ='Revenue Asumptions'!E102 -> 0 | F12: ='Revenue Asumptions'!F102 -> 0 | G12: ='Revenue Asumptions'!G102 -> 0 | H12: ='Revenue Asumptions'!H102 -> 0 | I12: ='Revenue Asumptions'!I102 -> 0 | ... BI12: ='Revenue Asumptions'!BI102 -> 0
A14: Total Revenue | B14: =SUM(B7:B12) -> 265600 | C14: =SUM(C7:C12) -> 135300 | D14: =SUM(D7:D12) -> 465000 | E14: =SUM(E7:E12) -> 641840 | F14: =SUM(F7:F12) -> 828500 | G14: =SUM(G7:G12) -> 1049600 | H14: =SUM(H7:H12) -> 724200 | I14: =SUM(I7:I12) -> 937500 | ... BI14: =SUM(BI7:BI12) -> 15425195
A16: Total Cost Of Sales (COS) | B16: ='Expense Assumptions'!B18 -> #N/A | C16: ='Expense Assumptions'!C18 -> #N/A | D16: ='Expense Assumptions'!D18 -> #N/A | E16: ='Expense Assumptions'!E18 -> #N/A | F16: ='Expense Assumptions'!F18 -> #N/A | G16: ='Expense Assumptions'!G18 -> #N/A | H16: ='Expense Assumptions'!H18 -> #N/A | I16: ='Expense Assumptions'!I18 -> #N/A | ... BI16: ='Expense Assumptions'!BI18 -> #N/A
A18: Gross Profit | B18: =B14-B16 -> #N/A | C18: =C14-C16 -> #N/A | D18: =D14-D16 -> #N/A | E18: =E14-E16 -> #N/A | F18: =F14-F16 -> #N/A | G18: =G14-G16 -> #N/A | H18: =H14-H16 -> #N/A | I18: =I14-I16 -> #N/A | ... BI18: =BI14-BI16 -> #N/A
A19: Gross Margin % | B19: =+IF(B18>0,B18/B14,"NA") -> #N/A | C19: =+IF(C18>0,C18/C14,"NA") -> #N/A | D19: =+IF(D18>0,D18/D14,"NA") -> #N/A | E19: =+IF(E18>0,E18/E14,"NA") -> #N/A | F19: =+IF(F18>0,F18/F14,"NA") -> #N/A | G19: =+IF(G18>0,G18/G14,"NA") -> #N/A | H19: =+IF(H18>0,H18/H14,"NA") -> #N/A | I19: =+IF(I18>0,I18/I14,"NA") -> #N/A | ... BI19: =+IF(BI18>0,BI18/BI14,"NA") -> #N/A
A21: Operating Expenses
A23: Internet and Phone | B23: ='Expense Assumptions'!B22 -> 750 | C23: ='Expense Assumptions'!C22 -> 750 | D23: ='Expense Assumptions'!D22 -> 750 | E23: ='Expense Assumptions'!E22 -> 750 | F23: ='Expense Assumptions'!F22 -> 750 | G23: ='Expense Assumptions'!G22 -> 750 | H23: ='Expense Assumptions'!H22 -> 750 | I23: ='Expense Assumptions'!I22 -> 750 | ... BI23: ='Expense Assumptions'!BI22 -> 1688.2632
A24: Insurance | B24: ='Expense Assumptions'!B23 -> 3000 | C24: ='Expense Assumptions'!C23 -> 3000 | D24: ='Expense Assumptions'!D23 -> 3000 | E24: ='Expense Assumptions'!E23 -> 3000 | F24: ='Expense Assumptions'!F23 -> 3000 | G24: ='Expense Assumptions'!G23 -> 3000 | H24: ='Expense Assumptions'!H23 -> 3000 | I24: ='Expense Assumptions'!I23 -> 3000 | ... BI24: ='Expense Assumptions'!BI23 -> 140180
A25: Professional Fees | B25: ='Expense Assumptions'!B24 -> 3500 | C25: ='Expense Assumptions'!C24 -> 3500 | D25: ='Expense Assumptions'!D24 -> 3500 | E25: ='Expense Assumptions'!E24 -> 3500 | F25: ='Expense Assumptions'!F24 -> 3500 | G25: ='Expense Assumptions'!G24 -> 3500 | H25: ='Expense Assumptions'!H24 -> 3500 | I25: ='Expense Assumptions'!I24 -> 3500 | ... BI25: ='Expense Assumptions'!BI24 -> 3939.2808
A26: Rent and Utility | B26: ='Expense Assumptions'!B25 -> 40000 | C26: ='Expense Assumptions'!C25 -> 40000 | D26: ='Expense Assumptions'!D25 -> 40000 | E26: ='Expense Assumptions'!E25 -> 40000 | F26: ='Expense Assumptions'!F25 -> 40000 | G26: ='Expense Assumptions'!G25 -> 40000 | H26: ='Expense Assumptions'!H25 -> 40000 | I26: ='Expense Assumptions'!I25 -> 40000 | ... BI26: ='Expense Assumptions'!BI25 -> 93588.685
A27: Office and Other Expenses (per employee) | B27: ='Expense Assumptions'!B26 -> 10000 | C27: ='Expense Assumptions'!C26 -> 0 | D27: ='Expense Assumptions'!D26 -> 0 | E27: ='Expense Assumptions'!E26 -> 70000 | F27: ='Expense Assumptions'!F26 -> 0 | G27: ='Expense Assumptions'!G26 -> 16825 | H27: ='Expense Assumptions'!H26 -> 0 | I27: ='Expense Assumptions'!I26 -> 5000 | ... BI27: ='Expense Assumptions'!BI26 -> 1406.886
A28: Marketing | B28: ='Expense Assumptions'!B27 -> 1500 | C28: ='Expense Assumptions'!C27 -> 1500 | D28: ='Expense Assumptions'!D27 -> 1500 | E28: ='Expense Assumptions'!E27 -> 1500 | F28: ='Expense Assumptions'!F27 -> 1500 | G28: ='Expense Assumptions'!G27 -> 15000 | H28: ='Expense Assumptions'!H27 -> 15000 | I28: ='Expense Assumptions'!I27 -> 15000 | ... BI28: ='Expense Assumptions'!BI27 -> 21961.5
A29: Travel Expenses | B29: ='Expense Assumptions'!B28 -> 3000 | C29: ='Expense Assumptions'!C28 -> 5000 | D29: ='Expense Assumptions'!D28 -> 5000 | E29: ='Expense Assumptions'!E28 -> 10000 | F29: ='Expense Assumptions'!F28 -> 10000 | G29: ='Expense Assumptions'!G28 -> 10000 | H29: ='Expense Assumptions'!H28 -> 20000 | I29: ='Expense Assumptions'!I28 -> 20000 | ... BI29: ='Expense Assumptions'!BI28 -> 22510.176
A30: Research and Development | B30: ='Expense Assumptions'!B29 -> 1000 | C30: ='Expense Assumptions'!C29 -> 1000 | D30: ='Expense Assumptions'!D29 -> 1000 | E30: ='Expense Assumptions'!E29 -> 1000 | F30: ='Expense Assumptions'!F29 -> 1000 | G30: ='Expense Assumptions'!G29 -> 5000 | H30: ='Expense Assumptions'!H29 -> 5000 | I30: ='Expense Assumptions'!I29 -> 5000 | ... BI30: ='Expense Assumptions'!BI29 -> 20000
A32: Total Operating Expenses | B32: =SUM(B23:B30) -> 62750 | C32: =SUM(C23:C30) -> 54750 | D32: =SUM(D23:D30) -> 54750 | E32: =SUM(E23:E30) -> 129750 | F32: =SUM(F23:F30) -> 59750 | G32: =SUM(G23:G30) -> 94075 | H32: =SUM(H23:H30) -> 87250 | I32: =SUM(I23:I30) -> 92250 | ... BI32: =SUM(BI23:BI30) -> 305274.79
A34: Payroll Expenses | B34: ='Payroll Assumptions'!B108 -> #N/A | C34: ='Payroll Assumptions'!C108 -> #N/A | D34: ='Payroll Assumptions'!D108 -> #N/A | E34: ='Payroll Assumptions'!E108 -> #N/A | F34: ='Payroll Assumptions'!F108 -> #N/A | G34: ='Payroll Assumptions'!G108 -> #N/A | H34: ='Payroll Assumptions'!H108 -> #N/A | I34: ='Payroll Assumptions'!I108 -> #N/A | ... BI34: ='Payroll Assumptions'!BI108 -> #N/A
A36: Total Operating Expenses including Payroll | B36: =B32+B34 -> #N/A | C36: =C32+C34 -> #N/A | D36: =D32+D34 -> #N/A | E36: =E32+E34 -> #N/A | F36: =F32+F34 -> #N/A | G36: =G32+G34 -> #N/A | H36: =H32+H34 -> #N/A | I36: =I32+I34 -> #N/A | ... BI36: =BI32+BI34 -> #N/A
A38: EBITDA | B38: =B18-B36 -> #N/A | C38: =C18-C36 -> #N/A | D38: =D18-D36 -> #N/A | E38: =E18-E36 -> #N/A | F38: =F18-F36 -> #N/A | G38: =G18-G36 -> #N/A | H38: =H18-H36 -> #N/A | I38: =I18-I36 -> #N/A | ... BI38: =BI18-BI36 -> #N/A
A39: EBITDA Margin (%) | B39: =+IF(B38>0,B38/B14,"NA") -> #N/A | C39: =+IF(C38>0,C38/C14,"NA") -> #N/A | D39: =+IF(D38>0,D38/D14,"NA") -> #N/A | E39: =+IF(E38>0,E38/E14,"NA") -> #N/A | F39: =+IF(F38>0,F38/F14,"NA") -> #N/A | G39: =+IF(G38>0,G38/G14,"NA") -> #N/A | H39: =+IF(H38>0,H38/H14,"NA") -> #N/A | I39: =+IF(I38>0,I38/I14,"NA") -> #N/A | ... BI39: =+IF(BI38>0,BI38/BI14,"NA") -> #N/A
A41: Depreciation & Amortization | B41: ='Fixed Asset Schedules'!B13+'Fixed Asset Schedules'!B21 -> 114687.76 | C41: ='Fixed Asset Schedules'!C13+'Fixed Asset Schedules'!C21 -> 114687.76 | D41: ='Fixed Asset Schedules'!D13+'Fixed Asset Schedules'!D21 -> 114687.76 | E41: ='Fixed Asset Schedules'!E13+'Fixed Asset Schedules'!E21 -> 123327.19 | F41: ='Fixed Asset Schedules'!F13+'Fixed Asset Schedules'!F21 -> 123327.19 | G41: ='Fixed Asset Schedules'!G13+'Fixed Asset Schedules'!G21 -> 123327.19 | H41: ='Fixed Asset Schedules'!H13+'Fixed Asset Schedules'!H21 -> 126941.44 | I41: ='Fixed Asset Schedules'!I13+'Fixed Asset Schedules'!I21 -> 126941.44 | ... BI41: ='Fixed Asset Schedules'!BI13+'Fixed Asset Schedules'!BI21 -> 478778.9
A43: Profit Before Tax (PBT) | B43: =+B38-B41 -> #N/A | C43: =+C38-C41 -> #N/A | D43: =+D38-D41 -> #N/A | E43: =+E38-E41 -> #N/A | F43: =+F38-F41 -> #N/A | G43: =+G38-G41 -> #N/A | H43: =+H38-H41 -> #N/A | I43: =+I38-I41 -> #N/A | ... BI43: =+BI38-BI41 -> #N/A
A45: Cumulative Operating Loss | B45: =B43 -> #N/A | C45: =B45+C43 -> #N/A | D45: =C45+D43 -> #N/A | E45: =D45+E43 -> #N/A | F45: =E45+F43 -> #N/A | G45: =F45+G43 -> #N/A | H45: =G45+H43 -> #N/A | I45: =H45+I43 -> #N/A | J45: =I45+J43 -> #N/A | ... BI45: =BH45+BI43 -> #N/A

Sheet Annual P&L
A1: EXOS Aerospace
A2: Annual Profit & Loss Statement
A3: Amounts in USD
A4: Back To Index | G4: NOTE: Years 6-10 removed — contained formula errors
A5: Assumptions for the Annual Period | B5: =Controls!B5 -> 1 | C5: =Controls!C5 -> 2 | D5: =Controls!D5 -> 3 | E5: =Controls!E5 -> 4 | F5: =Controls!F5 -> 5 | G5: (COS/OpEx grew at 40% regardless of revenue growth rate)
A7: Revenue from BLK4 360kg Launcher | B7: =SUMIF('Monthly P&L'!$B$3:$BI$3,'Annual P&L'!B$5,'Monthly P&L'!$B7:$BI7) -> 0 | C7: =SUMIF('Monthly P&L'!$B$3:$BI$3,'Annual P&L'!C$5,'Monthly P&L'!$B7:$BI7) -> 0 | D7: =SUMIF('Monthly P&L'!$B$3:$BI$3,'Annual P&L'!D$5,'Monthly P&L'!$B7:$BI7) -> 3277776.8 | E7: =SUMIF('Monthly P&L'!$B$3:$BI$3,'Annual P&L'!E$5,'Monthly P&L'!$B7:$BI7) -> 22055552 | F7: =SUMIF('Monthly P&L'!$B$3:$BI$3,'Annual P&L'!F$5,'Monthly P&L'!$B7:$BI7) -> 56499995
A8: Revenue from Propulsion System Sales | B8: =SUMIF('Monthly P&L'!$B$3:$BI$3,'Annual P&L'!B$5,'Monthly P&L'!$B8:$BI8) -> 3460000 | C8: =SUMIF('Monthly P&L'!$B$3:$BI$3,'Annual P&L'!C$5,'Monthly P&L'!$B8:$BI8) -> 6430000 | D8: =SUMIF('Monthly P&L'!$B$3:$BI$3,'Annual P&L'!D$5,'Monthly P&L'!$B8:$BI8) -> 10250000 | E8: =SUMIF('Monthly P&L'!$B$3:$BI$3,'Annual P&L'!E$5,'Monthly P&L'!$B8:$BI8) -> 21500000 | F8: =SUMIF('Monthly P&L'!$B$3:$BI$3,'Annual P&L'!F$5,'Monthly P&L'!$B8:$BI8) -> 32250000
A9: Revenue from EXOS US BLK4 Wet Lease Launches | B9: =SUMIF('Monthly P&L'!$B$3:$BI$3,'Annual P&L'!B$5,'Monthly P&L'!$B9:$BI9) -> 0 | C9: =SUMIF('Monthly P&L'!$B$3:$BI$3,'Annual P&L'!C$5,'Monthly P&L'!$B9:$BI9) -> 0 | D9: =SUMIF('Monthly P&L'!$B$3:$BI$3,'Annual P&L'!D$5,'Monthly P&L'!$B9:$BI9) -> 750000 | E9: =SUMIF('Monthly P&L'!$B$3:$BI$3,'Annual P&L'!E$5,'Monthly P&L'!$B9:$BI9) -> 1200000 | F9: =SUMIF('Monthly P&L'!$B$3:$BI$3,'Annual P&L'!F$5,'Monthly P&L'!$B9:$BI9) -> 4800000
A10: Revenue from Second Stage Sales | B10: =SUMIF('Monthly P&L'!$B$3:$BI$3,'Annual P&L'!B$5,'Monthly P&L'!$B10:$BI10) -> 0 | C10: =SUMIF('Monthly P&L'!$B$3:$BI$3,'Annual P&L'!C$5,'Monthly P&L'!$B10:$BI10) -> 0 | D10: =SUMIF('Monthly P&L'!$B$3:$BI$3,'Annual P&L'!D$5,'Monthly P&L'!$B10:$BI10) -> 0 | E10: =SUMIF('Monthly P&L'!$B$3:$BI$3,'Annual P&L'!E$5,'Monthly P&L'!$B10:$BI10) -> 0 | F10: =SUMIF('Monthly P&L'!$B$3:$BI$3,'Annual P&L'!F$5,'Monthly P&L'!$B10:$BI10) -> 350000
A11: Revenue from Scorpius Space Tank Sales | B11: =SUMIF('Monthly P&L'!$B$3:$BI$3,'Annual P&L'!B$5,'Monthly P&L'!$B11:$BI11) -> 4907540 | C11: =SUMIF('Monthly P&L'!$B$3:$BI$3,'Annual P&L'!C$5,'Monthly P&L'!$B11:$BI11) -> 8678525 | D11: =SUMIF('Monthly P&L'!$B$3:$BI$3,'Annual P&L'!D$5,'Monthly P&L'!$B11:$BI11) -> 19215000 | E11: =SUMIF('Monthly P&L'!$B$3:$BI$3,'Annual P&L'!E$5,'Monthly P&L'!$B11:$BI11) -> 33883594 | F11: =SUMIF('Monthly P&L'!$B$3:$BI$3,'Annual P&L'!F$5,'Monthly P&L'!$B11:$BI11) -> 54685547
A12: Revenue from Sarge Technology Sales | B12: =SUMIF('Monthly P&L'!$B$3:$BI$3,'Annual P&L'!B$5,'Monthly P&L'!$B12:$BI12) -> 500000 | C12: =SUMIF('Monthly P&L'!$B$3:$BI$3,'Annual P&L'!C$5,'Monthly P&L'!$B12:$BI12) -> 6000000 | D12: =SUMIF('Monthly P&L'!$B$3:$BI$3,'Annual P&L'!D$5,'Monthly P&L'!$B12:$BI12) -> 9600000 | E12: =SUMIF('Monthly P&L'!$B$3:$BI$3,'Annual P&L'!E$5,'Monthly P&L'!$B12:$BI12) -> 17280000 | F12: =SUMIF('Monthly P&L'!$B$3:$BI$3,'Annual P&L'!F$5,'Monthly P&L'!$B12:$BI12) -> 30600000
A14: Total Revenue | B14: =SUM(B7:B12) -> 8867540 | C14: =SUM(C7:C12) -> 21108525 | D14: =SUM(D7:D12) -> 43092777 | E14: =SUM(E7:E12) -> 95919145 | F14: =SUM(F7:F12) -> 1.7918554e+08
A15: Y.O.Y Growth (%) | C15: =+C14/B14-1 -> 1.3804263 | D15: =+D14/C14-1 -> 1.0414869 | E15: =+E14/D14-1 -> 1.2258753 | F15: =+F14/E14-1 -> 0.86808943
A17: Total COS | B17: =SUMIF('Monthly P&L'!$B$3:$BC$3,'Annual P&L'!B$5,'Monthly P&L'!$B16:$BC16) -> #N/A | C17: =SUMIF('Monthly P&L'!$B$3:$BC$3,'Annual P&L'!C$5,'Monthly P&L'!$B16:$BC16) -> #N/A | D17: =SUMIF('Monthly P&L'!$B$3:$BC$3,'Annual P&L'!D$5,'Monthly P&L'!$B16:$BC16) -> #N/A | E17: =SUMIF('Monthly P&L'!$B$3:$BC$3,'Annual P&L'!E$5,'Monthly P&L'!$B16:$BC16) -> #N/A | F17: =SUMIF('Monthly P&L'!$B$3:$BI$3,'Annual P&L'!F$5,'Monthly P&L'!$B16:$BI16) -> #N/A
A19: Gross Profit | B19: =B14-B17 -> #N/A | C19: =C14-C17 -> #N/A | D19: =D14-D17 -> #N/A | E19: =E14-E17 -> #N/A | F19: =F14-F17 -> #N/A
A20: Gross Margin % | B20: =+B19/B14 -> #N/A | C20: =+C19/C14 -> #N/A | D20: =+D19/D14 -> #N/A | E20: =+E19/E14 -> #N/A | F20: =+F19/F14 -> #N/A
A22: Operating Expenses
A24: Internet and Phone | B24: =SUMIF('Monthly P&L'!$B$3:$BI$3,'Annual P&L'!B$5,'Monthly P&L'!$B23:$BI23) -> 9000 | C24: =SUMIF('Monthly P&L'!$B$3:$BI$3,'Annual P&L'!C$5,'Monthly P&L'!$B23:$BI23) -> 9270 | D24: =SUMIF('Monthly P&L'!$B$3:$BI$3,'Annual P&L'!D$5,'Monthly P&L'!$B23:$BI23) -> 9548.1 | E24: =SUMIF('Monthly P&L'!$B$3:$BI$3,'Annual P&L'!E$5,'Monthly P&L'!$B23:$BI23) -> 19669.086 | F24: =SUMIF('Monthly P&L'!$B$3:$BI$3,'Annual P&L'!F$5,'Monthly P&L'!$B23:$BI23) -> 20259.159
A25: Insurance | B25: =SUMIF('Monthly P&L'!$B$3:$BI$3,'Annual P&L'!B$5,'Monthly P&L'!$B24:$BI24) -> 36000 | C25: =SUMIF('Monthly P&L'!$B$3:$BI$3,'Annual P&L'!C$5,'Monthly P&L'!$B24:$BI24) -> 74160 | D25: =SUMIF('Monthly P&L'!$B$3:$BI$3,'Annual P&L'!D$5,'Monthly P&L'!$B24:$BI24) -> 146160 | E25: =SUMIF('Monthly P&L'!$B$3:$BI$3,'Annual P&L'!E$5,'Monthly P&L'!$B24:$BI24) -> 455160 | F25: =SUMIF('Monthly P&L'!$B$3:$BI$3,'Annual P&L'!F$5,'Monthly P&L'!$B24:$BI24) -> 1682160
A26: Professional Fees | B26: =SUMIF('Monthly P&L'!$B$3:$BI$3,'Annual P&L'!B$5,'Monthly P&L'!$B25:$BI25) -> 42000 | C26: =SUMIF('Monthly P&L'!$B$3:$BI$3,'Annual P&L'!C$5,'Monthly P&L'!$B25:$BI25) -> 43260 | D26: =SUMIF('Monthly P&L'!$B$3:$BI$3,'Annual P&L'!D$5,'Monthly P&L'!$B25:$BI25) -> 44557.8 | E26: =SUMIF('Monthly P&L'!$B$3:$BI$3,'Annual P&L'!E$5,'Monthly P&L'!$B25:$BI25) -> 45894.534 | F26: =SUMIF('Monthly P&L'!$B$3:$BI$3,'Annual P&L'!F$5,'Monthly P&L'!$B25:$BI25) -> 47271.37
A27: Rent and Utility | B27: =SUMIF('Monthly P&L'!$B$3:$BI$3,'Annual P&L'!B$5,'Monthly P&L'!$B26:$BI26) -> 480000 | C27: =SUMIF('Monthly P&L'!$B$3:$BI$3,'Annual P&L'!C$5,'Monthly P&L'!$B26:$BI26) -> 499200 | D27: =SUMIF('Monthly P&L'!$B$3:$BI$3,'Annual P&L'!D$5,'Monthly P&L'!$B26:$BI26) -> 519168 | E27: =SUMIF('Monthly P&L'!$B$3:$BI$3,'Annual P&L'!E$5,'Monthly P&L'!$B26:$BI26) -> 1079869.4 | F27: =SUMIF('Monthly P&L'!$B$3:$BI$3,'Annual P&L'!F$5,'Monthly P&L'!$B26:$BI26) -> 1123064.2
A28: Office and Other Expenses (per employee) | B28: =SUMIF('Monthly P&L'!$B$3:$BI$3,'Annual P&L'!B$5,'Monthly P&L'!$B27:$BI27) -> 116825 | C28: =SUMIF('Monthly P&L'!$B$3:$BI$3,'Annual P&L'!C$5,'Monthly P&L'!$B27:$BI27) -> 56804.5 | D28: =SUMIF('Monthly P&L'!$B$3:$BI$3,'Annual P&L'!D$5,'Monthly P&L'!$B27:$BI27) -> -185657.5 | E28: =SUMIF('Monthly P&L'!$B$3:$BI$3,'Annual P&L'!E$5,'Monthly P&L'!$B27:$BI27) -> 0 | F28: =SUMIF('Monthly P&L'!$B$3:$BI$3,'Annual P&L'!F$5,'Monthly P&L'!$B27:$BI27) -> 16882.632
A29: Marketing | B29: =SUMIF('Monthly P&L'!$B$3:$BI$3,'Annual P&L'!B$5,'Monthly P&L'!$B28:$BI28) -> 112500 | C29: =SUMIF('Monthly P&L'!$B$3:$BI$3,'Annual P&L'!C$5,'Monthly P&L'!$B28:$BI28) -> 198000 | D29: =SUMIF('Monthly P&L'!$B$3:$BI$3,'Annual P&L'!D$5,'Monthly P&L'!$B28:$BI28) -> 217800 | E29: =SUMIF('Monthly P&L'!$B$3:$BI$3,'Annual P&L'!E$5,'Monthly P&L'!$B28:$BI28) -> 239580 | F29: =SUMIF('Monthly P&L'!$B$3:$BI$3,'Annual P&L'!F$5,'Monthly P&L'!$B28:$BI28) -> 263538
A30: Travel Expenses | B30: =SUMIF('Monthly P&L'!$B$3:$BI$3,'Annual P&L'!B$5,'Monthly P&L'!$B29:$BI29) -> 163000 | C30: =SUMIF('Monthly P&L'!$B$3:$BI$3,'Annual P&L'!C$5,'Monthly P&L'!$B29:$BI29) -> 247200 | D30: =SUMIF('Monthly P&L'!$B$3:$BI$3,'Annual P&L'!D$5,'Monthly P&L'!$B29:$BI29) -> 254616 | E30: =SUMIF('Monthly P&L'!$B$3:$BI$3,'Annual P&L'!E$5,'Monthly P&L'!$B29:$BI29) -> 262254.48 | F30: =SUMIF('Monthly P&L'!$B$3:$BI$3,'Annual P&L'!F$5,'Monthly P&L'!$B29:$BI29) -> 270122.11
A31: Research and Development | B31: =SUMIF('Monthly P&L'!$B$3:$BI$3,'Annual P&L'!B$5,'Monthly P&L'!$B30:$BI30) -> 40000 | C31: =SUMIF('Monthly P&L'!$B$3:$BI$3,'Annual P&L'!C$5,'Monthly P&L'!$B30:$BI30) -> 240000 | D31: =SUMIF('Monthly P&L'!$B$3:$BI$3,'Annual P&L'!D$5,'Monthly P&L'!$B30:$BI30) -> 240000 | E31: =SUMIF('Monthly P&L'!$B$3:$BI$3,'Annual P&L'!E$5,'Monthly P&L'!$B30:$BI30) -> 240000 | F31: =SUMIF('Monthly P&L'!$B$3:$BI$3,'Annual P&L'!F$5,'Monthly P&L'!$B30:$BI30) -> 240000
A33: Total Operating Expenses | B33: =SUM(B24:B31) -> 999325 | C33: =SUM(C24:C31) -> 1367894.5 | D33: =SUM(D24:D31) -> 1246192.4 | E33: =SUM(E24:E31) -> 2342427.5 | F33: =SUM(F24:F31) -> 3663297.5
A35: Payroll Expenses | B35: =SUMIF('Monthly P&L'!$B$3:$BI$3,'Annual P&L'!B$5,'Monthly P&L'!$B34:$BI34) -> #N/A | C35: =SUMIF('Monthly P&L'!$B$3:$BI$3,'Annual P&L'!C$5,'Monthly P&L'!$B34:$BI34) -> #N/A | D35: =SUMIF('Monthly P&L'!$B$3:$BI$3,'Annual P&L'!D$5,'Monthly P&L'!$B34:$BI34) -> #N/A | E35: =SUMIF('Monthly P&L'!$B$3:$BI$3,'Annual P&L'!E$5,'Monthly P&L'!$B34:$BI34) -> #N/A | F35: =SUMIF('Monthly P&L'!$B$3:$BI$3,'Annual P&L'!F$5,'Monthly P&L'!$B34:$BI34) -> #N/A
A37: Total Operating Expenses including Payroll | B37: =+B35+B33 -> #N/A | C37: =+C35+C33 -> #N/A | D37: =+D35+D33 -> #N/A | E37: =+E35+E33 -> #N/A | F37: =+F35+F33 -> #N/A
A39: EBITDA | B39: =+B19-B37 -> #N/A | C39: =+C19-C37 -> #N/A | D39: =+D19-D37 -> #N/A | E39: =+E19-E37 -> #N/A | F39: =+F19-F37 -> #N/A
A40: EBITDA Margin (%) | B40: =+B39/B14 -> #N/A | C40: =+C39/C14 -> #N/A | D40: =+D39/D14 -> #N/A | E40: =+E39/E14 -> #N/A | F40: =+F39/F14 -> #N/A
A42: Depreciation & Amortization | B42: =SUMIF('Monthly P&L'!$B$3:$BC$3,'Annual P&L'!B$5,'Monthly P&L'!$B41:$BC41) -> 1477386.2 | C42: =SUMIF('Monthly P&L'!$B$3:$BC$3,'Annual P&L'!C$5,'Monthly P&L'!$B41:$BC41) -> 1918909.1 | D42: =SUMIF('Monthly P&L'!$B$3:$BC$3,'Annual P&L'!D$5,'Monthly P&L'!$B41:$BC41) -> 1942973.7 | E42: =SUMIF('Monthly P&L'!$B$3:$BC$3,'Annual P&L'!E$5,'Monthly P&L'!$B41:$BC41) -> 3099887.5 | F42: =SUMIF('Monthly P&L'!$B$3:$BC$3,'Annual P&L'!F$5,'Monthly P&L'!$B41:$BC41) -> 2315336.9
A44: Profit Before Tax (PBT) | B44: =+B39-B42 -> #N/A | C44: =+C39-C42 -> #N/A | D44: =+D39-D42 -> #N/A | E44: =+E39-E42 -> #N/A | F44: =+F39-F42 -> #N/A
A46: Cumulative Operating EBT | B46: ='Monthly P&L'!M45 -> #N/A | C46: ='Monthly P&L'!Y45 -> #N/A | D46: ='Monthly P&L'!AK45 -> #N/A | E46: ='Monthly P&L'!AW45 -> #N/A | F46: ='Monthly P&L'!BI45 -> #N/A
A48: Income Tax | B48: =IF(B46<0,0,HLOOKUP(B$5,Controls!$A$5:$F$177,MATCH('Annual P&L'!$A48,Controls!$A$5:$A$178,0),0)*B44) -> #N/A | C48: =IF(C46<0,0,HLOOKUP(C$5,Controls!$A$5:$F$177,MATCH('Annual P&L'!$A48,Controls!$A$5:$A$178,0),0)*C44) -> #N/A | D48: =IF(D46<0,0,HLOOKUP(D$5,Controls!$A$5:$F$177,MATCH('Annual P&L'!$A48,Controls!$A$5:$A$178,0),0)*D44) -> #N/A | E48: =IF(E46<0,0,HLOOKUP(E$5,Controls!$A$5:$F$177,MATCH('Annual P&L'!$A48,Controls!$A$5:$A$178,0),0)*E44) -> #N/A | F48: =IF(F46<0,0,HLOOKUP(F$5,Controls!$A$5:$F$177,MATCH('Annual P&L'!$A48,Controls!$A$5:$A$178,0),0)*F44) -> #N/A
